Workbook

Sheet Info
B2: Hello 👋
B4: Welcome to the labeling exercise for SDG 7.
B5: The objective of this exercise is to label 100 texts in terms of their relevance to SDG 7.
B7: Your Labeling Sheet
B8: You have your own personal sheet for assigning the labels. You will find it by clicking on your name in the list at the bottom of this page.
B9: Each sheet has the same 100 texts, but the order in which they appear has been randomized.
B10: Later on, we will put everyone's labels side-by-side. This will help us identify texts with high and low alignment.
B11: At our next meeting, we will discuss the texts where we have disagreements and see if we can reach a consensus for the "true" label for every text.
B12: Please resist the temptation to look at other people's labels until you are done labeling. 🙂
B14: Explanation of Labels
B15: On your personal sheet, you will find the text in column C.
B16: Column D contains a drop-down for picking the appropriate label. The options are:
B18: SDG 7 | C18: This text is relevant to SDG 7
B19: NOT SDG 7 | C19: This text is not relevant to SDG 7
B20: SKIP | C20: You can use this if you are not sure about the label
B22: If you want, you can put any comments in column E.
B24: Instructions for Labeling
B25: The text should be annotated as SDG 7 only if:
B27: 1. The text addresses SDG 7 or one of its targets
B28: See the official definitions of SDG 7 and its targets below ("SDG 7 Description & Targets").
B30: AND
B32: 2. The text addresses SDG 7 or its targets directly:
B33: - the text should be directly relevant to SDG 7 or to achieving SDG 7
B34: - if a text only has an indirect relevance, it should not be labeled SDG 7
B35: Example: "We are subsidizing the costs of silicon" does not qualify for SDG 7, even though silicon is one of the materials for making photovoltaic cells and reduced cost of silicon might have indirect benefits for the expansion of solar energy.
B37: AND
B39: 3. The text addresses SDG 7 or its targets specifically:
... B68: Please click on your name to access your personal labeling sheet. Names are listed in alphabetical order.
B70: Name | C70: Progress (will update automatically)
B71: Dina | C71: =IFERROR(__xludf.DUMMYFUNCTION("SPARKLINE((100-COUNTIF(INDIRECT(B71&""!D:D""), ""TO DO""))/100+0.01,{""charttype"",""bar"";""max"",1.01;""min"",0; ""color1"", ""#4285f4""})"),"") | D71: =(100-COUNTIF(INDIRECT(B71&"!D:D"), "TO DO")) & " / 100" -> 0 / 100
B72: Finn | C72: =IFERROR(__xludf.DUMMYFUNCTION("SPARKLINE((100-COUNTIF(INDIRECT(B72&""!D:D""), ""TO DO""))/100+0.01,{""charttype"",""bar"";""max"",1.01;""min"",0; ""color1"", ""#4285f4""})"),"") | D72: =(100-COUNTIF(INDIRECT(B72&"!D:D"), "TO DO")) & " / 100" -> 100 / 100
B73: Gib | C73: =IFERROR(__xludf.DUMMYFUNCTION("SPARKLINE((100-COUNTIF(INDIRECT(B73&""!D:D""), ""TO DO""))/100+0.01,{""charttype"",""bar"";""max"",1.01;""min"",0; ""color1"", ""#4285f4""})"),"") | D73: =(100-COUNTIF(INDIRECT(B73&"!D:D"), "TO DO")) & " / 100" -> 11 / 100
B74: Jean-Baptiste | C74: =IFERROR(__xludf.DUMMYFUNCTION("SPARKLINE((100-COUNTIF(INDIRECT(B74&""!D:D""), ""TO DO""))/100+0.01,{""charttype"",""bar"";""max"",1.01;""min"",0; ""color1"", ""#4285f4""})"),"") | D74: =(100-COUNTIF(INDIRECT(B74&"!D:D"), "TO DO")) & " / 100" -> 100 / 100
B75: Meike | C75: =IFERROR(__xludf.DUMMYFUNCTION("SPARKLINE((100-COUNTIF(INDIRECT(B75&""!D:D""), ""TO DO""))/100+0.01,{""charttype"",""bar"";""max"",1.01;""min"",0; ""color1"", ""#4285f4""})"),"") | D75: =(100-COUNTIF(INDIRECT(B75&"!D:D"), "TO DO")) & " / 100" -> 0 / 100
B76: Steve | C76: =IFERROR(__xludf.DUMMYFUNCTION("SPARKLINE((100-COUNTIF(INDIRECT(B76&""!D:D""), ""TO DO""))/100+0.01,{""charttype"",""bar"";""max"",1.01;""min"",0; ""color1"", ""#4285f4""})"),"") | D76: =(100-COUNTIF(INDIRECT(B76&"!D:D"), "TO DO")) & " / 100" -> 100 / 100
B78: Thank you for being part of this exercise and thanks to OSDG for the dataset! ❤️

Sheet Coding Manual
A1: Construct definition
A2: Goal 7. Ensure access to affordable, reliable, sustainable and modern energy for all
A3: 7.1 By 2030, ensure universal access to affordable, reliable and modern energy services
A4: 7.2 By 2030, increase substantially the share of renewable energy in the global energy mix
A5: 7.3 By 2030, double the global rate of improvement in energy efficiency
A6: 7.a By 2030, enhance international cooperation to facilitate access to clean energy research and technology, including renewable energy, energy efficiency and advanced and cleaner fossil-fuel technology, and promote investment in energy infrastructure and clean energy technology
A7: 7.b By 2030, expand infrastructure and upgrade technology for supplying modern and sustainable energy services for all in developing countries, in particular least developed countries, small island developing States, and land-locked developing countries, in accordance with their respective programmes of support
A9: Rules of annotation
A10: The text should be annotated as SDG 7 only if:
A11: 1. The content addresses SDG 7 or one of its targets
A12: - affordable/ reliable/ sustainable/ modern energy
A13: - the (access to) this energy
... A40: - transportation: when about transportation in energy-efficient way, should be SDG 11

Sheet Dina
A1: DOI | B1: Text ID | C1: Text | D1: Label | E1: Comments (optional)
A2: 10.1787/5kg20639kgkj-en | B2: 90e3f33798e2cfc95c140ef186fb00a9 | C2: Sustainability Advantage is a business support service from the Department of Environment and Climate Change NSW. It is designed to help organisations understand sustainability, successfully manage for a better environment and add business value79. Industry' Investment NSW offers “LEAN and green” business master classes for people who want to leam how they can improve business efficiency through the application of “lean” business practices, coupled with environmental sustainability, to reduce costs, increase profits, open new markets and create jobs . Despite initiatives like these, it is not always easy for SMEs to take up training opportunities in skills for sustainability. | D2: TO DO
A3: 10.1787/9789264303119-en | B3: 3b67ed2c408fb9348a08325fa98f3dbe | C3: Furthermore, the most severe accidents have occurred in these stages. Most of the severe accidents involved tankers (collisions, explosions, fires and impact with the ground) and road accidents during regional distribution. In the oil chain, fatalities are fairly evenly distributed among workers and the public (Burgherr and Hirschberg, 2008a). | D3: TO DO
A4: 10.18356/fcd1ba6c-en | B4: 2528f76d29c8a44be2769f22b552e9a8 | C4: Scepticism about the science is no longer an option: the world’s scientists have never been so unanimous, and so ominous, in their projections of future perils. The bad news is that too many participants in the debate consider a climate policy as consisting primarily of manipulating markets and prices. If the only tool available were market liberalization, then the solution to every problem would seem to be a matter of getting the prices right. But setting a price for carbon emissions is only the beginning of climate policy - not the end. | D4: TO DO
A5: 10.18356/7e830810-en | B5: 0edfe3b90c82ce644cf8c58342f13172 | C5: Where energy supply is unreliable, firms are more concerned with availability than with efficiency. Similarly, small and medium-size industrial firms find it much harder to get a loan than do larger firms. And while the barriers to energy efficiency are also present in developed countries, they are more formidable in developing countries. What are the appropriate roles of the public and private sectors? | D5: TO DO
A6: 10.1787/5k9312v21l6f-en | B6: 60a148ee953bd6d9349f85d897641289 | C6: These initiatives need to be encouraged, carefully monitored, and expanded where successful. Fiona Stewart is a principal administrator in the Financial Affairs Division of the OECD’s Directorate for Financial and Enterprise Affairs. The views expressed are the sole responsibility of the authors and do not reflect those of their organisations or the governments of OECD Member countries. The authors are solely responsible for any errors. | D6: TO DO
A7: 10.14217/9781848599574-13-en | B7: 1982e8b824ff8e01f7ec3ac363f26441 | C7: Electricity grids in the Pacific will need to be strongly interconnected, flexible enough to accommodate this change, and resilient enough to withstand climate impacts, as well as cope with potential demand growth from growing populations and growing electric vehicle use. Commonwealth Pacific small states are more dependent on the fossil fuels used in cars, trucks and boats than for generating electricity, and more cost-effective displacement of fossil fuel can occur through energy efficiency. However, the attention and funding of development partners is not always directed accordingly to these areas. Moreover, although this is improving, consumers generally lack awareness on how they can reduce their energy consumption or be more energy efficient. The International Renewable Energy Agency (IRENA) estimates that deploying renewables worldwide on the scale necessary to limit global temperature rise below 2 degrees would require current investment to double by 2020, and triple by 2030 to around US$900 billion annually (IRENA 2016b). | D7: TO DO
A8: 10.1787/9789264188617-en | B8: 6c094b959f7578c34063732cedc4a7ae | C8: The OECD is also at the forefront of efforts to understand and to help governments respond to new developments and concerns, such as corporate governance, the information economy and the challenges of an ageing population. The Organisation provides a setting where governments can compare policy experiences, seek answers to common problems, identify good practice and work to co-ordinate domestic and international policies. The European Commission takes part in the work of the OECD. Current NEA membership consists of 30 OECD member countries: Australia, Austria, Belgium, Canada, the Czech Republic, Denmark, Finland, France, Germany, Greece, Hungary, Iceland, Ireland, Italy, Japan, Luxembourg, Mexico, the Netherlands, Norway, Poland, Portugal, the Republic of Korea, the Slovak Republic, Slovenia, Spain, Sweden, Switzerland, Turkey, the United Kingdom and the United States. The European Commission also takes part in the work of the Agency. | D8: TO DO
A9: 10.1787/5kmh3nj5rzs4-en | B9: be8a2af1834e66add5d63d32dcf2761e | C9: This debate is in line with South Africa's rural electrification agenda, as new power generation will be necessary to service more households. The average official50 unemployment figures are above 20% (see Table 33), excluding the under-employed in the rural and urban areas or those who are not registered in employment agencies. Payment for electricity is an issue for people who have no or very little income. Many cases of domestic violence in newly electrified households have been amply documented. It is argued that domestic trouble starts over priorities when resources are scarce (Habitat for Humanity, 2009). However, the long-term effect of ensuring universal access to electricity should lead to general opportunities for a broad-based economic development. | D9: TO DO
A10: 10.6027/9789289330954-4-en | B10: 138cf928dfb2490a23508d1175375c10 | C10: The country's potential in developing energy production technologies like wave power and osmotic power is also substantial. Norway is Europe's largest producer of hydropower, which delivers 99% of the country's electricity. On January 1 2008, Norway had a total installed capacity of 29030 MW at 699 hydropower stations larger than 1 MW. The Kvill-dal hydropower station in Rogaland county is Norway’s largest, with a maximum generating capacity of 1240 MW. | D10: TO DO
A11: 10.18356/a81ec314-en | B11: ddd9ab387d2fc7238a7336e01f4480c3 | C11: These new partnerships arc working to provide the most cost-cfTcctivc electrification solutions, especially in remote communities that arc often the most disadvantaged in terms of electricity access. Though progress in electrification continued at the regional level, it slowed in the recent period, attributable to population growth in rural areas and the ongoing difficulty of extending services to remote areas. The rate of progress has declined in countries with the largest deficits, namely India, Bangladesh, and Myanmar, while the lowest access rates arc found among a number of Pacific Island and least developed State.4 Though urban areas in most economics have achieved universal access, rural areas lag behind, and, in a few cases with growing rural populations, rural electrification rates are falling. | D11: TO DO
A12: 10.1787/9789264180444-17-en | B12: 0d02b195616490f828e9c7e99e293799 | C12: The University of Troms0 has over 9 000 students and some 2 500 employees. Since Troms County has only 1% of its surface area classed as cultivable land, agriculture is a relatively minor part of land use. It is mainly located around the coast and was traditionally combined with fishing to form a key part of rural livelihoods. Troms County is at the northern limits of agricultural production possibilities, but the Gulf Stream enables some seasonal farming around the coasts and fjords, while the Sami people also carry out traditional reindeer herding. | D12: TO DO
A13: 10.1787/5kmh3nj5rzs4-en | B13: 09d371f072d386c66ae086329a44aa38 | C13: In 2008, 70.8% of India's total population lived in rural areas, progressively migrating to urban areas at an annual rate of 2.3%, a rate which is below that of many other countries (UNPD, 2008). While such economic development has led to an average increase in the standards of living, it has left the agricultural sector untouched, bypassing most of the rural poor. Therefore, although India has enjoyed a growth of GDP per capita, poverty remains a challenge. Poverty is also more concentrated in some states such as the eastern and north-eastern states as Figure 7 shows. In March 2007, the Indian Planning Commission estimated that over the 2004-2005 Page | 63 period, more than one-quarter of India's total population (27.5%) still lived below the poverty line (BPL), with a distribution of 25.7% urban dwellers and 28.3% rural dwellers (Planning Commission, Government of India, 2007)37 as seen in Table 17. But strong economic growth alone does not bring such amenities to the rural poor. | D13: TO DO
... A101: 10.6027/9789289329163-8-en | B101: f8a730809d29ac515eb7c5e34389c1b6 | C101: Consequently, there are more business options for the forest industry and forest-based raw materials than ever before. It still needs to be remembered that all four levels must be able to co-exist also in the future, even if their shares may change. All that can be produced without felling trees, e.g. carbon sinks, berries, game, tourism, etc. | D101: TO DO

Sheet Finn
A1: DOI | B1: Text ID | C1: Text | D1: Label | E1: Comments (optional)
A2: 10.1787/5kg20639kgkj-en | B2: 448cfebe196e9aed00270dbd6ed9d3ce | C2: Not only does this have potentially negative effects on gender pay gaps and levels of social inclusion, but also Sydney is not fully utilising the skills currently available in its workforce. Moreover, this mixed labour market picture suggests that the low levels of unemployment are masking higher levels of inactivity. Youth unemployment is also high, although this is very much a global trend amongst advanced economies. | D2: NOT SDG 7
A3: 10.1787/5bbcdeac-en | B3: 6194ce1da1e7aed5cd5e9929d75f9742 | C3: An enabling policy environment is important for the development of a strong and competitive renewable energy sector to supply both industrial and domestic consumers. Section 3 identifies key enabling policy factors required for the replicability and accelerated uptake of the available renewable energy solutions throughout the mining sector. Major companies and conglomerates, among others, such as Glencore, Barrick Gold, Rio Tinto, Antofagasta, Codelco and IAMGOLD have all made use of renewable energy in their mines (Table 2.1). | D3: SDG 7
A4: 10.1787/9789264303119-en | B4: 881afd0ec024eaac99cb05f2a12897f2 | C4: If the latter are already difficult to determine for marketed goods, the intrinsic complexity of external costs prevents the establishment of social welfare functions adopting a broader notion of welfare. To a large extent social costs are external, i.e. not internalised, precisely because no well-defined utility functions exist. Discussion quickly shows that any framework based solely on static optimisation will run into internal contradictions. | D4: NOT SDG 7
A5: 10.6027/9789289349918-3-en | B5: 725de70f6686eefb96c1653b790d6b6a | C5: A way to improve energy efficiency is to tap the huge potential for efficiency gains in the building sector which is the largest single energy consumer in Europe, absorbing 40% of final energy. About 75% of buildings are energy inefficient and, depending on the Member State, only o.4-1.2% of the stock is renovated each year. ( The energy efficiency target on EU level is set on fixed Mtoe-level for final energy and primary energy use in 2030, and the Member States have to set their targets so that this target will be reached. The Commission will lay down a process to ensure that the contributions add up to the Union's 2030 energy efficiency target in the legislative proposal on Energy Union Governance. | D5: SDG 7
A6: 10.18356/1e8b62ff-en | B6: 4cb4009dc0f591e05e2f3e8e69a32234 | C6: By 2014, more than 1,000 microhydro systems had been installed, with total generating capacity of 22 MW, providing off-grid electricity access to 20 per cent of the population. Credible long-term policy commitment, with flexible approach to implementation and reduced administrative burdens, is essential to sustaining mini-grid deployment. In this respect, the availability of a potential anchor load — i.e., a consumer of a large and possibly stable proportion of the power generated (for instance a small factory, hospital or farmer cooperative) — supplementing households’ electricity demand is usually critical to support mini-grid profitability and increase capacity utilization. | D6: SDG 7
A7: 10.1787/5kmh3nj5rzs4-en | B7: 09d371f072d386c66ae086329a44aa38 | C7: In 2008, 70.8% of India's total population lived in rural areas, progressively migrating to urban areas at an annual rate of 2.3%, a rate which is below that of many other countries (UNPD, 2008). While such economic development has led to an average increase in the standards of living, it has left the agricultural sector untouched, bypassing most of the rural poor. Therefore, although India has enjoyed a growth of GDP per capita, poverty remains a challenge. Poverty is also more concentrated in some states such as the eastern and north-eastern states as Figure 7 shows. In March 2007, the Indian Planning Commission estimated that over the 2004-2005 Page | 63 period, more than one-quarter of India's total population (27.5%) still lived below the poverty line (BPL), with a distribution of 25.7% urban dwellers and 28.3% rural dwellers (Planning Commission, Government of India, 2007)37 as seen in Table 17. But strong economic growth alone does not bring such amenities to the rural poor. | D7: NOT SDG 7
A8: 10.1787/5k3wb8fmsz6h-en | B8: e45e89c440f096f7dedfee2104c05be1 | C8: Looking forward, the development of storage technologies and the development of international interconnections are foreseen to further facilitate the integration of wind and solar power. In these situations, balancing the power system during periods of low load will necessitate further adaptations to maintain the physical parameters of the network. An ongoing IEA work within the Grid Integration of Variable Renewables project (GIVAR) analyses these options in more detail. Hence, it will be necessary in the next 20 years to keep some conventional power plants online to provide ancillary services and ramp-up capabilities. | D8: SDG 7
A9: 10.14217/9781848599574-13-en | B9: 4ab2d07728c9a63879cfc15e268f6aba | C9: The percentage of the population that has access to electricity ranges from 18 per cent in PNG to 100 per cent in Samoa (Figure 9.4). A larger proportion of hydro power, for example in Fiji, is likely to reduce the electricity tariff, whereas a country that relies mostly on fossil fuels, such as Kiribati or Tuvalu, is more vulnerable to increasing oil prices. Another factor affecting the residential electricity tariff is whether it is subsidised through the Government budget, for example in Fiji, or using a cross subsidy from larger users of electricity, for example in Vanuatu. Each power utility in each country determines its tariffs differently. | D9: SDG 7
A10: 10.1787/5k49dv6c5xmv-en | B10: 7b76b91e09d54abc84b480f0db7f37e8 | C10: Low-wage residents are less likely to have access to a car, and commuter train lines and bus routes do not serve the south side of the Tri-State metro-region as well as they serve other parts of the region. Commuting times are even longer for those who commute across the region instead of following the hub and spoke system. Investment in public transport infrastructure does not sufficiently respond to demand for access to jobs, especially in lower -income neighbourhoods. While the Tri-State metro-region ranks high among OECD regions on many technology-based innovation indicators in terms of volume, its position has slipped and it is not among top regions when controlling for the size of its population and economy. For instance, in terms of patents per capita, the Tri-State metro-region ranked 23rd among OECD metro-regions and 11th among US metro-regions in 2007, the last year for which data are available, it ranked 27th and 12th, respectively, when adjusting for GDP (Table 1.5). These are hardly poor scores, but neither do they suggest that the Tri-State metro-region is fulfilling its innovation potential, particularly given that it ranks below so many other US metro-regions, including San Diego, San Francisco, New York, Boston, Los Angeles and Houston. | D10: NOT SDG 7
A11: 10.14217/9781848599574-13-en | B11: 2a678f26ee1012ffd2f13e781a70ad92 | C11: In its recent national plan, the Kiribati Development Plan 2016-19, the government has focused on improving infrastructure for the energy sector, including in renewables. The Kiribati Joint Implementation Plan on Climate Change and Disaster Risk Management notes the vulnerability of women, youth and children. In the past, Nauru’s economy was dependent on the phosphate industry, which also fuelled its energy demand. | D11: SDG 7
A12: 10.1787/9789264303119-en | B12: 07f17e85fc779d9e2b6f72fc7e884546 | C12: There are, however, many other potential impacts of accidents that are borne by the society as a whole and for which the internalisation is less straightforward and more complex. This is the case for the economic consequences on health and on the business property of a third party or on the environment. The entity liable for the accident is held responsible for the victims’ compensation, which ensures a certain internalisation of accident costs. | D12: NOT SDG 7
A13: 10.18356/cefc94d2-en | B13: 03aceee76df8ed0511df92e8262c69c8 | C13: Tracking progress towards achieving the Sustainable Development Goals requires the collection, processing, analysis and dissemination of data and statistics at the subnational, national, and regional levels, including those derived from official statistical systems and from new and innovative data sources. Many national statistical systems face serious challenges in this regard. As a result, accurate and timely information about certain aspects of people's lives are unknown, and many development challenges are still poorly understood. | D13: NOT SDG 7
A14: 10.1787/saeo-2017-8-en | B14: d974c1ee71b4e0f13b3df4e577c038e4 | C14: This corresponded to 32% of the total final energy consumption in the entire region. In parallel, India’s industry will play an increasingly important role as a driver for energy consumption in the region. While India’s industry accounted for 7% of the TFC in emerging Asia in 2013, this share is expected to increase to 13% by 2040. | D14: NOT SDG 7 | E14: This text is clearly about energy — but is specific to the objectives of SDG 7?
A15: 10.1787/5k49dv6c5xmv-en | B15: 7cf11d73e5bb2de5ea82cb92952a4065 | C15: Despite benefiting from past investments that have given it the second-longest commuter rail system in the US, investment has not kept up with the region’s needs. The Chicago Tri-State metro-region's competitiveness is being undermined in part by the growing inadequacy of its transportation infrastructure, which is typified by high rates of road congestion. Over 80% of the 4 009 stream miles assessed in Illinois are considered sufficiently polluted to prohibit primary human contact (e.g. swimming) (IEPA, 2010). | D15: NOT SDG 7
A16: 10.18356/fcd1ba6c-en | B16: e5b9f53cfda6ec1c21ceadb708f69d48 | C16: The world’s leaders call for massive investment in the developing world, and UNEP insists that this investment be in green development. The International Energy Agency estimates that some $44 trillion - over and above the business-as-usual scenario - will be needed by 2050 to meet even the lowest of the IPCC’s estimates for stabilizing global climate, most of it in the developing world. Indeed, the agreements and contracts signed contain clauses that make a sustainable approach to development well-nigh impossible. We call for one thing in our political declarations, but do a very different thing in reality. | D16: NOT SDG 7
A17: 10.1787/9789264188617-en | B17: 5541a26c0b86bbefdc00ed32a2db20ad | C17: Connecting an individual consumer to a power plant would be prohibitively expensive. However, each additional customer in the area reduces the average cost for all involved since the cost for connecting the additional customer is small. The physical link through the grid, however, not only links customers to a producer but also links all producers with each other. | D17: SDG 7
A18: 10.18356/d0196687-en | B18: 46d475ceaa034365791d668459aa60cb | C18: In addition to targets, the scope of instruments related to renewable energy being introduced is also broadening, demonstrating a deepening commitment towards renewable energy. For instance, Sri Lanka, under its latest energy sector development plan, is seeking to significantly increase the share of renewable energy while reducing petroleum imports, which have risen dramatically over the past decades (Sri Lanka, Ministry of Power and Renewable Energy, 2015). Pacific Island States, particularly the Cook Islands, Fiji, Samoa, Tuvalu, and Vanuatu, are leading the region in setting up an ambitious target of 100 per cent renewable energy. Additionally, under the country’s Energy Development Strategic Action Plan, hydro is expected to reach approximately 350 GW. | D18: SDG 7
A19: 10.1787/5k3wb8h0dg7h-en | B19: 08f9f7626f2c2baf6922a89d1b569335 | C19: Since 2007 Italy has provided tax relief for energy efficiency improvements to existing buildings including the installation of double-glazed windows, thermal insulation, high-efficiency boilers and the installation of solar panels. In 2009, building owners submitted 240,000 tax credit applications. As the programme was originally expected to be terminated in 2010, the number of applications in 2010 exceeded the previous year by around 71%. | D19: SDG 7
A20: 10.18356/893fb414-en | B20: 0c0f79ed4ec9a79fca8cc8392ba2c73f | C20: Energy poverty both signifies and drives overall poverty. More than 95% of the world population without electricity lives in Sub-Saharan Africa and developing Asia. In Sub-Saharan Africa, two-thirds of the population (620 million people) does not have access to electricity (IEA 2015a). Lack of electricity is generally most prevalent in rural areas. | D20: SDG 7
A21: 10.1787/5kg51nfc1321-en | B21: baebc2406cec83bb365787cbd8c18104 | C21: This option could lead to achieving the goal of a 40% reduction in energy intensity by 2030. The largest impact in energy intensity reduction will stem from efficiency improvements in the industrial and residential sectors. These products must be rapidly distributed on a large scale to achieve energy savings and reduce worldwide emissions. | D21: SDG 7
A22: 10.1787/5kgglrw4n7s0-en | B22: 29d5da40fe85cc32f02d021b960ce2f8 | C22: Large areas of about 500 000 km2 between Mumbai and Bhopal and in Gujarat are covered by thick basalt layers. If basalt is shown to be a suitable cap rock, it is estimated that this would allow storage of 300 Gt C02 (Sonde, 2007). Three of the nine sites designated so far for UMPP projects are on the coast not far from these potential storage areas.13 For inland sites relying on domestic coal, additional costs of USD 5/tC02 for transporting the C02 are expected compared to coastal sites (Mott MacDonald, 2008). Gas consumption has been rapidly growing at a rate of 8% between 1990 and 2009. | D22: NOT SDG 7
A23: 11.1002/pub/807e55db-ec047466-en | B23: 0e70884074d0aaff7bcc68c77c674a8b | C23: According to the battery specification, the voltage is 3.3 V and capacity is 0.8 Ah, which implies Cphone = 2.96 [12]. The final parameter is calculated as F = 0.375, derived from the average monthly charging expenses of $2.25 and the average price per charge of $0.20 [3]. Consequently, Ephone = 24.5. | D23: NOT SDG 7
A24: 10.18356/a81ec314-en | B24: ddd9ab387d2fc7238a7336e01f4480c3 | C24: These new partnerships arc working to provide the most cost-cfTcctivc electrification solutions, especially in remote communities that arc often the most disadvantaged in terms of electricity access. Though progress in electrification continued at the regional level, it slowed in the recent period, attributable to population growth in rural areas and the ongoing difficulty of extending services to remote areas. The rate of progress has declined in countries with the largest deficits, namely India, Bangladesh, and Myanmar, while the lowest access rates arc found among a number of Pacific Island and least developed State.4 Though urban areas in most economics have achieved universal access, rural areas lag behind, and, in a few cases with growing rural populations, rural electrification rates are falling. | D24: SDG 7 | E24: Typos in text
A25: 10.6027/9789289330954-4-en | B25: 138cf928dfb2490a23508d1175375c10 | C25: The country's potential in developing energy production technologies like wave power and osmotic power is also substantial. Norway is Europe's largest producer of hydropower, which delivers 99% of the country's electricity. On January 1 2008, Norway had a total installed capacity of 29030 MW at 699 hydropower stations larger than 1 MW. The Kvill-dal hydropower station in Rogaland county is Norway’s largest, with a maximum generating capacity of 1240 MW. | D25: SDG 7
A26: 10.6027/8a4204a0-en | B26: 3de3a33b6c50a93b9bf0e13ad8c0d089 | C26: Throughout this week, electricity prices are relatively high, with a clear day-night pattern. Night prices of around 50 EUR/MWh are close to the marginal cost of coal fired power plants, while the higher prices during day times of around 90-100 EUR/MWh are close to the marginal cost of natural gas fired power plants. Total consumption (red dashed line), however, is more constant over the week, because electricity consumption for heating and pumping (pumped storage) increases at night, when electricity prices are low. | D26: SDG 7
A27: 10.1787/5k49dv6c5xmv-en | B27: 23f59c31e9d0ddbb55a5f4b2df177abb | C27: Although its ranking in terms of GDP per capita among OECD metro-regions is not as high as it is in terms of GDP (16lh among the 90 metro-regions vs. 8lh), Chicago still counts among the big players in the OECD urban world. With GDP per capita over USD 55 000 in 2008, Chicago ranked higher than traditionally rich European metro-regions such as London, Stockholm, Helsinki, Amsterdam-Utrecht, Paris and Milan (Figure 1.2). Among US metro-regions, Chicago’s GDP per capita is similar to that of San Diego and Philadelphia, but below that of a number of US metro-regions such as New York, Los Angeles, San Francisco-Oakland, Boston or Houston. | D27: NOT SDG 7
A28: 10.18356/04b2e7d9-en | B28: 02bac9d17475999b1e8cd569255dca67 | C28: Strategies include building national and regional institutional capacity, cost sharing across borders, governance and regulations, enhancing access to modern energy, developing low-carbon and renewable domestic resources, improving regional energy cooperation and energy security, and promoting private sector participation in energy development. One key focus area is the development of hydropower potential, especially in the Lao People's Democratic Republic. Other activities pertaining to the energy sector include issues related to development of new and renewable sources (including small hydro), addressing the food-energy nexus, standardization and testing. These are captured in the BIMSTEC Memorandum of Understanding on Grid Interconnection. | D28: SDG 7
A29: 10.18356/73c3a080-en | B29: 62d5095d5d7ac925505de89dc9f446e1 | C29: Electricity access is commonly acknowledged as a basic need for human development (Scott and Seth, 2013), and has been described as a moral imperative, socially prudent and an economic necessity (GEA, 2016: 19). Aside from the public-good dimension of safe and reliable electricity supply, consumer protection and guaranteed access are important political-economy considerations (Bamber et al., Such energy-security concerns generally serve to reinforce State control and regulation of the electricity sector (Kuik et al., | D29: SDG 7
A30: 11.1002/pub/80f4cf5d-443a6582-en | B30: 96e05c536ae4c2f5e574d841bb9a5d41 | C30: The IAEA uses ICTs to support Member States in improving the functionality, safety and security of existing and new Nuclear Power Plants (NPPs) to ensure Affordable and Clean Energy (SDG 7) and improve Industry, Innovation and Infrastructure (SDG 9) by managing complex nuclear lifecycle technology systems. However, the applications of nuclear techniques - and the IAEA's work -in fact extend far beyond just nuclear energy. The IAEA's work extends into the education and training of health professionals in nuclear medicine techniques (SDGs 3 and 4 on health and education, respectively), monitoring of marine contaminants (SDG 14). | D30: SDG 7
A31: 10.1787/5kmh3nj5rzs4-en | B31: 04922124925495a57473febc0637998d | C31: Electrification of schools, however, is facing problems largely stemming from lack of information about the number of schools and their electrification status. Some municipalities fail to report the number of schools in their area or fail to provide accurate information on whether the schools are electrified or not. It is clear that this poses a major constraint for the entities in charge of the electrification of the as-yet un-electrified schools. | D31: SDG 7
A32: 10.1787/9789264236813-6-en | B32: 4cf9ebc3e44f6f6fe764d85a6f3abc99 | C32: In the short-term, a favourable future for the post-2015 sustainable development framework and an ambitious climate deal in Paris will not be possible without policy input. In the longer term, development objectives, including climate-related goals, need policy coherence as well as cash. Governments will need to adapt accordingly. | D32: NOT SDG 7
A33: 10.1787/5kgglrw4n7s0-en | B33: 0bc3671b295153b56be5727afdf182de | C33: On the production side (industry, commerce and agriculture), significant changes are expected as the economy grows nearly eightfold. This implies a massive expansion of the commercial/services sector (by a factor of six), a significant expansion of manufacturing activity, and more limited growth of activity in agriculture. However, water needs to be pumped from increasing depth and this is the main source of electricity demand in agriculture. Sources: IEA, 2009b, IEA, 2010a, IEA, 2009c. | D33: NOT SDG 7
A34: 10.18356/e9fa9dd4-en | B34: b9444ad7737b7622d6c248eff6b124ee | C34: Building an attractive rurality for young people is a major public policy challenge. Restoring the attractiveness of rural areas and achieving a new inclusive and equitable rurality is fundamental for rural territories to benefit from having more and better educated young people with a greater capacity for innovation. Thus, the rural agenda increasingly overlaps with the indigenous agenda, which includes an integral vision of that world, as territory and habitat, and not only as a space and production resource. Nonetheless, public must also be formulated for rural Afrodescendent populations, which are significant in various countries and constitute one of the least visible social groups. | D34: NOT SDG 7
A35: 10.1787/9789264096356-en | B35: bbae2a4b69f76f38ff7f5668b95ed44e | C35: Prices that are too low or too volatile discourage investment. Volatile prices also discourage consumers, particularly if their demand elasticity is low. It is a challenge to reach optimal investments levels. Liquid markets on the one side and long-term contracts on the other are important factors in providing investors in producer countries with the necessary visibility for investing in adequate capacity for production, storage and transport. | D35: NOT SDG 7
A36: 10.1787/9789264303119-en | B36: f6d5efdef2f9ea14a47527c057a04920 | C36: Compared with other instances of social costs, one may think of tobacco smoking or lead concentration in drinking water, this process has developed reasonably quickly. First, there is public awareness and opinion creation by means of public communication. These may be commercial means of communication, such as television or newspapers, but also non-commercial means of public awareness creation such as demonstrations, sit-ins, public speeches and the like. Again, information is the first step in internalising external costs. This way, the set of choices is transformed into new choices that integrate a higher share of public concerns. | D36: NOT SDG 7
... A56: 10.18356/5b6c49ea-en | B56: cb7bc8e45845a3c9f2ff7666fe2eaddd | C56: While it is correct that, aside from hydro (the potential of which is low but of high quality) and wind (which provides low-quality power), modern renewables continue to be significantly more expensive, economic limits are ultimately a lesser constraint, as they can be overcome with political will and special efForts. In fact, most energy technology debates completely disregard associated socio-political limits. In pluralistic democracies, the “not-in-my-backyard” (NIMBY) attitude is a powerful factor. | D56: SDG 7
A57: 10.18356/9a9b4252-en | B57: ab620f843a27c589f1c827210740acb6 | C57: For example, in Kenya, the paper manufacturer Chandaria Industries experienced savings of 40 per cent in energy, 48 percent in materials and 181 percent in water through involvement in the programme. Primary education is critical for developing a semi-skilled labour force. In low-income countries with large rural sectors, it can be vital for equipping farmers with the basic skills necessary to their being informed on and implementing sustainable agricultural and forestry practices. However, while the significance of achieving universal primary education is highlighted by its inclusion as a Millennium Development Goal, secondary, vocational and tertiary education are just as important in the field of green technology. Secondary education can provide core skills and knowledge needed for countries’ economic growth. Vocational schooling can be particularly useful in building technological competencies, successful vocational education also provides important links between education and industry. | D57: NOT SDG 7 | E57: "savings of 40 per cent in energy" → SDG 7 or not?
A58: 10.6027/9789289330718-10-en | B58: 87e874216f787a9abf3e6bb66f9fb712 | C58: Both systems also heat water, which integrates with the existing systems on campus to heat the buildings and provide hot water on campus. The system not only provides a sustainable energy system for the campus. For northern communities, the bioenergy project shows how future energy supply in areas with access to biomass may provide a sustainable energy supply. | D58: SDG 7
A59: 10.18356/e1196521-en | B59: 1c4e0e93da40bc305d44546ba12ada49 | C59: Additionally, renewable energy depends on variable wind, sun and exogenous conditions that are intermittent and more difficult to schedule than conventional fossil fuels. Given the limited and still developing electricity storage technology' at utility scale, it is economical to integrate intermittent renewables into larger, flexible electricity systems. The fossil fuel-based generation can be backed down when renewables are available, and with an electricity grid system that covers large geographical areas, the available average renewable resources would be easier to schedule. | D59: SDG 7
A60: 10.1787/9789264303119-en | B60: 3b67ed2c408fb9348a08325fa98f3dbe | C60: Furthermore, the most severe accidents have occurred in these stages. Most of the severe accidents involved tankers (collisions, explosions, fires and impact with the ground) and road accidents during regional distribution. In the oil chain, fatalities are fairly evenly distributed among workers and the public (Burgherr and Hirschberg, 2008a). | D60: NOT SDG 7
A61: 10.1787/9789264284319-9-en | B61: 5c18bc73a355e3bb2f41f8006c717c65 | C61: In addition, in 2014, EUR 5.8 mln from local budgets was used to finance eneigy efficiency measures (EEA, 2015). To date, there have been three calls. The first, in 2013, was launched for public institutions (including schools and hospitals), resulting in the selection of 86 projects worth a total of MDL 135 mln (about EUR 78 000 per project on average). | D61: SDG 7
A62: 10.1787/9789264202276-9-en | B62: 002f6840660d0e3051543f0ba55c82ca | C62: Several hotels and universities have also contracted private firm to construct wastewater treatment plants. Certain groups of consumers - particularly in industry tourism, commerce and agriculture - are expected to pay a tariff reflecting the full cost of water service provision. An increase in the water tariff was approved in late 2010, potentially helping to improve cost recovery, but the Ministry of Water and Irrigation stated in June 2012 that tariffs would not increase further in the near future. | D62: NOT SDG 7
A63: 10.1787/9789264278530-8-en | B63: 69c3547d0a4dde1fb18ad2e5e8654d0a | C63: It provides financial assistance to producers to install and maintain conservation practices on eligible agricultural and forest land. Energy conservation projects occur as part of the On-Farm Energy Initiative. Landscape AgEMPs have been available since 2009, and take a more holistic view of on-farm energy use, addressing issues, such as water use and erosion. Once the initial energy audit is complete, EQIP helps farmers develop a plan for implementing conservation practices. | D63: SDG 7 | E63: Energy conservation is not explicitly part of SDG 7, but should be considered SDG 7 for all intents and purposes?
A64: 10.18356/aac9b96c-en | B64: 05ad33f26eff857ea273b271a7c648f5 | C64: If too much water is stored behind the reservoir, sections of the river downstream from the reservoir can dry out if an insufficient amount of water is released at certain times of the year. This can lead to detrimental effects on animal and plant life downstream from the facility. Because of this, the channel may show signs of degradation (loss of sediments) or aggradation (accumulation of sediments), depending on whether floods can move the remaining incoming sediments. | D64: NOT SDG 7
A65: 10.18356/fcd1ba6c-en | B65: 2528f76d29c8a44be2769f22b552e9a8 | C65: Scepticism about the science is no longer an option: the world’s scientists have never been so unanimous, and so ominous, in their projections of future perils. The bad news is that too many participants in the debate consider a climate policy as consisting primarily of manipulating markets and prices. If the only tool available were market liberalization, then the solution to every problem would seem to be a matter of getting the prices right. But setting a price for carbon emissions is only the beginning of climate policy - not the end. | D65: NOT SDG 7
A66: 10.6027/9789289350167-3-en | B66: 5f74051cc940cc85f3e35bf0c678484f | C66: Data over the last 30 years suggests that, had we switched off government subsidies to fossil fuels, global emissions would have been more than a third lower than they actually were in 2010. Countries need to make a SWAP. Nordic countries have started this shift away from fossil fuel subsidies and toward government support to heat pumps as in Sweden, electric cars as in Norway and wind power in Denmark. | D66: SDG 7
A67: 10.1787/9789264224582-8-en | B67: 1b8096a8c65472366f9a60f60ec1c43b | C67: Every time a lender underwrites an eligible loan under this programme, the Connecticut Green Bank reserves a percentage of the loan principal (between 7.5-15%) for the lender in the event of a default (Energize CT, 2013). In the Connecticut model, to promote sound lending practices and share risks, the lender assumes the “first loss” (1.5%) on its portfolio before it is permitted to access the reserve fund. When discussing credit enhancement, the terms guarantee and insurance are often used interchangeably. | D67: NOT SDG 7
A68: 10.14217/9781848599574-13-en | B68: 3f5c7425b73a3628b98b9c9ef3317dde | C68: Under this Programme, homeowners received grants of up to US$6,000, deducted from their loans, for incorporating energy efficient measures into their homes, such as east-west orientation, white roofs, radiant barrier insulation under roofs, tinted windows, shading, ceiling fans, energy efficient lighting, and solar or instantaneous hot water systems. Following the adoption of the programme by the Palau Housing Authority, every new housing loan in Palau is eligible for the grant. The programme was later revised to include existing houses and for loans for solar PV. | D68: SDG 7
A69: 10.6027/9789289329163-8-en | B69: 2d9020466b5292b7a7e34b4d706eef80 | C69: This kind of system has been used successfully in Norway over a decade. As trees grow they continuously sequester carbon from the atmosphere. As cellulose, hemicellulose, lignin and other wood and bark components will be used for new purposes carbon can be stored for longer times in plastics and fabrics, and for shorter times in pharmaceutical products, chemicals, food and beverages, and so on. | D69: NOT SDG 7
A70: 10.1787/9789264180444-17-en | B70: 355caa7c220d2fa90e8c0f53f57bf574 | C70: The central government had been planning to capitalise on the good wind resource in the north of the country by increasing production of wind energy in these areas. It had selected several sites for locating wind farms. However, as the production of RE does not represent a concrete advantage for the hosting communities, and as there is a general perception that negative externalities are not being compensated for by the RE policy, they have tended to oppose them. | D70: SDG 7
A71: 10.18356/7e830810-en | B71: 229d51baaa3e76c88692e28a318c6720 | C71: Nigeria’s severe shortage of energy prompted the government to establish the University of Lagos National Centre for Energy Efficiency and Conservation in 2008, which is responsible for R&D in energy-efficiency and -conservation options and technologies. Following the 2010 enactment of the Russian Federation’s energy-efficiency legislation, the country has intensified efforts to create an R&D capacity in energy efficiency. The Russian Federation recognizes the role of a growing number of organizations engaged in research on improving energy efficiency, such as the Centre for Energy Efficiency, the Sustainable Energy Development Centre and the Institute of Energy Strategy. Standards for industrial equipment and system optimization can make it easier for firms to trade off capital and energy costs, but they can also impose limits on product choice and undesirable costs for adopters. | D71: SDG 7
A72: 10.18356/bcf52e9f-en | B72: 8852c54a8b7143f8c44fe58eff9c0b84 | C72: For low-level consumption the higher income group is charged 150 per cent of the price paid by the low-income group. With a sufficiently large consumer base that has enough high-income consumers, the water tariff enables the recovery of costs and the progressive structure supports poor people. The costs are associated with operating, maintaining and extending the water networks and providing basic levels of service. | D72: NOT SDG 7
A73: 10.6027/9789289329163-8-en | B73: f8a730809d29ac515eb7c5e34389c1b6 | C73: Consequently, there are more business options for the forest industry and forest-based raw materials than ever before. It still needs to be remembered that all four levels must be able to co-exist also in the future, even if their shares may change. All that can be produced without felling trees, e.g. carbon sinks, berries, game, tourism, etc. | D73: NOT SDG 7
A74: 10.1787/5k3wb8fmsz6h-en | B74: e1bcf5fe2ef14dbec5a8169cb1a36703 | C74: However, at high penetration levels of variable renewables, i.e. above 20% of annual generation, the increase of variability and uncertainty leads to new challenges. The four challenges are summarized in the following table. The system operator needs to have enough capacity available during the hours where electricity demand is the highest, plus a reserve margin to cope with contingencies. | D74: SDG 7
A75: 10.1787/5kmh3nj5rzs4-en | B75: be8a2af1834e66add5d63d32dcf2761e | C75: This debate is in line with South Africa's rural electrification agenda, as new power generation will be necessary to service more households. The average official50 unemployment figures are above 20% (see Table 33), excluding the under-employed in the rural and urban areas or those who are not registered in employment agencies. Payment for electricity is an issue for people who have no or very little income. Many cases of domestic violence in newly electrified households have been amply documented. It is argued that domestic trouble starts over priorities when resources are scarce (Habitat for Humanity, 2009). However, the long-term effect of ensuring universal access to electricity should lead to general opportunities for a broad-based economic development. | D75: SDG 7 | E75: typos in text
A76: 10.1787/5km5zrrvzr42-en | B76: ab3c26a36fa747b6fc4899fb49a3dab5 | C76: Some energy efficient devices (e.g. variable speed drives) may be more susceptible to voltage or frequency fluctuations on the grid. Energy efficient devices moreover often involve new technology with low operating experience. The highly technical realities underlying such investments result in investors demanding an implicitly higher rate of return to offset the perceived higher risk of energy efficiency projects. Finally, a perception of high transaction costs can emerge because of the small size of EE projects relative to other projects. | D76: SDG 7
A77: 10.1787/5km5zrrvzr42-en | B77: 305254be699b0759eb03d5ef6b6c603d | C77: More specifically, it analyses the impact of risks - actual and perceived -associated with EE projects. Much has been written about the many barriers to energy-efficiency investments, including market organisation, price distortions, split incentives, lack of information, transaction costs, institutional biases, product availability, regulatory policy, and others.3 This report does not delve into the full array of these barriers. Instead, it focuses on the financial and risk barriers. | D77: SDG 7
A78: 10.1787/9789264180444-17-en | B78: 0d02b195616490f828e9c7e99e293799 | C78: The University of Troms0 has over 9 000 students and some 2 500 employees. Since Troms County has only 1% of its surface area classed as cultivable land, agriculture is a relatively minor part of land use. It is mainly located around the coast and was traditionally combined with fishing to form a key part of rural livelihoods. Troms County is at the northern limits of agricultural production possibilities, but the Gulf Stream enables some seasonal farming around the coasts and fjords, while the Sami people also carry out traditional reindeer herding. | D78: NOT SDG 7
A79: 10.14217/9781848599574-13-en | B79: 1982e8b824ff8e01f7ec3ac363f26441 | C79: Electricity grids in the Pacific will need to be strongly interconnected, flexible enough to accommodate this change, and resilient enough to withstand climate impacts, as well as cope with potential demand growth from growing populations and growing electric vehicle use. Commonwealth Pacific small states are more dependent on the fossil fuels used in cars, trucks and boats than for generating electricity, and more cost-effective displacement of fossil fuel can occur through energy efficiency. However, the attention and funding of development partners is not always directed accordingly to these areas. Moreover, although this is improving, consumers generally lack awareness on how they can reduce their energy consumption or be more energy efficient. The International Renewable Energy Agency (IRENA) estimates that deploying renewables worldwide on the scale necessary to limit global temperature rise below 2 degrees would require current investment to double by 2020, and triple by 2030 to around US$900 billion annually (IRENA 2016b). | D79: SDG 7
A80: 10.18356/9a9b4252-en | B80: 97d9dbfe4eb2a9a7c84995452bf460f9 | C80: An innovative economy is based on interactive learning, information exchange, timely availability of finance and other resources, and coordination among firms, universities, research centres, policymakers and other actors. Building technological capacities can help developing countries “catch up” with more advanced countries, and innovation policy must play an important role in facilitating sustainable development. The present chapter argues that green sustainable development-oriented innovation policies should be an integral part of countries’ national development strategies. | D80: NOT SDG 7
A81: 10.1787/5k49dv6c5xmv-en | B81: eb2688a4a4cc3e62cf272196046f4f3e | C81: Green job growth over the next 5-10 years is expected to be highest in the building and transportation sectors. Higher energy consumption, rising greenhouse gas emissions, road congestion and deteriorating water quality are the negative externalities that have come with urban growth. Many metropolitan regions across the OECD have turned their attention to the concept of green growth as a means of increasing economic competitiveness through addressing environmental challenges (Box 1.1). What do we mean by urban green growth? | D81: NOT SDG 7
A82: 10.6027/fcafdf5b-en | B82: 52148c3d2fdb1fb63687cf5e2dbe698c | C82: Greenland, the Faroe Islands and Svalbard have experienced an increase in tourism levels as well, though at a lower level than Iceland, with a growth ranging from 15% to 45% since 2012. As the duration of the visits have not increased, the increased spending is caused by a higher daily spending by the tourists. Tourism may create short and long-term profits and jobs for a region leading to economic growth, provided it is managed sustainably. | D82: NOT SDG 7
A83: 10.1787/5k9312v21l6f-en | B83: 60a148ee953bd6d9349f85d897641289 | C83: These initiatives need to be encouraged, carefully monitored, and expanded where successful. Fiona Stewart is a principal administrator in the Financial Affairs Division of the OECD’s Directorate for Financial and Enterprise Affairs. The views expressed are the sole responsibility of the authors and do not reflect those of their organisations or the governments of OECD Member countries. The authors are solely responsible for any errors. | D83: NOT SDG 7
A84: 10.1787/5km4knxj9tf3-en | B84: 0bb74afcdcfc75d8381638bb154c4a29 | C84: In most countries governments are significant energy users, and government operations present significant opportunities for efficiency improvements. By procuring energy efficiency services from the private sector, governments can help build capacity and critical mass within this important service sector. This is a win-win option, since energy use is major public sector expense. | D84: SDG 7
A85: 10.18356/7e830810-en | B85: 0934a08badd098559da1fff3aedb86a0 | C85: Some firms might be more sensitive to some types of barriers than to others. One is commonly known as the rebound effect. An example is the driver who replaces a car with a more fuel-efficient model, only to take advantage of its cheaper running costs to drive further and more often. Rebound effects have long been neglected, but their consequences could be profound. | D85: NOT SDG 7
A86: 10.1787/9789264115118-6-en | B86: 8d5c4d3906214299799340e13fe6047d | C86: The project is huge on several scales: at 4 800 MW, the plant will be the seventh-largest in the world, and the estimated construction costs of USD 17.8 billion is equivalent to 10% of South Africa’s GDP. The electricity from the plant will provide much-needed supply to South Africa’s mining and other industries, as well as generally supporting the quality of supply for household users. And being situated close to large low-cost domestic resources of coal provides a secure supply of fuel. The decision by the South African government to support this project was backed up by the World Bank which is providing just over USD 3 billion of loans, and USD 2.5 billion from the African Development Bank (Sovacool and Rafey, 2011). | D86: SDG 7 | E86: tricky: quality of supply + low cost vs fossil fuels
A87: 10.18356/a2206e44-en | B87: 4c567911242e96a326b0d95605fa3573 | C87: Since poor households tend to consume little electricity, they would likely benefit from overall reduced rates, or a “lifeline rate”. Commercial and industrial users could be charged higher rates, while SMEs would need more favourable treatment. Other ways to mobilize resources through tariffs include setting a transparent surcharge applied to higher income, commercial or industrial consumers, and using the proceeds to extend the service to poorer consumers. | D87: SDG 7
A88: 10.18356/665c59ff-en | B88: 85b6a7e4c9eb4f7a2467b2b1b96596cd | C88: The surveys fed into the "Sustainability Index Consortium", an open platform database that allowed for analysis of the information collected from Walmart's 100,000 suppliers. At a Global Sustainability Milestone Meeting in Beijing in 2008, Walmart's chief executive officer announced plans to expand participation to 70 per cent of suppliers by 2017, making clear that failure to participate in the index would lead to removal of the firm from Walmart's supply chain. They typically address quality, cost and delivery procedures and, increasingly, environmental processes. | D88: NOT SDG 7
A89: 10.1787/5kg7068011hb-en | B89: b4ff5d93a99f6112f717a546f404b3c4 | C89: In 2009, wind energy accounted for 56%of global clean energy investment. Investment in solar energy follows wind’s leading position and is poised to expand as a result of declining solar energy prices and the potential of new, thin-film technologies as noted by Pew (2010). New investment in biomass, geothermal and small hydro seems to play a marginal role in the total market (see Figure 7). Financial sector new investment (incl. | D89: SDG 7
A90: 10.18356/a2206e44-en | B90: 4a01cc17157fe6fb3a1155729326dc7f | C90: By creating an enabling environment for the emergence of income-generating or income-improving activities, electrification projects can directly contribute to poverty eradication policies. Benefits for agricultural production include irrigation (perhaps with the use of water pumps), increased utilization of motors, food processing, refrigeration and also better access to training through information and communication technologies (ICT). Successful electrification programmes linked to agriculture would not only result in more competitive farming and create employment opportunities, but would also improve trading opportunities and local food security, including through the reduction of post-harvest losses. | D90: SDG 7
A91: 10.18356/6e8bb756-en | B91: 30c83a848738f5d86d6bd284107e5232 | C91: In the EU, for instance, there was a rapid increase in the market share of the most energy-efficient appliances. Sales of Class A refrigerators increased from less than 5 per cent of total sales in 1995 to 23 per cent in 2000 and 61 per cent in 2005, in addition, 19 per cent of refrigerators sold in 2005 were in the two new, more efficient classes (A+ and A++). For washing machines, progress was even more rapid: with an increase in sales of 1 per cent in 1996, 38 per cent in 2000 and 90 per cent in 2005. | D91: SDG 7
A92: 10.1787/5kg20639kgkj-en | B92: 66e3db40126ffb45baee5598c3121304 | C92: The development of a shared evidence base and understanding of the city’s problems will help future planning and enable Sydney to better showcase its strengths and weaknesses to State and Federal policy makers. This is particularly relevant to the sustainability agenda where key stakeholders were beginning to come together across the city. Building on these relationships and partnerships should be a priority, in order act as a catalyst for a citywide sustainability strategy, which could potentially be seen as a working template for future city wide strategic partnerships and work. | D92: NOT SDG 7
A93: 10.1787/9789264115118-7-en | B93: 10c26acfd397b509bd035a8bd93401d5 | C93: According to the IEA’s WEO-2011, 1.3 billion people - nearly 20% of world population - currently lack access to electricity and about 2.7 billion people - 40% of the world population - rely on the traditional use of biomass for cooking (IEA, 2011a). The outlook suggests that the problem will persist and even deepen in some places. The IEA and World Health Organization estimate that household air pollution from the use of biomass in inefficient stoves would lead to more than 4 000 premature deaths per day in 2030, greater than estimates for premature deaths from malaria, tuberculosis or Human Immunodeficiency Virus (HIV)/Acquired immune deficiency syndrome (AIDS) (IEA, 2011a). The index seeks to capture the quality of energy services as well as their quantity. It is calculated in such a way as to mirror the United Nations Development Programme’s Human Development Index. | D93: SDG 7
A94: 10.1787/5k49dv6c5xmv-en | B94: d8af30adabb56201cb5606f036364f14 | C94: Significant restructuring of the region’s economy over the past twenty years has transformed the demand for skills, making it more difficult for low-skilled workers to find employment in more knowledge-based, innovation-driven, growing sectors. Despite the higher-than-average levels of educational attainment in the region, chronic low graduation rates from the region’s public post-secondary educational institutions, particularly community colleges, slows the upgrading of the region’s workforce. Further, the increase in specialisation towards higher value-added activities in the Chicago Tri-State metro-region has not gone hand in hand with an increase of the share of the labour force with high qualifications. | D94: NOT SDG 7
A95: 10.18356/fcd1ba6c-en | B95: ac46c07bfea1873694224ecfd4ca833c | C95: For developing countries, it is based on the evolution of absolute poverty (i.e. the proportion of population living on less than $1 a day). For developed countries, poverty is measured as relative income poverty (i.e. with the threshold set as a percentage of the median income in each countty in each of the years considered). Only a few OECD countries have “official” measures of poverty that rely on “absolute" standards, typically in the form of the cost of a basket of goods and services required to assure minimum living conditions and indexed for price changes over time. | D95: NOT SDG 7
A96: 10.18356/95417570-en | B96: 0856c7a172a9fe91126e6e9d82492c9b | C96: Sources of energy like geothermal, tidal power, hydrogen, nuclear fusion and so forth will require a more visionary approach and even greater scientific and technological advancement. These advances, in turn, will require substantial investment which, at present, is not forthcoming from public and private sources on a large enough scale. Only by ensuring a reliable, affordable supply of energy will it be possible to chart a stable course for economic recovery and growth. Addressing energy insecurity and transforming the global energy system must therefore constitute a major priority for any long-term programme of economic and climate stabilization in advanced countries. Such a course will simultaneously address the climate challenge. | D96: SDG 7
A97: 10.18356/95417570-en | B97: c6c0c3f173e584185fcd6269ca3ff227 | C97: However, in the earlier stages, RD&D accounts for a larger share of performance improvements and cost reductions. While the depression is very disruptive and particularly destructive for the poor, it does at least potentially sow the seeds of renewal, provided that the world is prepared to make the necessary institutional and financial investments. This needs to occur without risking irreversible changes in ecological, biophysical and biochemical systems. | D97: NOT SDG 7
A98: 10.1787/5k9crzjbpkkc-en | B98: 5cbab6e5118d697ee7147b8b0b34ecf1 | C98: A discussion of the rebound effect in energy efficiency is needed that incorporates not just the expected energy savings from energy efficiency but also the wider socioeconomic outcomes. Policy measures are needed to overcome the market and behavioural failures that lead to less investment in energy efficiency than is optimal. It is important to overcome critical challenges that involve complex synergies and trade-offs among the different aspects of energy efficiency policy. | D98: SDG 7
... A101: 10.1787/9789264188617-en | B101: e18ef8fe59453b36226b3a625bcc78b6 | C101: In the scenario with an 80% renewable share, electricity prices are considerably lower compared to the other scenarios and the number of hours with electricity prices equal to or below zero rises to an astonishing 2 850 hours. A reduced occurrence of electricity prices higher than variable costs in combination with reduced utilisation hours means lower infra-marginal rents for recovering capital costs. Consequently, it is highly questionable whether conventional power plants can be profitably operated with high shares of renewables in energy-only markets with price formation being based on marginal costs. | D101: SDG 7

Sheet Gib
A1: DOI | B1: Text ID | C1: Text | D1: Label | E1: Comments (optional)
A2: 10.1787/9789264236813-6-en | B2: 4cf9ebc3e44f6f6fe764d85a6f3abc99 | C2: In the short-term, a favourable future for the post-2015 sustainable development framework and an ambitious climate deal in Paris will not be possible without policy input. In the longer term, development objectives, including climate-related goals, need policy coherence as well as cash. Governments will need to adapt accordingly. | D2: NOT SDG 7
A3: 10.18356/95417570-en | B3: 0856c7a172a9fe91126e6e9d82492c9b | C3: Sources of energy like geothermal, tidal power, hydrogen, nuclear fusion and so forth will require a more visionary approach and even greater scientific and technological advancement. These advances, in turn, will require substantial investment which, at present, is not forthcoming from public and private sources on a large enough scale. Only by ensuring a reliable, affordable supply of energy will it be possible to chart a stable course for economic recovery and growth. Addressing energy insecurity and transforming the global energy system must therefore constitute a major priority for any long-term programme of economic and climate stabilization in advanced countries. Such a course will simultaneously address the climate challenge. | D3: SDG 7
A4: 10.1787/5kg20639kgkj-en | B4: 448cfebe196e9aed00270dbd6ed9d3ce | C4: Not only does this have potentially negative effects on gender pay gaps and levels of social inclusion, but also Sydney is not fully utilising the skills currently available in its workforce. Moreover, this mixed labour market picture suggests that the low levels of unemployment are masking higher levels of inactivity. Youth unemployment is also high, although this is very much a global trend amongst advanced economies. | D4: NOT SDG 7
A5: 11.1002/pub/80f4cf5d-443a6582-en | B5: 96e05c536ae4c2f5e574d841bb9a5d41 | C5: The IAEA uses ICTs to support Member States in improving the functionality, safety and security of existing and new Nuclear Power Plants (NPPs) to ensure Affordable and Clean Energy (SDG 7) and improve Industry, Innovation and Infrastructure (SDG 9) by managing complex nuclear lifecycle technology systems. However, the applications of nuclear techniques - and the IAEA's work -in fact extend far beyond just nuclear energy. The IAEA's work extends into the education and training of health professionals in nuclear medicine techniques (SDGs 3 and 4 on health and education, respectively), monitoring of marine contaminants (SDG 14). | D5: SDG 7
A6: 10.14217/9781848599574-13-en | B6: 2a678f26ee1012ffd2f13e781a70ad92 | C6: In its recent national plan, the Kiribati Development Plan 2016-19, the government has focused on improving infrastructure for the energy sector, including in renewables. The Kiribati Joint Implementation Plan on Climate Change and Disaster Risk Management notes the vulnerability of women, youth and children. In the past, Nauru’s economy was dependent on the phosphate industry, which also fuelled its energy demand. | D6: SDG 7
A7: 10.18356/fcd1ba6c-en | B7: e5b9f53cfda6ec1c21ceadb708f69d48 | C7: The world’s leaders call for massive investment in the developing world, and UNEP insists that this investment be in green development. The International Energy Agency estimates that some $44 trillion - over and above the business-as-usual scenario - will be needed by 2050 to meet even the lowest of the IPCC’s estimates for stabilizing global climate, most of it in the developing world. Indeed, the agreements and contracts signed contain clauses that make a sustainable approach to development well-nigh impossible. We call for one thing in our political declarations, but do a very different thing in reality. | D7: NOT SDG 7
A8: 10.1787/5kgglrw4n7s0-en | B8: 0bc3671b295153b56be5727afdf182de | C8: On the production side (industry, commerce and agriculture), significant changes are expected as the economy grows nearly eightfold. This implies a massive expansion of the commercial/services sector (by a factor of six), a significant expansion of manufacturing activity, and more limited growth of activity in agriculture. However, water needs to be pumped from increasing depth and this is the main source of electricity demand in agriculture. Sources: IEA, 2009b, IEA, 2010a, IEA, 2009c. | D8: NOT SDG 7
A9: 10.1787/5bbcdeac-en | B9: 6194ce1da1e7aed5cd5e9929d75f9742 | C9: An enabling policy environment is important for the development of a strong and competitive renewable energy sector to supply both industrial and domestic consumers. Section 3 identifies key enabling policy factors required for the replicability and accelerated uptake of the available renewable energy solutions throughout the mining sector. Major companies and conglomerates, among others, such as Glencore, Barrick Gold, Rio Tinto, Antofagasta, Codelco and IAMGOLD have all made use of renewable energy in their mines (Table 2.1). | D9: SDG 7
A10: 10.1787/5k49dv6c5xmv-en | B10: eb2688a4a4cc3e62cf272196046f4f3e | C10: Green job growth over the next 5-10 years is expected to be highest in the building and transportation sectors. Higher energy consumption, rising greenhouse gas emissions, road congestion and deteriorating water quality are the negative externalities that have come with urban growth. Many metropolitan regions across the OECD have turned their attention to the concept of green growth as a means of increasing economic competitiveness through addressing environmental challenges (Box 1.1). What do we mean by urban green growth? | D10: NOT SDG 7
A11: 10.18356/e9fa9dd4-en | B11: b5fdc51af03856168f0dd458f1c47547 | C11: The proportion of the region's population living in slums fell from 34% in 1990 to 21% in 2014 (see figure V.19). In terms of absolute numbers however, although 2 million people left the slums, over 100 million still live in such settlements. This is exemplified by the negotiation of the New Urban Agenda, adopted at the United Nations Conference on Housing and Sustainable Urban Development (Habitat III), held in 2016. | D11: NOT SDG 7
A12: 10.1787/9789264236813-6-en | B12: a5c19681ebb07ae9341468a13396d831 | C12: In 2012,63% of trips during morning and evening peak times were on public transport, compared to 59% in 2008. To increase this number even further, the LTA aims to make the transport system even more accessible and competitive. By 2030, 80% of households should be within a 10-minute walk of a train station, 85% of public transport journeys (less than 20km) will be completed within 60 minutes and 75% of all journeys in peak hours will be via public transport. | D12: NOT SDG 7
A13: 10.1787/5kg51nfc1321-en | B13: baebc2406cec83bb365787cbd8c18104 | C13: This option could lead to achieving the goal of a 40% reduction in energy intensity by 2030. The largest impact in energy intensity reduction will stem from efficiency improvements in the industrial and residential sectors. These products must be rapidly distributed on a large scale to achieve energy savings and reduce worldwide emissions. | D13: TO DO
... A101: 10.18356/7e830810-en | B101: 0934a08badd098559da1fff3aedb86a0 | C101: Some firms might be more sensitive to some types of barriers than to others. One is commonly known as the rebound effect. An example is the driver who replaces a car with a more fuel-efficient model, only to take advantage of its cheaper running costs to drive further and more often. Rebound effects have long been neglected, but their consequences could be profound. | D101: TO DO

Sheet Jean-Baptiste
A1: DOI | B1: Text ID | C1: Text | D1: Label | E1: Comments (optional)
A2: 10.18356/6e8bb756-en | B2: 30c83a848738f5d86d6bd284107e5232 | C2: In the EU, for instance, there was a rapid increase in the market share of the most energy-efficient appliances. Sales of Class A refrigerators increased from less than 5 per cent of total sales in 1995 to 23 per cent in 2000 and 61 per cent in 2005, in addition, 19 per cent of refrigerators sold in 2005 were in the two new, more efficient classes (A+ and A++). For washing machines, progress was even more rapid: with an increase in sales of 1 per cent in 1996, 38 per cent in 2000 and 90 per cent in 2005. | D2: NOT SDG 7
A3: 10.1787/5k9crzjbpkkc-en | B3: 5cbab6e5118d697ee7147b8b0b34ecf1 | C3: A discussion of the rebound effect in energy efficiency is needed that incorporates not just the expected energy savings from energy efficiency but also the wider socioeconomic outcomes. Policy measures are needed to overcome the market and behavioural failures that lead to less investment in energy efficiency than is optimal. It is important to overcome critical challenges that involve complex synergies and trade-offs among the different aspects of energy efficiency policy. | D3: SDG 7
A4: 10.18356/5b6c49ea-en | B4: cb7bc8e45845a3c9f2ff7666fe2eaddd | C4: While it is correct that, aside from hydro (the potential of which is low but of high quality) and wind (which provides low-quality power), modern renewables continue to be significantly more expensive, economic limits are ultimately a lesser constraint, as they can be overcome with political will and special efForts. In fact, most energy technology debates completely disregard associated socio-political limits. In pluralistic democracies, the “not-in-my-backyard” (NIMBY) attitude is a powerful factor. | D4: SDG 7
A5: 10.1787/5kg51nfc1321-en | B5: baebc2406cec83bb365787cbd8c18104 | C5: This option could lead to achieving the goal of a 40% reduction in energy intensity by 2030. The largest impact in energy intensity reduction will stem from efficiency improvements in the industrial and residential sectors. These products must be rapidly distributed on a large scale to achieve energy savings and reduce worldwide emissions. | D5: SDG 7
A6: 10.1787/5kg20639kgkj-en | B6: 66e3db40126ffb45baee5598c3121304 | C6: The development of a shared evidence base and understanding of the city’s problems will help future planning and enable Sydney to better showcase its strengths and weaknesses to State and Federal policy makers. This is particularly relevant to the sustainability agenda where key stakeholders were beginning to come together across the city. Building on these relationships and partnerships should be a priority, in order act as a catalyst for a citywide sustainability strategy, which could potentially be seen as a working template for future city wide strategic partnerships and work. | D6: NOT SDG 7
A7: 10.18356/fcd1ba6c-en | B7: 1b8b3de79df5c5923493cd5050d3ceae | C7: Indeed, the rising incidence of non-standard employment has widened the gap in earnings distribution and contributed to an increase in poverty. In Germany, the total income gain of households has gone to the richest 10 per cent of households since 2003 (Parma and Vontobel, 2009:129). The recent widening of inequalities marked a complete reversal of the previous trend. | D7: NOT SDG 7
A8: 10.6027/9789289329163-8-en | B8: 2d9020466b5292b7a7e34b4d706eef80 | C8: This kind of system has been used successfully in Norway over a decade. As trees grow they continuously sequester carbon from the atmosphere. As cellulose, hemicellulose, lignin and other wood and bark components will be used for new purposes carbon can be stored for longer times in plastics and fabrics, and for shorter times in pharmaceutical products, chemicals, food and beverages, and so on. | D8: NOT SDG 7
A9: 10.1787/9789264303119-en | B9: f6d5efdef2f9ea14a47527c057a04920 | C9: Compared with other instances of social costs, one may think of tobacco smoking or lead concentration in drinking water, this process has developed reasonably quickly. First, there is public awareness and opinion creation by means of public communication. These may be commercial means of communication, such as television or newspapers, but also non-commercial means of public awareness creation such as demonstrations, sit-ins, public speeches and the like. Again, information is the first step in internalising external costs. This way, the set of choices is transformed into new choices that integrate a higher share of public concerns. | D9: NOT SDG 7
A10: 10.1787/9789264115118-6-en | B10: 8d5c4d3906214299799340e13fe6047d | C10: The project is huge on several scales: at 4 800 MW, the plant will be the seventh-largest in the world, and the estimated construction costs of USD 17.8 billion is equivalent to 10% of South Africa’s GDP. The electricity from the plant will provide much-needed supply to South Africa’s mining and other industries, as well as generally supporting the quality of supply for household users. And being situated close to large low-cost domestic resources of coal provides a secure supply of fuel. The decision by the South African government to support this project was backed up by the World Bank which is providing just over USD 3 billion of loans, and USD 2.5 billion from the African Development Bank (Sovacool and Rafey, 2011). | D10: SDG 7
A11: 10.1787/5k3w6ljtrj0q-en | B11: 6cc45f35957a70dc1f450fbc4ab74b22 | C11: This motivation is still strong with the reality of recession and austerity in many countries making the idea of green employment growth a welcome antidote to the high unemployment rates. Capacity building and skill development within the regional communities are also important benefits of green initiatives. | D11: NOT SDG 7
A12: 10.18356/04b2e7d9-en | B12: 02bac9d17475999b1e8cd569255dca67 | C12: Strategies include building national and regional institutional capacity, cost sharing across borders, governance and regulations, enhancing access to modern energy, developing low-carbon and renewable domestic resources, improving regional energy cooperation and energy security, and promoting private sector participation in energy development. One key focus area is the development of hydropower potential, especially in the Lao People's Democratic Republic. Other activities pertaining to the energy sector include issues related to development of new and renewable sources (including small hydro), addressing the food-energy nexus, standardization and testing. These are captured in the BIMSTEC Memorandum of Understanding on Grid Interconnection. | D12: SDG 7
A13: 10.18356/7e830810-en | B13: 2cd4fdfbe38a99441412e37921a2da5d | C13: Given industry’s substantial contribution to global energy intensity, credible specific industrial energy-efficiency targets must be formulated. But to keep increases in industrial energy consumption to the minimum required to satisfy development needs, future efficiency efforts must be ambitious. They must double today’s pace and reach energy intensity reduction rates similar to those in the 1990s. Doubling the industrial energy-intensity reduction rate is consistent with a similar exhortation made at the global level in the AGECC (2010) report. | D13: SDG 7
... A31: 10.6027/fcafdf5b-en | B31: 52148c3d2fdb1fb63687cf5e2dbe698c | C31: Greenland, the Faroe Islands and Svalbard have experienced an increase in tourism levels as well, though at a lower level than Iceland, with a growth ranging from 15% to 45% since 2012. As the duration of the visits have not increased, the increased spending is caused by a higher daily spending by the tourists. Tourism may create short and long-term profits and jobs for a region leading to economic growth, provided it is managed sustainably. | D31: NOT SDG 7
A32: 10.1787/9789264284319-9-en | B32: 5c18bc73a355e3bb2f41f8006c717c65 | C32: In addition, in 2014, EUR 5.8 mln from local budgets was used to finance eneigy efficiency measures (EEA, 2015). To date, there have been three calls. The first, in 2013, was launched for public institutions (including schools and hospitals), resulting in the selection of 86 projects worth a total of MDL 135 mln (about EUR 78 000 per project on average). | D32: NOT SDG 7 | E32: Could be labelled SDG 7 but there is a spelling mistake in "eneigy"
A33: 10.18356/f00277f1-en | B33: 51623ee78c26efaa4fbc70e63e7d503a | C33: Energy efficiency targets are now in place at all levels of government. Nevertheless, in all countries and economic sectors, increased synergies between renewables and energy efficiency measures are possible, and oftentimes strengthening one will, in turn, strengthen the other. In both technical and policy contexts, renewable energy can have a positive effect on energy efficiency—and vice versa. Each of these steps presents opportunities to strengthen the energy efficiency of the overall system. | D33: SDG 7
A34: 10.6027/9789289330954-4-en | B34: 138cf928dfb2490a23508d1175375c10 | C34: The country's potential in developing energy production technologies like wave power and osmotic power is also substantial. Norway is Europe's largest producer of hydropower, which delivers 99% of the country's electricity. On January 1 2008, Norway had a total installed capacity of 29030 MW at 699 hydropower stations larger than 1 MW. The Kvill-dal hydropower station in Rogaland county is Norway’s largest, with a maximum generating capacity of 1240 MW. | D34: SDG 7
A35: 10.1787/5k3wb8h0dg7h-en | B35: 08f9f7626f2c2baf6922a89d1b569335 | C35: Since 2007 Italy has provided tax relief for energy efficiency improvements to existing buildings including the installation of double-glazed windows, thermal insulation, high-efficiency boilers and the installation of solar panels. In 2009, building owners submitted 240,000 tax credit applications. As the programme was originally expected to be terminated in 2010, the number of applications in 2010 exceeded the previous year by around 71%. | D35: SDG 7
A36: 10.6027/9789289329163-8-en | B36: f8a730809d29ac515eb7c5e34389c1b6 | C36: Consequently, there are more business options for the forest industry and forest-based raw materials than ever before. It still needs to be remembered that all four levels must be able to co-exist also in the future, even if their shares may change. All that can be produced without felling trees, e.g. carbon sinks, berries, game, tourism, etc. | D36: NOT SDG 7
A37: 10.1787/5km5zrrvzr42-en | B37: ab3c26a36fa747b6fc4899fb49a3dab5 | C37: Some energy efficient devices (e.g. variable speed drives) may be more susceptible to voltage or frequency fluctuations on the grid. Energy efficient devices moreover often involve new technology with low operating experience. The highly technical realities underlying such investments result in investors demanding an implicitly higher rate of return to offset the perceived higher risk of energy efficiency projects. Finally, a perception of high transaction costs can emerge because of the small size of EE projects relative to other projects. | D37: SDG 7
A38: 10.18356/9a9b4252-en | B38: 97d9dbfe4eb2a9a7c84995452bf460f9 | C38: An innovative economy is based on interactive learning, information exchange, timely availability of finance and other resources, and coordination among firms, universities, research centres, policymakers and other actors. Building technological capacities can help developing countries “catch up” with more advanced countries, and innovation policy must play an important role in facilitating sustainable development. The present chapter argues that green sustainable development-oriented innovation policies should be an integral part of countries’ national development strategies. | D38: NOT SDG 7
A39: 10.1787/9789264180444-17-en | B39: 0d02b195616490f828e9c7e99e293799 | C39: The University of Troms0 has over 9 000 students and some 2 500 employees. Since Troms County has only 1% of its surface area classed as cultivable land, agriculture is a relatively minor part of land use. It is mainly located around the coast and was traditionally combined with fishing to form a key part of rural livelihoods. Troms County is at the northern limits of agricultural production possibilities, but the Gulf Stream enables some seasonal farming around the coasts and fjords, while the Sami people also carry out traditional reindeer herding. | D39: NOT SDG 7
A40: 10.1787/5k49dv6c5xmv-en | B40: d8af30adabb56201cb5606f036364f14 | C40: Significant restructuring of the region’s economy over the past twenty years has transformed the demand for skills, making it more difficult for low-skilled workers to find employment in more knowledge-based, innovation-driven, growing sectors. Despite the higher-than-average levels of educational attainment in the region, chronic low graduation rates from the region’s public post-secondary educational institutions, particularly community colleges, slows the upgrading of the region’s workforce. Further, the increase in specialisation towards higher value-added activities in the Chicago Tri-State metro-region has not gone hand in hand with an increase of the share of the labour force with high qualifications. | D40: NOT SDG 7
A41: 10.1787/5k3wb8fmsz6h-en | B41: e45e89c440f096f7dedfee2104c05be1 | C41: Looking forward, the development of storage technologies and the development of international interconnections are foreseen to further facilitate the integration of wind and solar power. In these situations, balancing the power system during periods of low load will necessitate further adaptations to maintain the physical parameters of the network. An ongoing IEA work within the Grid Integration of Variable Renewables project (GIVAR) analyses these options in more detail. Hence, it will be necessary in the next 20 years to keep some conventional power plants online to provide ancillary services and ramp-up capabilities. | D41: SDG 7
A42: 10.1787/9789264303119-en | B42: 3b67ed2c408fb9348a08325fa98f3dbe | C42: Furthermore, the most severe accidents have occurred in these stages. Most of the severe accidents involved tankers (collisions, explosions, fires and impact with the ground) and road accidents during regional distribution. In the oil chain, fatalities are fairly evenly distributed among workers and the public (Burgherr and Hirschberg, 2008a). | D42: NOT SDG 7
A43: 10.1787/5k3wb8fmsz6h-en | B43: e1bcf5fe2ef14dbec5a8169cb1a36703 | C43: However, at high penetration levels of variable renewables, i.e. above 20% of annual generation, the increase of variability and uncertainty leads to new challenges. The four challenges are summarized in the following table. The system operator needs to have enough capacity available during the hours where electricity demand is the highest, plus a reserve margin to cope with contingencies. | D43: SDG 7
A44: 10.1787/5k49dv6c5xmv-en | B44: 23f59c31e9d0ddbb55a5f4b2df177abb | C44: Although its ranking in terms of GDP per capita among OECD metro-regions is not as high as it is in terms of GDP (16lh among the 90 metro-regions vs. 8lh), Chicago still counts among the big players in the OECD urban world. With GDP per capita over USD 55 000 in 2008, Chicago ranked higher than traditionally rich European metro-regions such as London, Stockholm, Helsinki, Amsterdam-Utrecht, Paris and Milan (Figure 1.2). Among US metro-regions, Chicago’s GDP per capita is similar to that of San Diego and Philadelphia, but below that of a number of US metro-regions such as New York, Los Angeles, San Francisco-Oakland, Boston or Houston. | D44: NOT SDG 7
... A69: 10.18356/cefc94d2-en | B69: 03aceee76df8ed0511df92e8262c69c8 | C69: Tracking progress towards achieving the Sustainable Development Goals requires the collection, processing, analysis and dissemination of data and statistics at the subnational, national, and regional levels, including those derived from official statistical systems and from new and innovative data sources. Many national statistical systems face serious challenges in this regard. As a result, accurate and timely information about certain aspects of people's lives are unknown, and many development challenges are still poorly understood. | D69: NOT SDG 7
A70: 10.1787/9789264278530-8-en | B70: 69c3547d0a4dde1fb18ad2e5e8654d0a | C70: It provides financial assistance to producers to install and maintain conservation practices on eligible agricultural and forest land. Energy conservation projects occur as part of the On-Farm Energy Initiative. Landscape AgEMPs have been available since 2009, and take a more holistic view of on-farm energy use, addressing issues, such as water use and erosion. Once the initial energy audit is complete, EQIP helps farmers develop a plan for implementing conservation practices. | D70: SDG 7 | E70: See 7.3.
A71: 10.1787/5kg7068011hb-en | B71: b4ff5d93a99f6112f717a546f404b3c4 | C71: In 2009, wind energy accounted for 56%of global clean energy investment. Investment in solar energy follows wind’s leading position and is poised to expand as a result of declining solar energy prices and the potential of new, thin-film technologies as noted by Pew (2010). New investment in biomass, geothermal and small hydro seems to play a marginal role in the total market (see Figure 7). Financial sector new investment (incl. | D71: SDG 7
A72: 10.18356/fcd1ba6c-en | B72: 2528f76d29c8a44be2769f22b552e9a8 | C72: Scepticism about the science is no longer an option: the world’s scientists have never been so unanimous, and so ominous, in their projections of future perils. The bad news is that too many participants in the debate consider a climate policy as consisting primarily of manipulating markets and prices. If the only tool available were market liberalization, then the solution to every problem would seem to be a matter of getting the prices right. But setting a price for carbon emissions is only the beginning of climate policy - not the end. | D72: NOT SDG 7
A73: 10.1787/5kgglrw4n7s0-en | B73: 29d5da40fe85cc32f02d021b960ce2f8 | C73: Large areas of about 500 000 km2 between Mumbai and Bhopal and in Gujarat are covered by thick basalt layers. If basalt is shown to be a suitable cap rock, it is estimated that this would allow storage of 300 Gt C02 (Sonde, 2007). Three of the nine sites designated so far for UMPP projects are on the coast not far from these potential storage areas.13 For inland sites relying on domestic coal, additional costs of USD 5/tC02 for transporting the C02 are expected compared to coastal sites (Mott MacDonald, 2008). Gas consumption has been rapidly growing at a rate of 8% between 1990 and 2009. | D73: NOT SDG 7
A74: 10.18356/d0196687-en | B74: 46d475ceaa034365791d668459aa60cb | C74: In addition to targets, the scope of instruments related to renewable energy being introduced is also broadening, demonstrating a deepening commitment towards renewable energy. For instance, Sri Lanka, under its latest energy sector development plan, is seeking to significantly increase the share of renewable energy while reducing petroleum imports, which have risen dramatically over the past decades (Sri Lanka, Ministry of Power and Renewable Energy, 2015). Pacific Island States, particularly the Cook Islands, Fiji, Samoa, Tuvalu, and Vanuatu, are leading the region in setting up an ambitious target of 100 per cent renewable energy. Additionally, under the country’s Energy Development Strategic Action Plan, hydro is expected to reach approximately 350 GW. | D74: SDG 7
A75: 10.1787/9789264202276-9-en | B75: 05e5041073e7db294006b31a460c46b5 | C75: There is also a number of construction and operations contracts across the country for wastewater treatment plants, desalination facilities and reverse osmosis units. Because agriculture accounts for 71% of water usage, there are some arrangements whereby farmer associations in the Jordan Valley have been contracted by the local authority to manage water distribution in the area. The number of associations is expected to increase to ten by 2020 (EDP 2011-13). | D75: NOT SDG 7
A76: 10.18356/893fb414-en | B76: 0c0f79ed4ec9a79fca8cc8392ba2c73f | C76: Energy poverty both signifies and drives overall poverty. More than 95% of the world population without electricity lives in Sub-Saharan Africa and developing Asia. In Sub-Saharan Africa, two-thirds of the population (620 million people) does not have access to electricity (IEA 2015a). Lack of electricity is generally most prevalent in rural areas. | D76: SDG 7
A77: 10.1787/9789264303119-en | B77: 07f17e85fc779d9e2b6f72fc7e884546 | C77: There are, however, many other potential impacts of accidents that are borne by the society as a whole and for which the internalisation is less straightforward and more complex. This is the case for the economic consequences on health and on the business property of a third party or on the environment. The entity liable for the accident is held responsible for the victims’ compensation, which ensures a certain internalisation of accident costs. | D77: NOT SDG 7
A78: 10.1787/5kmh3nj5rzs4-en | B78: be8a2af1834e66add5d63d32dcf2761e | C78: This debate is in line with South Africa's rural electrification agenda, as new power generation will be necessary to service more households. The average official50 unemployment figures are above 20% (see Table 33), excluding the under-employed in the rural and urban areas or those who are not registered in employment agencies. Payment for electricity is an issue for people who have no or very little income. Many cases of domestic violence in newly electrified households have been amply documented. It is argued that domestic trouble starts over priorities when resources are scarce (Habitat for Humanity, 2009). However, the long-term effect of ensuring universal access to electricity should lead to general opportunities for a broad-based economic development. | D78: SDG 7
A79: 10.18356/1e8b62ff-en | B79: 96a7c26e6b1dc4def35ff6ebdbff9d86 | C79: However, urbanization represents an additional challenge. Rapid increases in urban electrification rates in recent years have not matched the absolute increase in urban population, so that the number of urban dwellers without access to electricity has continued to rise. The continuation of such rapid urbanization, together with progress towards universal access, is likely to result in still greater pressure on the (already poor) T&D infrastructure, reinforcing the need for upgrading. | D79: SDG 7
A80: 10.1787/5k49dv6c5xmv-en | B80: 7b76b91e09d54abc84b480f0db7f37e8 | C80: Low-wage residents are less likely to have access to a car, and commuter train lines and bus routes do not serve the south side of the Tri-State metro-region as well as they serve other parts of the region. Commuting times are even longer for those who commute across the region instead of following the hub and spoke system. Investment in public transport infrastructure does not sufficiently respond to demand for access to jobs, especially in lower -income neighbourhoods. While the Tri-State metro-region ranks high among OECD regions on many technology-based innovation indicators in terms of volume, its position has slipped and it is not among top regions when controlling for the size of its population and economy. For instance, in terms of patents per capita, the Tri-State metro-region ranked 23rd among OECD metro-regions and 11th among US metro-regions in 2007, the last year for which data are available, it ranked 27th and 12th, respectively, when adjusting for GDP (Table 1.5). These are hardly poor scores, but neither do they suggest that the Tri-State metro-region is fulfilling its innovation potential, particularly given that it ranks below so many other US metro-regions, including San Diego, San Francisco, New York, Boston, Los Angeles and Houston. | D80: NOT SDG 7
A81: 10.1787/5kmh3nj5rzs4-en | B81: 04922124925495a57473febc0637998d | C81: Electrification of schools, however, is facing problems largely stemming from lack of information about the number of schools and their electrification status. Some municipalities fail to report the number of schools in their area or fail to provide accurate information on whether the schools are electrified or not. It is clear that this poses a major constraint for the entities in charge of the electrification of the as-yet un-electrified schools. | D81: SDG 7
A82: 10.6027/9789289349918-3-en | B82: 725de70f6686eefb96c1653b790d6b6a | C82: A way to improve energy efficiency is to tap the huge potential for efficiency gains in the building sector which is the largest single energy consumer in Europe, absorbing 40% of final energy. About 75% of buildings are energy inefficient and, depending on the Member State, only o.4-1.2% of the stock is renovated each year. ( The energy efficiency target on EU level is set on fixed Mtoe-level for final energy and primary energy use in 2030, and the Member States have to set their targets so that this target will be reached. The Commission will lay down a process to ensure that the contributions add up to the Union's 2030 energy efficiency target in the legislative proposal on Energy Union Governance. | D82: SDG 7
... A85: 10.6027/8a4204a0-en | B85: 3de3a33b6c50a93b9bf0e13ad8c0d089 | C85: Throughout this week, electricity prices are relatively high, with a clear day-night pattern. Night prices of around 50 EUR/MWh are close to the marginal cost of coal fired power plants, while the higher prices during day times of around 90-100 EUR/MWh are close to the marginal cost of natural gas fired power plants. Total consumption (red dashed line), however, is more constant over the week, because electricity consumption for heating and pumping (pumped storage) increases at night, when electricity prices are low. | D85: SDG 7
A86: 10.6027/9789289350167-3-en | B86: 5f74051cc940cc85f3e35bf0c678484f | C86: Data over the last 30 years suggests that, had we switched off government subsidies to fossil fuels, global emissions would have been more than a third lower than they actually were in 2010. Countries need to make a SWAP. Nordic countries have started this shift away from fossil fuel subsidies and toward government support to heat pumps as in Sweden, electric cars as in Norway and wind power in Denmark. | D86: SDG 7 | E86: SDG 12 also relevant
A87: 10.18356/73c3a080-en | B87: 62d5095d5d7ac925505de89dc9f446e1 | C87: Electricity access is commonly acknowledged as a basic need for human development (Scott and Seth, 2013), and has been described as a moral imperative, socially prudent and an economic necessity (GEA, 2016: 19). Aside from the public-good dimension of safe and reliable electricity supply, consumer protection and guaranteed access are important political-economy considerations (Bamber et al., Such energy-security concerns generally serve to reinforce State control and regulation of the electricity sector (Kuik et al., | D87: SDG 7
A88: 10.1787/5kmh3nj5rzs4-en | B88: 09d371f072d386c66ae086329a44aa38 | C88: In 2008, 70.8% of India's total population lived in rural areas, progressively migrating to urban areas at an annual rate of 2.3%, a rate which is below that of many other countries (UNPD, 2008). While such economic development has led to an average increase in the standards of living, it has left the agricultural sector untouched, bypassing most of the rural poor. Therefore, although India has enjoyed a growth of GDP per capita, poverty remains a challenge. Poverty is also more concentrated in some states such as the eastern and north-eastern states as Figure 7 shows. In March 2007, the Indian Planning Commission estimated that over the 2004-2005 Page | 63 period, more than one-quarter of India's total population (27.5%) still lived below the poverty line (BPL), with a distribution of 25.7% urban dwellers and 28.3% rural dwellers (Planning Commission, Government of India, 2007)37 as seen in Table 17. But strong economic growth alone does not bring such amenities to the rural poor. | D88: NOT SDG 7
A89: 10.1787/saeo-2017-8-en | B89: d974c1ee71b4e0f13b3df4e577c038e4 | C89: This corresponded to 32% of the total final energy consumption in the entire region. In parallel, India’s industry will play an increasingly important role as a driver for energy consumption in the region. While India’s industry accounted for 7% of the TFC in emerging Asia in 2013, this share is expected to increase to 13% by 2040. | D89: SDG 7
A90: 10.18356/faf8a648-en | B90: 99924b6f7da462bb2dc307cbbd942e1d | C90: The location was selected because of the competitive labour cost, skills and physical infrastructure. The layout and design of buildings draw from the latest standards developed in the industry, such as those established by the US Customs authority after the September 11, 2001, terrorist attacks, to ensure security of trade, and safety at work, after the fire disasters in Bangladesh textile factories in April 2013. A one-stop government service has been introduced to cut red tape and improve the business environment. The China Civil Engineering Corporation, a leading construction company is building the park as a turnkey "design and build" project. | D90: NOT SDG 7
A91: 10.1787/9789264115118-7-en | B91: 10c26acfd397b509bd035a8bd93401d5 | C91: According to the IEA’s WEO-2011, 1.3 billion people - nearly 20% of world population - currently lack access to electricity and about 2.7 billion people - 40% of the world population - rely on the traditional use of biomass for cooking (IEA, 2011a). The outlook suggests that the problem will persist and even deepen in some places. The IEA and World Health Organization estimate that household air pollution from the use of biomass in inefficient stoves would lead to more than 4 000 premature deaths per day in 2030, greater than estimates for premature deaths from malaria, tuberculosis or Human Immunodeficiency Virus (HIV)/Acquired immune deficiency syndrome (AIDS) (IEA, 2011a). The index seeks to capture the quality of energy services as well as their quantity. It is calculated in such a way as to mirror the United Nations Development Programme’s Human Development Index. | D91: SDG 7
A92: 10.18356/aac9b96c-en | B92: 05ad33f26eff857ea273b271a7c648f5 | C92: If too much water is stored behind the reservoir, sections of the river downstream from the reservoir can dry out if an insufficient amount of water is released at certain times of the year. This can lead to detrimental effects on animal and plant life downstream from the facility. Because of this, the channel may show signs of degradation (loss of sediments) or aggradation (accumulation of sediments), depending on whether floods can move the remaining incoming sediments. | D92: NOT SDG 7
A93: 10.18356/7e830810-en | B93: 229d51baaa3e76c88692e28a318c6720 | C93: Nigeria’s severe shortage of energy prompted the government to establish the University of Lagos National Centre for Energy Efficiency and Conservation in 2008, which is responsible for R&D in energy-efficiency and -conservation options and technologies. Following the 2010 enactment of the Russian Federation’s energy-efficiency legislation, the country has intensified efforts to create an R&D capacity in energy efficiency. The Russian Federation recognizes the role of a growing number of organizations engaged in research on improving energy efficiency, such as the Centre for Energy Efficiency, the Sustainable Energy Development Centre and the Institute of Energy Strategy. Standards for industrial equipment and system optimization can make it easier for firms to trade off capital and energy costs, but they can also impose limits on product choice and undesirable costs for adopters. | D93: SDG 7
A94: 10.14217/9781848599574-13-en | B94: 4ab2d07728c9a63879cfc15e268f6aba | C94: The percentage of the population that has access to electricity ranges from 18 per cent in PNG to 100 per cent in Samoa (Figure 9.4). A larger proportion of hydro power, for example in Fiji, is likely to reduce the electricity tariff, whereas a country that relies mostly on fossil fuels, such as Kiribati or Tuvalu, is more vulnerable to increasing oil prices. Another factor affecting the residential electricity tariff is whether it is subsidised through the Government budget, for example in Fiji, or using a cross subsidy from larger users of electricity, for example in Vanuatu. Each power utility in each country determines its tariffs differently. | D94: SDG 7
A95: 10.18356/e9fa9dd4-en | B95: b9444ad7737b7622d6c248eff6b124ee | C95: Building an attractive rurality for young people is a major public policy challenge. Restoring the attractiveness of rural areas and achieving a new inclusive and equitable rurality is fundamental for rural territories to benefit from having more and better educated young people with a greater capacity for innovation. Thus, the rural agenda increasingly overlaps with the indigenous agenda, which includes an integral vision of that world, as territory and habitat, and not only as a space and production resource. Nonetheless, public must also be formulated for rural Afrodescendent populations, which are significant in various countries and constitute one of the least visible social groups. | D95: NOT SDG 7
A96: 10.18356/e9fa9dd4-en | B96: ccafe2a0505dfd1d9932003746ef28d8 | C96: Moreover, access to water is often intermittent and vulnerable to interruptions caused by droughts or other factors. State of) (2015) Venezuela (Bol. This hinders online access to health, education and government services, and impairs e-commerce among Latin American countries, which could become a tool for regional integration, particularly in the area of digital goods and services. | D96: NOT SDG 7
A97: 10.1787/9789264236813-6-en | B97: 4cf9ebc3e44f6f6fe764d85a6f3abc99 | C97: In the short-term, a favourable future for the post-2015 sustainable development framework and an ambitious climate deal in Paris will not be possible without policy input. In the longer term, development objectives, including climate-related goals, need policy coherence as well as cash. Governments will need to adapt accordingly. | D97: NOT SDG 7
A98: 10.18356/bcf52e9f-en | B98: 8852c54a8b7143f8c44fe58eff9c0b84 | C98: For low-level consumption the higher income group is charged 150 per cent of the price paid by the low-income group. With a sufficiently large consumer base that has enough high-income consumers, the water tariff enables the recovery of costs and the progressive structure supports poor people. The costs are associated with operating, maintaining and extending the water networks and providing basic levels of service. | D98: NOT SDG 7
... A101: 10.1787/5k49dv6c5xmv-en | B101: 7cf11d73e5bb2de5ea82cb92952a4065 | C101: Despite benefiting from past investments that have given it the second-longest commuter rail system in the US, investment has not kept up with the region’s needs. The Chicago Tri-State metro-region's competitiveness is being undermined in part by the growing inadequacy of its transportation infrastructure, which is typified by high rates of road congestion. Over 80% of the 4 009 stream miles assessed in Illinois are considered sufficiently polluted to prohibit primary human contact (e.g. swimming) (IEPA, 2010). | D101: NOT SDG 7

Sheet Meike
A1: DOI | B1: Text ID | C1: Text | D1: Label | E1: Comments (optional)
A2: 10.18356/7e830810-en | B2: 0edfe3b90c82ce644cf8c58342f13172 | C2: Where energy supply is unreliable, firms are more concerned with availability than with efficiency. Similarly, small and medium-size industrial firms find it much harder to get a loan than do larger firms. And while the barriers to energy efficiency are also present in developed countries, they are more formidable in developing countries. What are the appropriate roles of the public and private sectors? | D2: TO DO
A3: 10.1787/9789264202276-9-en | B3: 002f6840660d0e3051543f0ba55c82ca | C3: Several hotels and universities have also contracted private firm to construct wastewater treatment plants. Certain groups of consumers - particularly in industry tourism, commerce and agriculture - are expected to pay a tariff reflecting the full cost of water service provision. An increase in the water tariff was approved in late 2010, potentially helping to improve cost recovery, but the Ministry of Water and Irrigation stated in June 2012 that tariffs would not increase further in the near future. | D3: TO DO
A4: 10.1787/5kg20639kgkj-en | B4: 90e3f33798e2cfc95c140ef186fb00a9 | C4: Sustainability Advantage is a business support service from the Department of Environment and Climate Change NSW. It is designed to help organisations understand sustainability, successfully manage for a better environment and add business value79. Industry' Investment NSW offers “LEAN and green” business master classes for people who want to leam how they can improve business efficiency through the application of “lean” business practices, coupled with environmental sustainability, to reduce costs, increase profits, open new markets and create jobs . Despite initiatives like these, it is not always easy for SMEs to take up training opportunities in skills for sustainability. | D4: TO DO
A5: 10.18356/faf8a648-en | B5: 99924b6f7da462bb2dc307cbbd942e1d | C5: The location was selected because of the competitive labour cost, skills and physical infrastructure. The layout and design of buildings draw from the latest standards developed in the industry, such as those established by the US Customs authority after the September 11, 2001, terrorist attacks, to ensure security of trade, and safety at work, after the fire disasters in Bangladesh textile factories in April 2013. A one-stop government service has been introduced to cut red tape and improve the business environment. The China Civil Engineering Corporation, a leading construction company is building the park as a turnkey "design and build" project. | D5: TO DO
A6: 10.1787/9789264284319-9-en | B6: 5c18bc73a355e3bb2f41f8006c717c65 | C6: In addition, in 2014, EUR 5.8 mln from local budgets was used to finance eneigy efficiency measures (EEA, 2015). To date, there have been three calls. The first, in 2013, was launched for public institutions (including schools and hospitals), resulting in the selection of 86 projects worth a total of MDL 135 mln (about EUR 78 000 per project on average). | D6: TO DO
A7: 10.18356/7e830810-en | B7: 2cd4fdfbe38a99441412e37921a2da5d | C7: Given industry’s substantial contribution to global energy intensity, credible specific industrial energy-efficiency targets must be formulated. But to keep increases in industrial energy consumption to the minimum required to satisfy development needs, future efficiency efforts must be ambitious. They must double today’s pace and reach energy intensity reduction rates similar to those in the 1990s. Doubling the industrial energy-intensity reduction rate is consistent with a similar exhortation made at the global level in the AGECC (2010) report. | D7: TO DO
A8: 10.18356/6e8bb756-en | B8: 30c83a848738f5d86d6bd284107e5232 | C8: In the EU, for instance, there was a rapid increase in the market share of the most energy-efficient appliances. Sales of Class A refrigerators increased from less than 5 per cent of total sales in 1995 to 23 per cent in 2000 and 61 per cent in 2005, in addition, 19 per cent of refrigerators sold in 2005 were in the two new, more efficient classes (A+ and A++). For washing machines, progress was even more rapid: with an increase in sales of 1 per cent in 1996, 38 per cent in 2000 and 90 per cent in 2005. | D8: TO DO
A9: 10.1787/5k9crzjbpkkc-en | B9: 5cbab6e5118d697ee7147b8b0b34ecf1 | C9: A discussion of the rebound effect in energy efficiency is needed that incorporates not just the expected energy savings from energy efficiency but also the wider socioeconomic outcomes. Policy measures are needed to overcome the market and behavioural failures that lead to less investment in energy efficiency than is optimal. It is important to overcome critical challenges that involve complex synergies and trade-offs among the different aspects of energy efficiency policy. | D9: TO DO
A10: 10.1787/9789264115118-7-en | B10: 10c26acfd397b509bd035a8bd93401d5 | C10: According to the IEA’s WEO-2011, 1.3 billion people - nearly 20% of world population - currently lack access to electricity and about 2.7 billion people - 40% of the world population - rely on the traditional use of biomass for cooking (IEA, 2011a). The outlook suggests that the problem will persist and even deepen in some places. The IEA and World Health Organization estimate that household air pollution from the use of biomass in inefficient stoves would lead to more than 4 000 premature deaths per day in 2030, greater than estimates for premature deaths from malaria, tuberculosis or Human Immunodeficiency Virus (HIV)/Acquired immune deficiency syndrome (AIDS) (IEA, 2011a). The index seeks to capture the quality of energy services as well as their quantity. It is calculated in such a way as to mirror the United Nations Development Programme’s Human Development Index. | D10: TO DO
A11: 10.1787/5k3w6ljtrj0q-en | B11: 6cc45f35957a70dc1f450fbc4ab74b22 | C11: This motivation is still strong with the reality of recession and austerity in many countries making the idea of green employment growth a welcome antidote to the high unemployment rates. Capacity building and skill development within the regional communities are also important benefits of green initiatives. | D11: TO DO
A12: 10.1787/9789264188617-en | B12: 5541a26c0b86bbefdc00ed32a2db20ad | C12: Connecting an individual consumer to a power plant would be prohibitively expensive. However, each additional customer in the area reduces the average cost for all involved since the cost for connecting the additional customer is small. The physical link through the grid, however, not only links customers to a producer but also links all producers with each other. | D12: TO DO
A13: 10.6027/9789289330954-4-en | B13: 138cf928dfb2490a23508d1175375c10 | C13: The country's potential in developing energy production technologies like wave power and osmotic power is also substantial. Norway is Europe's largest producer of hydropower, which delivers 99% of the country's electricity. On January 1 2008, Norway had a total installed capacity of 29030 MW at 699 hydropower stations larger than 1 MW. The Kvill-dal hydropower station in Rogaland county is Norway’s largest, with a maximum generating capacity of 1240 MW. | D13: TO DO
... A101: 10.18356/9a9b4252-en | B101: ab620f843a27c589f1c827210740acb6 | C101: For example, in Kenya, the paper manufacturer Chandaria Industries experienced savings of 40 per cent in energy, 48 percent in materials and 181 percent in water through involvement in the programme. Primary education is critical for developing a semi-skilled labour force. In low-income countries with large rural sectors, it can be vital for equipping farmers with the basic skills necessary to their being informed on and implementing sustainable agricultural and forestry practices. However, while the significance of achieving universal primary education is highlighted by its inclusion as a Millennium Development Goal, secondary, vocational and tertiary education are just as important in the field of green technology. Secondary education can provide core skills and knowledge needed for countries’ economic growth. Vocational schooling can be particularly useful in building technological competencies, successful vocational education also provides important links between education and industry. | D101: TO DO

Sheet Steve
A1: DOI | B1: Text ID | C1: Text | D1: Label | E1: Comments (optional)
A2: 10.1787/5km4knxj9tf3-en | B2: 0bb74afcdcfc75d8381638bb154c4a29 | C2: In most countries governments are significant energy users, and government operations present significant opportunities for efficiency improvements. By procuring energy efficiency services from the private sector, governments can help build capacity and critical mass within this important service sector. This is a win-win option, since energy use is major public sector expense. | D2: SDG 7
A3: 10.18356/7e830810-en | B3: 229d51baaa3e76c88692e28a318c6720 | C3: Nigeria’s severe shortage of energy prompted the government to establish the University of Lagos National Centre for Energy Efficiency and Conservation in 2008, which is responsible for R&D in energy-efficiency and -conservation options and technologies. Following the 2010 enactment of the Russian Federation’s energy-efficiency legislation, the country has intensified efforts to create an R&D capacity in energy efficiency. The Russian Federation recognizes the role of a growing number of organizations engaged in research on improving energy efficiency, such as the Centre for Energy Efficiency, the Sustainable Energy Development Centre and the Institute of Energy Strategy. Standards for industrial equipment and system optimization can make it easier for firms to trade off capital and energy costs, but they can also impose limits on product choice and undesirable costs for adopters. | D3: SDG 7
A4: 10.1787/9789264284319-9-en | B4: 5c18bc73a355e3bb2f41f8006c717c65 | C4: In addition, in 2014, EUR 5.8 mln from local budgets was used to finance eneigy efficiency measures (EEA, 2015). To date, there have been three calls. The first, in 2013, was launched for public institutions (including schools and hospitals), resulting in the selection of 86 projects worth a total of MDL 135 mln (about EUR 78 000 per project on average). | D4: SDG 7
A5: 10.14217/9781848599574-13-en | B5: 2a678f26ee1012ffd2f13e781a70ad92 | C5: In its recent national plan, the Kiribati Development Plan 2016-19, the government has focused on improving infrastructure for the energy sector, including in renewables. The Kiribati Joint Implementation Plan on Climate Change and Disaster Risk Management notes the vulnerability of women, youth and children. In the past, Nauru’s economy was dependent on the phosphate industry, which also fuelled its energy demand. | D5: SDG 7
A6: 10.1787/5k3wb8h0dg7h-en | B6: 08f9f7626f2c2baf6922a89d1b569335 | C6: Since 2007 Italy has provided tax relief for energy efficiency improvements to existing buildings including the installation of double-glazed windows, thermal insulation, high-efficiency boilers and the installation of solar panels. In 2009, building owners submitted 240,000 tax credit applications. As the programme was originally expected to be terminated in 2010, the number of applications in 2010 exceeded the previous year by around 71%. | D6: SDG 7
A7: 10.18356/e9fa9dd4-en | B7: b9444ad7737b7622d6c248eff6b124ee | C7: Building an attractive rurality for young people is a major public policy challenge. Restoring the attractiveness of rural areas and achieving a new inclusive and equitable rurality is fundamental for rural territories to benefit from having more and better educated young people with a greater capacity for innovation. Thus, the rural agenda increasingly overlaps with the indigenous agenda, which includes an integral vision of that world, as territory and habitat, and not only as a space and production resource. Nonetheless, public must also be formulated for rural Afrodescendent populations, which are significant in various countries and constitute one of the least visible social groups. | D7: NOT SDG 7
A8: 10.18356/feb1987a-en | B8: 8a3a6ccb763c0d5c97e81708e6e0a40a | C8: At the operational level, a skilled workforce is needed for building and operating installations. The main instruments for reaching policymakers and C-Level decision makers are industry-run instruments. An example at the national level in Germany is the "Maritime LNG Platform"15 and at the international level "Sea\LNG"’4. On the shore.no particular competence standard or model courses for training of personnel directly involved in LNG operations or indirectly related to LNG operations exist. | D8: NOT SDG 7
A9: 10.18356/1e8b62ff-en | B9: 96a7c26e6b1dc4def35ff6ebdbff9d86 | C9: However, urbanization represents an additional challenge. Rapid increases in urban electrification rates in recent years have not matched the absolute increase in urban population, so that the number of urban dwellers without access to electricity has continued to rise. The continuation of such rapid urbanization, together with progress towards universal access, is likely to result in still greater pressure on the (already poor) T&D infrastructure, reinforcing the need for upgrading. | D9: SDG 7
A10: 10.6027/9789289330954-4-en | B10: 138cf928dfb2490a23508d1175375c10 | C10: The country's potential in developing energy production technologies like wave power and osmotic power is also substantial. Norway is Europe's largest producer of hydropower, which delivers 99% of the country's electricity. On January 1 2008, Norway had a total installed capacity of 29030 MW at 699 hydropower stations larger than 1 MW. The Kvill-dal hydropower station in Rogaland county is Norway’s largest, with a maximum generating capacity of 1240 MW. | D10: SDG 7
A11: 10.1787/9789264303119-en | B11: f6d5efdef2f9ea14a47527c057a04920 | C11: Compared with other instances of social costs, one may think of tobacco smoking or lead concentration in drinking water, this process has developed reasonably quickly. First, there is public awareness and opinion creation by means of public communication. These may be commercial means of communication, such as television or newspapers, but also non-commercial means of public awareness creation such as demonstrations, sit-ins, public speeches and the like. Again, information is the first step in internalising external costs. This way, the set of choices is transformed into new choices that integrate a higher share of public concerns. | D11: NOT SDG 7
A12: 10.1787/9789264180444-17-en | B12: 355caa7c220d2fa90e8c0f53f57bf574 | C12: The central government had been planning to capitalise on the good wind resource in the north of the country by increasing production of wind energy in these areas. It had selected several sites for locating wind farms. However, as the production of RE does not represent a concrete advantage for the hosting communities, and as there is a general perception that negative externalities are not being compensated for by the RE policy, they have tended to oppose them. | D12: SDG 7
A13: 10.18356/9a9b4252-en | B13: ab620f843a27c589f1c827210740acb6 | C13: For example, in Kenya, the paper manufacturer Chandaria Industries experienced savings of 40 per cent in energy, 48 percent in materials and 181 percent in water through involvement in the programme. Primary education is critical for developing a semi-skilled labour force. In low-income countries with large rural sectors, it can be vital for equipping farmers with the basic skills necessary to their being informed on and implementing sustainable agricultural and forestry practices. However, while the significance of achieving universal primary education is highlighted by its inclusion as a Millennium Development Goal, secondary, vocational and tertiary education are just as important in the field of green technology. Secondary education can provide core skills and knowledge needed for countries’ economic growth. Vocational schooling can be particularly useful in building technological competencies, successful vocational education also provides important links between education and industry. | D13: NOT SDG 7
... A101: 10.18356/7e830810-en | B101: 0edfe3b90c82ce644cf8c58342f13172 | C101: Where energy supply is unreliable, firms are more concerned with availability than with efficiency. Similarly, small and medium-size industrial firms find it much harder to get a loan than do larger firms. And while the barriers to energy efficiency are also present in developed countries, they are more formidable in developing countries. What are the appropriate roles of the public and private sectors? | D101: SDG 7

Sheet Source
A1: doi | B1: text_id | C1: text | D1: sdg | E1: labels_negative | F1: labels_positive | G1: agreement | H1: difficulty | I1: label
A2: 10.6027/fcafdf5b-en | B2: 52148c3d2fdb1fb63687cf5e2dbe698c | C2: Greenland, the Faroe Islands and Svalbard have experienced an increase in tourism levels as well, though at a lower level than Iceland, with a growth ranging from 15% to 45% since 2012. As the duration of the visits have not increased, the increased spending is caused by a higher daily spending by the tourists. Tourism may create short and long-term profits and jobs for a region leading to economic growth, provided it is managed sustainably. | D2: 7 | E2: 10 | F2: 0 | G2: 1 | H2: =CHOOSE(ROUNDDOWN(G2*4.999999,0)+1, "very hard", "hard", "medium", "easy", "very easy") -> very easy | I2: =IF(F2>E2, "SDG 7", IF(E2>F2, "NOT SDG 7", "SKIP")) -> NOT SDG 7
A3: 10.18356/faf8a648-en | B3: 99924b6f7da462bb2dc307cbbd942e1d | C3: The location was selected because of the competitive labour cost, skills and physical infrastructure. The layout and design of buildings draw from the latest standards developed in the industry, such as those established by the US Customs authority after the September 11, 2001, terrorist attacks, to ensure security of trade, and safety at work, after the fire disasters in Bangladesh textile factories in April 2013. A one-stop government service has been introduced to cut red tape and improve the business environment. The China Civil Engineering Corporation, a leading construction company is building the park as a turnkey "design and build" project. | D3: 7 | E3: 9 | F3: 0 | G3: 1 | H3: =CHOOSE(ROUNDDOWN(G3*4.999999,0)+1, "very hard", "hard", "medium", "easy", "very easy") -> very easy | I3: =IF(F3>E3, "SDG 7", IF(E3>F3, "NOT SDG 7", "SKIP")) -> NOT SDG 7
A4: 10.1787/5k49dv6c5xmv-en | B4: d8af30adabb56201cb5606f036364f14 | C4: Significant restructuring of the region’s economy over the past twenty years has transformed the demand for skills, making it more difficult for low-skilled workers to find employment in more knowledge-based, innovation-driven, growing sectors. Despite the higher-than-average levels of educational attainment in the region, chronic low graduation rates from the region’s public post-secondary educational institutions, particularly community colleges, slows the upgrading of the region’s workforce. Further, the increase in specialisation towards higher value-added activities in the Chicago Tri-State metro-region has not gone hand in hand with an increase of the share of the labour force with high qualifications. | D4: 7 | E4: 9 | F4: 0 | G4: 1 | H4: =CHOOSE(ROUNDDOWN(G4*4.999999,0)+1, "very hard", "hard", "medium", "easy", "very easy") -> very easy | I4: =IF(F4>E4, "SDG 7", IF(E4>F4, "NOT SDG 7", "SKIP")) -> NOT SDG 7
A5: 10.1787/5kmh3nj5rzs4-en | B5: 09d371f072d386c66ae086329a44aa38 | C5: In 2008, 70.8% of India's total population lived in rural areas, progressively migrating to urban areas at an annual rate of 2.3%, a rate which is below that of many other countries (UNPD, 2008). While such economic development has led to an average increase in the standards of living, it has left the agricultural sector untouched, bypassing most of the rural poor. Therefore, although India has enjoyed a growth of GDP per capita, poverty remains a challenge. Poverty is also more concentrated in some states such as the eastern and north-eastern states as Figure 7 shows. In March 2007, the Indian Planning Commission estimated that over the 2004-2005 Page | 63 period, more than one-quarter of India's total population (27.5%) still lived below the poverty line (BPL), with a distribution of 25.7% urban dwellers and 28.3% rural dwellers (Planning Commission, Government of India, 2007)37 as seen in Table 17. But strong economic growth alone does not bring such amenities to the rural poor. | D5: 7 | E5: 5 | F5: 0 | G5: 1 | H5: =CHOOSE(ROUNDDOWN(G5*4.999999,0)+1, "very hard", "hard", "medium", "easy", "very easy") -> very easy | I5: =IF(F5>E5, "SDG 7", IF(E5>F5, "NOT SDG 7", "SKIP")) -> NOT SDG 7
A6: 10.18356/665c59ff-en | B6: 85b6a7e4c9eb4f7a2467b2b1b96596cd | C6: The surveys fed into the "Sustainability Index Consortium", an open platform database that allowed for analysis of the information collected from Walmart's 100,000 suppliers. At a Global Sustainability Milestone Meeting in Beijing in 2008, Walmart's chief executive officer announced plans to expand participation to 70 per cent of suppliers by 2017, making clear that failure to participate in the index would lead to removal of the firm from Walmart's supply chain. They typically address quality, cost and delivery procedures and, increasingly, environmental processes. | D6: 7 | E6: 4 | F6: 0 | G6: 1 | H6: =CHOOSE(ROUNDDOWN(G6*4.999999,0)+1, "very hard", "hard", "medium", "easy", "very easy") -> very easy | I6: =IF(F6>E6, "SDG 7", IF(E6>F6, "NOT SDG 7", "SKIP")) -> NOT SDG 7
A7: 10.18356/e9fa9dd4-en | B7: b9444ad7737b7622d6c248eff6b124ee | C7: Building an attractive rurality for young people is a major public policy challenge. Restoring the attractiveness of rural areas and achieving a new inclusive and equitable rurality is fundamental for rural territories to benefit from having more and better educated young people with a greater capacity for innovation. Thus, the rural agenda increasingly overlaps with the indigenous agenda, which includes an integral vision of that world, as territory and habitat, and not only as a space and production resource. Nonetheless, public must also be formulated for rural Afrodescendent populations, which are significant in various countries and constitute one of the least visible social groups. | D7: 7 | E7: 4 | F7: 0 | G7: 1 | H7: =CHOOSE(ROUNDDOWN(G7*4.999999,0)+1, "very hard", "hard", "medium", "easy", "very easy") -> very easy | I7: =IF(F7>E7, "SDG 7", IF(E7>F7, "NOT SDG 7", "SKIP")) -> NOT SDG 7
A8: 10.1787/5kgglrw4n7s0-en | B8: 0bc3671b295153b56be5727afdf182de | C8: On the production side (industry, commerce and agriculture), significant changes are expected as the economy grows nearly eightfold. This implies a massive expansion of the commercial/services sector (by a factor of six), a significant expansion of manufacturing activity, and more limited growth of activity in agriculture. However, water needs to be pumped from increasing depth and this is the main source of electricity demand in agriculture. Sources: IEA, 2009b, IEA, 2010a, IEA, 2009c. | D8: 7 | E8: 3 | F8: 0 | G8: 1 | H8: =CHOOSE(ROUNDDOWN(G8*4.999999,0)+1, "very hard", "hard", "medium", "easy", "very easy") -> very easy | I8: =IF(F8>E8, "SDG 7", IF(E8>F8, "NOT SDG 7", "SKIP")) -> NOT SDG 7
A9: 10.18356/faf8a648-en | B9: 796317916f6feac7e42344508a947fc6 | C9: Durante is a fully integrated business that, in addition to fish products, offers a full range of services, including advisory services and franchise systems to mid-scale farmers. It is one of Nigeria's leading fish-farming businesses (NRI, 2014). Durante shifted away from tank culture to pond and cage culture because of power cuts and water constraints. | D9: 7 | E9: 3 | F9: 0 | G9: 1 | H9: =CHOOSE(ROUNDDOWN(G9*4.999999,0)+1, "very hard", "hard", "medium", "easy", "very easy") -> very easy | I9: =IF(F9>E9, "SDG 7", IF(E9>F9, "NOT SDG 7", "SKIP")) -> NOT SDG 7
A10: 10.1787/5k49dv6c5xmv-en | B10: 7cf11d73e5bb2de5ea82cb92952a4065 | C10: Despite benefiting from past investments that have given it the second-longest commuter rail system in the US, investment has not kept up with the region’s needs. The Chicago Tri-State metro-region's competitiveness is being undermined in part by the growing inadequacy of its transportation infrastructure, which is typified by high rates of road congestion. Over 80% of the 4 009 stream miles assessed in Illinois are considered sufficiently polluted to prohibit primary human contact (e.g. swimming) (IEPA, 2010). | D10: 7 | E10: 3 | F10: 0 | G10: 1 | H10: =CHOOSE(ROUNDDOWN(G10*4.999999,0)+1, "very hard", "hard", "medium", "easy", "very easy") -> very easy | I10: =IF(F10>E10, "SDG 7", IF(E10>F10, "NOT SDG 7", "SKIP")) -> NOT SDG 7
A11: 10.18356/9a9b4252-en | B11: ab620f843a27c589f1c827210740acb6 | C11: For example, in Kenya, the paper manufacturer Chandaria Industries experienced savings of 40 per cent in energy, 48 percent in materials and 181 percent in water through involvement in the programme. Primary education is critical for developing a semi-skilled labour force. In low-income countries with large rural sectors, it can be vital for equipping farmers with the basic skills necessary to their being informed on and implementing sustainable agricultural and forestry practices. However, while the significance of achieving universal primary education is highlighted by its inclusion as a Millennium Development Goal, secondary, vocational and tertiary education are just as important in the field of green technology. Secondary education can provide core skills and knowledge needed for countries’ economic growth. Vocational schooling can be particularly useful in building technological competencies, successful vocational education also provides important links between education and industry. | D11: 7 | E11: 3 | F11: 0 | G11: 1 | H11: =CHOOSE(ROUNDDOWN(G11*4.999999,0)+1, "very hard", "hard", "medium", "easy", "very easy") -> very easy | I11: =IF(F11>E11, "SDG 7", IF(E11>F11, "NOT SDG 7", "SKIP")) -> NOT SDG 7
A12: 10.1787/5bbcdeac-en | B12: 6194ce1da1e7aed5cd5e9929d75f9742 | C12: An enabling policy environment is important for the development of a strong and competitive renewable energy sector to supply both industrial and domestic consumers. Section 3 identifies key enabling policy factors required for the replicability and accelerated uptake of the available renewable energy solutions throughout the mining sector. Major companies and conglomerates, among others, such as Glencore, Barrick Gold, Rio Tinto, Antofagasta, Codelco and IAMGOLD have all made use of renewable energy in their mines (Table 2.1). | D12: 7 | E12: 0 | F12: 11 | G12: 1 | H12: =CHOOSE(ROUNDDOWN(G12*4.999999,0)+1, "very hard", "hard", "medium", "easy", "very easy") -> very easy | I12: =IF(F12>E12, "SDG 7", IF(E12>F12, "NOT SDG 7", "SKIP")) -> SDG 7
A13: 10.18356/73c3a080-en | B13: 62d5095d5d7ac925505de89dc9f446e1 | C13: Electricity access is commonly acknowledged as a basic need for human development (Scott and Seth, 2013), and has been described as a moral imperative, socially prudent and an economic necessity (GEA, 2016: 19). Aside from the public-good dimension of safe and reliable electricity supply, consumer protection and guaranteed access are important political-economy considerations (Bamber et al., Such energy-security concerns generally serve to reinforce State control and regulation of the electricity sector (Kuik et al., | D13: 7 | E13: 0 | F13: 10 | G13: 1 | H13: =CHOOSE(ROUNDDOWN(G13*4.999999,0)+1, "very hard", "hard", "medium", "easy", "very easy") -> very easy | I13: =IF(F13>E13, "SDG 7", IF(E13>F13, "NOT SDG 7", "SKIP")) -> SDG 7
... A101: 10.6027/9789289329163-8-en | B101: f8a730809d29ac515eb7c5e34389c1b6 | C101: Consequently, there are more business options for the forest industry and forest-based raw materials than ever before. It still needs to be remembered that all four levels must be able to co-exist also in the future, even if their shares may change. All that can be produced without felling trees, e.g. carbon sinks, berries, game, tourism, etc. | D101: 7 | E101: 2 | F101: 2 | G101: 0 | H101: =CHOOSE(ROUNDDOWN(G101*4.999999,0)+1, "very hard", "hard", "medium", "easy", "very easy") -> very hard | I101: =IF(F101>E101, "SDG 7", IF(E101>F101, "NOT SDG 7", "SKIP")) -> SKIP

Sheet Final Review
A1: Text ID | B1: Text | C1: Steve | D1: Jean-Baptiste | E1: Finn | F1: Gib | G1: Alignment | H1: Consensus | I1: Rationale
A2: 52148c3d2fdb1fb63687cf5e2dbe698c | B2: Greenland, the Faroe Islands and Svalbard have experienced an increase in tourism levels as well, though at a lower level than Iceland, with a growth ranging from 15% to 45% since 2012. As the duration of the visits have not increased, the increased spending is caused by a higher daily spending by the tourists. Tourism may create short and long-term profits and jobs for a region leading to economic growth, provided it is managed sustainably. | C2: =VLOOKUP($A2, INDIRECT(C$1&"!B:D"), 3, FALSE) -> NOT SDG 7 | D2: =VLOOKUP($A2, INDIRECT(D$1&"!B:D"), 3, FALSE) -> NOT SDG 7 | E2: =VLOOKUP($A2, INDIRECT(E$1&"!B:D"), 3, FALSE) -> NOT SDG 7 | F2: =VLOOKUP($A2, INDIRECT(F$1&"!B:D"), 3, FALSE) -> TO DO | G2: =ABS((COUNTIF(C2:F2,"SDG 7")-COUNTIF(C2:F2, "NOT SDG 7")) / (COUNTA(C2:F2)-COUNTIF(C2:F2, "TO DO"))) -> 1 | H2: NOT SDG 7
A3: 99924b6f7da462bb2dc307cbbd942e1d | B3: The location was selected because of the competitive labour cost, skills and physical infrastructure. The layout and design of buildings draw from the latest standards developed in the industry, such as those established by the US Customs authority after the September 11, 2001, terrorist attacks, to ensure security of trade, and safety at work, after the fire disasters in Bangladesh textile factories in April 2013. A one-stop government service has been introduced to cut red tape and improve the business environment. The China Civil Engineering Corporation, a leading construction company is building the park as a turnkey "design and build" project. | C3: =VLOOKUP($A3, INDIRECT(C$1&"!B:D"), 3, FALSE) -> NOT SDG 7 | D3: =VLOOKUP($A3, INDIRECT(D$1&"!B:D"), 3, FALSE) -> NOT SDG 7 | E3: =VLOOKUP($A3, INDIRECT(E$1&"!B:D"), 3, FALSE) -> NOT SDG 7 | F3: =VLOOKUP($A3, INDIRECT(F$1&"!B:D"), 3, FALSE) -> TO DO | G3: =ABS((COUNTIF(C3:F3,"SDG 7")-COUNTIF(C3:F3, "NOT SDG 7")) / (COUNTA(C3:F3)-COUNTIF(C3:F3, "TO DO"))) -> 1 | H3: NOT SDG 7
A4: d8af30adabb56201cb5606f036364f14 | B4: Significant restructuring of the region’s economy over the past twenty years has transformed the demand for skills, making it more difficult for low-skilled workers to find employment in more knowledge-based, innovation-driven, growing sectors. Despite the higher-than-average levels of educational attainment in the region, chronic low graduation rates from the region’s public post-secondary educational institutions, particularly community colleges, slows the upgrading of the region’s workforce. Further, the increase in specialisation towards higher value-added activities in the Chicago Tri-State metro-region has not gone hand in hand with an increase of the share of the labour force with high qualifications. | C4: =VLOOKUP($A4, INDIRECT(C$1&"!B:D"), 3, FALSE) -> NOT SDG 7 | D4: =VLOOKUP($A4, INDIRECT(D$1&"!B:D"), 3, FALSE) -> NOT SDG 7 | E4: =VLOOKUP($A4, INDIRECT(E$1&"!B:D"), 3, FALSE) -> NOT SDG 7 | F4: =VLOOKUP($A4, INDIRECT(F$1&"!B:D"), 3, FALSE) -> TO DO | G4: =ABS((COUNTIF(C4:F4,"SDG 7")-COUNTIF(C4:F4, "NOT SDG 7")) / (COUNTA(C4:F4)-COUNTIF(C4:F4, "TO DO"))) -> 1 | H4: NOT SDG 7
A5: 09d371f072d386c66ae086329a44aa38 | B5: In 2008, 70.8% of India's total population lived in rural areas, progressively migrating to urban areas at an annual rate of 2.3%, a rate which is below that of many other countries (UNPD, 2008). While such economic development has led to an average increase in the standards of living, it has left the agricultural sector untouched, bypassing most of the rural poor. Therefore, although India has enjoyed a growth of GDP per capita, poverty remains a challenge. Poverty is also more concentrated in some states such as the eastern and north-eastern states as Figure 7 shows. In March 2007, the Indian Planning Commission estimated that over the 2004-2005 Page | 63 period, more than one-quarter of India's total population (27.5%) still lived below the poverty line (BPL), with a distribution of 25.7% urban dwellers and 28.3% rural dwellers (Planning Commission, Government of India, 2007)37 as seen in Table 17. But strong economic growth alone does not bring such amenities to the rural poor. | C5: =VLOOKUP($A5, INDIRECT(C$1&"!B:D"), 3, FALSE) -> NOT SDG 7 | D5: =VLOOKUP($A5, INDIRECT(D$1&"!B:D"), 3, FALSE) -> NOT SDG 7 | E5: =VLOOKUP($A5, INDIRECT(E$1&"!B:D"), 3, FALSE) -> NOT SDG 7 | F5: =VLOOKUP($A5, INDIRECT(F$1&"!B:D"), 3, FALSE) -> TO DO | G5: =ABS((COUNTIF(C5:F5,"SDG 7")-COUNTIF(C5:F5, "NOT SDG 7")) / (COUNTA(C5:F5)-COUNTIF(C5:F5, "TO DO"))) -> 1 | H5: NOT SDG 7
A6: 85b6a7e4c9eb4f7a2467b2b1b96596cd | B6: The surveys fed into the "Sustainability Index Consortium", an open platform database that allowed for analysis of the information collected from Walmart's 100,000 suppliers. At a Global Sustainability Milestone Meeting in Beijing in 2008, Walmart's chief executive officer announced plans to expand participation to 70 per cent of suppliers by 2017, making clear that failure to participate in the index would lead to removal of the firm from Walmart's supply chain. They typically address quality, cost and delivery procedures and, increasingly, environmental processes. | C6: =VLOOKUP($A6, INDIRECT(C$1&"!B:D"), 3, FALSE) -> NOT SDG 7 | D6: =VLOOKUP($A6, INDIRECT(D$1&"!B:D"), 3, FALSE) -> NOT SDG 7 | E6: =VLOOKUP($A6, INDIRECT(E$1&"!B:D"), 3, FALSE) -> NOT SDG 7 | F6: =VLOOKUP($A6, INDIRECT(F$1&"!B:D"), 3, FALSE) -> TO DO | G6: =ABS((COUNTIF(C6:F6,"SDG 7")-COUNTIF(C6:F6, "NOT SDG 7")) / (COUNTA(C6:F6)-COUNTIF(C6:F6, "TO DO"))) -> 1 | H6: NOT SDG 7
A7: b9444ad7737b7622d6c248eff6b124ee | B7: Building an attractive rurality for young people is a major public policy challenge. Restoring the attractiveness of rural areas and achieving a new inclusive and equitable rurality is fundamental for rural territories to benefit from having more and better educated young people with a greater capacity for innovation. Thus, the rural agenda increasingly overlaps with the indigenous agenda, which includes an integral vision of that world, as territory and habitat, and not only as a space and production resource. Nonetheless, public must also be formulated for rural Afrodescendent populations, which are significant in various countries and constitute one of the least visible social groups. | C7: =VLOOKUP($A7, INDIRECT(C$1&"!B:D"), 3, FALSE) -> NOT SDG 7 | D7: =VLOOKUP($A7, INDIRECT(D$1&"!B:D"), 3, FALSE) -> NOT SDG 7 | E7: =VLOOKUP($A7, INDIRECT(E$1&"!B:D"), 3, FALSE) -> NOT SDG 7 | F7: =VLOOKUP($A7, INDIRECT(F$1&"!B:D"), 3, FALSE) -> TO DO | G7: =ABS((COUNTIF(C7:F7,"SDG 7")-COUNTIF(C7:F7, "NOT SDG 7")) / (COUNTA(C7:F7)-COUNTIF(C7:F7, "TO DO"))) -> 1 | H7: NOT SDG 7
A8: 796317916f6feac7e42344508a947fc6 | B8: Durante is a fully integrated business that, in addition to fish products, offers a full range of services, including advisory services and franchise systems to mid-scale farmers. It is one of Nigeria's leading fish-farming businesses (NRI, 2014). Durante shifted away from tank culture to pond and cage culture because of power cuts and water constraints. | C8: =VLOOKUP($A8, INDIRECT(C$1&"!B:D"), 3, FALSE) -> NOT SDG 7 | D8: =VLOOKUP($A8, INDIRECT(D$1&"!B:D"), 3, FALSE) -> NOT SDG 7 | E8: =VLOOKUP($A8, INDIRECT(E$1&"!B:D"), 3, FALSE) -> NOT SDG 7 | F8: =VLOOKUP($A8, INDIRECT(F$1&"!B:D"), 3, FALSE) -> TO DO | G8: =ABS((COUNTIF(C8:F8,"SDG 7")-COUNTIF(C8:F8, "NOT SDG 7")) / (COUNTA(C8:F8)-COUNTIF(C8:F8, "TO DO"))) -> 1 | H8: NOT SDG 7
A9: 7cf11d73e5bb2de5ea82cb92952a4065 | B9: Despite benefiting from past investments that have given it the second-longest commuter rail system in the US, investment has not kept up with the region’s needs. The Chicago Tri-State metro-region's competitiveness is being undermined in part by the growing inadequacy of its transportation infrastructure, which is typified by high rates of road congestion. Over 80% of the 4 009 stream miles assessed in Illinois are considered sufficiently polluted to prohibit primary human contact (e.g. swimming) (IEPA, 2010). | C9: =VLOOKUP($A9, INDIRECT(C$1&"!B:D"), 3, FALSE) -> NOT SDG 7 | D9: =VLOOKUP($A9, INDIRECT(D$1&"!B:D"), 3, FALSE) -> NOT SDG 7 | E9: =VLOOKUP($A9, INDIRECT(E$1&"!B:D"), 3, FALSE) -> NOT SDG 7 | F9: =VLOOKUP($A9, INDIRECT(F$1&"!B:D"), 3, FALSE) -> TO DO | G9: =ABS((COUNTIF(C9:F9,"SDG 7")-COUNTIF(C9:F9, "NOT SDG 7")) / (COUNTA(C9:F9)-COUNTIF(C9:F9, "TO DO"))) -> 1 | H9: NOT SDG 7
A10: ab620f843a27c589f1c827210740acb6 | B10: For example, in Kenya, the paper manufacturer Chandaria Industries experienced savings of 40 per cent in energy, 48 percent in materials and 181 percent in water through involvement in the programme. Primary education is critical for developing a semi-skilled labour force. In low-income countries with large rural sectors, it can be vital for equipping farmers with the basic skills necessary to their being informed on and implementing sustainable agricultural and forestry practices. However, while the significance of achieving universal primary education is highlighted by its inclusion as a Millennium Development Goal, secondary, vocational and tertiary education are just as important in the field of green technology. Secondary education can provide core skills and knowledge needed for countries’ economic growth. Vocational schooling can be particularly useful in building technological competencies, successful vocational education also provides important links between education and industry. | C10: =VLOOKUP($A10, INDIRECT(C$1&"!B:D"), 3, FALSE) -> NOT SDG 7 | D10: =VLOOKUP($A10, INDIRECT(D$1&"!B:D"), 3, FALSE) -> NOT SDG 7 | E10: =VLOOKUP($A10, INDIRECT(E$1&"!B:D"), 3, FALSE) -> NOT SDG 7 | F10: =VLOOKUP($A10, INDIRECT(F$1&"!B:D"), 3, FALSE) -> TO DO | G10: =ABS((COUNTIF(C10:F10,"SDG 7")-COUNTIF(C10:F10, "NOT SDG 7")) / (COUNTA(C10:F10)-COUNTIF(C10:F10, "TO DO"))) -> 1 | H10: NOT SDG 7
A11: 6194ce1da1e7aed5cd5e9929d75f9742 | B11: An enabling policy environment is important for the development of a strong and competitive renewable energy sector to supply both industrial and domestic consumers. Section 3 identifies key enabling policy factors required for the replicability and accelerated uptake of the available renewable energy solutions throughout the mining sector. Major companies and conglomerates, among others, such as Glencore, Barrick Gold, Rio Tinto, Antofagasta, Codelco and IAMGOLD have all made use of renewable energy in their mines (Table 2.1). | C11: =VLOOKUP($A11, INDIRECT(C$1&"!B:D"), 3, FALSE) -> SDG 7 | D11: =VLOOKUP($A11, INDIRECT(D$1&"!B:D"), 3, FALSE) -> SDG 7 | E11: =VLOOKUP($A11, INDIRECT(E$1&"!B:D"), 3, FALSE) -> SDG 7 | F11: =VLOOKUP($A11, INDIRECT(F$1&"!B:D"), 3, FALSE) -> SDG 7 | G11: =ABS((COUNTIF(C11:F11,"SDG 7")-COUNTIF(C11:F11, "NOT SDG 7")) / (COUNTA(C11:F11)-COUNTIF(C11:F11, "TO DO"))) -> 1 | H11: SDG 7
A12: 62d5095d5d7ac925505de89dc9f446e1 | B12: Electricity access is commonly acknowledged as a basic need for human development (Scott and Seth, 2013), and has been described as a moral imperative, socially prudent and an economic necessity (GEA, 2016: 19). Aside from the public-good dimension of safe and reliable electricity supply, consumer protection and guaranteed access are important political-economy considerations (Bamber et al., Such energy-security concerns generally serve to reinforce State control and regulation of the electricity sector (Kuik et al., | C12: =VLOOKUP($A12, INDIRECT(C$1&"!B:D"), 3, FALSE) -> SDG 7 | D12: =VLOOKUP($A12, INDIRECT(D$1&"!B:D"), 3, FALSE) -> SDG 7 | E12: =VLOOKUP($A12, INDIRECT(E$1&"!B:D"), 3, FALSE) -> SDG 7 | F12: =VLOOKUP($A12, INDIRECT(F$1&"!B:D"), 3, FALSE) -> TO DO | G12: =ABS((COUNTIF(C12:F12,"SDG 7")-COUNTIF(C12:F12, "NOT SDG 7")) / (COUNTA(C12:F12)-COUNTIF(C12:F12, "TO DO"))) -> 1 | H12: SDG 7
A13: e18ef8fe59453b36226b3a625bcc78b6 | B13: In the scenario with an 80% renewable share, electricity prices are considerably lower compared to the other scenarios and the number of hours with electricity prices equal to or below zero rises to an astonishing 2 850 hours. A reduced occurrence of electricity prices higher than variable costs in combination with reduced utilisation hours means lower infra-marginal rents for recovering capital costs. Consequently, it is highly questionable whether conventional power plants can be profitably operated with high shares of renewables in energy-only markets with price formation being based on marginal costs. | C13: =VLOOKUP($A13, INDIRECT(C$1&"!B:D"), 3, FALSE) -> SDG 7 | D13: =VLOOKUP($A13, INDIRECT(D$1&"!B:D"), 3, FALSE) -> SDG 7 | E13: =VLOOKUP($A13, INDIRECT(E$1&"!B:D"), 3, FALSE) -> SDG 7 | F13: =VLOOKUP($A13, INDIRECT(F$1&"!B:D"), 3, FALSE) -> TO DO | G13: =ABS((COUNTIF(C13:F13,"SDG 7")-COUNTIF(C13:F13, "NOT SDG 7")) / (COUNTA(C13:F13)-COUNTIF(C13:F13, "TO DO"))) -> 1 | H13: SDG 7
... A93: f8a730809d29ac515eb7c5e34389c1b6 | B93: Consequently, there are more business options for the forest industry and forest-based raw materials than ever before. It still needs to be remembered that all four levels must be able to co-exist also in the future, even if their shares may change. All that can be produced without felling trees, e.g. carbon sinks, berries, game, tourism, etc. | C93: =VLOOKUP($A93, INDIRECT(C$1&"!B:D"), 3, FALSE) -> NOT SDG 7 | D93: =VLOOKUP($A93, INDIRECT(D$1&"!B:D"), 3, FALSE) -> NOT SDG 7 | E93: =VLOOKUP($A93, INDIRECT(E$1&"!B:D"), 3, FALSE) -> NOT SDG 7 | F93: =VLOOKUP($A93, INDIRECT(F$1&"!B:D"), 3, FALSE) -> TO DO | G93: =ABS((COUNTIF(C93:F93,"SDG 7")-COUNTIF(C93:F93, "NOT SDG 7")) / (COUNTA(C93:F93)-COUNTIF(C93:F93, "TO DO"))) -> 1 | H93: NOT SDG 7
A94: d974c1ee71b4e0f13b3df4e577c038e4 | B94: This corresponded to 32% of the total final energy consumption in the entire region. In parallel, India’s industry will play an increasingly important role as a driver for energy consumption in the region. While India’s industry accounted for 7% of the TFC in emerging Asia in 2013, this share is expected to increase to 13% by 2040. | C94: =VLOOKUP($A94, INDIRECT(C$1&"!B:D"), 3, FALSE) -> SDG 7 | D94: =VLOOKUP($A94, INDIRECT(D$1&"!B:D"), 3, FALSE) -> SDG 7 | E94: =VLOOKUP($A94, INDIRECT(E$1&"!B:D"), 3, FALSE) -> NOT SDG 7 | F94: =VLOOKUP($A94, INDIRECT(F$1&"!B:D"), 3, FALSE) -> TO DO | G94: =ABS((COUNTIF(C94:F94,"SDG 7")-COUNTIF(C94:F94, "NOT SDG 7")) / (COUNTA(C94:F94)-COUNTIF(C94:F94, "TO DO"))) -> 0.33333333 | H94: SDG 7 | I94: the notion of "growing energy consumption" relates to target 7.3
A95: 29d5da40fe85cc32f02d021b960ce2f8 | B95: Large areas of about 500 000 km2 between Mumbai and Bhopal and in Gujarat are covered by thick basalt layers. If basalt is shown to be a suitable cap rock, it is estimated that this would allow storage of 300 Gt C02 (Sonde, 2007). Three of the nine sites designated so far for UMPP projects are on the coast not far from these potential storage areas.13 For inland sites relying on domestic coal, additional costs of USD 5/tC02 for transporting the C02 are expected compared to coastal sites (Mott MacDonald, 2008). Gas consumption has been rapidly growing at a rate of 8% between 1990 and 2009. | C95: =VLOOKUP($A95, INDIRECT(C$1&"!B:D"), 3, FALSE) -> SDG 7 | D95: =VLOOKUP($A95, INDIRECT(D$1&"!B:D"), 3, FALSE) -> NOT SDG 7 | E95: =VLOOKUP($A95, INDIRECT(E$1&"!B:D"), 3, FALSE) -> NOT SDG 7 | F95: =VLOOKUP($A95, INDIRECT(F$1&"!B:D"), 3, FALSE) -> TO DO | G95: =ABS((COUNTIF(C95:F95,"SDG 7")-COUNTIF(C95:F95, "NOT SDG 7")) / (COUNTA(C95:F95)-COUNTIF(C95:F95, "TO DO"))) -> 0.33333333 | H95: NOT SDG 7 | I95: but remove the last sentence
A96: 0bc3671b295153b56be5727afdf182de | B96: On the production side (industry, commerce and agriculture), significant changes are expected as the economy grows nearly eightfold. This implies a massive expansion of the commercial/services sector (by a factor of six), a significant expansion of manufacturing activity, and more limited growth of activity in agriculture. However, water needs to be pumped from increasing depth and this is the main source of electricity demand in agriculture. Sources: IEA, 2009b, IEA, 2010a, IEA, 2009c. | C96: =VLOOKUP($A96, INDIRECT(C$1&"!B:D"), 3, FALSE) -> SDG 7 | D96: =VLOOKUP($A96, INDIRECT(D$1&"!B:D"), 3, FALSE) -> NOT SDG 7 | E96: =VLOOKUP($A96, INDIRECT(E$1&"!B:D"), 3, FALSE) -> NOT SDG 7 | F96: =VLOOKUP($A96, INDIRECT(F$1&"!B:D"), 3, FALSE) -> NOT SDG 7 | G96: =ABS((COUNTIF(C96:F96,"SDG 7")-COUNTIF(C96:F96, "NOT SDG 7")) / (COUNTA(C96:F96)-COUNTIF(C96:F96, "TO DO"))) -> 0.5 | H96: NOT SDG 7 | I96: the last sentence is tricky. We would consider it SDG 7 only, if it was something like "this is the main source of the growing electricity demand in agriculture"
A97: 1f58c4b1c412bf3dfc7812daa145daa7 | B97: Many off-shore wind farms have already been built and some governments are actively pursuing the large-scale deployment of this technology. Other low-carbon technologies such as CCS, which has a huge potential, are less mature and require a longer-term vision. Even where carbon pricing has been introduced, these technology policies have been kept or even accelerated. | C97: =VLOOKUP($A97, INDIRECT(C$1&"!B:D"), 3, FALSE) -> NOT SDG 7 | D97: =VLOOKUP($A97, INDIRECT(D$1&"!B:D"), 3, FALSE) -> SDG 7 | E97: =VLOOKUP($A97, INDIRECT(E$1&"!B:D"), 3, FALSE) -> SDG 7 | F97: =VLOOKUP($A97, INDIRECT(F$1&"!B:D"), 3, FALSE) -> TO DO | G97: =ABS((COUNTIF(C97:F97,"SDG 7")-COUNTIF(C97:F97, "NOT SDG 7")) / (COUNTA(C97:F97)-COUNTIF(C97:F97, "TO DO"))) -> 0.33333333 | H97: SDG 7 | I97: accidental mis-classification
A98: 5c18bc73a355e3bb2f41f8006c717c65 | B98: In addition, in 2014, EUR 5.8 mln from local budgets was used to finance eneigy efficiency measures (EEA, 2015). To date, there have been three calls. The first, in 2013, was launched for public institutions (including schools and hospitals), resulting in the selection of 86 projects worth a total of MDL 135 mln (about EUR 78 000 per project on average). | C98: =VLOOKUP($A98, INDIRECT(C$1&"!B:D"), 3, FALSE) -> SDG 7 | D98: =VLOOKUP($A98, INDIRECT(D$1&"!B:D"), 3, FALSE) -> NOT SDG 7 | E98: =VLOOKUP($A98, INDIRECT(E$1&"!B:D"), 3, FALSE) -> SDG 7 | F98: =VLOOKUP($A98, INDIRECT(F$1&"!B:D"), 3, FALSE) -> TO DO | G98: =ABS((COUNTIF(C98:F98,"SDG 7")-COUNTIF(C98:F98, "NOT SDG 7")) / (COUNTA(C98:F98)-COUNTIF(C98:F98, "TO DO"))) -> 0.33333333 | H98: SDG 7 | I98: as long as we fix the typo
A99: 4c567911242e96a326b0d95605fa3573 | B99: Since poor households tend to consume little electricity, they would likely benefit from overall reduced rates, or a “lifeline rate”. Commercial and industrial users could be charged higher rates, while SMEs would need more favourable treatment. Other ways to mobilize resources through tariffs include setting a transparent surcharge applied to higher income, commercial or industrial consumers, and using the proceeds to extend the service to poorer consumers. | C99: =VLOOKUP($A99, INDIRECT(C$1&"!B:D"), 3, FALSE) -> NOT SDG 7 | D99: =VLOOKUP($A99, INDIRECT(D$1&"!B:D"), 3, FALSE) -> SDG 7 | E99: =VLOOKUP($A99, INDIRECT(E$1&"!B:D"), 3, FALSE) -> SDG 7 | F99: =VLOOKUP($A99, INDIRECT(F$1&"!B:D"), 3, FALSE) -> TO DO | G99: =ABS((COUNTIF(C99:F99,"SDG 7")-COUNTIF(C99:F99, "NOT SDG 7")) / (COUNTA(C99:F99)-COUNTIF(C99:F99, "TO DO"))) -> 0.33333333 | H99: SDG 7 | I99: The "rate" in the text could be referring to something other than electricity (e.g., water rate). To remove the ambiguity, we add the word "energy" in the text: "... transparent energy surcharge ..."
A100: 4a01cc17157fe6fb3a1155729326dc7f | B100: By creating an enabling environment for the emergence of income-generating or income-improving activities, electrification projects can directly contribute to poverty eradication policies. Benefits for agricultural production include irrigation (perhaps with the use of water pumps), increased utilization of motors, food processing, refrigeration and also better access to training through information and communication technologies (ICT). Successful electrification programmes linked to agriculture would not only result in more competitive farming and create employment opportunities, but would also improve trading opportunities and local food security, including through the reduction of post-harvest losses. | C100: =VLOOKUP($A100, INDIRECT(C$1&"!B:D"), 3, FALSE) -> NOT SDG 7 | D100: =VLOOKUP($A100, INDIRECT(D$1&"!B:D"), 3, FALSE) -> SDG 7 | E100: =VLOOKUP($A100, INDIRECT(E$1&"!B:D"), 3, FALSE) -> SDG 7 | F100: =VLOOKUP($A100, INDIRECT(F$1&"!B:D"), 3, FALSE) -> TO DO | G100: =ABS((COUNTIF(C100:F100,"SDG 7")-COUNTIF(C100:F100, "NOT SDG 7")) / (COUNTA(C100:F100)-COUNTIF(C100:F100, "TO DO"))) -> 0.33333333 | H100: SDG 7 | I100: accidental mis-classification
A101: 30c83a848738f5d86d6bd284107e5232 | B101: In the EU, for instance, there was a rapid increase in the market share of the most energy-efficient appliances. Sales of Class A refrigerators increased from less than 5 per cent of total sales in 1995 to 23 per cent in 2000 and 61 per cent in 2005, in addition, 19 per cent of refrigerators sold in 2005 were in the two new, more efficient classes (A+ and A++). For washing machines, progress was even more rapid: with an increase in sales of 1 per cent in 1996, 38 per cent in 2000 and 90 per cent in 2005. | C101: =VLOOKUP($A101, INDIRECT(C$1&"!B:D"), 3, FALSE) -> SDG 7 | D101: =VLOOKUP($A101, INDIRECT(D$1&"!B:D"), 3, FALSE) -> NOT SDG 7 | E101: =VLOOKUP($A101, INDIRECT(E$1&"!B:D"), 3, FALSE) -> SDG 7 | F101: =VLOOKUP($A101, INDIRECT(F$1&"!B:D"), 3, FALSE) -> TO DO | G101: =ABS((COUNTIF(C101:F101,"SDG 7")-COUNTIF(C101:F101, "NOT SDG 7")) / (COUNTA(C101:F101)-COUNTIF(C101:F101, "TO DO"))) -> 0.33333333 | H101: SDG 7 | I101: Tricky because the sentence is about market share of energy-efficient devices, not devices becoming more energy-efficient. We add the sentence "Over the past decades, appliances have become increasingly energy-efficient." to the beginning to reduce ambiguity.

Sheet Output
A1: id | B1: text | C1: sdg | D1: label | E1: osdg_text_id | F1: doi | G1: comment
A2: =LEFT(MD5(B2), 7) -> #NAME? | B2: Not only does this have potentially negative effects on gender pay gaps and levels of social inclusion, but also Sydney is not fully utilising the skills currently available in its workforce. Moreover, this mixed labour market picture suggests that the low levels of unemployment are masking higher levels of inactivity. Youth unemployment is also high, although this is very much a global trend amongst advanced economies. | C2: 7 | D2: FALSE | E2: 448cfebe196e9aed00270dbd6ed9d3ce | F2: 10.1787/5kg20639kgkj-en
A3: =LEFT(MD5(B3), 7) -> #NAME? | B3: If too much water is stored behind the reservoir, sections of the river downstream from the reservoir can dry out if an insufficient amount of water is released at certain times of the year. This can lead to detrimental effects on animal and plant life downstream from the facility. Because of this, the channel may show signs of degradation (loss of sediments) or aggradation (accumulation of sediments), depending on whether floods can move the remaining incoming sediments. | C3: 7 | D3: FALSE | E3: 05ad33f26eff857ea273b271a7c648f5 | F3: 10.18356/aac9b96c-en
A4: =LEFT(MD5(B4), 7) -> #NAME? | B4: Energy efficiency targets are now in place at all levels of government. Nevertheless, in all countries and economic sectors, increased synergies between renewables and energy efficiency measures are possible, and oftentimes strengthening one will, in turn, strengthen the other. In both technical and policy contexts, renewable energy can have a positive effect on energy efficiency—and vice versa. Each of these steps presents opportunities to strengthen the energy efficiency of the overall system. | C4: 7 | D4: TRUE | E4: 51623ee78c26efaa4fbc70e63e7d503a | F4: 10.18356/f00277f1-en
A5: =LEFT(MD5(B5), 7) -> #NAME? | B5: Data over the last 30 years suggests that, had we switched off government subsidies to fossil fuels, global emissions would have been more than a third lower than they actually were in 2010. Countries need to make a SWAP. Nordic countries have started this shift away from fossil fuel subsidies and toward government support to heat pumps as in Sweden, electric cars as in Norway and wind power in Denmark. | C5: 7 | D5: TRUE | E5: 5f74051cc940cc85f3e35bf0c678484f | F5: 10.6027/9789289350167-3-en
A6: =LEFT(MD5(B6), 7) -> #NAME? | B6: Large areas of about 500 000 km2 between Mumbai and Bhopal and in Gujarat are covered by thick basalt layers. If basalt is shown to be a suitable cap rock, it is estimated that this would allow storage of 300 Gt C02 (Sonde, 2007). Three of the nine sites designated so far for UMPP projects are on the coast not far from these potential storage areas.13 For inland sites relying on domestic coal, additional costs of USD 5/tC02 for transporting the C02 are expected compared to coastal sites (Mott MacDonald, 2008). | C6: 7 | D6: FALSE | E6: 29d5da40fe85cc32f02d021b960ce2f8 | F6: 10.1787/5kgglrw4n7s0-en | G6: we have removed the last sentence about "gas consumption" to reduce ambiguity
A7: =LEFT(MD5(B7), 7) -> #NAME? | B7: The University of Troms0 has over 9 000 students and some 2 500 employees. Since Troms County has only 1% of its surface area classed as cultivable land, agriculture is a relatively minor part of land use. It is mainly located around the coast and was traditionally combined with fishing to form a key part of rural livelihoods. Troms County is at the northern limits of agricultural production possibilities, but the Gulf Stream enables some seasonal farming around the coasts and fjords, while the Sami people also carry out traditional reindeer herding. | C7: 7 | D7: FALSE | E7: 0d02b195616490f828e9c7e99e293799 | F7: 10.1787/9789264180444-17-en
A8: =LEFT(MD5(B8), 7) -> #NAME? | B8: In the short-term, a favourable future for the post-2015 sustainable development framework and an ambitious climate deal in Paris will not be possible without policy input. In the longer term, development objectives, including climate-related goals, need policy coherence as well as cash. Governments will need to adapt accordingly. | C8: 7 | D8: FALSE | E8: 4cf9ebc3e44f6f6fe764d85a6f3abc99 | F8: 10.1787/9789264236813-6-en
A9: =LEFT(MD5(B9), 7) -> #NAME? | B9: This motivation is still strong with the reality of recession and austerity in many countries making the idea of green employment growth a welcome antidote to the high unemployment rates. Capacity building and skill development within the regional communities are also important benefits of green initiatives. | C9: 7 | D9: FALSE | E9: 6cc45f35957a70dc1f450fbc4ab74b22 | F9: 10.1787/5k3w6ljtrj0q-en
A10: =LEFT(MD5(B10), 7) -> #NAME? | B10: By creating an enabling environment for the emergence of income-generating or income-improving activities, electrification projects can directly contribute to poverty eradication policies. Benefits for agricultural production include irrigation (perhaps with the use of water pumps), increased utilization of motors, food processing, refrigeration and also better access to training through information and communication technologies (ICT). Successful electrification programmes linked to agriculture would not only result in more competitive farming and create employment opportunities, but would also improve trading opportunities and local food security, including through the reduction of post-harvest losses. | C10: 7 | D10: TRUE | E10: 4a01cc17157fe6fb3a1155729326dc7f | F10: 10.18356/a2206e44-en
A11: =LEFT(MD5(B11), 7) -> #NAME? | B11: For developing countries, it is based on the evolution of absolute poverty (i.e. the proportion of population living on less than $1 a day). For developed countries, poverty is measured as relative income poverty (i.e. with the threshold set as a percentage of the median income in each county in each of the years considered). Only a few OECD countries have “official” measures of poverty that rely on “absolute" standards, typically in the form of the cost of a basket of goods and services required to assure minimum living conditions and indexed for price changes over time. | C11: 7 | D11: FALSE | E11: ac46c07bfea1873694224ecfd4ca833c | F11: 10.18356/fcd1ba6c-en | G11: fixed typo in text
A12: =LEFT(MD5(B12), 7) -> #NAME? | B12: These new partnerships arc working to provide the most cost-effective electrification solutions, especially in remote communities that arc often the most disadvantaged in terms of electricity access. Though progress in electrification continued at the regional level, it slowed in the recent period, attributable to population growth in rural areas and the ongoing difficulty of extending services to remote areas. The rate of progress has declined in countries with the largest deficits, namely India, Bangladesh, and Myanmar, while the lowest access rates arc found among a number of Pacific Island and least developed State.4 Though urban areas in most economics have achieved universal access, rural areas lag behind, and, in a few cases with growing rural populations, rural electrification rates are falling. | C12: 7 | D12: TRUE | E12: ddd9ab387d2fc7238a7336e01f4480c3 | F12: 10.18356/a81ec314-en | G12: fixed typo in text
A13: =LEFT(MD5(B13), 7) -> #NAME? | B13: In the scenario with an 80% renewable share, electricity prices are considerably lower compared to the other scenarios and the number of hours with electricity prices equal to or below zero rises to an astonishing 2 850 hours. A reduced occurrence of electricity prices higher than variable costs in combination with reduced utilisation hours means lower infra-marginal rents for recovering capital costs. Consequently, it is highly questionable whether conventional power plants can be profitably operated with high shares of renewables in energy-only markets with price formation being based on marginal costs. | C13: 7 | D13: TRUE | E13: e18ef8fe59453b36226b3a625bcc78b6 | F13: 10.1787/9789264188617-en
A14: =LEFT(MD5(B14), 7) -> #NAME? | B14: In its recent national plan, the Kiribati Development Plan 2016-19, the government has focused on improving infrastructure for the energy sector, including in renewables. The Kiribati Joint Implementation Plan on Climate Change and Disaster Risk Management notes the vulnerability of women, youth and children. In the past, Nauru’s economy was dependent on the phosphate industry, which also fuelled its energy demand. | C14: 7 | D14: TRUE | E14: 2a678f26ee1012ffd2f13e781a70ad92 | F14: 10.14217/9781848599574-13-en
A15: =LEFT(MD5(B15), 7) -> #NAME? | B15: At the operational level, a skilled workforce is needed for building and operating installations. The main instruments for reaching policymakers and C-Level decision makers are industry-run instruments. An example at the national level in Germany is the "Maritime LNG Platform"15 and at the international level "Sea\LNG"’4. On the shore.no particular competence standard or model courses for training of personnel directly involved in LNG operations or indirectly related to LNG operations exist. | C15: 7 | D15: FALSE | E15: 8a3a6ccb763c0d5c97e81708e6e0a40a | F15: 10.18356/feb1987a-en
A16: =LEFT(MD5(B16), 7) -> #NAME? | B16: A way to improve energy efficiency is to tap the huge potential for efficiency gains in the building sector which is the largest single energy consumer in Europe, absorbing 40% of final energy. About 75% of buildings are energy inefficient and, depending on the Member State, only o.4-1.2% of the stock is renovated each year. ( The energy efficiency target on EU level is set on fixed Mtoe-level for final energy and primary energy use in 2030, and the Member States have to set their targets so that this target will be reached. The Commission will lay down a process to ensure that the contributions add up to the Union's 2030 energy efficiency target in the legislative proposal on Energy Union Governance. | C16: 7 | D16: TRUE | E16: 725de70f6686eefb96c1653b790d6b6a | F16: 10.6027/9789289349918-3-en
A17: =LEFT(MD5(B17), 7) -> #NAME? | B17: However, at high penetration levels of variable renewables, i.e. above 20% of annual generation, the increase of variability and uncertainty leads to new challenges. The four challenges are summarized in the following table. The system operator needs to have enough capacity available during the hours where electricity demand is the highest, plus a reserve margin to cope with contingencies. | C17: 7 | D17: TRUE | E17: e1bcf5fe2ef14dbec5a8169cb1a36703 | F17: 10.1787/5k3wb8fmsz6h-en
A18: =LEFT(MD5(B18), 7) -> #NAME? | B18: The project is huge on several scales: at 4 800 MW, the plant will be the seventh-largest in the world, and the estimated construction costs of USD 17.8 billion is equivalent to 10% of South Africa’s GDP. The electricity from the plant will provide much-needed supply to South Africa’s mining and other industries, as well as generally supporting the quality of supply for household users. And being situated close to large low-cost domestic resources of coal provides a secure supply of fuel. The decision by the South African government to support this project was backed up by the World Bank which is providing just over USD 3 billion of loans, and USD 2.5 billion from the African Development Bank (Sovacool and Rafey, 2011). | C18: 7 | D18: TRUE | E18: 8d5c4d3906214299799340e13fe6047d | F18: 10.1787/9789264115118-6-en
A19: =LEFT(MD5(B19), 7) -> #NAME? | B19: The central government had been planning to capitalise on the good wind resource in the north of the country by increasing production of wind energy in these areas. It had selected several sites for locating wind farms. However, as the production of RE does not represent a concrete advantage for the hosting communities, and as there is a general perception that negative externalities are not being compensated for by the RE policy, they have tended to oppose them. | C19: 7 | D19: TRUE | E19: 355caa7c220d2fa90e8c0f53f57bf574 | F19: 10.1787/9789264180444-17-en
A20: =LEFT(MD5(B20), 7) -> #NAME? | B20: The proportion of the region's population living in slums fell from 34% in 1990 to 21% in 2014 (see figure V.19). In terms of absolute numbers however, although 2 million people left the slums, over 100 million still live in such settlements. This is exemplified by the negotiation of the New Urban Agenda, adopted at the United Nations Conference on Housing and Sustainable Urban Development (Habitat III), held in 2016. | C20: 7 | D20: FALSE | E20: b5fdc51af03856168f0dd458f1c47547 | F20: 10.18356/e9fa9dd4-en
A21: =LEFT(MD5(B21), 7) -> #NAME? | B21: Energy efficiency has very low priority in practice, determined by the fact that such a large proportion of the population does not have secure and reliable access to energy . This Programme aimed to ensure that the country’s distant regions receive power at a low price. It proposed construction of 189 small HPPs (SHPPs) with a total capacity of 103 MW by 2020, and generation of 800 million kWh of electricity per year. | C21: 7 | D21: TRUE | E21: 644786a2151dab6483b6521e865c0f32 | F21: 10.18356/aac9b96c-en
A22: =LEFT(MD5(B22), 7) -> #NAME? | B22: Throughout this week, electricity prices are relatively high, with a clear day-night pattern. Night prices of around 50 EUR/MWh are close to the marginal cost of coal fired power plants, while the higher prices during day times of around 90-100 EUR/MWh are close to the marginal cost of natural gas fired power plants. Total consumption (red dashed line), however, is more constant over the week, because electricity consumption for heating and pumping (pumped storage) increases at night, when electricity prices are low. | C22: 7 | D22: TRUE | E22: 3de3a33b6c50a93b9bf0e13ad8c0d089 | F22: 10.6027/8a4204a0-en
A23: =LEFT(MD5(B23), 7) -> #NAME? | B23: However, in the earlier stages, RD&D accounts for a larger share of performance improvements and cost reductions. While the depression is very disruptive and particularly destructive for the poor, it does at least potentially sow the seeds of renewal, provided that the world is prepared to make the necessary institutional and financial investments. This needs to occur without risking irreversible changes in ecological, biophysical and biochemical systems. | C23: 7 | D23: FALSE | E23: c6c0c3f173e584185fcd6269ca3ff227 | F23: 10.18356/95417570-en
A24: =LEFT(MD5(B24), 7) -> #NAME? | B24: The IAEA uses ICTs to support Member States in improving the functionality, safety and security of existing and new Nuclear Power Plants (NPPs) to ensure Affordable and Clean Energy (SDG 7) and improve Industry, Innovation and Infrastructure (SDG 9) by managing complex nuclear lifecycle technology systems. However, the applications of nuclear techniques - and the IAEA's work -in fact extend far beyond just nuclear energy. The IAEA's work extends into the education and training of health professionals in nuclear medicine techniques (SDGs 3 and 4 on health and education, respectively), monitoring of marine contaminants (SDG 14). | C24: 7 | D24: TRUE | E24: 96e05c536ae4c2f5e574d841bb9a5d41 | F24: 11.1002/pub/80f4cf5d-443a6582-en
A25: =LEFT(MD5(B25), 7) -> #NAME? | B25: Since poor households tend to consume little electricity, they would likely benefit from overall reduced rates, or a “lifeline rate”. Commercial and industrial users could be charged higher rates, while SMEs would need more favourable treatment. Other ways to mobilize resources through tariffs include setting a transparent energy surcharge applied to higher income, commercial or industrial consumers, and using the proceeds to extend the service to poorer consumers. | C25: 7 | D25: TRUE | E25: 4c567911242e96a326b0d95605fa3573 | F25: 10.18356/a2206e44-en | G25: The "rate" in the text could be referring to something other than electricity (e.g., water rate), so we added the word "energy" in the phrase "... transparent energy surcharge ..." to remove the ambiguity
A26: =LEFT(MD5(B26), 7) -> #NAME? | B26: Furthermore, the most severe accidents have occurred in these stages. Most of the severe accidents involved tankers (collisions, explosions, fires and impact with the ground) and road accidents during regional distribution. In the oil chain, fatalities are fairly evenly distributed among workers and the public (Burgherr and Hirschberg, 2008a). | C26: 7 | D26: FALSE | E26: 3b67ed2c408fb9348a08325fa98f3dbe | F26: 10.1787/9789264303119-en
A27: =LEFT(MD5(B27), 7) -> #NAME? | B27: In 2009, wind energy accounted for 56%of global clean energy investment. Investment in solar energy follows wind’s leading position and is poised to expand as a result of declining solar energy prices and the potential of new, thin-film technologies as noted by Pew (2010). New investment in biomass, geothermal and small hydro seems to play a marginal role in the total market (see Figure 7). Financial sector new investment (incl. | C27: 7 | D27: TRUE | E27: b4ff5d93a99f6112f717a546f404b3c4 | F27: 10.1787/5kg7068011hb-en
A28: =LEFT(MD5(B28), 7) -> #NAME? | B28: Indeed, the rising incidence of non-standard employment has widened the gap in earnings distribution and contributed to an increase in poverty. In Germany, the total income gain of households has gone to the richest 10 per cent of households since 2003 (Parma and Vontobel, 2009:129). The recent widening of inequalities marked a complete reversal of the previous trend. | C28: 7 | D28: FALSE | E28: 1b8b3de79df5c5923493cd5050d3ceae | F28: 10.18356/fcd1ba6c-en
A29: =LEFT(MD5(B29), 7) -> #NAME? | B29: The world’s leaders call for massive investment in the developing world, and UNEP insists that this investment be in green development. The International Energy Agency estimates that some $44 trillion - over and above the business-as-usual scenario - will be needed by 2050 to meet even the lowest of the IPCC’s estimates for stabilizing global climate, most of it in the developing world. Indeed, the agreements and contracts signed contain clauses that make a sustainable approach to development well-nigh impossible. We call for one thing in our political declarations, but do a very different thing in reality. | C29: 7 | D29: FALSE | E29: e5b9f53cfda6ec1c21ceadb708f69d48 | F29: 10.18356/fcd1ba6c-en
A30: =LEFT(MD5(B30), 7) -> #NAME? | B30: Scepticism about the science is no longer an option: the world’s scientists have never been so unanimous, and so ominous, in their projections of future perils. The bad news is that too many participants in the debate consider a climate policy as consisting primarily of manipulating markets and prices. If the only tool available were market liberalization, then the solution to every problem would seem to be a matter of getting the prices right. But setting a price for carbon emissions is only the beginning of climate policy - not the end. | C30: 7 | D30: FALSE | E30: 2528f76d29c8a44be2769f22b552e9a8 | F30: 10.18356/fcd1ba6c-en
A31: =LEFT(MD5(B31), 7) -> #NAME? | B31: According to the IEA’s WEO-2011, 1.3 billion people - nearly 20% of world population - currently lack access to electricity and about 2.7 billion people - 40% of the world population - rely on the traditional use of biomass for cooking (IEA, 2011a). The outlook suggests that the problem will persist and even deepen in some places. The IEA and World Health Organization estimate that household air pollution from the use of biomass in inefficient stoves would lead to more than 4 000 premature deaths per day in 2030, greater than estimates for premature deaths from malaria, tuberculosis or Human Immunodeficiency Virus (HIV)/Acquired immune deficiency syndrome (AIDS) (IEA, 2011a). The index seeks to capture the quality of energy services as well as their quantity. It is calculated in such a way as to mirror the United Nations Development Programme’s Human Development Index. | C31: 7 | D31: TRUE | E31: 10c26acfd397b509bd035a8bd93401d5 | F31: 10.1787/9789264115118-7-en
A32: =LEFT(MD5(B32), 7) -> #NAME? | B32: In 2012,63% of trips during morning and evening peak times were on public transport, compared to 59% in 2008. To increase this number even further, the LTA aims to make the transport system even more accessible and competitive. By 2030, 80% of households should be within a 10-minute walk of a train station, 85% of public transport journeys (less than 20km) will be completed within 60 minutes and 75% of all journeys in peak hours will be via public transport. | C32: 7 | D32: FALSE | E32: a5c19681ebb07ae9341468a13396d831 | F32: 10.1787/9789264236813-6-en
A33: =LEFT(MD5(B33), 7) -> #NAME? | B33: There is also a number of construction and operations contracts across the country for wastewater treatment plants, desalination facilities and reverse osmosis units. Because agriculture accounts for 71% of water usage, there are some arrangements whereby farmer associations in the Jordan Valley have been contracted by the local authority to manage water distribution in the area. The number of associations is expected to increase to ten by 2020 (EDP 2011-13). | C33: 7 | D33: FALSE | E33: 05e5041073e7db294006b31a460c46b5 | F33: 10.1787/9789264202276-9-en
A34: =LEFT(MD5(B34), 7) -> #NAME? | B34: This kind of system has been used successfully in Norway over a decade. As trees grow they continuously sequester carbon from the atmosphere. As cellulose, hemicellulose, lignin and other wood and bark components will be used for new purposes carbon can be stored for longer times in plastics and fabrics, and for shorter times in pharmaceutical products, chemicals, food and beverages, and so on. | C34: 7 | D34: FALSE | E34: 2d9020466b5292b7a7e34b4d706eef80 | F34: 10.6027/9789289329163-8-en
A35: =LEFT(MD5(B35), 7) -> #NAME? | B35: Durante is a fully integrated business that, in addition to fish products, offers a full range of services, including advisory services and franchise systems to mid-scale farmers. It is one of Nigeria's leading fish-farming businesses (NRI, 2014). Durante shifted away from tank culture to pond and cage culture because of power cuts and water constraints. | C35: 7 | D35: FALSE | E35: 796317916f6feac7e42344508a947fc6 | F35: 10.18356/faf8a648-en
A36: =LEFT(MD5(B36), 7) -> #NAME? | B36: In 2008, 70.8% of India's total population lived in rural areas, progressively migrating to urban areas at an annual rate of 2.3%, a rate which is below that of many other countries (UNPD, 2008). While such economic development has led to an average increase in the standards of living, it has left the agricultural sector untouched, bypassing most of the rural poor. Therefore, although India has enjoyed a growth of GDP per capita, poverty remains a challenge. Poverty is also more concentrated in some states such as the eastern and north-eastern states as Figure 7 shows. In March 2007, the Indian Planning Commission estimated that over the 2004-2005 Page | 63 period, more than one-quarter of India's total population (27.5%) still lived below the poverty line (BPL), with a distribution of 25.7% urban dwellers and 28.3% rural dwellers (Planning Commission, Government of India, 2007)37 as seen in Table 17. But strong economic growth alone does not bring such amenities to the rural poor. | C36: 7 | D36: FALSE | E36: 09d371f072d386c66ae086329a44aa38 | F36: 10.1787/5kmh3nj5rzs4-en
A37: =LEFT(MD5(B37), 7) -> #NAME? | B37: Given industry’s substantial contribution to global energy intensity, credible specific industrial energy-efficiency targets must be formulated. But to keep increases in industrial energy consumption to the minimum required to satisfy development needs, future efficiency efforts must be ambitious. They must double today’s pace and reach energy intensity reduction rates similar to those in the 1990s. Doubling the industrial energy-intensity reduction rate is consistent with a similar exhortation made at the global level in the AGECC (2010) report. | C37: 7 | D37: TRUE | E37: 2cd4fdfbe38a99441412e37921a2da5d | F37: 10.18356/7e830810-en
... A49: =LEFT(MD5(B49), 7) -> #NAME? | B49: Compared with other instances of social costs, one may think of tobacco smoking or lead concentration in drinking water, this process has developed reasonably quickly. First, there is public awareness and opinion creation by means of public communication. These may be commercial means of communication, such as television or newspapers, but also non-commercial means of public awareness creation such as demonstrations, sit-ins, public speeches and the like. Again, information is the first step in internalising external costs. This way, the set of choices is transformed into new choices that integrate a higher share of public concerns. | C49: 7 | D49: FALSE | E49: f6d5efdef2f9ea14a47527c057a04920 | F49: 10.1787/9789264303119-en
A50: =LEFT(MD5(B50), 7) -> #NAME? | B50: Electricity access is commonly acknowledged as a basic need for human development (Scott and Seth, 2013), and has been described as a moral imperative, socially prudent and an economic necessity (GEA, 2016: 19). Aside from the public-good dimension of safe and reliable electricity supply, consumer protection and guaranteed access are important political-economy considerations (Bamber et al., 2014; Scott and Seth, 2013). Such energy-security concerns generally serve to reinforce State control and regulation of the electricity sector (Kuik et al., 2011). | C50: 7 | D50: TRUE | E50: 62d5095d5d7ac925505de89dc9f446e1 | F50: 10.18356/73c3a080-en | G50: fixed academic references in text
A51: =LEFT(MD5(B51), 7) -> #NAME? | B51: The development of a shared evidence base and understanding of the city’s problems will help future planning and enable Sydney to better showcase its strengths and weaknesses to State and Federal policy makers. This is particularly relevant to the sustainability agenda where key stakeholders were beginning to come together across the city. Building on these relationships and partnerships should be a priority, in order act as a catalyst for a citywide sustainability strategy, which could potentially be seen as a working template for future city wide strategic partnerships and work. | C51: 7 | D51: FALSE | E51: 66e3db40126ffb45baee5598c3121304 | F51: 10.1787/5kg20639kgkj-en
A52: =LEFT(MD5(B52), 7) -> #NAME? | B52: Over the past decades, appliances have become increasingly energy-efficient. In the EU, for instance, there was a rapid increase in the market share of the most energy-efficient appliances. Sales of Class A refrigerators increased from less than 5 per cent of total sales in 1995 to 23 per cent in 2000 and 61 per cent in 2005, in addition, 19 per cent of refrigerators sold in 2005 were in the two new, more efficient classes (A+ and A++). For washing machines, progress was even more rapid: with an increase in sales of 1 per cent in 1996, 38 per cent in 2000 and 90 per cent in 2005. | C52: 7 | D52: TRUE | E52: 30c83a848738f5d86d6bd284107e5232 | F52: 10.18356/6e8bb756-en | G52: Tricky because there is a sentence about the market share of energy-efficient devices, not devices becoming more energy-efficient. We add the sentence "Over the past decades, appliances have become increasingly energy-efficient." to the beginning to reduce ambiguity.
A53: =LEFT(MD5(B53), 7) -> #NAME? | B53: Significant restructuring of the region’s economy over the past twenty years has transformed the demand for skills, making it more difficult for low-skilled workers to find employment in more knowledge-based, innovation-driven, growing sectors. Despite the higher-than-average levels of educational attainment in the region, chronic low graduation rates from the region’s public post-secondary educational institutions, particularly community colleges, slows the upgrading of the region’s workforce. Further, the increase in specialisation towards higher value-added activities in the Chicago Tri-State metro-region has not gone hand in hand with an increase of the share of the labour force with high qualifications. | C53: 7 | D53: FALSE | E53: d8af30adabb56201cb5606f036364f14 | F53: 10.1787/5k49dv6c5xmv-en
A54: =LEFT(MD5(B54), 7) -> #NAME? | B54: Many off-shore wind farms have already been built and some governments are actively pursuing the large-scale deployment of this technology. Other low-carbon technologies such as CCS, which has a huge potential, are less mature and require a longer-term vision. Even where carbon pricing has been introduced, these technology policies have been kept or even accelerated. | C54: 7 | D54: TRUE | E54: 1f58c4b1c412bf3dfc7812daa145daa7 | F54: 10.1787/5k3wb8fmsz6h-en
A55: =LEFT(MD5(B55), 7) -> #NAME? | B55: The OECD is also at the forefront of efforts to understand and to help governments respond to new developments and concerns, such as corporate governance, the information economy and the challenges of an ageing population. The Organisation provides a setting where governments can compare policy experiences, seek answers to common problems, identify good practice and work to co-ordinate domestic and international policies. The European Commission takes part in the work of the OECD. Current NEA membership consists of 30 OECD member countries: Australia, Austria, Belgium, Canada, the Czech Republic, Denmark, Finland, France, Germany, Greece, Hungary, Iceland, Ireland, Italy, Japan, Luxembourg, Mexico, the Netherlands, Norway, Poland, Portugal, the Republic of Korea, the Slovak Republic, Slovenia, Spain, Sweden, Switzerland, Turkey, the United Kingdom and the United States. The European Commission also takes part in the work of the Agency. | C55: 7 | D55: FALSE | E55: 6c094b959f7578c34063732cedc4a7ae | F55: 10.1787/9789264188617-en
A56: =LEFT(MD5(B56), 7) -> #NAME? | B56: Tracking progress towards achieving the Sustainable Development Goals requires the collection, processing, analysis and dissemination of data and statistics at the subnational, national, and regional levels, including those derived from official statistical systems and from new and innovative data sources. Many national statistical systems face serious challenges in this regard. As a result, accurate and timely information about certain aspects of people's lives are unknown, and many development challenges are still poorly understood. | C56: 7 | D56: FALSE | E56: 03aceee76df8ed0511df92e8262c69c8 | F56: 10.18356/cefc94d2-en
A57: =LEFT(MD5(B57), 7) -> #NAME? | B57: This option could lead to achieving the goal of a 40% reduction in energy intensity by 2030. The largest impact in energy intensity reduction will stem from efficiency improvements in the industrial and residential sectors. These products must be rapidly distributed on a large scale to achieve energy savings and reduce worldwide emissions. | C57: 7 | D57: TRUE | E57: baebc2406cec83bb365787cbd8c18104 | F57: 10.1787/5kg51nfc1321-en
A58: =LEFT(MD5(B58), 7) -> #NAME? | B58: While it is correct that, aside from hydro (the potential of which is low but of high quality) and wind (which provides low-quality power), modern renewables continue to be significantly more expensive, economic limits are ultimately a lesser constraint, as they can be overcome with political will and special efforts. In fact, most energy technology debates completely disregard associated socio-political limits. In pluralistic democracies, the “not-in-my-backyard” (NIMBY) attitude is a powerful factor. | C58: 7 | D58: TRUE | E58: cb7bc8e45845a3c9f2ff7666fe2eaddd | F58: 10.18356/5b6c49ea-en | G58: fixed typo in text
A59: =LEFT(MD5(B59), 7) -> #NAME? | B59: Sources of energy like geothermal, tidal power, hydrogen, nuclear fusion and so forth will require a more visionary approach and even greater scientific and technological advancement. These advances, in turn, will require substantial investment which, at present, is not forthcoming from public and private sources on a large enough scale. Only by ensuring a reliable, affordable supply of energy will it be possible to chart a stable course for economic recovery and growth. Addressing energy insecurity and transforming the global energy system must therefore constitute a major priority for any long-term programme of economic and climate stabilization in advanced countries. Such a course will simultaneously address the climate challenge. | C59: 7 | D59: TRUE | E59: 0856c7a172a9fe91126e6e9d82492c9b | F59: 10.18356/95417570-en
A60: =LEFT(MD5(B60), 7) -> #NAME? | B60: Increasingly, governments in high income nations, such as the United States and regional blocs such as the European Union, set market-entry standards that determine the green content of supply chains, particularly for the agricultural and resource sectors, which account for the bulk of Africa's exports. Their power comes from their capacity to threaten non-compliant multinational firms with reputational damage. An alternative strategy by civil society has been to engage big firms in a collective attempt to raise standards and certify best practice. | C60: 7 | D60: FALSE | E60: 315b83d7468f012ed8030ca35ed55a6c | F60: 10.18356/665c59ff-en
A61: =LEFT(MD5(B61), 7) -> #NAME? | B61: Low-wage residents are less likely to have access to a car, and commuter train lines and bus routes do not serve the south side of the Tri-State metro-region as well as they serve other parts of the region. Commuting times are even longer for those who commute across the region instead of following the hub and spoke system. Investment in public transport infrastructure does not sufficiently respond to demand for access to jobs, especially in lower -income neighbourhoods. While the Tri-State metro-region ranks high among OECD regions on many technology-based innovation indicators in terms of volume, its position has slipped and it is not among top regions when controlling for the size of its population and economy. For instance, in terms of patents per capita, the Tri-State metro-region ranked 23rd among OECD metro-regions and 11th among US metro-regions in 2007, the last year for which data are available, it ranked 27th and 12th, respectively, when adjusting for GDP (Table 1.5). These are hardly poor scores, but neither do they suggest that the Tri-State metro-region is fulfilling its innovation potential, particularly given that it ranks below so many other US metro-regions, including San Diego, San Francisco, New York, Boston, Los Angeles and Houston. | C61: 7 | D61: FALSE | E61: 7b76b91e09d54abc84b480f0db7f37e8 | F61: 10.1787/5k49dv6c5xmv-en
A62: =LEFT(MD5(B62), 7) -> #NAME? | B62: Although its ranking in terms of GDP per capita among OECD metro-regions is not as high as it is in terms of GDP (16lh among the 90 metro-regions vs. 8lh), Chicago still counts among the big players in the OECD urban world. With GDP per capita over USD 55 000 in 2008, Chicago ranked higher than traditionally rich European metro-regions such as London, Stockholm, Helsinki, Amsterdam-Utrecht, Paris and Milan (Figure 1.2). Among US metro-regions, Chicago’s GDP per capita is similar to that of San Diego and Philadelphia, but below that of a number of US metro-regions such as New York, Los Angeles, San Francisco-Oakland, Boston or Houston. | C62: 7 | D62: FALSE | E62: 23f59c31e9d0ddbb55a5f4b2df177abb | F62: 10.1787/5k49dv6c5xmv-en
A63: =LEFT(MD5(B63), 7) -> #NAME? | B63: According to the battery specification, the voltage is 3.3 V and capacity is 0.8 Ah, which implies Cphone = 2.96 [12]. The final parameter is calculated as F = 0.375, derived from the average monthly charging expenses of $2.25 and the average price per charge of $0.20 [3]. Consequently, Ephone = 24.5. | C63: 7 | D63: FALSE | E63: 0e70884074d0aaff7bcc68c77c674a8b | F63: 11.1002/pub/807e55db-ec047466-en
A64: =LEFT(MD5(B64), 7) -> #NAME? | B64: However, urbanization represents an additional challenge. Rapid increases in urban electrification rates in recent years have not matched the absolute increase in urban population, so that the number of urban dwellers without access to electricity has continued to rise. The continuation of such rapid urbanization, together with progress towards universal access, is likely to result in still greater pressure on the (already poor) T&D infrastructure, reinforcing the need for upgrading. | C64: 7 | D64: TRUE | E64: 96a7c26e6b1dc4def35ff6ebdbff9d86 | F64: 10.18356/1e8b62ff-en
A65: =LEFT(MD5(B65), 7) -> #NAME? | B65: Several hotels and universities have also contracted private firm to construct wastewater treatment plants. Certain groups of consumers - particularly in industry tourism, commerce and agriculture - are expected to pay a tariff reflecting the full cost of water service provision. An increase in the water tariff was approved in late 2010, potentially helping to improve cost recovery, but the Ministry of Water and Irrigation stated in June 2012 that tariffs would not increase further in the near future. | C65: 7 | D65: FALSE | E65: 002f6840660d0e3051543f0ba55c82ca | F65: 10.1787/9789264202276-9-en
A66: =LEFT(MD5(B66), 7) -> #NAME? | B66: It provides financial assistance to producers to install and maintain conservation practices on eligible agricultural and forest land. Energy conservation projects occur as part of the On-Farm Energy Initiative. Landscape AgEMPs have been available since 2009, and take a more holistic view of on-farm energy use, addressing issues, such as water use and erosion. Once the initial energy audit is complete, EQIP helps farmers develop a plan for implementing conservation practices. | C66: 7 | D66: TRUE | E66: 69c3547d0a4dde1fb18ad2e5e8654d0a | F66: 10.1787/9789264278530-8-en
A67: =LEFT(MD5(B67), 7) -> #NAME? | B67: Every time a lender underwrites an eligible loan under this programme, the Connecticut Green Bank reserves a percentage of the loan principal (between 7.5-15%) for the lender in the event of a default (Energize CT, 2013). In the Connecticut model, to promote sound lending practices and share risks, the lender assumes the “first loss” (1.5%) on its portfolio before it is permitted to access the reserve fund. When discussing credit enhancement, the terms guarantee and insurance are often used interchangeably. | C67: 7 | D67: FALSE | E67: 1b8096a8c65472366f9a60f60ec1c43b | F67: 10.1787/9789264224582-8-en
A68: =LEFT(MD5(B68), 7) -> #NAME? | B68: There are, however, many other potential impacts of accidents that are borne by the society as a whole and for which the internalisation is less straightforward and more complex. This is the case for the economic consequences on health and on the business property of a third party or on the environment. The entity liable for the accident is held responsible for the victims’ compensation, which ensures a certain internalisation of accident costs. | C68: 7 | D68: FALSE | E68: 07f17e85fc779d9e2b6f72fc7e884546 | F68: 10.1787/9789264303119-en
A69: =LEFT(MD5(B69), 7) -> #NAME? | B69: Electricity grids in the Pacific will need to be strongly interconnected, flexible enough to accommodate this change, and resilient enough to withstand climate impacts, as well as cope with potential demand growth from growing populations and growing electric vehicle use. Commonwealth Pacific small states are more dependent on the fossil fuels used in cars, trucks and boats than for generating electricity, and more cost-effective displacement of fossil fuel can occur through energy efficiency. However, the attention and funding of development partners is not always directed accordingly to these areas. Moreover, although this is improving, consumers generally lack awareness on how they can reduce their energy consumption or be more energy efficient. The International Renewable Energy Agency (IRENA) estimates that deploying renewables worldwide on the scale necessary to limit global temperature rise below 2 degrees would require current investment to double by 2020, and triple by 2030 to around US$900 billion annually (IRENA 2016b). | C69: 7 | D69: TRUE | E69: 1982e8b824ff8e01f7ec3ac363f26441 | F69: 10.14217/9781848599574-13-en
