Workbook

Sheet Info
B2: Hello 👋
B4: Welcome to the labeling exercise for SDG 5.
B5: The objective of this exercise is to label 100 texts in terms of their relevance to SDG 5.
B7: Your Labeling Sheet
B8: You have your own personal sheet for assigning the labels. You will find it by clicking on your name in the list at the bottom of this page.
B9: Each sheet has the same 100 texts, but the order in which they appear has been randomized.
B10: Later on, we will put everyone's labels side-by-side. This will help us identify texts with high and low alignment.
B11: At our next meeting, we will discuss the texts where we have disagreements and see if we can reach a consensus for the "true" label for every text.
B12: Please resist the temptation to look at other people's labels until you are done labeling. 🙂
B14: Explanation of Labels
B15: On your personal sheet, you will find the text in column C.
B16: Column D contains a drop-down for picking the appropriate label. The options are:
B18: TRUE | C18: This text is relevant to SDG 5
B19: FALSE | C19: This text is not relevant to SDG 5
B20: SKIP | C20: You can use this if you are not sure about the label
B22: If you want, you can put any comments in column E.
B24: Instructions for Labeling
B25: The text should be annotated as SDG 5 only if:
B27: 1. The text addresses SDG 5 or one of its targets
B28: See the official definitions of SDG 5 and its targets below ("SDG 5 Description & Targets").
B30: AND
B32: 2. The text addresses SDG 5 or its targets directly:
B33: - the text should be directly relevant to SDG 5 or to achieving SDG 5
B34: - if a text only has an indirect or implicit relevance, it should not be labeled SDG 5
B36: AND
B38: 3. The text addresses SDG 5 or its targets specifically:
B39: - the text should be specific to SDG 5 and its targets
... B77: Please click on your name to access your personal labeling sheet. Names are listed in alphabetical order.
B79: Name | C79: Progress (will update automatically)
B80: Finn | C80: =IFERROR(__xludf.DUMMYFUNCTION("SPARKLINE((100-COUNTIF(INDIRECT(B80&""!D:D""), ""TO DO""))/100+0.01,{""charttype"",""bar"";""max"",1.01;""min"",0; ""color1"", ""#4285f4""})"),"") | D80: =(100-COUNTIF(INDIRECT(B80&"!D:D"), "TO DO")) & " / 100" -> 100 / 100
B81: Gib | C81: =IFERROR(__xludf.DUMMYFUNCTION("SPARKLINE((100-COUNTIF(INDIRECT(B81&""!D:D""), ""TO DO""))/100+0.01,{""charttype"",""bar"";""max"",1.01;""min"",0; ""color1"", ""#4285f4""})"),"") | D81: =(100-COUNTIF(INDIRECT(B81&"!D:D"), "TO DO")) & " / 100" -> 62 / 100
B82: Jean-Baptiste | C82: =IFERROR(__xludf.DUMMYFUNCTION("SPARKLINE((100-COUNTIF(INDIRECT(B82&""!D:D""), ""TO DO""))/100+0.01,{""charttype"",""bar"";""max"",1.01;""min"",0; ""color1"", ""#4285f4""})"),"") | D82: =(100-COUNTIF(INDIRECT(B82&"!D:D"), "TO DO")) & " / 100" -> 0 / 100
B83: Meike | C83: =IFERROR(__xludf.DUMMYFUNCTION("SPARKLINE((100-COUNTIF(INDIRECT(B83&""!D:D""), ""TO DO""))/100+0.01,{""charttype"",""bar"";""max"",1.01;""min"",0; ""color1"", ""#4285f4""})"),"") | D83: =(100-COUNTIF(INDIRECT(B83&"!D:D"), "TO DO")) & " / 100" -> 100 / 100
B84: Steve | C84: =IFERROR(__xludf.DUMMYFUNCTION("SPARKLINE((100-COUNTIF(INDIRECT(B84&""!D:D""), ""TO DO""))/100+0.01,{""charttype"",""bar"";""max"",1.01;""min"",0; ""color1"", ""#4285f4""})"),"") | D84: =(100-COUNTIF(INDIRECT(B84&"!D:D"), "TO DO")) & " / 100" -> 100 / 100
B86: Thank you for being part of this exercise and thanks to OSDG for the dataset! ❤️
B88: Text Selection
B89: FYI: You do not need to read this section. We are just documenting how the texts for this exercise were selected.
B91: In total, 100 texts were selected from the OSDG dataset for SDG 5. The reason for selecting each text is documented in the "Source" sheet.
B93: Random Selection
B94: 50 texts were selected at random (using Google Sheet's RAND() function)
B95: - 25 texts that OSDG community labeled as "SDG 5"
B96: - 25 texts that OSDG community labeled as "not SDG 5"
B97: In the OSDG dataset, each text has an agreement score between 0 (equal positive and negative labels) to 1 (full consensus).
B98: Each set of the 25 texts above consist of:
B99: - 5 texts with agreement score > 0.8
B100: - 5 texts with agreement score > 0.6 and <= 0.8
... B117: - 1 text with agrement score > 0 and <= 0.2

Sheet Finn
A1: DOI | B1: Text ID | C1: Text | D1: SDG 5 Label | E1: Comments (optional)
A2: 10.1787/9789264224636-4-en | B2: 1212f63edf3c0cc3d070ffe8800ea6d3 | C2: Equality under the law, equality of opportunity' and equality of (political) voice have not yet been fully achieved in many MENA countries. Despite a number of steps taken, women in the MENA region continue to have a rather low level of legal protection against gender-based discrimination. The domestic laws in MENA countries are not always consistent with the gender equality principles set by international law, including the CEDAW. | D2: TRUE
A3: 10.18356/efc21c19-en | B3: 4c1b31c7bec2e84a3ca6802a5c46a8ca | C3: The maturity stages of e-Government for Gender Equality, which is an adaptation of the EGDI’s four-stage model, suggest key characteristics of the e-Government evolution regarding the usefulness of contents and services, technical sophistication and ease of use, degree of integration, etc. The framework was used for the analysis of national gender machinery websites from 11 countries presented in Chapter 3 of this report. They have links to ministries, departments and other branches of government. | D3: TRUE
A4: 10.18356/77d08b03-en | B4: f040d7270a4160b55f0ba9f8508bfb76 | C4: They entail wide-ranging coordination between different authorities, i.e., they are not the exclusive responsibility of labour ministries (ECLAC, 2005). Labour regulation policies, on the other hand, are those that act upon the relationship between workers and employers through provisions designed to secure rights: non-discrimination, minimum wages and social security, among others. Labour market policies, for their part, have the object of combating unemployment, mitigating its effects and supporting the population at risk of joblessness. These policies can be divided into passive ones designed to offset the loss of pay, such as subsidies, and active ones, which are meant to preserve existing jobs and support the creation of new ones, help the unemployed find work, facilitate the connection between labour supply and demand and improve the skills of the unemployed and those working in microenterprises and small businesses (Samaniego, 2002). | D4: FALSE | E4: not specific to gender
A5: 10.1787/9789264179370-6-en | B5: e1338993d5cbc255cb6640d43c46fee1 | C5: The survey was carried out in 2011 by Gallup Inc. as part of its Gallup World Poll, and covered over 150 000 people. The target population was the entire civilian population aged 15 and older. Interviews were conducted face-to-face in economies where telephone coverage represented less than 80% of the population and by telephone in countries with higher coverage. | D5: FALSE
A6: 10.6027/9789289338974-12-en | B6: bdc51a5af542282c68a617bd88facd08 | C6: Marshall defined social citizenship as "including social rights, these being the right to a modicum of economic welfare and security and right to live the life of a civilized being (quoted in Jenson, 2006:6)" (Poppel, M. 2014: 127). You can be provided for by your family, by charity organizations or by friends. Fulfilling the norms of a given community gives access to its resources. | D6: FALSE
A7: 10.18356/0899dee9-en | B7: f9180ca14ff754bcd98d9ea8e1d7314f | C7: Organized in the Red de Genera y Familia, the first step was convening Care Dialogues, an advocacy strategy which aimed to raise the visibility of care on the public agenda.154 But in contrast to the above-mentioned cases, it was die engagement with the ruling party, Frente Amplio, and the inclusion of the SNIC as part of the electoral campaign programme for 2010-2015 that proved crucial.155 Care thus became a political, and not only a technical, public policy issue. Because the importance of unpaid care and domestic work had already been recognized, the discussion could centre on concrete policy design and implementation. These data have yielded, for example, measurements of “time poverty”168 and its relation with income poverty. | D7: TRUE
A8: 10.18356/a5e42fa0-en | B8: 8a0c60386ec53a00c7302c3a929f50b3 | C8: Despite this progress, bilateral aid to LDCs fell by 3.9 per cent in real terms. However, remittances to developing countries fell in 2016 for a second consecutive year, declining by 2.4 per cent over 2015. This section provides a few highlights of these interconnections in the context of the theme and Goals under review at the High-Level Political Forum on Sustainable Development in July 2017. | D8: FALSE
A9: 10.18356/1c6c11de-en | B9: 8d7dc9b37931f38c5039e8cb2eef2d6f | C9: Savings' made from cutting back on government funding of public services often increase demands on unpaid care and domestic work. Because these hidden costs are not recognized in economic planning, this can create the illusion of efficiency gains when in fact costs are being transferred from the public sector to the private sphere.32 In the health sector, for example, efficiency may seem to increase when the time that patients spend in the hospital decreases and as a result the cost of providing treatment per patient appears to drop. But cuts to public health expenditure can have substantial and unrecognized knock-on effects for caregivers in households, who may be forced to take time off paid work to care for a sick family member. | D9: TRUE | E9: not specific to gender; but neither is the target
A10: 10.18356/f5ce8f94-en | B10: 3382aade6de482a469b43b0ac076bdee | C10: Intimate partner violence against women: experiences from a woman-focused development programme in matlab, Bangladesh, Journal of Health Population and Nutrition 23(1): 95-101. Combating gender-based violence and enhancing economic empowerment of women in Northern Uganda through cash transfers. Love on the Rocks: Domestic Violence and Alcohol Abuse in Rural Mexico. The B.E. Journal of Economic Analysis & Policy: 8(1), article 43. | D10: TRUE
A11: 10.18356/0899dee9-en | B11: 5d71c3bd1a3b9b86517b23e200483317 | C11: Enrolment is increasing in all regions of the world but still varies widely between and within regions. In Central and Eastern Europe, and Latin America and the Caribbean, enrolment is high due to a historically strong public education sector. In Central Asia, the Arab States and sub-Saharan Africa, enrolment rates are very low, although there are some intra-regional variations. Even in regions with better coverage, the inclusion of marginalized populations is still a challenge. In the Arab States, private providers cover almost half of all enrolment and in Africa around 60 percent. In Kenya, for example, the government programmes target children aged 4 to 5 years, even though the policy framework identifies children within the 0 to 5 age range as intended beneficiaries. | D11: FALSE
A12: 10.18356/2c8682bc-en | B12: 4b810c6f99caddec8b250387b1589964 | C12: Its effect on the quality of Lw is related to the values transmitted through education within households and to the health care carried out there. Domestic labour also influences the number of hours of wage labour available, as it releases this from care responsibilities. Reproduction is caught between a given wage and people’s needs and wants. “ | D12: TRUE | E12: not specific to gender; but neither is the target
A13: 10.18356/caeceb38-en | B13: 097588fda30192cce1b6fb3efb5a1f66 | C13: As we would expect, these proportions increase with age such that between half and three quarters of older adolescents are working, or seeking work. However, adolescents frequently combine school and work. Research in South Africa and Zimbabwe on distribution shows that most working adolescents live in very poor households in rural areas and are engaged in subsistence agriculture, many combining this with domestic work (including care) and commercial agriculture (Robson, 2004, Bray, 2012, Dawes et al., | D13: FALSE
A14: 10.1787/soc/aag-2014-5-en | B14: aa2e650903052a45c6c1b6828135bfac | C14: This is the case in Azerbaijan (90%), the Kyrgyz Republic (87%), Armenia (83%), New Zealand (82%), Myanmar (81%), Korea (76%) and Australia (72%). As in most OECD countries, health and the humanities are the other most popular degrees women obtain in the Asia/Pacific region (Figure 2.3). Women, on the other hand, are underrepresented among students and graduates of degrees in the so-called STEM fields of study - science, technology, engineering and mathematics (STEM). Innovation can benefit from a concentration of individuals with STEM skills. | D14: TRUE
A15: 10.14217/9781848599451-24-en | B15: 56bdf2e958ecda277070ad0e78ae42a0 | C15: The success of GBV integrated service provision depends on co-ordinated programming that engages the different sectors across multiple levels with institutional buy-in of key stakeholders. Collaboration between the various service providers (medical, legal, police) is essential and services that are adequately resourced and located under one roof can be more readily accessed, leading to increased report and service demand as more people are able to benefit. The last decade has been the most progressive in terms of introducing new laws aimed at preventing VAWG. | D15: TRUE | E15: VAWG = violence against women and girls
A16: 10.1787/5js30tvj21hh-en | B16: b41993950e8ada940f2ce81ffe3a2781 | C16: This result is significant, and it is quite high compared to other factors. The marginal effect is less important than having technical or vocational education, but NREG is particularly well fitted for rural female work. It gives a local (computed on the household who did enter the programme) evaluation of the effect, which is more accurate. The average treatment effect on the treated (part of the programme) is 0.095. | D16: TRUE | E16: Mahatma Gandhi National Rural Employment Guarantee Scheme (MGNREGS); indirect benefit only?
A17: 10.18356/5085bf5a-en | B17: 6a390516c7b15f3b27739ce3b4337184 | C17: Although a number of countries, mostly in Europe, that have adopted such measures have experienced modest increases in fertility between 2000-2005 and 2005-2010 (United Nations, 2013a), the implementation and effectiveness of such measures have been difficult to ascertain. While the percentage of Governments with policies to raise fertility has increased steadily from just 9 per cent in 1976 to 27 per cent in 2013, the percentage of Governments with policies to lower fertility increased from 27 per cent in 1976 to 42 per cent in 1996, and then remained at 43 per cent in 2013. During this time, the percentage of Governments that did not have policies to influence fertility has declined steadily from 52 per cent in 1976 to 13 per cent in 2013 (table III.l). In 1976, only about one in every five Governments in more developed regions had policies to raise fertility, but by 2013 this proportion had risen steadily to more than two thirds. | D17: TRUE
A18: 10.1787/9789264213944-8-en | B18: c63b1ade007787cd8e30feacb3a31f18 | C18: It provides the financing and capital necessary for their development, it supports the entrepreneur when strategic decisions have to be made, and it facilitates the improvement of the company’s potential for generating value for its customers, shareholders and all officers and employees. The objective of this stage, which is financially very risky, is to finalise the development of a technological prototype that makes it possible to meet the technological challenge, and begin to assess the existence of a potential market. The signing of a first client constitutes the transition to the venture capital stage. The few successful projects should more than offset the capital losses of those who fail. | D18: FALSE
A19: 10.18356/604a5a2e-en | B19: 3170e6ccd61878ce07fbc1a0149eba25 | C19: Pregnant women have blood and body fluids that could expose health workers to the virus," Jallah says. I suffered a lot and was afraid I was going to die. The only thing I hoped for was for a miracle to happen," she says. One did: Comfort gave birth to two healthy baby girls with the assistance of a nurse aid who happened to pass by at the right time. | D19: FALSE | E19: Target 3.1
A20: 10.18356/c30f3d31-en | B20: 64889f77b8ac3876aa12ab72f6e3ea1f | C20: Coverage and enforcement of legal minimum wages are equally important. In developing countries many women in the informal economy are not legally covered by minimum wages. However, minimum wage legislation can still play a positive role:first there is some evidence that minimum wages in the formal sector improve wage levels in the informal sector too, known as a "lighthouse effect"” and second, the minimum wage sets a standard for pressure groups and trade unions to aim at when pressingfor improved conditions for informal workers in a subcontracting chain. | D20: TRUE
A21: 10.18356/efc21c19-en | B21: 54adceba3c4278906b489527f4097858 | C21: An efficient use of ICT can disseminate government information to a broader audience in a fast and convenient manner. At the initial stage of national e-Government development, an ideal point of entry for developing countries would be setting up a website for the national gender machinery. The website, as an official gateway to gender-related policies and programmes, would provide a ready access to online information ranging from the organizational structure of the national gender machinery to government statistics, publications, government services and programmes aimed for women’s empowerment. Through the use of technology, the interaction between the governments and women can be stimulated and become more effective. Basic forms of interactivity available through emails, downloadable forms, discussion forums and online polls not only provide an improved delivery of basic services, but also build up a basis for online participation. | D21: TRUE
A22: 10.18356/07f2a46c-en | B22: e2c0b3bd85978d0798b4069b139c32fe | C22: While in Cambodia and Thailand the epidemic is slowing down, this is not yet the case with Indonesia and Viet Nam. More and more, however, new cases of infections are women who have acquired HIV from unsafe sex with their stable partners. In Thailand, this group accounted for more than 4 in 10 (or 43 per cent) of new infections in 2005 (UNAIDS and WHO, 2008, p. 16). | D22: TRUE
A23: 10.18356/3a0cd6ba-en | B23: d6641ebe70f6fbd4981994ea47fc1e99 | C23: The most significant gaps were in: technology and technology transfer, access to finance, promotion of entrepreneurial education, cheaper, faster start-up and better regulations, and access to support services. These gaps reflected weaknesses in national legal frameworks and SME agencies, as well as in the elaboration and implementation of specific policy measures. Drawing on the World Economic Forum’s Global Competitiveness Index, this framework focuses on key entrepreneurial conditions (Box 2).'9 GEM is the basis for an annual national Adult Population Survey, along with National Expert Surveys. | D23: FALSE
A24: 10.1787/9789264265493-8-en | B24: 810c738ee49a6592c53e055950cddf2e | C24: Leaders and managers in organisations, who likely made time sacrifices to reach their current rank, often have difficulty accepting that work can be done in fewer hours. In some workplaces, “non-compliers” - those employees who opt to take flexible work hours and family leave - may actually be punished via denied promotions, reduced visibility to superiors, or exclusion from important projects. In-office “face time” remains an important metric of evaluating employees, even if it does not correspond with output (Elsbach and Cable, 2012). | D24: FALSE | E24: this is indirectly limiting women's ability to take leadership roles
A25: 10.18356/5085bf5a-en | B25: db5fb32cbad0993b82ca58f3da36a8bf | C25: Since the mid-1990s, the proportion of Governments that viewed adolescent fertility as a major concern has risen steadily in all major world regions, except in Northern America. Such programmes also include innovative educational approaches, including peer counselling for young people and orientation for parents, as well as strengthening education on reproductive and sexual health in non-formal settings, vocational training programmes and youth clubs (United Nations Population Fund, 2007). In 2013, 94 per cent of Governments in less developed regions had policies and programmes to reduce adolescent fertility, compared with 77 per cent of Governments in more developed regions. All Governments in Latin America and the Caribbean, Northern America and Oceania, and all but one Government in Africa, had policies and programmes to reduce adolescent fertility in 2013, whereas 23 per cent of Governments in Europe and 19 per cent in Asia did not have such policies or programmes. | D25: TRUE
A26: 10.18356/ca9f4916-en | B26: b6dee1e7c9523d4f0a3984cad1d2bbc7 | C26: The sheer volume of women adding their voices to the conversation, saying “I hear you, I understand you, I believe you”, has enabled them to find courage. Providing women with a chance to unburden painful experiences, and ultimately find relief, serves as collective therapy that is free and open to all. Women everywhere can say “me too” to someone else, whether that means “it happened to me” or simply “I believe you.” | D26: TRUE
A27: 10.18356/27e660be-en | B27: 772a64e323ae3b9a00ab99cef581966a | C27: A diverse group of women through the Liberian Women's Initiative prevailed upon warlords and political leaders in concerted actions all over Liberia, as well as in Nigeria and Ghana during the peace negotiation processes (African Women and Peace Support Group, 2004). Through the Women of Liberia Mass Action for Peace under the banner of the Women in Peacebuilding Network, which I coordinated, Liberian women mobilized aggressively for peace between 2000 and 2003, using advocacy, mass protests and sit-ins as well as the presentation of petitions to the former Liberian President Charles Taylor and other international actors. Our activism combined with international action on war crimes and military action resulted in the signing of the peace agreement, officially ending the war. While these causes are diverse, social, political and economic inequality plays a significant role together with state collapse, economic decline, and historical patterns of conflict and battles for control of natural resources (DFID, 2001). | D27: FALSE
A28: 10.18356/914e7bcc-en | B28: f43d0e85dc177042358b28e93e6c51ea | C28: In terms of context, these CoSOs may precede the eruption of conflict, may deal with issues not relating to the conflict (in Israel and Turkey for example) or may be established as a result of the conflict (in Bosnia, Cyprus and Thrkey). In terms of identity, the vast majority of these CoSOs are civic, post-national or multicultural. In terms of FOA the organizations work on issues directly relating to the conflict, but also on political issues that do not relate strictu sensu to the conflict. | D28: FALSE
A29: 10.1787/9789264027862-12-en | B29: 291fef8c6e48972332d63f5ab0ffdff2 | C29: Policies that increase and improve family contact are also essential as well as policies to prevent and respond to sexual harassment and rape of male and female prisoners. Female prisoners are likely to find strip searches particularly traumatic, and policies regarding strip searching should be separately and carefully formulated as it regards male and female prisoners. Other matters to be considered include: arrangements for privacy when people are required to remove their clothing, privacy in toilets and showers, use of private locks on cells, provision of hygiene items for women, and minimising indignity in the way urine and other samples are collected for drug testing. Poor prison conditions, lack of proper care and facilities, and the high level of stress that accompanies incarceration may place at risk both the health of a pregnant woman and that of her unborn child. Pregnant women should only be held in prison in the most extreme circumstances, such as when there is a concrete threat of violent crime. Special provisions should be made for ante and post-natal care and treatment, and babies should not be born in prison. | D29: TRUE
A30: 10.1787/9789264281318-13-en | B30: 1d739c81852aec6acdf3904d919d0524 | C30: The 2015 OECD/INFE survey showed that in 15 countries and economies men are less likely than women to agree with at least one of the statements: “Before I buy something I carefully consider whether I can afford it” and “I keep a close personal watch on my financial affairs”. In 13 countries and economies men are more likely to agree with at least one of the statements: “I tend to live for today and let tomorrow take care of itself’ and “I find it more satisfying to spend money than to save it for the long term” (Table 10.A 1.3 in OnUne Annex 10.A1). Fewer women than men in 19 out of 30 countries and economies would be prepared to risk some of their own money when saving or making an investment. | D30: TRUE
A31: 10.14217/967bd43c-en | B31: 1e0a700a4aabfbb4408648e08f6daf33 | C31: For purposes of this paper the definition will focus on ‘forced marriage’ and ‘early marriage.’ The reason for this is that by definition, ‘child’ marriages7 can be considered ‘forced marriage’, or a form thereof, because children especially those under the age of 15 are not able to make an informed decision as to whether or not they want to be married. Most often this decision is influenced by a parent or family member. | D31: TRUE
A32: 10.1787/9789264259157-5-en | B32: 63068a4c52e7d377dee1d40aed455865 | C32: There is a lot that companies can do to prevent long hours. The overarching goal is to adjust workplace culture so that managers prioritise tasks, time management, and efficient output rather than time in the office. Leaders must recognise that working long hours is not necessaiy for high-quality work and may even prevent it. | D32: FALSE
A33: 10.18356/2e1a4924-en | B33: 1bbfbe8960be36484e2a78c9ace6b313 | C33: Second, qr is less sensitive than ols to outliers in the dependent variable since it minimizes the weighted sum of absolute deviations. Moreover, when the error terms are non-normal, qr also gives a more efficient estimator than least squares. Lastly, qr has a linear programming representation that makes estimation easy. | D33: FALSE
A34: 10.1787/9789264259157-7-en | B34: b4567b9a5b7330fb9b2f60323c881bb5 | C34: A recent reform has further enabled parents of children bom after June 2016 to make even more flexible use of the job protection provision: With the employer’s consent, they can use 12 months of the 36 month employment-protection period any time between the child’s third and eighth birthday. But, beyond the provisions of parental leave (Elternzeit) and family care leave (Pflegezeit and Familienpflegezeit), employees in Germany are not legally entitled to resume full-time work once their reduced working hours have been approved by their employer (see Chapter 3 for an international comparison of legal provisions). On average, full-time working mothers in Germany put in nearly 42 hours per week, outstripped only by Swiss and Austrian mothers with about 44 hours per week (Figure 4.6). | D34: TRUE
A35: 10.18356/fa8ae033-en | B35: b06f04f91816c525adcc20747a5dee7b | C35: Gender Equality Observatory of Latin America and the Caribbean: Annual Report 2012-A Look at Grants, Support and Burden for Women. Santiago, Chile: ECLAC. Accessed 14 September 2017, https://www.cepa!. The Impact of Conditional Cash Transfer Programs on the Time Allocation of Beneficiaries: The Case of’Oportunidades’ Program in Mexico." | D35: TRUE
A36: 10.18356/b82bdbfb-en | B36: 318fe8fdc7167bdb17eedef9d584aac9 | C36: Evidence demonstrates that when a critical mass of women participates in decision-making, their contributions and needs are more likely to be recognized and addressed. Even though attention has largely focused on women's leadership and participation in national parliaments, there is a pressing need to realize women’s leadership throughout the daily lives of all Africans - in the home, in the economy and markets, and in society as broadly defined. Reducing inequalities in access to health and education, in addition to giving women greater choice in family decisionmaking, can have significant benefits for women and important inter-generational benefits. | D36: TRUE
... A38: 10.1787/9789264265493-7-en | B38: 4b3e00eda804bc06de54bf2c37995ede | C38: Providing both parents with flexible work schedules and the possibility of short-term part-time work can also ease tensions between caregiving and work as children age (Chapter 4). Designed to be used around childbirth and when children are very young, employment-protected leave provides job security while allowing mothers to recuperate from childbirth and gives both parents time to care for young children. Paid leave gives families valuable income support at a time of increased stress on household budgets. | D38: TRUE
A39: 10.1787/5jm2hz8dgls6-en | B39: afb2f20182972c1ba7041c3f86b05e84 | C39: It is an average of the squares of its five sub-indices (equation 10). It ranges from 0, indicating very low levels of discrimination, to 1, indicating very high levels of discrimination. Three-years average (2009-11). Three-years average (2009-11). Three-years average (2009-11). Three-years average (2009-11). | D39: FALSE | E39: not specific to gender
A40: 10.18356/cb17bdad-en | B40: 4916d8af58848267431dae37fcbf81d0 | C40: Poverty is not solely a lack of income, but rather is characterized by a vicious cycle of powerlessness, stigmatization,discrimination, exclusion and material deprivation,which all mutually reinforce each other' (ibid, para. The vicious cycle means that ‘the greater the inequality, the less the participation, the less the participation, the greater the inequality’ (ibid, para. Lack of participation is both a cause and consequence of poverty. Poverty is itself a ground of discrimination, but people living in poverty often experience other forms of discrimination based on,for example, gender, disability, ethnicity, and so on. | D40: TRUE
A41: 10.1787/9789264224636-7-en | B41: 3f641e23050c65d90672a8290295bb67 | C41: The committee facilitates the integration of women’s needs in the government’s work plan as well as monitors and evaluates the mainstreaming of women’s needs in national policies. Furthermore, it also supports the creation of gender-sensitive budgets. The committee conducts studies and reviews the impact of policies on women and men. It is composed of parliamentarians from all political parties and includes a chair, two vice-chairs and eight members who study, evaluate and report on matters and bills relating to the status of women. | D41: TRUE
A42: 10.1787/9789264265493-9-en | B42: 72bc2099057c5d0da7d38f1cee7f3e77 | C42: The concept of critical mass as applied to women’s political representation, and the UN targets that have flowed from it, have played an important role in supporting countries in the adoption of gender quotas in various spheres of the public and private sectors. According to data provided by the Inter-Parliamentary Union (IPU, 2015), the global average of women in national parliaments has nearly doubled in the past 20 years from 11.3% in 1995 to 22.1% in 2015 (a rise of 10.8 points). However, recent socio-political studies (Childs and Krook, 2008), as well as IPU data (IPU, 2015) confirm that the achievement of a critical mass is no longer seen as the sole target of efforts to bring about gender-equal participation in positions of leadership. | D42: TRUE
A43: 10.1787/5js30tvj21hh-en | B43: 650df03322e86b6f089f407ba080b21a | C43: If all those reforms happened in a particularly rigid state - as it is likely to be the case, it is highly probable that employment will still suffer from this former rigidity. It will then introduce a negative bias in the evaluation. A positive value means a pro-worker state’s legislation (often tied to institutional rigidity) and a negative value means pro-employer legislation (more liberal). Conversely to labor reform’s index we do not have this index for every states. | D43: FALSE
A44: 10.1787/5jm0xdx0b06g-en | B44: 68cc56f99f7433126251488792ae8b82 | C44: The law entered into force the last quarter of 2014, though some provisions will be phased in over the 2015-2018 period. The overall goal tax reform is to raise the tax-to-GDP ratio to finance a large increase in education spending. The tax measures aim to raise an extra 3% of GDP. More than half of the increased revenues are forecasted to come from increased income taxation, mainly from corporate income (Table 1). Increases in compliance are forecast to increase revenues by 0.5% of GDP (17% of the overall reform revenue goal), while expansions in the VAT base will account for 0.3% of GDP (12% of the overall reform target. To raise more revenues Chile could focus on broadening the tax base of the personal income tax (PIT), which does not contribute significantly to reduce inequality. | D44: FALSE
A45: 10.1787/9789264210745-6-en | B45: 8b8efdd6ae34ef52bbded7d658b5866a | C45: The Inter-Departmental Co-ordination Group assumes responsibility for: promoting co-operation between ministries, adopting a federal plan of action, preparing an intermediary' report and a final report at the end of the term, and exchanging good practices and promoting instruments useful to enforcing the law. The representatives of the ministries participating in the co-ordination group are also appointed as gender focal points in their respective entities. They receive compulsory' training on gender mainstreaming and are tasked with ensuring follow-up on the diverse measures foreseen by the law (e.g, gender statistics, gender-responsive budgeting and the “gender test”). | D45: TRUE
A46: 10.18356/ea8c16ef-en | B46: cc7ff9087fabcdc500e8966e260520e3 | C46: They reported that cash transfers had the greatest impact on marriage-related indicators, noting that the transfers worked as an incentive to stay in school and increase financial independence, both of which could have reduced adolescent marriage. Enrolment rates were higher for children participating in the programme, and there was a slight increase in the number of years of schooling they received. The mixed results suggest that the design of transfer programmes may be important for achieving outcomes. Cash payments made directly to girls rather than their parents had the greatest impact on reducing adolescent pregnancy and HIV in Malawi’s Zomba programme (Baird et al., | D46: TRUE
A47: 10.18356/8146c4ff-en | B47: 2cc009dd9dffb00802a9ff617a66100d | C47: According to official figures, there were 7,133 humanitarian entrants from Ethiopia in 1991-2015 (Government of Australia undated). Several thousand more Ethiopians have been sponsored under categories of spouse or family reunification visas, and the 2011 census records 8,452 Ethiopian-born people in the population. Like other humanitarian entrants who have been granted Permanent Protection Visas, Ethiopian refugees receive resettlement assistance through the Humanitarian Settlement Strategy (HSS), which was introduced in 2000 to provide a range of specialized services for humanitarian entrants. | D47: FALSE
A48: 10.1787/9789264259157-7-en | B48: 419163df6dbb548003cfb59af8e8565d | C48: Countiy Group 4: France, Iceland, Norway and Sweden Source: OECD calculations based on European Union Statistics on Income and Living Conditions (EU SILC) 2012. Country' Group 2: Italy, Greece, Spain, Portugal, Lithuania, Poland and Slovenia. Country Group 3: the Czech Republic, Estonia, Finland, Hungary, Latvia and the Slovak Republic. | D48: FALSE
A49: 10.14217/9e070c99-en | B49: 54206b6ebcc7a64bd3916a62d01a2f7d | C49: Judicial officers ensure the authoritative adjudication of controversies over the application of laws in specific situations, make law and public policy, especially when they exercise their power of judicial review to declare laws, government actions or omissions as unconstitutional, act as administrators for out-of-court settlements, and ensure enforcement of decisions. Judicial officers are barometers of a society’s conscience and must be seen to take restorative steps with impartiality and professionalism to address VAW by establishing and enforcing social and behavioural norms in line with the principles of the rule of law, as embodied in the law applicable and the practice before adjudicating institutions, and educating within and outside the court system. Failure to hold perpetrators accountable makes victims lose confidence in the institution of the judiciary and in the ability of the state to protect them from violence. | D49: TRUE
A50: 10.1787/9789264210745-5-en | B50: 53c49d95e8e01516bc7a3cf10eaee6f9 | C50: The employer’s role is largely associated with the obligation to act as a model employer. There is an expectation that the public sector, by the excellence of its modern employment policies and practices, will act as a leading force and as an example for the rest of the country’s employers. Therefore, it is crucial that the public sector embeds and exemplifies gender equality in its own employment policies. | D50: TRUE
A51: 10.18356/b620ec70-en | B51: 65679dcea5d83c2d52fe028007f3f341 | C51: Providing and Paying for Long Term Care, Paris, 2011, Starting Strong II. Early Childhood Education and Care, 2006: International Labour Organization (ILO), Un buen comienzo: la educadbnyioseducadores delaprimera infancla, Geneva, 2012: Ran American Health Organization (PAHO), "Ensenanza de la enfermeriaen saiud del adulto mayor", Human Resource for Health Series No. Few countries integrate this kind of nursing as a specific course in the undergraduate nursing curriculum. A diagnostic performed by the Pan American Health Organization (PAHO) for the region (PAHO, 2012) found that the main difficulties in strengthening nurse training in this area had to do with the lack of suitable clinical fields, the shortage of teachers trained to teach nursing of older persons, and the shortage of candidates interested in the area. | D51: FALSE
... A56: 10.18356/0899dee9-en | B56: 0bdff1a16124338ba120c46cbd9b44cd | C56: The work is regarded as voluntary, and working conditions are casual.91 In the case of South Africa, the pay levels of ECEC workers do not allow them to move out of poverty. Sometimes ECEC workers enrol in training, topping up their incomes with the EPWP stipend. However, when the training ends, they have higher skills but the same remuneration as before 92 Poor worker remuneration is also common in ECEC programmes in other African countries, like those reviewed in Kenya95 and Nigeria. Improvements in national legislation in South Africa and Uruguay, and the ratification of the ILO’s Domestic Workers Convention (No. | D56: FALSE
A57: 10.18356/ecc83295-en | B57: 007f06a3cc366285d2d1530065749c62 | C57: Some countries have responded to shrinking populations with policies to attract migrants, especially younger people who can fill gaps in labour forces. By the 1970s, the fertility transition had occurred in Australia, Japan, and all highly developed countries in Europe and North America. Fertility in China fell sharply in the 1970s in response to policies to promote later and less frequent childbearing, and the introduction of the country’s 1979 family planning policy, which generally limited couples to one child. | D57: TRUE | E57: reproductive rights
A58: 10.18356/fa683360-en | B58: f81b06bcdbc7a57989e6e445bb53808b | C58: Key factors in not completing the initial process were being disbelieved or fear of the police and the criminal justice system. For example, it is not always clear whether cases were “lost” or “dropped”. Dropped cases are those where either the police or prosecutor makes a clear and explicit decision not to proceed with a case. | D58: FALSE
A59: 10.18356/fa8ae033-en | B59: 13bd9f055dab0f9d915f1ab5c8617225 | C59: At the regional level, the right to equality and non-discrimination is also guaranteed by, for example, the African Charter on Human and People's Rights (arts. This means that States must take all necessary legislative, administrative and other measures to ensure that no family may be subject to discrimination on any ground. Any right, benefit, privilege or obligation to one ‘family’ (e.g., in social or welfare benefits, inheritance, social security and pensions) must be accorded to all of them. | D59: FALSE | E59: not specific to gender?
A60: 10.18356/1c6c11de-en | B60: aebeb8ff59842b3e252c0a01e1fa88e1 | C60: Differences in the dynamics of women's and men's employment also appear to be less pronounced when exchange rates are kept at a competitive level. When demand for labour grows slowly relative to supply, levels of open unemployment increase, informal employment expands and other atypical and non-standard forms of work—such as part-time work, short-term hires and day labour markets— proliferate. At the same time, bargaining power shifts in favour of employers and the owners of firms. A reduced share of public sector jobs in overall employment reinforces this trend. | D60: TRUE
A61: 10.18356/137d57b2-en | B61: 33f15d8472ee9dac57b488d9ad445543 | C61: In a mega-city such as Lagos, Nigeria, planners are trying to redevelop neighbourhoods and create more cohesive, manageable and livable communities. Nations like Ethiopia and India have launched campaigns to end child marriages and prevent life-threatening adolescent pregnancies. With good planning and thoughtful policies. When young people can claim their rights to health, education and decent working conditions, they become a powerful force for economic development and positive change. Throughout the developing world, social scientists and policymakers want to make the most of large youthful populations, for the sake of hopeful young people themselves as well as in the interests of economic growth and development. | D61: TRUE
A62: 10.14217/967bd43c-en | B62: 244c387f232fa8b0e81f78f3793a63f5 | C62: In Article 198, the law defines ‘marital rape’ as any act of sexual intercourse committed by one spouse on the other by violence, threat or trickery. The penalty for ‘marital rape’ is found in Article 199, where is provided that such a person shall be liable to a term of imprisonment of at least two (2) months but less than six (6) months and a fine of one hundred thousand (100,000) to three hundred thousand (300,000) Rwandan francs or one of these penalties. If ‘marital rape’ results in an ordinary disease, the offender shall be liable to a term of imprisonment of six (6) months to two (2) years. | D62: TRUE
A63: 10.1787/9789264224636-13-en | B63: 4d07e5e027cb0c07a4c1e9f269c70c0d | C63: Djibouti Law of 27 December 2007. With the arrival of many citizens from African countries and from transit countries, Egypt is becoming a transit zone for women, or crossing South-East Asia, the former Soviet Union and Eastern Europe. What is more, since 2003 the Suez Canal has been considered a very important factor in the trafficking of human beings and of counterfeit goods. Amongst these missions, the committee must draw up plans for the implementation, supervised implementation and revision of legislation in order to prevent human trafficking, and also to draw up proposals or recommendations, and to publish a national directory including instructions and pertinent educational material, and the adoption of measures that aim to protect victims of human trafficking. The committee will also lead an awareness-raising campaign for the benefit of employers who bring in foreign workers, on issues relating to human trafficking, and will also examine reports of national and international organisations on the banning of human trafficking, and co-operate with all official and non-official programmes that provide social support for victims affected physically or psychologically or people affected by human trafficking crimes. | D63: TRUE
A64: 10.18356/e617261d-en | B64: 00f5ff6cbf35b0736888a769b8e02d49 | C64: In these aspects, there are no statistically significant differences between female and male migrants. The only difference is in situations when respondents were taken from the workplace to die Federal Migration Service, which happened to 23 per cent of male migrants and 8 per cent of females.18 Agadjanian and others (2017) showed diat 34 per cent of female migrants from Central Asia had faced ethnicity-based harassment. Migrants in the Russian Federation do not settle in ethnic neighbourhoods but are spread out across cities (Vendina, 2012) so there are no places to avoid discrimination in the "mainstream" housing market (Agadjanian and Zotova, 2011). | D64: TRUE
A65: 10.18356/caeceb38-en | B65: 7f640e6d16c269e5e8b2f71de1be4ae5 | C65: Evidence brought together in this review suggests that such attempts would also require working with existing power structures at local levels, and perhaps more broadly. It also requires substantial local choice, power, management and ultimately ownership of both the "trigger" (the actual stimulus for change) and the process (Panter-Brick et al., 2006).Thus far, parenting programmes are the chosen trigger through which the feasibility of offering parenting support is being tested in the region. However, there are many other models that exist around the world (Daly et al., | D65: FALSE
A66: 10.18356/56f09402-en | B66: 34e246391352524b78302363287313a1 | C66: In addition to sexuality education, this effort involves implementing change processes in health services and putting in place guidelines and care protocols for prevention and for the sexual and reproductive health of this population, with an approach that differs from the one used for the adult population. The countries of Latin America have made significant progress in this direction, through different instruments. To this end there is a specific list of medicines that must be provided free to the requestor, with a proper medical prescription. | D66: TRUE
A67: 10.1787/9789264279322-4-en | B67: 69954e2fd1e94c64dbb6825f2919bd69 | C67: Legislation in some countries may have changed since this period, and can be expected to change in the future. Such instances should be considered and factored in during any follow'-up discussions at the country level or in international fora. Eventually, this work may also call for a revised draft to acknowledge progress and impacts made. It offers policy recommendations for boosting women’s employment and entrepreneurship through changes to legislative and institutional frameworks. The recommendations are general and will need tailoring to the particular context of each country. | D67: TRUE
A68: 10.18356/caeceb38-en | B68: 0bd5c32157352edddc8533212da40462 | C68: Collaboration over domestic work (for girls) or maintaining the home (for boys) is a vehicle through which parents ascribe value to adolescents, model appropriate behaviour and include them in social reproduction in ways that are consistent with the aspirations of parenting captured in the WHO's five dimensions. Adolescents are proud of their participation in the running of the family and prioritise their "right to help in the home" as well as engage in family activities (Bray, 2012,Thorpe, 2005). For reasons we go on to explain, the pressures and motivations around work influence the notion of 'good parenting' in this region, differing from those commonly expected or assessed using standard measures. Poverty plus additional vulnerability due to HIV, including orphanhood and family dispersal, lies behind adolescent engagement in commercial sex work (Nyambedha, 2007), while transactional sex in the community is commonplace across poor neighbourhoods (Juma et al., 2013).Young people's reliance on these informal and often exploitative relationships increases where lone mothers, or small families, cannot meet material needs or connect adolescents to genuine alternative routes towards upward social mobility (Ngugi et al., | D68: TRUE
A69: 10.18356/401c524c-en | B69: 0b177884ae8cc3bcdb52efa3286336a5 | C69: These results were related to shifts in power and changes in norms, often in relation to traditional practices. An example is the establishment of villages free of female genital mutilation. Transformative outcomes generally emerge from a change process that has several stages, moving from awareness raising, to attitude change, to change in behaviour and rules, often accompanied by institutionalization of a new norm (as described in the Gender@Work framework). In such cases, UNDP was one actor among many that contributed to the end result. | D69: TRUE
A70: 10.1787/9789264259157-5-en | B70: f4f48b94110197a2586938f4a9226d0d | C70: Even software engineers argue that programming errors are more likely to occur (and take longer to fix) after long hours, despite the tech industiy’s glorification of seemingly endless workdays (Robinson, 2005). Working-hour legislation and the legal right to request flexible working arrangements have historically helped protect workers. However, real change needs to occur in organisational culture and practice. | D70: FALSE
A71: 10.14217/967bd43c-en | B71: 00550a0fe64ba38833102f529118d5be | C71: Early marriage, also refers to marriages where both spouses are 18 years and over but certain factors make them unready to consent to marriage, for example their level of physical, emotional, sexual and psychosocial development, or lack of information regarding the person’s life options.10 Within the context of the law in East Africa, CEFM does not have a concrete definition. Most information gathered on CEFM places child marriages into two categories: those married before 15 years and those married before 18 years. This categorisation is of importance as it enables those researching CEFM to understand the trends in various countries. | D71: TRUE
... A79: 10.18356/5085bf5a-en | B79: d6ca8e89fd99a81141f2fc79638f5711 | C79: In 2008, an estimated 44 million induced abortions occurred in the world (6 million in developed countries and 38 million in developing countries), almost half of which were carried out using unsafe procedures (Guttmacher Institute, 2012). Globally, it is estimated that 47,000 women die each year from complications associated with unsafe abortion. Many of these deaths could be prevented through better access to sexuality education, contraceptive information and supplies, and safe abortion services where allowed by law (Shah and Ahman, 2010). | D79: TRUE
A80: 10.1787/empl/outlook-2016-8-en | B80: 7d9eea8c9d93b2273037530717ae79ec | C80: Providing employers with a code of good practice can help them to navigate the existing legislation, which can often be complex, and reduce non-compliance. Lowering the burden of proof for plaintiffs and shifting it to employers can be a step in the right direction, but should be accompanied by measures to help complainants gather the necessary evidence to initiate the case and sustain the costs of the trial (OECD, 2008, Chapter 3). In the early 2000s, most European countries lowered the burden of proof for plaintiffs, who are now only required to provide evidence of differential treatment without having to prove that it was indeed due to discrimination. | D80: FALSE | E80: not specific to gender
A81: 10.18356/56f09402-en | B81: ba0b47e69221eb2f34cbe80257d4d636 | C81: In Latin America there is strong evidence of the conditions in which young people enter the labour market. Youth unemployment has traditionally been higher than in other age groups, and it is usually the first to rise in times of economic crisis and the last to fall in booms (Tokman, 1997, ECLAC, 2010). In other words, "the young are among those who bear the brunt of the recessionary and regressive effects of crises" (ECLAC, 2012a, p. 89). As a result, adolescents and youths are still overrepresented among the unemployed. | D81: FALSE
A82: 10.18356/6f7c638a-en | B82: 00dd087c250922be90724c77bf6de004 | C82: In Uruguay for example, data is collected on care provided to dependent persons aged 65 or older and questions focus on care for adults who require assistance with personal hygiene, feeding or medical care, including transportation to health centres. The national time-use survey in Mexico collects information on the time spent caring for persons aged 60 or older, including support in the use of information technology, transportation and accompaniment, even when the older person is not dependent or does not have a disability. In households where persons in this age range are present, women spend 18 hours per week on average caring for them, compared with 15 hours spent by men. | D82: TRUE
A83: 10.18356/6f7c638a-en | B83: d86780cec7d02f4c9590e02a42f77295 | C83: One of the targets of Goal 8 of the 2030 Agenda for Sustainable Development is the reduction in the number of young people in this situation, which means there is a need for information that explains the barriers to their integration into the labour market and the education system. The time-use data for this age group show that, on average, women who are out of school and the labour market spend at least 40 hours per week on unpaid domestic work, which confirms that they are not in school and not being paid for their work (ECLAC, 2016a). For example, in Costa Rica and Mexico, young people spend more than 70 hours per week on domestic and care work (see figure IV.6). | D83: TRUE
A84: 10.14217/9781848591561-7-en | B84: 6c1f5aea016e803275bc8304b47a0147 | C84: Following a typical banking model may not be sufficient to cater to the financial and non-financial needs of unbanked women. Savings and credit products need to be fine-tuned to cater to the various lifecycle needs of women, such as children’s education, a daughter’s marriage or long-term saving for old age and medical emergencies. While savings and credit products remain the most important pillars for a women-owned/ managed SACO, other services such as financial literacy awareness programmes, insurance services or pension products can also be delivered through the same co-operative banking channel, if regulatory institutions permit such product offering. Although the grass-roots women owners and senior managers of the SACO need to be mentored and trained in the initial years, it is necessary to let them lead and choose the path for the organisation once they have matured in their leadership roles. As their sense of ownership increases, the women become more involved in runningthese enterprises. Grass-roots women are more aware of the key challenges that plague poor women clients. | D84: TRUE
A85: 10.18356/fa683360-en | B85: 09fc4d592aa2455c6f662a78a77379e1 | C85: The part of the brain primarily responsible for the detection of, and reaction to, a threat is called the amygdala. Threat detection and survival is given priority over all other brain functions. The human system will respond to the perceived threat in one or more of five predictable ways: friend, fight, fright, freeze and/or flop. | D85: FALSE
A86: 10.18356/fa8ae033-en | B86: 6d49772b7e0bfae5e119cc583570a9d2 | C86: Adopted in March 2007 by a group of human rights experts convened by the International Commission of Jurists and the I nternational Service for H u ma n Rights on beha If of a coa I i-tion of human rights organizations. From these developments, it is evident that States have a positive duty to prevent, protect and punish cases of violence even when the harm takes place within the family. In its General Recommendation No. | D86: TRUE
A87: 10.18356/137d57b2-en | B87: 259637989620bd5f167fc67894ccc7c9 | C87: Successful programmes, she says, provide timely, sufficient and scientific information, tailored to the needs of each age group. “ Evaluation studies have shown that sex education has an impact in delaying the age at the first sexual intercourse, in increasing the use of contraception methods and condoms, and in decreasing the levels of violence against young girls,” she says. “ The above implies the reduction of early and unwanted pregnancies, and the decrease of HIV/AIDS.” It looks at the decisions that individuals make—or would like to make, if they had the opportunity. | D87: TRUE
A88: 10.1787/7ddddd07-en | B88: db3642428aed20e21239f80b89d96d02 | C88: Recent studies of high growth start-ups in the United States find that only 10-15% of them are founded by women (Brush etal., Looking more specifically at start-up funding, several studies have shown that women are extremely under-represented among venture-backed entrepreneurs in the United States. Gompers and Wang (2017[i2]) find that just 10.7% of US venture-backed founders were women from 2010-2015. 2014(H)) estimate the number to be 15% using data from 2011-2013. | D88: TRUE
A89: 10.18356/32ea1505-en | B89: b543ea0cea2c54404f4f83e1fd619f27 | C89: Women are generally as active as men in cash crop production, often providing the bulk of labour on contracted farms. There are, however, important gender differences in control over the commercial proceeds (men are contracted, while women supply unpaid family labour) and in the scale of operations (due to the constraints women face on increasing sales of their produce). Global Employment Trends 2014: supporting data sets: Employment by status and sex (http://www.ilo.org/legacy/english/geiy2014/GET_sector_share.xlsx) (accessed July 2015). Note: Data for the following countries are unavailable: Djibouti, Kiribati, Sao Tome and Principe, South Sudan, Sudan (Former), Timor-Leste, Tuvalu and Vanuatu. Evidence from a number of studies points to similar dynamics in both traditional export sectors (e.g. cocoa, coffee and tea) and non-traditional exports (e.g. fruit, horticulture and flowers). | D89: TRUE
A90: 10.18356/c93219ca-en | B90: 9912d14c0ab6c021c89160b486b1d27d | C90: The section then presents current practices to promote access to sexual and reproductive health and reproductive rights for persons with disabilities, before concluding with recommendations for the way forward. Target 5.6, which is placed under the goal calling for gender equality and empowerment of all women and girls, calls for ensuring universal access to sexual and reproductive health and reproductive rights as agreed in accordance with the Programme of Action of the International Conference on Population and Development and the Beijing Platform for Action and the outcome documents of their review conferences. The CPRD is the first Convention to explicitly recognize the need for sexual and reproductive health for persons with disabilities. Article 25 underscores the need to provide persons with disabilities with the same range, quality and standard of free or affordable sexual and reproductive health care and programmes as provided to other persons. | D90: TRUE
A91: 10.18356/5f92f30f-en | B91: 15ef01a67332f8f91841d700c1bafbf3 | C91: Emergency contraception is a method to prevent pregnancy within five days of unprotected intercourse, failure or misuse of a contraceptive (such as a forgotten pill), rape or coerced sex. It disrupts ovulation and reduces the likelihood of pregnancy by up to 90 per cent. It cannot prevent implantation of a fertilized egg, harm a developing embryo or end a pregnancy. Even in countries where emergency contraception is available, adolescents may be reluctant to obtain it from traditional health outlets, such as clinics, which may be staffed by judgmental providers. The initiative trained pharmacy staff and peer educators to provide accurate, up-to-date information on emergency contraception and other reproductive health services. | D91: TRUE
A92: 10.18356/8a6d677c-en | B92: ed20f3ece97567ca70521b9a806d9ba1 | C92: For each spotlight, pressing data gaps and measurement challenges are also highlighted. These supplemental indicators were selected based on an open consultation with civil society organizations and inputs from other international experts (see Box 3.1). Respondents, including international agencies and civil society organizations, submitted suggestions for additional indicators, along with information on their relevance and, where possible, data sources and how often the data are produced. The recommendations included, for instance, monitoring the "average weekly time spent by women and girls on water collection" for Goal 6 and the "share of women aged 15-49 whose BMI [body mass index] is less than 18.5 (underweight)" for Goal 2. | D92: TRUE
... A94: 10.18356/70095f8a-en | B94: 3557e13e2d3c31da34ba81b195b13145 | C94: Key elements to achieve this are: empowering client communities to become active parties in decision-making instead of considering them mere subjects of consultations, incorporating information feedback loops to avoid knowledge being reserved for a selected few, and ensuring accountability at a personal, individual level so that policies, strategic plans, budgets, performance management systems and individual accountability and responsibility are all aligned. Finally, students and their families, users, affected groups, communities and taxpayers must play an integral part in defining the parameters and systems of monitoring and evaluation. In South Africa, although there seems to be higher educational achievement, many observers question the quality of education received in state schools, asking whether the pass rate actually reflects students’ learning achievements. A recent court judgment finding the Government in contempt of court for ignoring earlier court orders to provide textbooks for schoolchildren appears to support this argument (Nkosi, 2012). | D94: FALSE
A95: 10.1787/5k8xb6hw1wjf-en | B95: c220beceff9bca5dfa440eb2842a49f4 | C95: However, a cash-for-care payment may be made to parents taking care of a child until he/she reaches his or her third birthday. In Sweden, a municipal child-raising allowance (“vardnadsbidrag”) was reinstituted since 2008 on top of the statutory period of leave. Since 2009, the country’s municipalities have been able to choose whether or not to allocate benefit to parents with a child of between one and three years old who do not use publicly funded childcare services and who have already used 250 days of parental leave to care for the child. | D95: TRUE | E95: recognizing unpaid care work
A96: 10.1787/9789264210745-6-en | B96: 68bb5eab1e1f88a44ec3334d96430377 | C96: In this way, the Council harmonises strategies of relevant organisations and provides for transfer of information and a sharing of resources. Additionally, there are extended plenary meetings twice per year with the mandate of nurturing political leadership. The CEO oversees the technical task teams for programmes (i.e. policy and legislation, research, prevention), monitoring and evaluation, administration, communication and resource mobilisation teams. | D96: FALSE
A97: 10.18356/9c9efe4c-en | B97: 32f44f50fcc3f9dfccaa4a22c0e4013f | C97: According to the United Nations Environment Programme (UNEP), which launched its Green Economy Initiative in 2008, a green economy is one that results in improved human well-being and social equity, while significantly reducing environmental risks and ecological scarcities, it is low-carbon, resource-efficient and socially inclusive (UNEP, 2011). This general definition integrates economic, social and environmental concerns in ways akin to sustainable development. Yet in practice, as the World Survey shows, there are many versions of green economy thinking. It is argued that the emerging green technology economy will be worth $4.2 trillion annually by 2020.’3 Other strands emphasize market-based approaches to environmental protection through financial valuation of natural capital, payments for ecosystem services and schemes for trading carbon and biodiversity credits and offsets. | D97: FALSE
A98: 10.18356/8e0dd871-en | B98: dacdf4451bcdcd917e1f922f2349752f | C98: Target 3.7 calls for universal access to sexual and reproductive health care services (including family planning), information and education, which would help to prevent adolescent childbearing and unintended pregnancies. Globally, childbearing among adolescents declined by 21 per cent between 2000 and 2015. Central and Southern Asia made the greatest progress: the region reduced the adolescent birth rate by more than 50 per cent, largely due to advances in Southern Asia. | D98: TRUE
A99: 10.18356/caeceb38-en | B99: 46085ee4d03cb4e81ad600c2469e9814 | C99: A growing proportion of initiation ceremonies are being devised by Christian groups to teach young people about what is expected of them as they enter adulthood - including pre-marital sexual abstinence - as an alternative to the alleged sexual focus of teaching in traditional practice (Munthali, 2007). Ncaca, 2014).The last decade has seen increasing public debate about whether and how male circumcision should be continued following media reports of problems including commercialisation, malpractice by guardians, and deaths or permanent injury from botched circumcision (Ntombana, 2011b). However, studies also report the beneficial role of circumcision against sexually transmitted infections (Lagarde et al., | D99: TRUE
A100: 10.14217/9781848599451-18-en | B100: b7da16da7c29f33f10e1938d32ceb20f | C100: This assistance is designed to help people cope with their trauma, provide strategies for protecting themselves and their families, and make the necessary plans to achieve safety and stability. The minister emphasised the need for collaboration and co-operation at the national, community and individual levels in order to reduce and abate GBV, calling for a holistic approach that went beyond the government to include churches, NGOs, trade unions, the healthcare sector and others. These include (but are not limited to): lack of special DVUs or mechanisms, inadequate psychological support services for abusers, lack of legal aid services and victim support programmes, insufficient shelter, psychological and legal counselling and education support services, lack of sufficient preparation by healthcare providers to collect and present medical/legal evidence, lack of sufficient co-ordination between the medical, law enforcement, social services and justice sectors, and prevalence of stigma, discrimination, victim blaming and gender inequality. | D100: TRUE
A101: 10.18356/ea56e86b-en | B101: 75c1fd7e470a6f66ae0657eb63a63c40 | C101: Let us shift the focus away from mutilation to education," the Secretary-General said at a special event in February 2016 marking the 2030 commitment. " Let us make a world where FGM stands for Focus on Girls’ Minds. To fast-track progress, in March 2016, UNFPA and UNICEF launched the Global Programme to Accelerate Action to End Child Marriage. | D101: TRUE

Sheet Gib
A1: DOI | B1: Text ID | C1: Text | D1: SDG 5 Label | E1: Comments (optional)
A2: 10.18356/5f92f30f-en | B2: 15ef01a67332f8f91841d700c1bafbf3 | C2: Emergency contraception is a method to prevent pregnancy within five days of unprotected intercourse, failure or misuse of a contraceptive (such as a forgotten pill), rape or coerced sex. It disrupts ovulation and reduces the likelihood of pregnancy by up to 90 per cent. It cannot prevent implantation of a fertilized egg, harm a developing embryo or end a pregnancy. Even in countries where emergency contraception is available, adolescents may be reluctant to obtain it from traditional health outlets, such as clinics, which may be staffed by judgmental providers. The initiative trained pharmacy staff and peer educators to provide accurate, up-to-date information on emergency contraception and other reproductive health services. | D2: TRUE
A3: 10.18356/fa8ae033-en | B3: 6d49772b7e0bfae5e119cc583570a9d2 | C3: Adopted in March 2007 by a group of human rights experts convened by the International Commission of Jurists and the I nternational Service for H u ma n Rights on beha If of a coa I i-tion of human rights organizations. From these developments, it is evident that States have a positive duty to prevent, protect and punish cases of violence even when the harm takes place within the family. In its General Recommendation No. | D3: FALSE
A4: 10.18356/36aba0c4-en | B4: f19db2735a2f32ec978a5e1c0961207c | C4: As such, pursuing a shift to demand-led growth, on its own, is unlikely to address the environmental costs associated with sustained growth, unless the higher wages and earnings of lower income groups that will result from such a shift are spent on goods that are less reliant on fossil fuels and natural resource extraction, and increased public expenditure and investment is also allocated to fuel-efficient sectors and technologies. This is where proposals for green economy become relevant. There are, however, different variants of green economy. | D4: FALSE
A5: 10.14217/2d08a027-en | B5: b1b6995b10ce561b7bfc2333f49aa089 | C5: We protested against political parties requesting huge sums of money as part of the party nomination process.' In 2016, the organisation signed an agreement with the Cameroon government to empower hundreds of youth and women in elections participation. This process involved building capacity to reinforce leadership and civic education. | D5: TRUE
A6: 10.18356/efc21c19-en | B6: 4c1b31c7bec2e84a3ca6802a5c46a8ca | C6: The maturity stages of e-Government for Gender Equality, which is an adaptation of the EGDI’s four-stage model, suggest key characteristics of the e-Government evolution regarding the usefulness of contents and services, technical sophistication and ease of use, degree of integration, etc. The framework was used for the analysis of national gender machinery websites from 11 countries presented in Chapter 3 of this report. They have links to ministries, departments and other branches of government. | D6: TRUE
A7: 10.18356/32ea1505-en | B7: b543ea0cea2c54404f4f83e1fd619f27 | C7: Women are generally as active as men in cash crop production, often providing the bulk of labour on contracted farms. There are, however, important gender differences in control over the commercial proceeds (men are contracted, while women supply unpaid family labour) and in the scale of operations (due to the constraints women face on increasing sales of their produce). Global Employment Trends 2014: supporting data sets: Employment by status and sex (http://www.ilo.org/legacy/english/geiy2014/GET_sector_share.xlsx) (accessed July 2015). Note: Data for the following countries are unavailable: Djibouti, Kiribati, Sao Tome and Principe, South Sudan, Sudan (Former), Timor-Leste, Tuvalu and Vanuatu. Evidence from a number of studies points to similar dynamics in both traditional export sectors (e.g. cocoa, coffee and tea) and non-traditional exports (e.g. fruit, horticulture and flowers). | D7: TRUE
A8: 10.18356/caeceb38-en | B8: 097588fda30192cce1b6fb3efb5a1f66 | C8: As we would expect, these proportions increase with age such that between half and three quarters of older adolescents are working, or seeking work. However, adolescents frequently combine school and work. Research in South Africa and Zimbabwe on distribution shows that most working adolescents live in very poor households in rural areas and are engaged in subsistence agriculture, many combining this with domestic work (including care) and commercial agriculture (Robson, 2004, Bray, 2012, Dawes et al., | D8: FALSE
A9: 10.18356/137d57b2-en | B9: 259637989620bd5f167fc67894ccc7c9 | C9: Successful programmes, she says, provide timely, sufficient and scientific information, tailored to the needs of each age group. “ Evaluation studies have shown that sex education has an impact in delaying the age at the first sexual intercourse, in increasing the use of contraception methods and condoms, and in decreasing the levels of violence against young girls,” she says. “ The above implies the reduction of early and unwanted pregnancies, and the decrease of HIV/AIDS.” It looks at the decisions that individuals make—or would like to make, if they had the opportunity. | D9: TRUE
A10: 10.14217/9781848591561-7-en | B10: 6c1f5aea016e803275bc8304b47a0147 | C10: Following a typical banking model may not be sufficient to cater to the financial and non-financial needs of unbanked women. Savings and credit products need to be fine-tuned to cater to the various lifecycle needs of women, such as children’s education, a daughter’s marriage or long-term saving for old age and medical emergencies. While savings and credit products remain the most important pillars for a women-owned/ managed SACO, other services such as financial literacy awareness programmes, insurance services or pension products can also be delivered through the same co-operative banking channel, if regulatory institutions permit such product offering. Although the grass-roots women owners and senior managers of the SACO need to be mentored and trained in the initial years, it is necessary to let them lead and choose the path for the organisation once they have matured in their leadership roles. As their sense of ownership increases, the women become more involved in runningthese enterprises. Grass-roots women are more aware of the key challenges that plague poor women clients. | D10: TRUE
A11: 10.1787/9789264279322-7-en | B11: d0a96662f990a04e6eec02af04738769 | C11: A widow will receive one-eighth of her deceased husband’s assets or one-fourth if he has no children. For example, it is not uncommon for the family to pressure female heirs into relinquishing their full inheritance rights in favour of male relatives. Many women do not know that they can refuse to cede their rights or can appeal to the courts. | D11: TRUE
A12: 10.18356/e617261d-en | B12: 00f5ff6cbf35b0736888a769b8e02d49 | C12: In these aspects, there are no statistically significant differences between female and male migrants. The only difference is in situations when respondents were taken from the workplace to die Federal Migration Service, which happened to 23 per cent of male migrants and 8 per cent of females.18 Agadjanian and others (2017) showed diat 34 per cent of female migrants from Central Asia had faced ethnicity-based harassment. Migrants in the Russian Federation do not settle in ethnic neighbourhoods but are spread out across cities (Vendina, 2012) so there are no places to avoid discrimination in the "mainstream" housing market (Agadjanian and Zotova, 2011). | D12: TRUE
A13: 10.18356/0a98da25-en | B13: c668a492db5a964d3b747b541f4eaa0e | C13: Again, the private sector would provide the bulk of credit, but it would be characterized by low interest rates leveraged with government loan guarantees. The real targeting approach might also be complemented by other policies, such as capital management techniques to deal with possible capital flight (discussed in more detail below). These loan guarantees substitute for collateral, leveraging access to credit and potentially bringing informal sector businesses into the formal sector. | D13: FALSE
... A20: 10.18356/5085bf5a-en | B20: db5fb32cbad0993b82ca58f3da36a8bf | C20: Since the mid-1990s, the proportion of Governments that viewed adolescent fertility as a major concern has risen steadily in all major world regions, except in Northern America. Such programmes also include innovative educational approaches, including peer counselling for young people and orientation for parents, as well as strengthening education on reproductive and sexual health in non-formal settings, vocational training programmes and youth clubs (United Nations Population Fund, 2007). In 2013, 94 per cent of Governments in less developed regions had policies and programmes to reduce adolescent fertility, compared with 77 per cent of Governments in more developed regions. All Governments in Latin America and the Caribbean, Northern America and Oceania, and all but one Government in Africa, had policies and programmes to reduce adolescent fertility in 2013, whereas 23 per cent of Governments in Europe and 19 per cent in Asia did not have such policies or programmes. | D20: TRUE
A21: 10.18356/5085bf5a-en | B21: 6a390516c7b15f3b27739ce3b4337184 | C21: Although a number of countries, mostly in Europe, that have adopted such measures have experienced modest increases in fertility between 2000-2005 and 2005-2010 (United Nations, 2013a), the implementation and effectiveness of such measures have been difficult to ascertain. While the percentage of Governments with policies to raise fertility has increased steadily from just 9 per cent in 1976 to 27 per cent in 2013, the percentage of Governments with policies to lower fertility increased from 27 per cent in 1976 to 42 per cent in 1996, and then remained at 43 per cent in 2013. During this time, the percentage of Governments that did not have policies to influence fertility has declined steadily from 52 per cent in 1976 to 13 per cent in 2013 (table III.l). In 1976, only about one in every five Governments in more developed regions had policies to raise fertility, but by 2013 this proportion had risen steadily to more than two thirds. | D21: FALSE | E21: not specifically about women
A22: 10.18356/fa8ae033-en | B22: 13bd9f055dab0f9d915f1ab5c8617225 | C22: At the regional level, the right to equality and non-discrimination is also guaranteed by, for example, the African Charter on Human and People's Rights (arts. This means that States must take all necessary legislative, administrative and other measures to ensure that no family may be subject to discrimination on any ground. Any right, benefit, privilege or obligation to one ‘family’ (e.g., in social or welfare benefits, inheritance, social security and pensions) must be accorded to all of them. | D22: FALSE | E22: not specifically about women
A23: 10.1787/soc/aag-2014-5-en | B23: aa2e650903052a45c6c1b6828135bfac | C23: This is the case in Azerbaijan (90%), the Kyrgyz Republic (87%), Armenia (83%), New Zealand (82%), Myanmar (81%), Korea (76%) and Australia (72%). As in most OECD countries, health and the humanities are the other most popular degrees women obtain in the Asia/Pacific region (Figure 2.3). Women, on the other hand, are underrepresented among students and graduates of degrees in the so-called STEM fields of study - science, technology, engineering and mathematics (STEM). Innovation can benefit from a concentration of individuals with STEM skills. | D23: TRUE
A24: 10.18356/6f7c638a-en | B24: d86780cec7d02f4c9590e02a42f77295 | C24: One of the targets of Goal 8 of the 2030 Agenda for Sustainable Development is the reduction in the number of young people in this situation, which means there is a need for information that explains the barriers to their integration into the labour market and the education system. The time-use data for this age group show that, on average, women who are out of school and the labour market spend at least 40 hours per week on unpaid domestic work, which confirms that they are not in school and not being paid for their work (ECLAC, 2016a). For example, in Costa Rica and Mexico, young people spend more than 70 hours per week on domestic and care work (see figure IV.6). | D24: TRUE
A25: 10.18356/8146c4ff-en | B25: a983e648796057f81f6185b8e43331c3 | C25: However, the larger agenda of recognition of the care needs of migrants and valuation of social reproduction as a central axis of the analysis of migration would require the tough political challenge of transformative, universalized access to childcare services in both Australia and Lebanon that is delinked from parents'income levels,from productivist assumptions (as in Australia) and from parents’ migrant status (as in Lebanon). Power,production and social reproduction: Human in/security in the global political economy. In Transnational Families, Migration and the Circulation of Care: Understanding Mobility and Absence in Family Life, edited by Loretta Baldassar and Laura Merla. | D25: FALSE | E25: not specific enough to be about women
A26: 10.1787/9789264210745-6-en | B26: 8b8efdd6ae34ef52bbded7d658b5866a | C26: The Inter-Departmental Co-ordination Group assumes responsibility for: promoting co-operation between ministries, adopting a federal plan of action, preparing an intermediary' report and a final report at the end of the term, and exchanging good practices and promoting instruments useful to enforcing the law. The representatives of the ministries participating in the co-ordination group are also appointed as gender focal points in their respective entities. They receive compulsory' training on gender mainstreaming and are tasked with ensuring follow-up on the diverse measures foreseen by the law (e.g, gender statistics, gender-responsive budgeting and the “gender test”). | D26: TRUE
A27: 10.1787/5js30tvj21hh-en | B27: 650df03322e86b6f089f407ba080b21a | C27: If all those reforms happened in a particularly rigid state - as it is likely to be the case, it is highly probable that employment will still suffer from this former rigidity. It will then introduce a negative bias in the evaluation. A positive value means a pro-worker state’s legislation (often tied to institutional rigidity) and a negative value means pro-employer legislation (more liberal). Conversely to labor reform’s index we do not have this index for every states. | D27: FALSE
A28: 10.1787/empl/outlook-2016-8-en | B28: 7d9eea8c9d93b2273037530717ae79ec | C28: Providing employers with a code of good practice can help them to navigate the existing legislation, which can often be complex, and reduce non-compliance. Lowering the burden of proof for plaintiffs and shifting it to employers can be a step in the right direction, but should be accompanied by measures to help complainants gather the necessary evidence to initiate the case and sustain the costs of the trial (OECD, 2008, Chapter 3). In the early 2000s, most European countries lowered the burden of proof for plaintiffs, who are now only required to provide evidence of differential treatment without having to prove that it was indeed due to discrimination. | D28: FALSE
A29: 10.14217/967bd43c-en | B29: 1e0a700a4aabfbb4408648e08f6daf33 | C29: For purposes of this paper the definition will focus on ‘forced marriage’ and ‘early marriage.’ The reason for this is that by definition, ‘child’ marriages7 can be considered ‘forced marriage’, or a form thereof, because children especially those under the age of 15 are not able to make an informed decision as to whether or not they want to be married. Most often this decision is influenced by a parent or family member. | D29: TRUE
A30: 10.18356/137d57b2-en | B30: 33f15d8472ee9dac57b488d9ad445543 | C30: In a mega-city such as Lagos, Nigeria, planners are trying to redevelop neighbourhoods and create more cohesive, manageable and livable communities. Nations like Ethiopia and India have launched campaigns to end child marriages and prevent life-threatening adolescent pregnancies. With good planning and thoughtful policies. When young people can claim their rights to health, education and decent working conditions, they become a powerful force for economic development and positive change. Throughout the developing world, social scientists and policymakers want to make the most of large youthful populations, for the sake of hopeful young people themselves as well as in the interests of economic growth and development. | D30: TRUE
A31: 10.18356/5085bf5a-en | B31: d6ca8e89fd99a81141f2fc79638f5711 | C31: In 2008, an estimated 44 million induced abortions occurred in the world (6 million in developed countries and 38 million in developing countries), almost half of which were carried out using unsafe procedures (Guttmacher Institute, 2012). Globally, it is estimated that 47,000 women die each year from complications associated with unsafe abortion. Many of these deaths could be prevented through better access to sexuality education, contraceptive information and supplies, and safe abortion services where allowed by law (Shah and Ahman, 2010). | D31: TRUE
A32: 10.18356/604a5a2e-en | B32: 3170e6ccd61878ce07fbc1a0149eba25 | C32: Pregnant women have blood and body fluids that could expose health workers to the virus," Jallah says. I suffered a lot and was afraid I was going to die. The only thing I hoped for was for a miracle to happen," she says. One did: Comfort gave birth to two healthy baby girls with the assistance of a nurse aid who happened to pass by at the right time. | D32: TRUE
A33: 10.14217/967bd43c-en | B33: 244c387f232fa8b0e81f78f3793a63f5 | C33: In Article 198, the law defines ‘marital rape’ as any act of sexual intercourse committed by one spouse on the other by violence, threat or trickery. The penalty for ‘marital rape’ is found in Article 199, where is provided that such a person shall be liable to a term of imprisonment of at least two (2) months but less than six (6) months and a fine of one hundred thousand (100,000) to three hundred thousand (300,000) Rwandan francs or one of these penalties. If ‘marital rape’ results in an ordinary disease, the offender shall be liable to a term of imprisonment of six (6) months to two (2) years. | D33: TRUE
A34: 10.18356/2c8682bc-en | B34: 4b810c6f99caddec8b250387b1589964 | C34: Its effect on the quality of Lw is related to the values transmitted through education within households and to the health care carried out there. Domestic labour also influences the number of hours of wage labour available, as it releases this from care responsibilities. Reproduction is caught between a given wage and people’s needs and wants. “ | D34: FALSE
A35: 10.18356/914e7bcc-en | B35: f43d0e85dc177042358b28e93e6c51ea | C35: In terms of context, these CoSOs may precede the eruption of conflict, may deal with issues not relating to the conflict (in Israel and Turkey for example) or may be established as a result of the conflict (in Bosnia, Cyprus and Thrkey). In terms of identity, the vast majority of these CoSOs are civic, post-national or multicultural. In terms of FOA the organizations work on issues directly relating to the conflict, but also on political issues that do not relate strictu sensu to the conflict. | D35: FALSE
A36: 10.18356/e617261d-en | B36: e95d9b6864d5595d1cd7f4e8dca7d4d2 | C36: Another 25 per cent said that they would like to stay in the Russian Federation and live there permanently, while 21 per cent said that they would like to live in the Russian Federation for several years and then return home permanently (Tyuryukanova, 2011, p. 155). Among them, females from Uzbekistan more often wanted to "come and go" (66 per cent) and were the least willing to apply for Russian citizenship (70 per cent of them did not have such plans) (Tyuryukanova, 2011, pp. Contrary to these findings, another survey of Central Asian female migrants in the Russian Federation showed that 70 per cent of them had firm plans to return home (Agadjanian and others, 2014). | D36: FALSE
A37: 10.18356/fa683360-en | B37: f81b06bcdbc7a57989e6e445bb53808b | C37: Key factors in not completing the initial process were being disbelieved or fear of the police and the criminal justice system. For example, it is not always clear whether cases were “lost” or “dropped”. Dropped cases are those where either the police or prosecutor makes a clear and explicit decision not to proceed with a case. | D37: FALSE
A38: 10.18356/0899dee9-en | B38: 0bdff1a16124338ba120c46cbd9b44cd | C38: The work is regarded as voluntary, and working conditions are casual.91 In the case of South Africa, the pay levels of ECEC workers do not allow them to move out of poverty. Sometimes ECEC workers enrol in training, topping up their incomes with the EPWP stipend. However, when the training ends, they have higher skills but the same remuneration as before 92 Poor worker remuneration is also common in ECEC programmes in other African countries, like those reviewed in Kenya95 and Nigeria. Improvements in national legislation in South Africa and Uruguay, and the ratification of the ILO’s Domestic Workers Convention (No. | D38: FALSE
A39: 10.18356/caeceb38-en | B39: 0bd5c32157352edddc8533212da40462 | C39: Collaboration over domestic work (for girls) or maintaining the home (for boys) is a vehicle through which parents ascribe value to adolescents, model appropriate behaviour and include them in social reproduction in ways that are consistent with the aspirations of parenting captured in the WHO's five dimensions. Adolescents are proud of their participation in the running of the family and prioritise their "right to help in the home" as well as engage in family activities (Bray, 2012,Thorpe, 2005). For reasons we go on to explain, the pressures and motivations around work influence the notion of 'good parenting' in this region, differing from those commonly expected or assessed using standard measures. Poverty plus additional vulnerability due to HIV, including orphanhood and family dispersal, lies behind adolescent engagement in commercial sex work (Nyambedha, 2007), while transactional sex in the community is commonplace across poor neighbourhoods (Juma et al., 2013).Young people's reliance on these informal and often exploitative relationships increases where lone mothers, or small families, cannot meet material needs or connect adolescents to genuine alternative routes towards upward social mobility (Ngugi et al., | D39: FALSE | E39: Not sure. It's more about youth in general rather than girls
A40: 10.18356/3a0cd6ba-en | B40: d6641ebe70f6fbd4981994ea47fc1e99 | C40: The most significant gaps were in: technology and technology transfer, access to finance, promotion of entrepreneurial education, cheaper, faster start-up and better regulations, and access to support services. These gaps reflected weaknesses in national legal frameworks and SME agencies, as well as in the elaboration and implementation of specific policy measures. Drawing on the World Economic Forum’s Global Competitiveness Index, this framework focuses on key entrepreneurial conditions (Box 2).'9 GEM is the basis for an annual national Adult Population Survey, along with National Expert Surveys. | D40: FALSE
A41: 10.1787/9789264265493-9-en | B41: 72bc2099057c5d0da7d38f1cee7f3e77 | C41: The concept of critical mass as applied to women’s political representation, and the UN targets that have flowed from it, have played an important role in supporting countries in the adoption of gender quotas in various spheres of the public and private sectors. According to data provided by the Inter-Parliamentary Union (IPU, 2015), the global average of women in national parliaments has nearly doubled in the past 20 years from 11.3% in 1995 to 22.1% in 2015 (a rise of 10.8 points). However, recent socio-political studies (Childs and Krook, 2008), as well as IPU data (IPU, 2015) confirm that the achievement of a critical mass is no longer seen as the sole target of efforts to bring about gender-equal participation in positions of leadership. | D41: TRUE
A42: 10.18356/c93219ca-en | B42: 9912d14c0ab6c021c89160b486b1d27d | C42: The section then presents current practices to promote access to sexual and reproductive health and reproductive rights for persons with disabilities, before concluding with recommendations for the way forward. Target 5.6, which is placed under the goal calling for gender equality and empowerment of all women and girls, calls for ensuring universal access to sexual and reproductive health and reproductive rights as agreed in accordance with the Programme of Action of the International Conference on Population and Development and the Beijing Platform for Action and the outcome documents of their review conferences. The CPRD is the first Convention to explicitly recognize the need for sexual and reproductive health for persons with disabilities. Article 25 underscores the need to provide persons with disabilities with the same range, quality and standard of free or affordable sexual and reproductive health care and programmes as provided to other persons. | D42: TRUE
A43: 10.18356/efc21c19-en | B43: 54adceba3c4278906b489527f4097858 | C43: An efficient use of ICT can disseminate government information to a broader audience in a fast and convenient manner. At the initial stage of national e-Government development, an ideal point of entry for developing countries would be setting up a website for the national gender machinery. The website, as an official gateway to gender-related policies and programmes, would provide a ready access to online information ranging from the organizational structure of the national gender machinery to government statistics, publications, government services and programmes aimed for women’s empowerment. Through the use of technology, the interaction between the governments and women can be stimulated and become more effective. Basic forms of interactivity available through emails, downloadable forms, discussion forums and online polls not only provide an improved delivery of basic services, but also build up a basis for online participation. | D43: TRUE
A44: 10.18356/ea56e86b-en | B44: 75c1fd7e470a6f66ae0657eb63a63c40 | C44: Let us shift the focus away from mutilation to education," the Secretary-General said at a special event in February 2016 marking the 2030 commitment. " Let us make a world where FGM stands for Focus on Girls’ Minds. To fast-track progress, in March 2016, UNFPA and UNICEF launched the Global Programme to Accelerate Action to End Child Marriage. | D44: TRUE
A45: 10.18356/2e1a4924-en | B45: 1bbfbe8960be36484e2a78c9ace6b313 | C45: Second, qr is less sensitive than ols to outliers in the dependent variable since it minimizes the weighted sum of absolute deviations. Moreover, when the error terms are non-normal, qr also gives a more efficient estimator than least squares. Lastly, qr has a linear programming representation that makes estimation easy. | D45: FALSE
A46: 10.14217/9781848599451-24-en | B46: 56bdf2e958ecda277070ad0e78ae42a0 | C46: The success of GBV integrated service provision depends on co-ordinated programming that engages the different sectors across multiple levels with institutional buy-in of key stakeholders. Collaboration between the various service providers (medical, legal, police) is essential and services that are adequately resourced and located under one roof can be more readily accessed, leading to increased report and service demand as more people are able to benefit. The last decade has been the most progressive in terms of introducing new laws aimed at preventing VAWG. | D46: TRUE | E46: VAWG = violence against women and girls
A47: 10.1787/9789264281318-13-en | B47: 1d739c81852aec6acdf3904d919d0524 | C47: The 2015 OECD/INFE survey showed that in 15 countries and economies men are less likely than women to agree with at least one of the statements: “Before I buy something I carefully consider whether I can afford it” and “I keep a close personal watch on my financial affairs”. In 13 countries and economies men are more likely to agree with at least one of the statements: “I tend to live for today and let tomorrow take care of itself’ and “I find it more satisfying to spend money than to save it for the long term” (Table 10.A 1.3 in OnUne Annex 10.A1). Fewer women than men in 19 out of 30 countries and economies would be prepared to risk some of their own money when saving or making an investment. | D47: FALSE | E47: About different preference in financial decison between men-women. Not really about inequality yet.
A48: 10.1787/9789264265493-8-en | B48: 810c738ee49a6592c53e055950cddf2e | C48: Leaders and managers in organisations, who likely made time sacrifices to reach their current rank, often have difficulty accepting that work can be done in fewer hours. In some workplaces, “non-compliers” - those employees who opt to take flexible work hours and family leave - may actually be punished via denied promotions, reduced visibility to superiors, or exclusion from important projects. In-office “face time” remains an important metric of evaluating employees, even if it does not correspond with output (Elsbach and Cable, 2012). | D48: FALSE | E48: Can eventually be extrapolated to women vs men work opportunity. But this is not explicit here.
A49: 10.18356/caeceb38-en | B49: 46085ee4d03cb4e81ad600c2469e9814 | C49: A growing proportion of initiation ceremonies are being devised by Christian groups to teach young people about what is expected of them as they enter adulthood - including pre-marital sexual abstinence - as an alternative to the alleged sexual focus of teaching in traditional practice (Munthali, 2007). Ncaca, 2014).The last decade has seen increasing public debate about whether and how male circumcision should be continued following media reports of problems including commercialisation, malpractice by guardians, and deaths or permanent injury from botched circumcision (Ntombana, 2011b). However, studies also report the beneficial role of circumcision against sexually transmitted infections (Lagarde et al., | D49: TRUE
A50: 10.18356/1c6c11de-en | B50: 8d7dc9b37931f38c5039e8cb2eef2d6f | C50: Savings' made from cutting back on government funding of public services often increase demands on unpaid care and domestic work. Because these hidden costs are not recognized in economic planning, this can create the illusion of efficiency gains when in fact costs are being transferred from the public sector to the private sphere.32 In the health sector, for example, efficiency may seem to increase when the time that patients spend in the hospital decreases and as a result the cost of providing treatment per patient appears to drop. But cuts to public health expenditure can have substantial and unrecognized knock-on effects for caregivers in households, who may be forced to take time off paid work to care for a sick family member. | D50: TRUE | E50: Assuming that caregivers are likely to be women. Could also be false.
A51: 10.18356/0899dee9-en | B51: f9180ca14ff754bcd98d9ea8e1d7314f | C51: Organized in the Red de Genera y Familia, the first step was convening Care Dialogues, an advocacy strategy which aimed to raise the visibility of care on the public agenda.154 But in contrast to the above-mentioned cases, it was die engagement with the ruling party, Frente Amplio, and the inclusion of the SNIC as part of the electoral campaign programme for 2010-2015 that proved crucial.155 Care thus became a political, and not only a technical, public policy issue. Because the importance of unpaid care and domestic work had already been recognized, the discussion could centre on concrete policy design and implementation. These data have yielded, for example, measurements of “time poverty”168 and its relation with income poverty. | D51: TRUE | E51: Assuming that caregivers and domestic workers are likely to be women. Could also be false.
A52: 10.1787/9789264259157-5-en | B52: 63068a4c52e7d377dee1d40aed455865 | C52: There is a lot that companies can do to prevent long hours. The overarching goal is to adjust workplace culture so that managers prioritise tasks, time management, and efficient output rather than time in the office. Leaders must recognise that working long hours is not necessaiy for high-quality work and may even prevent it. | D52: FALSE
A53: 10.18356/8146c4ff-en | B53: 2cc009dd9dffb00802a9ff617a66100d | C53: According to official figures, there were 7,133 humanitarian entrants from Ethiopia in 1991-2015 (Government of Australia undated). Several thousand more Ethiopians have been sponsored under categories of spouse or family reunification visas, and the 2011 census records 8,452 Ethiopian-born people in the population. Like other humanitarian entrants who have been granted Permanent Protection Visas, Ethiopian refugees receive resettlement assistance through the Humanitarian Settlement Strategy (HSS), which was introduced in 2000 to provide a range of specialized services for humanitarian entrants. | D53: FALSE
A54: 10.1787/5k8xb6hw1wjf-en | B54: c220beceff9bca5dfa440eb2842a49f4 | C54: However, a cash-for-care payment may be made to parents taking care of a child until he/she reaches his or her third birthday. In Sweden, a municipal child-raising allowance (“vardnadsbidrag”) was reinstituted since 2008 on top of the statutory period of leave. Since 2009, the country’s municipalities have been able to choose whether or not to allocate benefit to parents with a child of between one and three years old who do not use publicly funded childcare services and who have already used 250 days of parental leave to care for the child. | D54: FALSE | E54: Not sure. Child care benefits are usually linked to women work opportunity. But this is not explicitly stated here.
A55: 10.18356/1c6c11de-en | B55: aebeb8ff59842b3e252c0a01e1fa88e1 | C55: Differences in the dynamics of women's and men's employment also appear to be less pronounced when exchange rates are kept at a competitive level. When demand for labour grows slowly relative to supply, levels of open unemployment increase, informal employment expands and other atypical and non-standard forms of work—such as part-time work, short-term hires and day labour markets— proliferate. At the same time, bargaining power shifts in favour of employers and the owners of firms. A reduced share of public sector jobs in overall employment reinforces this trend. | D55: TRUE
A56: 10.18356/cb17bdad-en | B56: 4916d8af58848267431dae37fcbf81d0 | C56: Poverty is not solely a lack of income, but rather is characterized by a vicious cycle of powerlessness, stigmatization,discrimination, exclusion and material deprivation,which all mutually reinforce each other' (ibid, para. The vicious cycle means that ‘the greater the inequality, the less the participation, the less the participation, the greater the inequality’ (ibid, para. Lack of participation is both a cause and consequence of poverty. Poverty is itself a ground of discrimination, but people living in poverty often experience other forms of discrimination based on,for example, gender, disability, ethnicity, and so on. | D56: TRUE
A57: 10.18356/fa683360-en | B57: 09fc4d592aa2455c6f662a78a77379e1 | C57: The part of the brain primarily responsible for the detection of, and reaction to, a threat is called the amygdala. Threat detection and survival is given priority over all other brain functions. The human system will respond to the perceived threat in one or more of five predictable ways: friend, fight, fright, freeze and/or flop. | D57: FALSE
A58: 10.18356/56f09402-en | B58: ba0b47e69221eb2f34cbe80257d4d636 | C58: In Latin America there is strong evidence of the conditions in which young people enter the labour market. Youth unemployment has traditionally been higher than in other age groups, and it is usually the first to rise in times of economic crisis and the last to fall in booms (Tokman, 1997, ECLAC, 2010). In other words, "the young are among those who bear the brunt of the recessionary and regressive effects of crises" (ECLAC, 2012a, p. 89). As a result, adolescents and youths are still overrepresented among the unemployed. | D58: FALSE
A59: 10.18356/b82bdbfb-en | B59: 318fe8fdc7167bdb17eedef9d584aac9 | C59: Evidence demonstrates that when a critical mass of women participates in decision-making, their contributions and needs are more likely to be recognized and addressed. Even though attention has largely focused on women's leadership and participation in national parliaments, there is a pressing need to realize women’s leadership throughout the daily lives of all Africans - in the home, in the economy and markets, and in society as broadly defined. Reducing inequalities in access to health and education, in addition to giving women greater choice in family decisionmaking, can have significant benefits for women and important inter-generational benefits. | D59: TRUE
A60: 10.18356/c30f3d31-en | B60: 64889f77b8ac3876aa12ab72f6e3ea1f | C60: Coverage and enforcement of legal minimum wages are equally important. In developing countries many women in the informal economy are not legally covered by minimum wages. However, minimum wage legislation can still play a positive role:first there is some evidence that minimum wages in the formal sector improve wage levels in the informal sector too, known as a "lighthouse effect"” and second, the minimum wage sets a standard for pressure groups and trade unions to aim at when pressingfor improved conditions for informal workers in a subcontracting chain. | D60: TRUE
A61: 10.1787/9789264224636-7-en | B61: 3f641e23050c65d90672a8290295bb67 | C61: The committee facilitates the integration of women’s needs in the government’s work plan as well as monitors and evaluates the mainstreaming of women’s needs in national policies. Furthermore, it also supports the creation of gender-sensitive budgets. The committee conducts studies and reviews the impact of policies on women and men. It is composed of parliamentarians from all political parties and includes a chair, two vice-chairs and eight members who study, evaluate and report on matters and bills relating to the status of women. | D61: TRUE
A62: 10.18356/0899dee9-en | B62: 5d71c3bd1a3b9b86517b23e200483317 | C62: Enrolment is increasing in all regions of the world but still varies widely between and within regions. In Central and Eastern Europe, and Latin America and the Caribbean, enrolment is high due to a historically strong public education sector. In Central Asia, the Arab States and sub-Saharan Africa, enrolment rates are very low, although there are some intra-regional variations. Even in regions with better coverage, the inclusion of marginalized populations is still a challenge. In the Arab States, private providers cover almost half of all enrolment and in Africa around 60 percent. In Kenya, for example, the government programmes target children aged 4 to 5 years, even though the policy framework identifies children within the 0 to 5 age range as intended beneficiaries. | D62: FALSE
A63: 10.18356/32ea1505-en | B63: 97056e9d8418caf1b9cb18de4249b46a | C63: While all female-headed households with outstanding loans used land as collateral, male-headed households also used livestock, houses and other property (UNCTAD, 2014). Major obstacles include target groups’ lack of awareness and inability to comply with lending requirements. Cooperatives and other civil society organizations could serve as a bridge between these lending institutions and individual women, but establishment and registration procedures are often cumbersome and involve high transaction costs, and civil society organizations often lack the financial and human resources necessary to perform such a role on a large scale (UNCTAD, 2014). | D63: TRUE
A64: 10.18356/9c9efe4c-en | B64: 32f44f50fcc3f9dfccaa4a22c0e4013f | C64: According to the United Nations Environment Programme (UNEP), which launched its Green Economy Initiative in 2008, a green economy is one that results in improved human well-being and social equity, while significantly reducing environmental risks and ecological scarcities, it is low-carbon, resource-efficient and socially inclusive (UNEP, 2011). This general definition integrates economic, social and environmental concerns in ways akin to sustainable development. Yet in practice, as the World Survey shows, there are many versions of green economy thinking. It is argued that the emerging green technology economy will be worth $4.2 trillion annually by 2020.’3 Other strands emphasize market-based approaches to environmental protection through financial valuation of natural capital, payments for ecosystem services and schemes for trading carbon and biodiversity credits and offsets. | D64: TO DO
A65: 10.18356/ecc83295-en | B65: 007f06a3cc366285d2d1530065749c62 | C65: Some countries have responded to shrinking populations with policies to attract migrants, especially younger people who can fill gaps in labour forces. By the 1970s, the fertility transition had occurred in Australia, Japan, and all highly developed countries in Europe and North America. Fertility in China fell sharply in the 1970s in response to policies to promote later and less frequent childbearing, and the introduction of the country’s 1979 family planning policy, which generally limited couples to one child. | D65: TO DO
A66: 10.14217/9e070c99-en | B66: 54206b6ebcc7a64bd3916a62d01a2f7d | C66: Judicial officers ensure the authoritative adjudication of controversies over the application of laws in specific situations, make law and public policy, especially when they exercise their power of judicial review to declare laws, government actions or omissions as unconstitutional, act as administrators for out-of-court settlements, and ensure enforcement of decisions. Judicial officers are barometers of a society’s conscience and must be seen to take restorative steps with impartiality and professionalism to address VAW by establishing and enforcing social and behavioural norms in line with the principles of the rule of law, as embodied in the law applicable and the practice before adjudicating institutions, and educating within and outside the court system. Failure to hold perpetrators accountable makes victims lose confidence in the institution of the judiciary and in the ability of the state to protect them from violence. | D66: TO DO
A67: 10.18356/07f2a46c-en | B67: e2c0b3bd85978d0798b4069b139c32fe | C67: While in Cambodia and Thailand the epidemic is slowing down, this is not yet the case with Indonesia and Viet Nam. More and more, however, new cases of infections are women who have acquired HIV from unsafe sex with their stable partners. In Thailand, this group accounted for more than 4 in 10 (or 43 per cent) of new infections in 2005 (UNAIDS and WHO, 2008, p. 16). | D67: TO DO
A68: 10.18356/27e660be-en | B68: 772a64e323ae3b9a00ab99cef581966a | C68: A diverse group of women through the Liberian Women's Initiative prevailed upon warlords and political leaders in concerted actions all over Liberia, as well as in Nigeria and Ghana during the peace negotiation processes (African Women and Peace Support Group, 2004). Through the Women of Liberia Mass Action for Peace under the banner of the Women in Peacebuilding Network, which I coordinated, Liberian women mobilized aggressively for peace between 2000 and 2003, using advocacy, mass protests and sit-ins as well as the presentation of petitions to the former Liberian President Charles Taylor and other international actors. Our activism combined with international action on war crimes and military action resulted in the signing of the peace agreement, officially ending the war. While these causes are diverse, social, political and economic inequality plays a significant role together with state collapse, economic decline, and historical patterns of conflict and battles for control of natural resources (DFID, 2001). | D68: TO DO
A69: 10.18356/ca9f4916-en | B69: b6dee1e7c9523d4f0a3984cad1d2bbc7 | C69: The sheer volume of women adding their voices to the conversation, saying “I hear you, I understand you, I believe you”, has enabled them to find courage. Providing women with a chance to unburden painful experiences, and ultimately find relief, serves as collective therapy that is free and open to all. Women everywhere can say “me too” to someone else, whether that means “it happened to me” or simply “I believe you.” | D69: TO DO
A70: 10.14217/967bd43c-en | B70: 0033dadef04b7adbdd14320547f92c95 | C70: This paper examines the effects of child, early and forced marriages (CEFM) within the Commonwealth, with a specific focus on East Africa, and highlights how to best address the issue using international, regional, and national legal norms and judicial processes currently in place. The East African countries examined are Kenya, Rwanda, Uganda and Tanzania. The introduction is then followed by the background section which gives a historical overview of CEFM at the global level. | D70: TO DO
A71: 10.18356/b620ec70-en | B71: 65679dcea5d83c2d52fe028007f3f341 | C71: Providing and Paying for Long Term Care, Paris, 2011, Starting Strong II. Early Childhood Education and Care, 2006: International Labour Organization (ILO), Un buen comienzo: la educadbnyioseducadores delaprimera infancla, Geneva, 2012: Ran American Health Organization (PAHO), "Ensenanza de la enfermeriaen saiud del adulto mayor", Human Resource for Health Series No. Few countries integrate this kind of nursing as a specific course in the undergraduate nursing curriculum. A diagnostic performed by the Pan American Health Organization (PAHO) for the region (PAHO, 2012) found that the main difficulties in strengthening nurse training in this area had to do with the lack of suitable clinical fields, the shortage of teachers trained to teach nursing of older persons, and the shortage of candidates interested in the area. | D71: TO DO
A72: 10.18356/401c524c-en | B72: 0b177884ae8cc3bcdb52efa3286336a5 | C72: These results were related to shifts in power and changes in norms, often in relation to traditional practices. An example is the establishment of villages free of female genital mutilation. Transformative outcomes generally emerge from a change process that has several stages, moving from awareness raising, to attitude change, to change in behaviour and rules, often accompanied by institutionalization of a new norm (as described in the Gender@Work framework). In such cases, UNDP was one actor among many that contributed to the end result. | D72: TO DO
A73: 10.1787/7ddddd07-en | B73: db3642428aed20e21239f80b89d96d02 | C73: Recent studies of high growth start-ups in the United States find that only 10-15% of them are founded by women (Brush etal., Looking more specifically at start-up funding, several studies have shown that women are extremely under-represented among venture-backed entrepreneurs in the United States. Gompers and Wang (2017[i2]) find that just 10.7% of US venture-backed founders were women from 2010-2015. 2014(H)) estimate the number to be 15% using data from 2011-2013. | D73: TO DO
A74: 10.18356/fa8ae033-en | B74: b06f04f91816c525adcc20747a5dee7b | C74: Gender Equality Observatory of Latin America and the Caribbean: Annual Report 2012-A Look at Grants, Support and Burden for Women. Santiago, Chile: ECLAC. Accessed 14 September 2017, https://www.cepa!. The Impact of Conditional Cash Transfer Programs on the Time Allocation of Beneficiaries: The Case of’Oportunidades’ Program in Mexico." | D74: TO DO
A75: 10.1787/5js30tvj21hh-en | B75: b41993950e8ada940f2ce81ffe3a2781 | C75: This result is significant, and it is quite high compared to other factors. The marginal effect is less important than having technical or vocational education, but NREG is particularly well fitted for rural female work. It gives a local (computed on the household who did enter the programme) evaluation of the effect, which is more accurate. The average treatment effect on the treated (part of the programme) is 0.095. | D75: TO DO
... A101: 10.18356/56f09402-en | B101: 34e246391352524b78302363287313a1 | C101: In addition to sexuality education, this effort involves implementing change processes in health services and putting in place guidelines and care protocols for prevention and for the sexual and reproductive health of this population, with an approach that differs from the one used for the adult population. The countries of Latin America have made significant progress in this direction, through different instruments. To this end there is a specific list of medicines that must be provided free to the requestor, with a proper medical prescription. | D101: TO DO

Sheet Jean-Baptiste
A1: DOI | B1: Text ID | C1: Text | D1: SDG 5 Label | E1: Comments (optional)
A2: 10.18356/6f7c638a-en | B2: d86780cec7d02f4c9590e02a42f77295 | C2: One of the targets of Goal 8 of the 2030 Agenda for Sustainable Development is the reduction in the number of young people in this situation, which means there is a need for information that explains the barriers to their integration into the labour market and the education system. The time-use data for this age group show that, on average, women who are out of school and the labour market spend at least 40 hours per week on unpaid domestic work, which confirms that they are not in school and not being paid for their work (ECLAC, 2016a). For example, in Costa Rica and Mexico, young people spend more than 70 hours per week on domestic and care work (see figure IV.6). | D2: TO DO
A3: 10.1787/9789264224636-13-en | B3: 4d07e5e027cb0c07a4c1e9f269c70c0d | C3: Djibouti Law of 27 December 2007. With the arrival of many citizens from African countries and from transit countries, Egypt is becoming a transit zone for women, or crossing South-East Asia, the former Soviet Union and Eastern Europe. What is more, since 2003 the Suez Canal has been considered a very important factor in the trafficking of human beings and of counterfeit goods. Amongst these missions, the committee must draw up plans for the implementation, supervised implementation and revision of legislation in order to prevent human trafficking, and also to draw up proposals or recommendations, and to publish a national directory including instructions and pertinent educational material, and the adoption of measures that aim to protect victims of human trafficking. The committee will also lead an awareness-raising campaign for the benefit of employers who bring in foreign workers, on issues relating to human trafficking, and will also examine reports of national and international organisations on the banning of human trafficking, and co-operate with all official and non-official programmes that provide social support for victims affected physically or psychologically or people affected by human trafficking crimes. | D3: TO DO
A4: 10.1787/9789264279322-7-en | B4: d0a96662f990a04e6eec02af04738769 | C4: A widow will receive one-eighth of her deceased husband’s assets or one-fourth if he has no children. For example, it is not uncommon for the family to pressure female heirs into relinquishing their full inheritance rights in favour of male relatives. Many women do not know that they can refuse to cede their rights or can appeal to the courts. | D4: TO DO
A5: 10.18356/604a5a2e-en | B5: 3170e6ccd61878ce07fbc1a0149eba25 | C5: Pregnant women have blood and body fluids that could expose health workers to the virus," Jallah says. I suffered a lot and was afraid I was going to die. The only thing I hoped for was for a miracle to happen," she says. One did: Comfort gave birth to two healthy baby girls with the assistance of a nurse aid who happened to pass by at the right time. | D5: TO DO
A6: 10.18356/0a98da25-en | B6: e851c33286390a6e3b9ae4ee35c6f113 | C6: First, higher interest rates dampen aggregate demand and thus employment. Second, the policy interest rate tails to address the underlying causes of inflationary pressures in many countries. Those pressures are often best dealt with through targeted fiscal policies in education,health care.and investment in strategic sectors, such as agriculture and infrastructure. The lens for identifying appropriate public investment projects and credit targets needs to be gendered and ethnically representative, underscoring the important role of affirmative action in private and public decision-making bodies. | D6: TO DO
A7: 10.1787/9789264179370-6-en | B7: e1338993d5cbc255cb6640d43c46fee1 | C7: The survey was carried out in 2011 by Gallup Inc. as part of its Gallup World Poll, and covered over 150 000 people. The target population was the entire civilian population aged 15 and older. Interviews were conducted face-to-face in economies where telephone coverage represented less than 80% of the population and by telephone in countries with higher coverage. | D7: TO DO
A8: 10.1787/9789264279322-4-en | B8: 69954e2fd1e94c64dbb6825f2919bd69 | C8: Legislation in some countries may have changed since this period, and can be expected to change in the future. Such instances should be considered and factored in during any follow'-up discussions at the country level or in international fora. Eventually, this work may also call for a revised draft to acknowledge progress and impacts made. It offers policy recommendations for boosting women’s employment and entrepreneurship through changes to legislative and institutional frameworks. The recommendations are general and will need tailoring to the particular context of each country. | D8: TO DO
A9: 10.18356/27e660be-en | B9: 772a64e323ae3b9a00ab99cef581966a | C9: A diverse group of women through the Liberian Women's Initiative prevailed upon warlords and political leaders in concerted actions all over Liberia, as well as in Nigeria and Ghana during the peace negotiation processes (African Women and Peace Support Group, 2004). Through the Women of Liberia Mass Action for Peace under the banner of the Women in Peacebuilding Network, which I coordinated, Liberian women mobilized aggressively for peace between 2000 and 2003, using advocacy, mass protests and sit-ins as well as the presentation of petitions to the former Liberian President Charles Taylor and other international actors. Our activism combined with international action on war crimes and military action resulted in the signing of the peace agreement, officially ending the war. While these causes are diverse, social, political and economic inequality plays a significant role together with state collapse, economic decline, and historical patterns of conflict and battles for control of natural resources (DFID, 2001). | D9: TO DO
A10: 10.18356/137d57b2-en | B10: 259637989620bd5f167fc67894ccc7c9 | C10: Successful programmes, she says, provide timely, sufficient and scientific information, tailored to the needs of each age group. “ Evaluation studies have shown that sex education has an impact in delaying the age at the first sexual intercourse, in increasing the use of contraception methods and condoms, and in decreasing the levels of violence against young girls,” she says. “ The above implies the reduction of early and unwanted pregnancies, and the decrease of HIV/AIDS.” It looks at the decisions that individuals make—or would like to make, if they had the opportunity. | D10: TO DO
A11: 10.1787/soc/aag-2014-5-en | B11: aa2e650903052a45c6c1b6828135bfac | C11: This is the case in Azerbaijan (90%), the Kyrgyz Republic (87%), Armenia (83%), New Zealand (82%), Myanmar (81%), Korea (76%) and Australia (72%). As in most OECD countries, health and the humanities are the other most popular degrees women obtain in the Asia/Pacific region (Figure 2.3). Women, on the other hand, are underrepresented among students and graduates of degrees in the so-called STEM fields of study - science, technology, engineering and mathematics (STEM). Innovation can benefit from a concentration of individuals with STEM skills. | D11: TO DO
A12: 10.18356/fa8ae033-en | B12: b06f04f91816c525adcc20747a5dee7b | C12: Gender Equality Observatory of Latin America and the Caribbean: Annual Report 2012-A Look at Grants, Support and Burden for Women. Santiago, Chile: ECLAC. Accessed 14 September 2017, https://www.cepa!. The Impact of Conditional Cash Transfer Programs on the Time Allocation of Beneficiaries: The Case of’Oportunidades’ Program in Mexico." | D12: TO DO
A13: 10.18356/2c8682bc-en | B13: 4b810c6f99caddec8b250387b1589964 | C13: Its effect on the quality of Lw is related to the values transmitted through education within households and to the health care carried out there. Domestic labour also influences the number of hours of wage labour available, as it releases this from care responsibilities. Reproduction is caught between a given wage and people’s needs and wants. “ | D13: TO DO
... A101: 10.6027/9789289338974-12-en | B101: bdc51a5af542282c68a617bd88facd08 | C101: Marshall defined social citizenship as "including social rights, these being the right to a modicum of economic welfare and security and right to live the life of a civilized being (quoted in Jenson, 2006:6)" (Poppel, M. 2014: 127). You can be provided for by your family, by charity organizations or by friends. Fulfilling the norms of a given community gives access to its resources. | D101: TO DO

Sheet Meike
A1: DOI | B1: Text ID | C1: Text | D1: SDG 5 Label | E1: Comments (optional)
A2: 10.18356/5085bf5a-en | B2: d6ca8e89fd99a81141f2fc79638f5711 | C2: In 2008, an estimated 44 million induced abortions occurred in the world (6 million in developed countries and 38 million in developing countries), almost half of which were carried out using unsafe procedures (Guttmacher Institute, 2012). Globally, it is estimated that 47,000 women die each year from complications associated with unsafe abortion. Many of these deaths could be prevented through better access to sexuality education, contraceptive information and supplies, and safe abortion services where allowed by law (Shah and Ahman, 2010). | D2: TRUE
A3: 10.18356/6f7c638a-en | B3: 00dd087c250922be90724c77bf6de004 | C3: In Uruguay for example, data is collected on care provided to dependent persons aged 65 or older and questions focus on care for adults who require assistance with personal hygiene, feeding or medical care, including transportation to health centres. The national time-use survey in Mexico collects information on the time spent caring for persons aged 60 or older, including support in the use of information technology, transportation and accompaniment, even when the older person is not dependent or does not have a disability. In households where persons in this age range are present, women spend 18 hours per week on average caring for them, compared with 15 hours spent by men. | D3: FALSE | E3: it mentions that women spend more time on caring but not how this is unfair or should be dealth with
A4: 10.1787/7ddddd07-en | B4: db3642428aed20e21239f80b89d96d02 | C4: Recent studies of high growth start-ups in the United States find that only 10-15% of them are founded by women (Brush etal., Looking more specifically at start-up funding, several studies have shown that women are extremely under-represented among venture-backed entrepreneurs in the United States. Gompers and Wang (2017[i2]) find that just 10.7% of US venture-backed founders were women from 2010-2015. 2014(H)) estimate the number to be 15% using data from 2011-2013. | D4: TRUE | E4: it mentions that women are less likely entrepeneurs, but now whether (and how) this would be increased. but extremely underrepresented has a negative connotation
A5: 10.18356/efc21c19-en | B5: 54adceba3c4278906b489527f4097858 | C5: An efficient use of ICT can disseminate government information to a broader audience in a fast and convenient manner. At the initial stage of national e-Government development, an ideal point of entry for developing countries would be setting up a website for the national gender machinery. The website, as an official gateway to gender-related policies and programmes, would provide a ready access to online information ranging from the organizational structure of the national gender machinery to government statistics, publications, government services and programmes aimed for women’s empowerment. Through the use of technology, the interaction between the governments and women can be stimulated and become more effective. Basic forms of interactivity available through emails, downloadable forms, discussion forums and online polls not only provide an improved delivery of basic services, but also build up a basis for online participation. | D5: TRUE | E5: promote gender equality via website
A6: 10.1787/9789264259157-7-en | B6: b4567b9a5b7330fb9b2f60323c881bb5 | C6: A recent reform has further enabled parents of children bom after June 2016 to make even more flexible use of the job protection provision: With the employer’s consent, they can use 12 months of the 36 month employment-protection period any time between the child’s third and eighth birthday. But, beyond the provisions of parental leave (Elternzeit) and family care leave (Pflegezeit and Familienpflegezeit), employees in Germany are not legally entitled to resume full-time work once their reduced working hours have been approved by their employer (see Chapter 3 for an international comparison of legal provisions). On average, full-time working mothers in Germany put in nearly 42 hours per week, outstripped only by Swiss and Austrian mothers with about 44 hours per week (Figure 4.6). | D6: FALSE | E6: most about parents, not on how this ensures equality between genders. just a remark about high working hours among german women
A7: 10.18356/9c9efe4c-en | B7: 32f44f50fcc3f9dfccaa4a22c0e4013f | C7: According to the United Nations Environment Programme (UNEP), which launched its Green Economy Initiative in 2008, a green economy is one that results in improved human well-being and social equity, while significantly reducing environmental risks and ecological scarcities, it is low-carbon, resource-efficient and socially inclusive (UNEP, 2011). This general definition integrates economic, social and environmental concerns in ways akin to sustainable development. Yet in practice, as the World Survey shows, there are many versions of green economy thinking. It is argued that the emerging green technology economy will be worth $4.2 trillion annually by 2020.’3 Other strands emphasize market-based approaches to environmental protection through financial valuation of natural capital, payments for ecosystem services and schemes for trading carbon and biodiversity credits and offsets. | D7: FALSE
A8: 10.18356/36aba0c4-en | B8: f19db2735a2f32ec978a5e1c0961207c | C8: As such, pursuing a shift to demand-led growth, on its own, is unlikely to address the environmental costs associated with sustained growth, unless the higher wages and earnings of lower income groups that will result from such a shift are spent on goods that are less reliant on fossil fuels and natural resource extraction, and increased public expenditure and investment is also allocated to fuel-efficient sectors and technologies. This is where proposals for green economy become relevant. There are, however, different variants of green economy. | D8: FALSE
A9: 10.1787/9789264279322-4-en | B9: 69954e2fd1e94c64dbb6825f2919bd69 | C9: Legislation in some countries may have changed since this period, and can be expected to change in the future. Such instances should be considered and factored in during any follow'-up discussions at the country level or in international fora. Eventually, this work may also call for a revised draft to acknowledge progress and impacts made. It offers policy recommendations for boosting women’s employment and entrepreneurship through changes to legislative and institutional frameworks. The recommendations are general and will need tailoring to the particular context of each country. | D9: TRUE
A10: 10.18356/27e660be-en | B10: 772a64e323ae3b9a00ab99cef581966a | C10: A diverse group of women through the Liberian Women's Initiative prevailed upon warlords and political leaders in concerted actions all over Liberia, as well as in Nigeria and Ghana during the peace negotiation processes (African Women and Peace Support Group, 2004). Through the Women of Liberia Mass Action for Peace under the banner of the Women in Peacebuilding Network, which I coordinated, Liberian women mobilized aggressively for peace between 2000 and 2003, using advocacy, mass protests and sit-ins as well as the presentation of petitions to the former Liberian President Charles Taylor and other international actors. Our activism combined with international action on war crimes and military action resulted in the signing of the peace agreement, officially ending the war. While these causes are diverse, social, political and economic inequality plays a significant role together with state collapse, economic decline, and historical patterns of conflict and battles for control of natural resources (DFID, 2001). | D10: FALSE | E10: while women protest, it doesnt say anything about inequality between women and men
A11: 10.18356/a5e42fa0-en | B11: 8a0c60386ec53a00c7302c3a929f50b3 | C11: Despite this progress, bilateral aid to LDCs fell by 3.9 per cent in real terms. However, remittances to developing countries fell in 2016 for a second consecutive year, declining by 2.4 per cent over 2015. This section provides a few highlights of these interconnections in the context of the theme and Goals under review at the High-Level Political Forum on Sustainable Development in July 2017. | D11: FALSE
A12: 10.14217/967bd43c-en | B12: 0033dadef04b7adbdd14320547f92c95 | C12: This paper examines the effects of child, early and forced marriages (CEFM) within the Commonwealth, with a specific focus on East Africa, and highlights how to best address the issue using international, regional, and national legal norms and judicial processes currently in place. The East African countries examined are Kenya, Rwanda, Uganda and Tanzania. The introduction is then followed by the background section which gives a historical overview of CEFM at the global level. | D12: TRUE | E12: child marriage policy
A13: 10.1787/9789264259157-7-en | B13: 419163df6dbb548003cfb59af8e8565d | C13: Countiy Group 4: France, Iceland, Norway and Sweden Source: OECD calculations based on European Union Statistics on Income and Living Conditions (EU SILC) 2012. Country' Group 2: Italy, Greece, Spain, Portugal, Lithuania, Poland and Slovenia. Country Group 3: the Czech Republic, Estonia, Finland, Hungary, Latvia and the Slovak Republic. | D13: FALSE
A14: 10.14217/9781848599451-24-en | B14: 56bdf2e958ecda277070ad0e78ae42a0 | C14: The success of GBV integrated service provision depends on co-ordinated programming that engages the different sectors across multiple levels with institutional buy-in of key stakeholders. Collaboration between the various service providers (medical, legal, police) is essential and services that are adequately resourced and located under one roof can be more readily accessed, leading to increased report and service demand as more people are able to benefit. The last decade has been the most progressive in terms of introducing new laws aimed at preventing VAWG. | D14: FALSE
A15: 10.1787/5k8xb6hw1wjf-en | B15: c220beceff9bca5dfa440eb2842a49f4 | C15: However, a cash-for-care payment may be made to parents taking care of a child until he/she reaches his or her third birthday. In Sweden, a municipal child-raising allowance (“vardnadsbidrag”) was reinstituted since 2008 on top of the statutory period of leave. Since 2009, the country’s municipalities have been able to choose whether or not to allocate benefit to parents with a child of between one and three years old who do not use publicly funded childcare services and who have already used 250 days of parental leave to care for the child. | D15: FALSE | E15: does not say anything about how women might benefit
A16: 10.18356/137d57b2-en | B16: 33f15d8472ee9dac57b488d9ad445543 | C16: In a mega-city such as Lagos, Nigeria, planners are trying to redevelop neighbourhoods and create more cohesive, manageable and livable communities. Nations like Ethiopia and India have launched campaigns to end child marriages and prevent life-threatening adolescent pregnancies. With good planning and thoughtful policies. When young people can claim their rights to health, education and decent working conditions, they become a powerful force for economic development and positive change. Throughout the developing world, social scientists and policymakers want to make the most of large youthful populations, for the sake of hopeful young people themselves as well as in the interests of economic growth and development. | D16: TRUE | E16: policy to protect girls
A17: 10.18356/e617261d-en | B17: 00f5ff6cbf35b0736888a769b8e02d49 | C17: In these aspects, there are no statistically significant differences between female and male migrants. The only difference is in situations when respondents were taken from the workplace to die Federal Migration Service, which happened to 23 per cent of male migrants and 8 per cent of females.18 Agadjanian and others (2017) showed diat 34 per cent of female migrants from Central Asia had faced ethnicity-based harassment. Migrants in the Russian Federation do not settle in ethnic neighbourhoods but are spread out across cities (Vendina, 2012) so there are no places to avoid discrimination in the "mainstream" housing market (Agadjanian and Zotova, 2011). | D17: FALSE | E17: fact statement diff migrants women and men
A18: 10.18356/fa8ae033-en | B18: 6d49772b7e0bfae5e119cc583570a9d2 | C18: Adopted in March 2007 by a group of human rights experts convened by the International Commission of Jurists and the I nternational Service for H u ma n Rights on beha If of a coa I i-tion of human rights organizations. From these developments, it is evident that States have a positive duty to prevent, protect and punish cases of violence even when the harm takes place within the family. In its General Recommendation No. | D18: FALSE
A19: 10.1787/9789264210745-6-en | B19: 68bb5eab1e1f88a44ec3334d96430377 | C19: In this way, the Council harmonises strategies of relevant organisations and provides for transfer of information and a sharing of resources. Additionally, there are extended plenary meetings twice per year with the mandate of nurturing political leadership. The CEO oversees the technical task teams for programmes (i.e. policy and legislation, research, prevention), monitoring and evaluation, administration, communication and resource mobilisation teams. | D19: FALSE
A20: 10.14217/9781848599451-18-en | B20: b7da16da7c29f33f10e1938d32ceb20f | C20: This assistance is designed to help people cope with their trauma, provide strategies for protecting themselves and their families, and make the necessary plans to achieve safety and stability. The minister emphasised the need for collaboration and co-operation at the national, community and individual levels in order to reduce and abate GBV, calling for a holistic approach that went beyond the government to include churches, NGOs, trade unions, the healthcare sector and others. These include (but are not limited to): lack of special DVUs or mechanisms, inadequate psychological support services for abusers, lack of legal aid services and victim support programmes, insufficient shelter, psychological and legal counselling and education support services, lack of sufficient preparation by healthcare providers to collect and present medical/legal evidence, lack of sufficient co-ordination between the medical, law enforcement, social services and justice sectors, and prevalence of stigma, discrimination, victim blaming and gender inequality. | D20: FALSE
A21: 10.18356/fa683360-en | B21: f81b06bcdbc7a57989e6e445bb53808b | C21: Key factors in not completing the initial process were being disbelieved or fear of the police and the criminal justice system. For example, it is not always clear whether cases were “lost” or “dropped”. Dropped cases are those where either the police or prosecutor makes a clear and explicit decision not to proceed with a case. | D21: FALSE
A22: 10.1787/soc/aag-2014-5-en | B22: aa2e650903052a45c6c1b6828135bfac | C22: This is the case in Azerbaijan (90%), the Kyrgyz Republic (87%), Armenia (83%), New Zealand (82%), Myanmar (81%), Korea (76%) and Australia (72%). As in most OECD countries, health and the humanities are the other most popular degrees women obtain in the Asia/Pacific region (Figure 2.3). Women, on the other hand, are underrepresented among students and graduates of degrees in the so-called STEM fields of study - science, technology, engineering and mathematics (STEM). Innovation can benefit from a concentration of individuals with STEM skills. | D22: FALSE | E22: doesnt say how women in STEM will be increased
A23: 10.14217/967bd43c-en | B23: 244c387f232fa8b0e81f78f3793a63f5 | C23: In Article 198, the law defines ‘marital rape’ as any act of sexual intercourse committed by one spouse on the other by violence, threat or trickery. The penalty for ‘marital rape’ is found in Article 199, where is provided that such a person shall be liable to a term of imprisonment of at least two (2) months but less than six (6) months and a fine of one hundred thousand (100,000) to three hundred thousand (300,000) Rwandan francs or one of these penalties. If ‘marital rape’ results in an ordinary disease, the offender shall be liable to a term of imprisonment of six (6) months to two (2) years. | D23: TRUE | E23: end harmful practice
A24: 10.1787/5js30tvj21hh-en | B24: b41993950e8ada940f2ce81ffe3a2781 | C24: This result is significant, and it is quite high compared to other factors. The marginal effect is less important than having technical or vocational education, but NREG is particularly well fitted for rural female work. It gives a local (computed on the household who did enter the programme) evaluation of the effect, which is more accurate. The average treatment effect on the treated (part of the programme) is 0.095. | D24: FALSE
A25: 10.18356/ecc83295-en | B25: 007f06a3cc366285d2d1530065749c62 | C25: Some countries have responded to shrinking populations with policies to attract migrants, especially younger people who can fill gaps in labour forces. By the 1970s, the fertility transition had occurred in Australia, Japan, and all highly developed countries in Europe and North America. Fertility in China fell sharply in the 1970s in response to policies to promote later and less frequent childbearing, and the introduction of the country’s 1979 family planning policy, which generally limited couples to one child. | D25: FALSE
A26: 10.18356/0899dee9-en | B26: f9180ca14ff754bcd98d9ea8e1d7314f | C26: Organized in the Red de Genera y Familia, the first step was convening Care Dialogues, an advocacy strategy which aimed to raise the visibility of care on the public agenda.154 But in contrast to the above-mentioned cases, it was die engagement with the ruling party, Frente Amplio, and the inclusion of the SNIC as part of the electoral campaign programme for 2010-2015 that proved crucial.155 Care thus became a political, and not only a technical, public policy issue. Because the importance of unpaid care and domestic work had already been recognized, the discussion could centre on concrete policy design and implementation. These data have yielded, for example, measurements of “time poverty”168 and its relation with income poverty. | D26: FALSE
A27: 10.18356/401c524c-en | B27: 0b177884ae8cc3bcdb52efa3286336a5 | C27: These results were related to shifts in power and changes in norms, often in relation to traditional practices. An example is the establishment of villages free of female genital mutilation. Transformative outcomes generally emerge from a change process that has several stages, moving from awareness raising, to attitude change, to change in behaviour and rules, often accompanied by institutionalization of a new norm (as described in the Gender@Work framework). In such cases, UNDP was one actor among many that contributed to the end result. | D27: TRUE
A28: 10.1787/9789264210745-5-en | B28: 53c49d95e8e01516bc7a3cf10eaee6f9 | C28: The employer’s role is largely associated with the obligation to act as a model employer. There is an expectation that the public sector, by the excellence of its modern employment policies and practices, will act as a leading force and as an example for the rest of the country’s employers. Therefore, it is crucial that the public sector embeds and exemplifies gender equality in its own employment policies. | D28: TRUE
A29: 10.18356/32ea1505-en | B29: b543ea0cea2c54404f4f83e1fd619f27 | C29: Women are generally as active as men in cash crop production, often providing the bulk of labour on contracted farms. There are, however, important gender differences in control over the commercial proceeds (men are contracted, while women supply unpaid family labour) and in the scale of operations (due to the constraints women face on increasing sales of their produce). Global Employment Trends 2014: supporting data sets: Employment by status and sex (http://www.ilo.org/legacy/english/geiy2014/GET_sector_share.xlsx) (accessed July 2015). Note: Data for the following countries are unavailable: Djibouti, Kiribati, Sao Tome and Principe, South Sudan, Sudan (Former), Timor-Leste, Tuvalu and Vanuatu. Evidence from a number of studies points to similar dynamics in both traditional export sectors (e.g. cocoa, coffee and tea) and non-traditional exports (e.g. fruit, horticulture and flowers). | D29: TRUE | E29: a bit implicit, because nothing is proposed to create equality
A30: 10.1787/9789264213944-8-en | B30: c63b1ade007787cd8e30feacb3a31f18 | C30: It provides the financing and capital necessary for their development, it supports the entrepreneur when strategic decisions have to be made, and it facilitates the improvement of the company’s potential for generating value for its customers, shareholders and all officers and employees. The objective of this stage, which is financially very risky, is to finalise the development of a technological prototype that makes it possible to meet the technological challenge, and begin to assess the existence of a potential market. The signing of a first client constitutes the transition to the venture capital stage. The few successful projects should more than offset the capital losses of those who fail. | D30: FALSE
A31: 10.18356/56f09402-en | B31: ba0b47e69221eb2f34cbe80257d4d636 | C31: In Latin America there is strong evidence of the conditions in which young people enter the labour market. Youth unemployment has traditionally been higher than in other age groups, and it is usually the first to rise in times of economic crisis and the last to fall in booms (Tokman, 1997, ECLAC, 2010). In other words, "the young are among those who bear the brunt of the recessionary and regressive effects of crises" (ECLAC, 2012a, p. 89). As a result, adolescents and youths are still overrepresented among the unemployed. | D31: FALSE
A32: 10.1787/9789264224636-11-en | B32: 747776de24dc6a898960383ef0997e0b | C32: Overall, assistance for victims of violence, hotlines, shelters and counselling services remains very limited in MENA countries. More shelters are needed to ensure that all victims throughout the country can access immediate protection. According to recommendations of the Council of Europe, all countries should provide one place in a shelter per 7 500 residents, this coverage is not achieved by the existing geographical distribution of shelters (Council of Europe, 2007: 18). There is also a need for greater provision of free legal aid and advice services for victims of violence. | D32: FALSE
A33: 10.18356/ca9f4916-en | B33: b6dee1e7c9523d4f0a3984cad1d2bbc7 | C33: The sheer volume of women adding their voices to the conversation, saying “I hear you, I understand you, I believe you”, has enabled them to find courage. Providing women with a chance to unburden painful experiences, and ultimately find relief, serves as collective therapy that is free and open to all. Women everywhere can say “me too” to someone else, whether that means “it happened to me” or simply “I believe you.” | D33: TRUE
A34: 10.18356/c93219ca-en | B34: 9912d14c0ab6c021c89160b486b1d27d | C34: The section then presents current practices to promote access to sexual and reproductive health and reproductive rights for persons with disabilities, before concluding with recommendations for the way forward. Target 5.6, which is placed under the goal calling for gender equality and empowerment of all women and girls, calls for ensuring universal access to sexual and reproductive health and reproductive rights as agreed in accordance with the Programme of Action of the International Conference on Population and Development and the Beijing Platform for Action and the outcome documents of their review conferences. The CPRD is the first Convention to explicitly recognize the need for sexual and reproductive health for persons with disabilities. Article 25 underscores the need to provide persons with disabilities with the same range, quality and standard of free or affordable sexual and reproductive health care and programmes as provided to other persons. | D34: TRUE
A35: 10.18356/5085bf5a-en | B35: 6a390516c7b15f3b27739ce3b4337184 | C35: Although a number of countries, mostly in Europe, that have adopted such measures have experienced modest increases in fertility between 2000-2005 and 2005-2010 (United Nations, 2013a), the implementation and effectiveness of such measures have been difficult to ascertain. While the percentage of Governments with policies to raise fertility has increased steadily from just 9 per cent in 1976 to 27 per cent in 2013, the percentage of Governments with policies to lower fertility increased from 27 per cent in 1976 to 42 per cent in 1996, and then remained at 43 per cent in 2013. During this time, the percentage of Governments that did not have policies to influence fertility has declined steadily from 52 per cent in 1976 to 13 per cent in 2013 (table III.l). In 1976, only about one in every five Governments in more developed regions had policies to raise fertility, but by 2013 this proportion had risen steadily to more than two thirds. | D35: FALSE
A36: 10.18356/fa683360-en | B36: 09fc4d592aa2455c6f662a78a77379e1 | C36: The part of the brain primarily responsible for the detection of, and reaction to, a threat is called the amygdala. Threat detection and survival is given priority over all other brain functions. The human system will respond to the perceived threat in one or more of five predictable ways: friend, fight, fright, freeze and/or flop. | D36: FALSE
A37: 10.18356/6f7c638a-en | B37: d86780cec7d02f4c9590e02a42f77295 | C37: One of the targets of Goal 8 of the 2030 Agenda for Sustainable Development is the reduction in the number of young people in this situation, which means there is a need for information that explains the barriers to their integration into the labour market and the education system. The time-use data for this age group show that, on average, women who are out of school and the labour market spend at least 40 hours per week on unpaid domestic work, which confirms that they are not in school and not being paid for their work (ECLAC, 2016a). For example, in Costa Rica and Mexico, young people spend more than 70 hours per week on domestic and care work (see figure IV.6). | D37: TRUE | E37: doesnt say how unpaid domestic work will be more equally distributed
A38: 10.14217/967bd43c-en | B38: 00550a0fe64ba38833102f529118d5be | C38: Early marriage, also refers to marriages where both spouses are 18 years and over but certain factors make them unready to consent to marriage, for example their level of physical, emotional, sexual and psychosocial development, or lack of information regarding the person’s life options.10 Within the context of the law in East Africa, CEFM does not have a concrete definition. Most information gathered on CEFM places child marriages into two categories: those married before 15 years and those married before 18 years. This categorisation is of importance as it enables those researching CEFM to understand the trends in various countries. | D38: TRUE
A39: 10.1787/9789264210745-6-en | B39: 8b8efdd6ae34ef52bbded7d658b5866a | C39: The Inter-Departmental Co-ordination Group assumes responsibility for: promoting co-operation between ministries, adopting a federal plan of action, preparing an intermediary' report and a final report at the end of the term, and exchanging good practices and promoting instruments useful to enforcing the law. The representatives of the ministries participating in the co-ordination group are also appointed as gender focal points in their respective entities. They receive compulsory' training on gender mainstreaming and are tasked with ensuring follow-up on the diverse measures foreseen by the law (e.g, gender statistics, gender-responsive budgeting and the “gender test”). | D39: TRUE
A40: 10.18356/e617261d-en | B40: e95d9b6864d5595d1cd7f4e8dca7d4d2 | C40: Another 25 per cent said that they would like to stay in the Russian Federation and live there permanently, while 21 per cent said that they would like to live in the Russian Federation for several years and then return home permanently (Tyuryukanova, 2011, p. 155). Among them, females from Uzbekistan more often wanted to "come and go" (66 per cent) and were the least willing to apply for Russian citizenship (70 per cent of them did not have such plans) (Tyuryukanova, 2011, pp. Contrary to these findings, another survey of Central Asian female migrants in the Russian Federation showed that 70 per cent of them had firm plans to return home (Agadjanian and others, 2014). | D40: FALSE | E40: about migration among women, not about equality
A41: 10.1787/9789264259157-5-en | B41: 63068a4c52e7d377dee1d40aed455865 | C41: There is a lot that companies can do to prevent long hours. The overarching goal is to adjust workplace culture so that managers prioritise tasks, time management, and efficient output rather than time in the office. Leaders must recognise that working long hours is not necessaiy for high-quality work and may even prevent it. | D41: FALSE
A42: 10.18356/8e0dd871-en | B42: dacdf4451bcdcd917e1f922f2349752f | C42: Target 3.7 calls for universal access to sexual and reproductive health care services (including family planning), information and education, which would help to prevent adolescent childbearing and unintended pregnancies. Globally, childbearing among adolescents declined by 21 per cent between 2000 and 2015. Central and Southern Asia made the greatest progress: the region reduced the adolescent birth rate by more than 50 per cent, largely due to advances in Southern Asia. | D42: TRUE
A43: 10.18356/caeceb38-en | B43: 46085ee4d03cb4e81ad600c2469e9814 | C43: A growing proportion of initiation ceremonies are being devised by Christian groups to teach young people about what is expected of them as they enter adulthood - including pre-marital sexual abstinence - as an alternative to the alleged sexual focus of teaching in traditional practice (Munthali, 2007). Ncaca, 2014).The last decade has seen increasing public debate about whether and how male circumcision should be continued following media reports of problems including commercialisation, malpractice by guardians, and deaths or permanent injury from botched circumcision (Ntombana, 2011b). However, studies also report the beneficial role of circumcision against sexually transmitted infections (Lagarde et al., | D43: TRUE
A44: 10.18356/caeceb38-en | B44: 097588fda30192cce1b6fb3efb5a1f66 | C44: As we would expect, these proportions increase with age such that between half and three quarters of older adolescents are working, or seeking work. However, adolescents frequently combine school and work. Research in South Africa and Zimbabwe on distribution shows that most working adolescents live in very poor households in rural areas and are engaged in subsistence agriculture, many combining this with domestic work (including care) and commercial agriculture (Robson, 2004, Bray, 2012, Dawes et al., | D44: FALSE | E44: not about women per se
A45: 10.18356/0899dee9-en | B45: 0bdff1a16124338ba120c46cbd9b44cd | C45: The work is regarded as voluntary, and working conditions are casual.91 In the case of South Africa, the pay levels of ECEC workers do not allow them to move out of poverty. Sometimes ECEC workers enrol in training, topping up their incomes with the EPWP stipend. However, when the training ends, they have higher skills but the same remuneration as before 92 Poor worker remuneration is also common in ECEC programmes in other African countries, like those reviewed in Kenya95 and Nigeria. Improvements in national legislation in South Africa and Uruguay, and the ratification of the ILO’s Domestic Workers Convention (No. | D45: FALSE
A46: 10.18356/fa8ae033-en | B46: 13bd9f055dab0f9d915f1ab5c8617225 | C46: At the regional level, the right to equality and non-discrimination is also guaranteed by, for example, the African Charter on Human and People's Rights (arts. This means that States must take all necessary legislative, administrative and other measures to ensure that no family may be subject to discrimination on any ground. Any right, benefit, privilege or obligation to one ‘family’ (e.g., in social or welfare benefits, inheritance, social security and pensions) must be accorded to all of them. | D46: FALSE
A47: 10.18356/2c8682bc-en | B47: 4b810c6f99caddec8b250387b1589964 | C47: Its effect on the quality of Lw is related to the values transmitted through education within households and to the health care carried out there. Domestic labour also influences the number of hours of wage labour available, as it releases this from care responsibilities. Reproduction is caught between a given wage and people’s needs and wants. “ | D47: FALSE
A48: 10.1787/5jm2hz8dgls6-en | B48: afb2f20182972c1ba7041c3f86b05e84 | C48: It is an average of the squares of its five sub-indices (equation 10). It ranges from 0, indicating very low levels of discrimination, to 1, indicating very high levels of discrimination. Three-years average (2009-11). Three-years average (2009-11). Three-years average (2009-11). Three-years average (2009-11). | D48: FALSE
A49: 10.18356/ea8c16ef-en | B49: cc7ff9087fabcdc500e8966e260520e3 | C49: They reported that cash transfers had the greatest impact on marriage-related indicators, noting that the transfers worked as an incentive to stay in school and increase financial independence, both of which could have reduced adolescent marriage. Enrolment rates were higher for children participating in the programme, and there was a slight increase in the number of years of schooling they received. The mixed results suggest that the design of transfer programmes may be important for achieving outcomes. Cash payments made directly to girls rather than their parents had the greatest impact on reducing adolescent pregnancy and HIV in Malawi’s Zomba programme (Baird et al., | D49: TRUE
A50: 10.18356/8a6d677c-en | B50: ed20f3ece97567ca70521b9a806d9ba1 | C50: For each spotlight, pressing data gaps and measurement challenges are also highlighted. These supplemental indicators were selected based on an open consultation with civil society organizations and inputs from other international experts (see Box 3.1). Respondents, including international agencies and civil society organizations, submitted suggestions for additional indicators, along with information on their relevance and, where possible, data sources and how often the data are produced. The recommendations included, for instance, monitoring the "average weekly time spent by women and girls on water collection" for Goal 6 and the "share of women aged 15-49 whose BMI [body mass index] is less than 18.5 (underweight)" for Goal 2. | D50: TRUE | E50: policy ideas for achieving gender equality? eventhough also related to other goals?
A51: 10.14217/967bd43c-en | B51: 1e0a700a4aabfbb4408648e08f6daf33 | C51: For purposes of this paper the definition will focus on ‘forced marriage’ and ‘early marriage.’ The reason for this is that by definition, ‘child’ marriages7 can be considered ‘forced marriage’, or a form thereof, because children especially those under the age of 15 are not able to make an informed decision as to whether or not they want to be married. Most often this decision is influenced by a parent or family member. | D51: TRUE
A52: 10.1787/9789264281318-13-en | B52: 1d739c81852aec6acdf3904d919d0524 | C52: The 2015 OECD/INFE survey showed that in 15 countries and economies men are less likely than women to agree with at least one of the statements: “Before I buy something I carefully consider whether I can afford it” and “I keep a close personal watch on my financial affairs”. In 13 countries and economies men are more likely to agree with at least one of the statements: “I tend to live for today and let tomorrow take care of itself’ and “I find it more satisfying to spend money than to save it for the long term” (Table 10.A 1.3 in OnUne Annex 10.A1). Fewer women than men in 19 out of 30 countries and economies would be prepared to risk some of their own money when saving or making an investment. | D52: FALSE
A53: 10.14217/2d08a027-en | B53: b1b6995b10ce561b7bfc2333f49aa089 | C53: We protested against political parties requesting huge sums of money as part of the party nomination process.' In 2016, the organisation signed an agreement with the Cameroon government to empower hundreds of youth and women in elections participation. This process involved building capacity to reinforce leadership and civic education. | D53: FALSE
A54: 10.18356/77d08b03-en | B54: f040d7270a4160b55f0ba9f8508bfb76 | C54: They entail wide-ranging coordination between different authorities, i.e., they are not the exclusive responsibility of labour ministries (ECLAC, 2005). Labour regulation policies, on the other hand, are those that act upon the relationship between workers and employers through provisions designed to secure rights: non-discrimination, minimum wages and social security, among others. Labour market policies, for their part, have the object of combating unemployment, mitigating its effects and supporting the population at risk of joblessness. These policies can be divided into passive ones designed to offset the loss of pay, such as subsidies, and active ones, which are meant to preserve existing jobs and support the creation of new ones, help the unemployed find work, facilitate the connection between labour supply and demand and improve the skills of the unemployed and those working in microenterprises and small businesses (Samaniego, 2002). | D54: FALSE
A55: 10.18356/32ea1505-en | B55: 97056e9d8418caf1b9cb18de4249b46a | C55: While all female-headed households with outstanding loans used land as collateral, male-headed households also used livestock, houses and other property (UNCTAD, 2014). Major obstacles include target groups’ lack of awareness and inability to comply with lending requirements. Cooperatives and other civil society organizations could serve as a bridge between these lending institutions and individual women, but establishment and registration procedures are often cumbersome and involve high transaction costs, and civil society organizations often lack the financial and human resources necessary to perform such a role on a large scale (UNCTAD, 2014). | D55: FALSE
A56: 10.18356/ea56e86b-en | B56: 75c1fd7e470a6f66ae0657eb63a63c40 | C56: Let us shift the focus away from mutilation to education," the Secretary-General said at a special event in February 2016 marking the 2030 commitment. " Let us make a world where FGM stands for Focus on Girls’ Minds. To fast-track progress, in March 2016, UNFPA and UNICEF launched the Global Programme to Accelerate Action to End Child Marriage. | D56: TRUE
A57: 10.1787/5jm0xdx0b06g-en | B57: 68cc56f99f7433126251488792ae8b82 | C57: The law entered into force the last quarter of 2014, though some provisions will be phased in over the 2015-2018 period. The overall goal tax reform is to raise the tax-to-GDP ratio to finance a large increase in education spending. The tax measures aim to raise an extra 3% of GDP. More than half of the increased revenues are forecasted to come from increased income taxation, mainly from corporate income (Table 1). Increases in compliance are forecast to increase revenues by 0.5% of GDP (17% of the overall reform revenue goal), while expansions in the VAT base will account for 0.3% of GDP (12% of the overall reform target. To raise more revenues Chile could focus on broadening the tax base of the personal income tax (PIT), which does not contribute significantly to reduce inequality. | D57: FALSE
A58: 10.18356/914e7bcc-en | B58: f43d0e85dc177042358b28e93e6c51ea | C58: In terms of context, these CoSOs may precede the eruption of conflict, may deal with issues not relating to the conflict (in Israel and Turkey for example) or may be established as a result of the conflict (in Bosnia, Cyprus and Thrkey). In terms of identity, the vast majority of these CoSOs are civic, post-national or multicultural. In terms of FOA the organizations work on issues directly relating to the conflict, but also on political issues that do not relate strictu sensu to the conflict. | D58: FALSE
A59: 10.18356/0a98da25-en | B59: e851c33286390a6e3b9ae4ee35c6f113 | C59: First, higher interest rates dampen aggregate demand and thus employment. Second, the policy interest rate tails to address the underlying causes of inflationary pressures in many countries. Those pressures are often best dealt with through targeted fiscal policies in education,health care.and investment in strategic sectors, such as agriculture and infrastructure. The lens for identifying appropriate public investment projects and credit targets needs to be gendered and ethnically representative, underscoring the important role of affirmative action in private and public decision-making bodies. | D59: TRUE | E59: gendered representative stresses that the policy needs to reduce gender inequality, or is this merely implied?
A60: 10.18356/1c6c11de-en | B60: 8d7dc9b37931f38c5039e8cb2eef2d6f | C60: Savings' made from cutting back on government funding of public services often increase demands on unpaid care and domestic work. Because these hidden costs are not recognized in economic planning, this can create the illusion of efficiency gains when in fact costs are being transferred from the public sector to the private sphere.32 In the health sector, for example, efficiency may seem to increase when the time that patients spend in the hospital decreases and as a result the cost of providing treatment per patient appears to drop. But cuts to public health expenditure can have substantial and unrecognized knock-on effects for caregivers in households, who may be forced to take time off paid work to care for a sick family member. | D60: FALSE
A61: 10.1787/5db444d4-en | B61: 2619f36e9742dfe92717ebfcf7b0250c | C61: Addressing structural inequalities also requires an approach that cuts across silos. For example, promoting women’s business ownership requires a smart policy mix, which, among others, takes into consideration gender impacts of regulatory policies and competition frameworks, while removing potential barriers in access to public procurement and finance. These efforts must be coupled with an enabling social infrastructure (e.g. accessible and affordable child/elderly care) to reduce the burden of unpaid care work, as well as partnerships between the public and private sectors. | D61: TRUE | E61: tthe examples show that the inequality mentioned in frist sentence relates to gender inequalty
A62: 10.18356/1c6c11de-en | B62: aebeb8ff59842b3e252c0a01e1fa88e1 | C62: Differences in the dynamics of women's and men's employment also appear to be less pronounced when exchange rates are kept at a competitive level. When demand for labour grows slowly relative to supply, levels of open unemployment increase, informal employment expands and other atypical and non-standard forms of work—such as part-time work, short-term hires and day labour markets— proliferate. At the same time, bargaining power shifts in favour of employers and the owners of firms. A reduced share of public sector jobs in overall employment reinforces this trend. | D62: FALSE
A63: 10.18356/b620ec70-en | B63: 65679dcea5d83c2d52fe028007f3f341 | C63: Providing and Paying for Long Term Care, Paris, 2011, Starting Strong II. Early Childhood Education and Care, 2006: International Labour Organization (ILO), Un buen comienzo: la educadbnyioseducadores delaprimera infancla, Geneva, 2012: Ran American Health Organization (PAHO), "Ensenanza de la enfermeriaen saiud del adulto mayor", Human Resource for Health Series No. Few countries integrate this kind of nursing as a specific course in the undergraduate nursing curriculum. A diagnostic performed by the Pan American Health Organization (PAHO) for the region (PAHO, 2012) found that the main difficulties in strengthening nurse training in this area had to do with the lack of suitable clinical fields, the shortage of teachers trained to teach nursing of older persons, and the shortage of candidates interested in the area. | D63: FALSE
A64: 10.18356/1cef4f1d-en | B64: 5fcdf01bc70595a35bcbd3c03c7d6ed0 | C64: This is despite (or because of) its attendant market deregulation, attrition of the public realm, and the increasingly crowded and competitive scramble for an advantageous spot in the emerging international division of labour. It has largely followed a supply-side approach, one that overlooks the fact that individuals are already integrated into the global economy, but on exclusionary terms that stem from prevailing rules, norms and policies. The global policy narrative on women’s economic empowerment, which seems to focus largely on their inclusion in markets, is an example of this limited perspective. | D64: TRUE
A65: 10.18356/b82bdbfb-en | B65: 318fe8fdc7167bdb17eedef9d584aac9 | C65: Evidence demonstrates that when a critical mass of women participates in decision-making, their contributions and needs are more likely to be recognized and addressed. Even though attention has largely focused on women's leadership and participation in national parliaments, there is a pressing need to realize women’s leadership throughout the daily lives of all Africans - in the home, in the economy and markets, and in society as broadly defined. Reducing inequalities in access to health and education, in addition to giving women greater choice in family decisionmaking, can have significant benefits for women and important inter-generational benefits. | D65: TRUE
A66: 10.1787/9789264224636-13-en | B66: 4d07e5e027cb0c07a4c1e9f269c70c0d | C66: Djibouti Law of 27 December 2007. With the arrival of many citizens from African countries and from transit countries, Egypt is becoming a transit zone for women, or crossing South-East Asia, the former Soviet Union and Eastern Europe. What is more, since 2003 the Suez Canal has been considered a very important factor in the trafficking of human beings and of counterfeit goods. Amongst these missions, the committee must draw up plans for the implementation, supervised implementation and revision of legislation in order to prevent human trafficking, and also to draw up proposals or recommendations, and to publish a national directory including instructions and pertinent educational material, and the adoption of measures that aim to protect victims of human trafficking. The committee will also lead an awareness-raising campaign for the benefit of employers who bring in foreign workers, on issues relating to human trafficking, and will also examine reports of national and international organisations on the banning of human trafficking, and co-operate with all official and non-official programmes that provide social support for victims affected physically or psychologically or people affected by human trafficking crimes. | D66: TRUE | E66: trafficking is referred to, and in 2nd sentence that this applies to trafficking of women. so for rest of text it is implied about women?
A67: 10.18356/cb17bdad-en | B67: 4916d8af58848267431dae37fcbf81d0 | C67: Poverty is not solely a lack of income, but rather is characterized by a vicious cycle of powerlessness, stigmatization,discrimination, exclusion and material deprivation,which all mutually reinforce each other' (ibid, para. The vicious cycle means that ‘the greater the inequality, the less the participation, the less the participation, the greater the inequality’ (ibid, para. Lack of participation is both a cause and consequence of poverty. Poverty is itself a ground of discrimination, but people living in poverty often experience other forms of discrimination based on,for example, gender, disability, ethnicity, and so on. | D67: FALSE
A68: 10.18356/8146c4ff-en | B68: 2cc009dd9dffb00802a9ff617a66100d | C68: According to official figures, there were 7,133 humanitarian entrants from Ethiopia in 1991-2015 (Government of Australia undated). Several thousand more Ethiopians have been sponsored under categories of spouse or family reunification visas, and the 2011 census records 8,452 Ethiopian-born people in the population. Like other humanitarian entrants who have been granted Permanent Protection Visas, Ethiopian refugees receive resettlement assistance through the Humanitarian Settlement Strategy (HSS), which was introduced in 2000 to provide a range of specialized services for humanitarian entrants. | D68: FALSE
A69: 10.18356/8146c4ff-en | B69: a983e648796057f81f6185b8e43331c3 | C69: However, the larger agenda of recognition of the care needs of migrants and valuation of social reproduction as a central axis of the analysis of migration would require the tough political challenge of transformative, universalized access to childcare services in both Australia and Lebanon that is delinked from parents'income levels,from productivist assumptions (as in Australia) and from parents’ migrant status (as in Lebanon). Power,production and social reproduction: Human in/security in the global political economy. In Transnational Families, Migration and the Circulation of Care: Understanding Mobility and Absence in Family Life, edited by Loretta Baldassar and Laura Merla. | D69: FALSE
A70: 10.18356/5085bf5a-en | B70: db5fb32cbad0993b82ca58f3da36a8bf | C70: Since the mid-1990s, the proportion of Governments that viewed adolescent fertility as a major concern has risen steadily in all major world regions, except in Northern America. Such programmes also include innovative educational approaches, including peer counselling for young people and orientation for parents, as well as strengthening education on reproductive and sexual health in non-formal settings, vocational training programmes and youth clubs (United Nations Population Fund, 2007). In 2013, 94 per cent of Governments in less developed regions had policies and programmes to reduce adolescent fertility, compared with 77 per cent of Governments in more developed regions. All Governments in Latin America and the Caribbean, Northern America and Oceania, and all but one Government in Africa, had policies and programmes to reduce adolescent fertility in 2013, whereas 23 per cent of Governments in Europe and 19 per cent in Asia did not have such policies or programmes. | D70: TRUE | E70: access to reproductive health, but only implied for gender equality?
A71: 10.14217/9e070c99-en | B71: 54206b6ebcc7a64bd3916a62d01a2f7d | C71: Judicial officers ensure the authoritative adjudication of controversies over the application of laws in specific situations, make law and public policy, especially when they exercise their power of judicial review to declare laws, government actions or omissions as unconstitutional, act as administrators for out-of-court settlements, and ensure enforcement of decisions. Judicial officers are barometers of a society’s conscience and must be seen to take restorative steps with impartiality and professionalism to address VAW by establishing and enforcing social and behavioural norms in line with the principles of the rule of law, as embodied in the law applicable and the practice before adjudicating institutions, and educating within and outside the court system. Failure to hold perpetrators accountable makes victims lose confidence in the institution of the judiciary and in the ability of the state to protect them from violence. | D71: FALSE
A72: 10.1787/9789264259157-5-en | B72: f4f48b94110197a2586938f4a9226d0d | C72: Even software engineers argue that programming errors are more likely to occur (and take longer to fix) after long hours, despite the tech industiy’s glorification of seemingly endless workdays (Robinson, 2005). Working-hour legislation and the legal right to request flexible working arrangements have historically helped protect workers. However, real change needs to occur in organisational culture and practice. | D72: FALSE
A73: 10.18356/137d57b2-en | B73: 259637989620bd5f167fc67894ccc7c9 | C73: Successful programmes, she says, provide timely, sufficient and scientific information, tailored to the needs of each age group. “ Evaluation studies have shown that sex education has an impact in delaying the age at the first sexual intercourse, in increasing the use of contraception methods and condoms, and in decreasing the levels of violence against young girls,” she says. “ The above implies the reduction of early and unwanted pregnancies, and the decrease of HIV/AIDS.” It looks at the decisions that individuals make—or would like to make, if they had the opportunity. | D73: TRUE
A74: 10.18356/56f09402-en | B74: 34e246391352524b78302363287313a1 | C74: In addition to sexuality education, this effort involves implementing change processes in health services and putting in place guidelines and care protocols for prevention and for the sexual and reproductive health of this population, with an approach that differs from the one used for the adult population. The countries of Latin America have made significant progress in this direction, through different instruments. To this end there is a specific list of medicines that must be provided free to the requestor, with a proper medical prescription. | D74: TRUE | E74: reproductive health, implied to benefit gender equality
A75: 10.18356/c45e5372-en | B75: 290cccf721087d8cfd64f720caf883b2 | C75: Companies with appropriate certification can register as diverse suppliers in a Supplier Diversity Registration Portal. Its global Supplier Inclusion and Diversity programme started in 2002 in the United States and now spans more than 16 countries and three regions. The focus is to integrate more women-owned businesses into supply chains. | D75: FALSE
A76: 10.14217/9781848591561-7-en | B76: 6c1f5aea016e803275bc8304b47a0147 | C76: Following a typical banking model may not be sufficient to cater to the financial and non-financial needs of unbanked women. Savings and credit products need to be fine-tuned to cater to the various lifecycle needs of women, such as children’s education, a daughter’s marriage or long-term saving for old age and medical emergencies. While savings and credit products remain the most important pillars for a women-owned/ managed SACO, other services such as financial literacy awareness programmes, insurance services or pension products can also be delivered through the same co-operative banking channel, if regulatory institutions permit such product offering. Although the grass-roots women owners and senior managers of the SACO need to be mentored and trained in the initial years, it is necessary to let them lead and choose the path for the organisation once they have matured in their leadership roles. As their sense of ownership increases, the women become more involved in runningthese enterprises. Grass-roots women are more aware of the key challenges that plague poor women clients. | D76: TRUE
A77: 10.18356/0a98da25-en | B77: c668a492db5a964d3b747b541f4eaa0e | C77: Again, the private sector would provide the bulk of credit, but it would be characterized by low interest rates leveraged with government loan guarantees. The real targeting approach might also be complemented by other policies, such as capital management techniques to deal with possible capital flight (discussed in more detail below). These loan guarantees substitute for collateral, leveraging access to credit and potentially bringing informal sector businesses into the formal sector. | D77: FALSE
A78: 10.1787/9789264027862-12-en | B78: 291fef8c6e48972332d63f5ab0ffdff2 | C78: Policies that increase and improve family contact are also essential as well as policies to prevent and respond to sexual harassment and rape of male and female prisoners. Female prisoners are likely to find strip searches particularly traumatic, and policies regarding strip searching should be separately and carefully formulated as it regards male and female prisoners. Other matters to be considered include: arrangements for privacy when people are required to remove their clothing, privacy in toilets and showers, use of private locks on cells, provision of hygiene items for women, and minimising indignity in the way urine and other samples are collected for drug testing. Poor prison conditions, lack of proper care and facilities, and the high level of stress that accompanies incarceration may place at risk both the health of a pregnant woman and that of her unborn child. Pregnant women should only be held in prison in the most extreme circumstances, such as when there is a concrete threat of violent crime. Special provisions should be made for ante and post-natal care and treatment, and babies should not be born in prison. | D78: TRUE
A79: 10.18356/caeceb38-en | B79: 0bd5c32157352edddc8533212da40462 | C79: Collaboration over domestic work (for girls) or maintaining the home (for boys) is a vehicle through which parents ascribe value to adolescents, model appropriate behaviour and include them in social reproduction in ways that are consistent with the aspirations of parenting captured in the WHO's five dimensions. Adolescents are proud of their participation in the running of the family and prioritise their "right to help in the home" as well as engage in family activities (Bray, 2012,Thorpe, 2005). For reasons we go on to explain, the pressures and motivations around work influence the notion of 'good parenting' in this region, differing from those commonly expected or assessed using standard measures. Poverty plus additional vulnerability due to HIV, including orphanhood and family dispersal, lies behind adolescent engagement in commercial sex work (Nyambedha, 2007), while transactional sex in the community is commonplace across poor neighbourhoods (Juma et al., 2013).Young people's reliance on these informal and often exploitative relationships increases where lone mothers, or small families, cannot meet material needs or connect adolescents to genuine alternative routes towards upward social mobility (Ngugi et al., | D79: FALSE | E79: not specifically about gender inequality, it treats vulnerability of youth
A80: 10.18356/c30f3d31-en | B80: 64889f77b8ac3876aa12ab72f6e3ea1f | C80: Coverage and enforcement of legal minimum wages are equally important. In developing countries many women in the informal economy are not legally covered by minimum wages. However, minimum wage legislation can still play a positive role:first there is some evidence that minimum wages in the formal sector improve wage levels in the informal sector too, known as a "lighthouse effect"” and second, the minimum wage sets a standard for pressure groups and trade unions to aim at when pressingfor improved conditions for informal workers in a subcontracting chain. | D80: FALSE
A81: 10.18356/2e1a4924-en | B81: 1bbfbe8960be36484e2a78c9ace6b313 | C81: Second, qr is less sensitive than ols to outliers in the dependent variable since it minimizes the weighted sum of absolute deviations. Moreover, when the error terms are non-normal, qr also gives a more efficient estimator than least squares. Lastly, qr has a linear programming representation that makes estimation easy. | D81: FALSE
A82: 10.1787/9789264265493-8-en | B82: 810c738ee49a6592c53e055950cddf2e | C82: Leaders and managers in organisations, who likely made time sacrifices to reach their current rank, often have difficulty accepting that work can be done in fewer hours. In some workplaces, “non-compliers” - those employees who opt to take flexible work hours and family leave - may actually be punished via denied promotions, reduced visibility to superiors, or exclusion from important projects. In-office “face time” remains an important metric of evaluating employees, even if it does not correspond with output (Elsbach and Cable, 2012). | D82: FALSE
A83: 10.18356/efc21c19-en | B83: 4c1b31c7bec2e84a3ca6802a5c46a8ca | C83: The maturity stages of e-Government for Gender Equality, which is an adaptation of the EGDI’s four-stage model, suggest key characteristics of the e-Government evolution regarding the usefulness of contents and services, technical sophistication and ease of use, degree of integration, etc. The framework was used for the analysis of national gender machinery websites from 11 countries presented in Chapter 3 of this report. They have links to ministries, departments and other branches of government. | D83: TRUE
A84: 10.18356/70095f8a-en | B84: 3557e13e2d3c31da34ba81b195b13145 | C84: Key elements to achieve this are: empowering client communities to become active parties in decision-making instead of considering them mere subjects of consultations, incorporating information feedback loops to avoid knowledge being reserved for a selected few, and ensuring accountability at a personal, individual level so that policies, strategic plans, budgets, performance management systems and individual accountability and responsibility are all aligned. Finally, students and their families, users, affected groups, communities and taxpayers must play an integral part in defining the parameters and systems of monitoring and evaluation. In South Africa, although there seems to be higher educational achievement, many observers question the quality of education received in state schools, asking whether the pass rate actually reflects students’ learning achievements. A recent court judgment finding the Government in contempt of court for ignoring earlier court orders to provide textbooks for schoolchildren appears to support this argument (Nkosi, 2012). | D84: FALSE
A85: 10.1787/empl/outlook-2016-8-en | B85: 7d9eea8c9d93b2273037530717ae79ec | C85: Providing employers with a code of good practice can help them to navigate the existing legislation, which can often be complex, and reduce non-compliance. Lowering the burden of proof for plaintiffs and shifting it to employers can be a step in the right direction, but should be accompanied by measures to help complainants gather the necessary evidence to initiate the case and sustain the costs of the trial (OECD, 2008, Chapter 3). In the early 2000s, most European countries lowered the burden of proof for plaintiffs, who are now only required to provide evidence of differential treatment without having to prove that it was indeed due to discrimination. | D85: FALSE
A86: 10.1787/9789264179370-6-en | B86: e1338993d5cbc255cb6640d43c46fee1 | C86: The survey was carried out in 2011 by Gallup Inc. as part of its Gallup World Poll, and covered over 150 000 people. The target population was the entire civilian population aged 15 and older. Interviews were conducted face-to-face in economies where telephone coverage represented less than 80% of the population and by telephone in countries with higher coverage. | D86: FALSE
A87: 10.18356/3a0cd6ba-en | B87: d6641ebe70f6fbd4981994ea47fc1e99 | C87: The most significant gaps were in: technology and technology transfer, access to finance, promotion of entrepreneurial education, cheaper, faster start-up and better regulations, and access to support services. These gaps reflected weaknesses in national legal frameworks and SME agencies, as well as in the elaboration and implementation of specific policy measures. Drawing on the World Economic Forum’s Global Competitiveness Index, this framework focuses on key entrepreneurial conditions (Box 2).'9 GEM is the basis for an annual national Adult Population Survey, along with National Expert Surveys. | D87: FALSE
A88: 10.1787/9789264265493-9-en | B88: 72bc2099057c5d0da7d38f1cee7f3e77 | C88: The concept of critical mass as applied to women’s political representation, and the UN targets that have flowed from it, have played an important role in supporting countries in the adoption of gender quotas in various spheres of the public and private sectors. According to data provided by the Inter-Parliamentary Union (IPU, 2015), the global average of women in national parliaments has nearly doubled in the past 20 years from 11.3% in 1995 to 22.1% in 2015 (a rise of 10.8 points). However, recent socio-political studies (Childs and Krook, 2008), as well as IPU data (IPU, 2015) confirm that the achievement of a critical mass is no longer seen as the sole target of efforts to bring about gender-equal participation in positions of leadership. | D88: TRUE
A89: 10.18356/5f92f30f-en | B89: 15ef01a67332f8f91841d700c1bafbf3 | C89: Emergency contraception is a method to prevent pregnancy within five days of unprotected intercourse, failure or misuse of a contraceptive (such as a forgotten pill), rape or coerced sex. It disrupts ovulation and reduces the likelihood of pregnancy by up to 90 per cent. It cannot prevent implantation of a fertilized egg, harm a developing embryo or end a pregnancy. Even in countries where emergency contraception is available, adolescents may be reluctant to obtain it from traditional health outlets, such as clinics, which may be staffed by judgmental providers. The initiative trained pharmacy staff and peer educators to provide accurate, up-to-date information on emergency contraception and other reproductive health services. | D89: TRUE
A90: 10.18356/07f2a46c-en | B90: e2c0b3bd85978d0798b4069b139c32fe | C90: While in Cambodia and Thailand the epidemic is slowing down, this is not yet the case with Indonesia and Viet Nam. More and more, however, new cases of infections are women who have acquired HIV from unsafe sex with their stable partners. In Thailand, this group accounted for more than 4 in 10 (or 43 per cent) of new infections in 2005 (UNAIDS and WHO, 2008, p. 16). | D90: TRUE | E90: about sex health, women are implied to suffer from men who cheat and get diseases
A91: 10.1787/9789264279322-7-en | B91: d0a96662f990a04e6eec02af04738769 | C91: A widow will receive one-eighth of her deceased husband’s assets or one-fourth if he has no children. For example, it is not uncommon for the family to pressure female heirs into relinquishing their full inheritance rights in favour of male relatives. Many women do not know that they can refuse to cede their rights or can appeal to the courts. | D91: TRUE
A92: 10.18356/604a5a2e-en | B92: 3170e6ccd61878ce07fbc1a0149eba25 | C92: Pregnant women have blood and body fluids that could expose health workers to the virus," Jallah says. I suffered a lot and was afraid I was going to die. The only thing I hoped for was for a miracle to happen," she says. One did: Comfort gave birth to two healthy baby girls with the assistance of a nurse aid who happened to pass by at the right time. | D92: TRUE | E92: is tthis about the targets, or just personal story? no reference to policy or measure to protect women
A93: 10.18356/caeceb38-en | B93: 7f640e6d16c269e5e8b2f71de1be4ae5 | C93: Evidence brought together in this review suggests that such attempts would also require working with existing power structures at local levels, and perhaps more broadly. It also requires substantial local choice, power, management and ultimately ownership of both the "trigger" (the actual stimulus for change) and the process (Panter-Brick et al., 2006).Thus far, parenting programmes are the chosen trigger through which the feasibility of offering parenting support is being tested in the region. However, there are many other models that exist around the world (Daly et al., | D93: FALSE
A94: 10.18356/fa8ae033-en | B94: b06f04f91816c525adcc20747a5dee7b | C94: Gender Equality Observatory of Latin America and the Caribbean: Annual Report 2012-A Look at Grants, Support and Burden for Women. Santiago, Chile: ECLAC. Accessed 14 September 2017, https://www.cepa!. The Impact of Conditional Cash Transfer Programs on the Time Allocation of Beneficiaries: The Case of’Oportunidades’ Program in Mexico." | D94: TRUE
A95: 10.1787/5js30tvj21hh-en | B95: 650df03322e86b6f089f407ba080b21a | C95: If all those reforms happened in a particularly rigid state - as it is likely to be the case, it is highly probable that employment will still suffer from this former rigidity. It will then introduce a negative bias in the evaluation. A positive value means a pro-worker state’s legislation (often tied to institutional rigidity) and a negative value means pro-employer legislation (more liberal). Conversely to labor reform’s index we do not have this index for every states. | D95: FALSE
A96: 10.6027/9789289338974-12-en | B96: bdc51a5af542282c68a617bd88facd08 | C96: Marshall defined social citizenship as "including social rights, these being the right to a modicum of economic welfare and security and right to live the life of a civilized being (quoted in Jenson, 2006:6)" (Poppel, M. 2014: 127). You can be provided for by your family, by charity organizations or by friends. Fulfilling the norms of a given community gives access to its resources. | D96: FALSE
A97: 10.1787/9789264265493-7-en | B97: 4b3e00eda804bc06de54bf2c37995ede | C97: Providing both parents with flexible work schedules and the possibility of short-term part-time work can also ease tensions between caregiving and work as children age (Chapter 4). Designed to be used around childbirth and when children are very young, employment-protected leave provides job security while allowing mothers to recuperate from childbirth and gives both parents time to care for young children. Paid leave gives families valuable income support at a time of increased stress on household budgets. | D97: TRUE
A98: 10.18356/0899dee9-en | B98: 5d71c3bd1a3b9b86517b23e200483317 | C98: Enrolment is increasing in all regions of the world but still varies widely between and within regions. In Central and Eastern Europe, and Latin America and the Caribbean, enrolment is high due to a historically strong public education sector. In Central Asia, the Arab States and sub-Saharan Africa, enrolment rates are very low, although there are some intra-regional variations. Even in regions with better coverage, the inclusion of marginalized populations is still a challenge. In the Arab States, private providers cover almost half of all enrolment and in Africa around 60 percent. In Kenya, for example, the government programmes target children aged 4 to 5 years, even though the policy framework identifies children within the 0 to 5 age range as intended beneficiaries. | D98: FALSE
A99: 10.1787/9789264224636-7-en | B99: 3f641e23050c65d90672a8290295bb67 | C99: The committee facilitates the integration of women’s needs in the government’s work plan as well as monitors and evaluates the mainstreaming of women’s needs in national policies. Furthermore, it also supports the creation of gender-sensitive budgets. The committee conducts studies and reviews the impact of policies on women and men. It is composed of parliamentarians from all political parties and includes a chair, two vice-chairs and eight members who study, evaluate and report on matters and bills relating to the status of women. | D99: TRUE
A100: 10.1787/9789264224636-4-en | B100: 1212f63edf3c0cc3d070ffe8800ea6d3 | C100: Equality under the law, equality of opportunity' and equality of (political) voice have not yet been fully achieved in many MENA countries. Despite a number of steps taken, women in the MENA region continue to have a rather low level of legal protection against gender-based discrimination. The domestic laws in MENA countries are not always consistent with the gender equality principles set by international law, including the CEDAW. | D100: TRUE
...

Sheet Steve
A1: DOI | B1: Text ID | C1: Text | D1: SDG 5 Label | E1: Comments (optional)
A2: 10.1787/7ddddd07-en | B2: db3642428aed20e21239f80b89d96d02 | C2: Recent studies of high growth start-ups in the United States find that only 10-15% of them are founded by women (Brush etal., Looking more specifically at start-up funding, several studies have shown that women are extremely under-represented among venture-backed entrepreneurs in the United States. Gompers and Wang (2017[i2]) find that just 10.7% of US venture-backed founders were women from 2010-2015. 2014(H)) estimate the number to be 15% using data from 2011-2013. | D2: TRUE
A3: 10.18356/9c9efe4c-en | B3: 32f44f50fcc3f9dfccaa4a22c0e4013f | C3: According to the United Nations Environment Programme (UNEP), which launched its Green Economy Initiative in 2008, a green economy is one that results in improved human well-being and social equity, while significantly reducing environmental risks and ecological scarcities, it is low-carbon, resource-efficient and socially inclusive (UNEP, 2011). This general definition integrates economic, social and environmental concerns in ways akin to sustainable development. Yet in practice, as the World Survey shows, there are many versions of green economy thinking. It is argued that the emerging green technology economy will be worth $4.2 trillion annually by 2020.’3 Other strands emphasize market-based approaches to environmental protection through financial valuation of natural capital, payments for ecosystem services and schemes for trading carbon and biodiversity credits and offsets. | D3: FALSE
A4: 10.14217/9781848591561-7-en | B4: 6c1f5aea016e803275bc8304b47a0147 | C4: Following a typical banking model may not be sufficient to cater to the financial and non-financial needs of unbanked women. Savings and credit products need to be fine-tuned to cater to the various lifecycle needs of women, such as children’s education, a daughter’s marriage or long-term saving for old age and medical emergencies. While savings and credit products remain the most important pillars for a women-owned/ managed SACO, other services such as financial literacy awareness programmes, insurance services or pension products can also be delivered through the same co-operative banking channel, if regulatory institutions permit such product offering. Although the grass-roots women owners and senior managers of the SACO need to be mentored and trained in the initial years, it is necessary to let them lead and choose the path for the organisation once they have matured in their leadership roles. As their sense of ownership increases, the women become more involved in runningthese enterprises. Grass-roots women are more aware of the key challenges that plague poor women clients. | D4: TRUE | E4: 5.a
A5: 10.18356/cb17bdad-en | B5: 4916d8af58848267431dae37fcbf81d0 | C5: Poverty is not solely a lack of income, but rather is characterized by a vicious cycle of powerlessness, stigmatization,discrimination, exclusion and material deprivation,which all mutually reinforce each other' (ibid, para. The vicious cycle means that ‘the greater the inequality, the less the participation, the less the participation, the greater the inequality’ (ibid, para. Lack of participation is both a cause and consequence of poverty. Poverty is itself a ground of discrimination, but people living in poverty often experience other forms of discrimination based on,for example, gender, disability, ethnicity, and so on. | D5: TRUE | E5: mentions discrimination based on (for example) gender, linking to 5.1
