Workbook

Sheet Info
B2: Hello 👋
B4: Welcome to the labeling exercise for SDG 12.
B5: The objective of this exercise is to label 100 texts in terms of their relevance to SDG 12.
B7: Your Labeling Sheet
B8: You have your own personal sheet for assigning the labels. You will find it by clicking on your name in the list at the bottom of this page.
B9: Each sheet has the same 100 texts, but the order in which they appear has been randomized.
B10: Later on, we will put everyone's labels side-by-side. This will help us identify texts with high and low alignment.
B11: At our next meeting, we will discuss the texts where we have disagreements and see if we can reach a consensus for the "true" label for every text.
B12: Please resist the temptation to look at other people's labels until you are done labeling. 🙂
B14: Explanation of Labels
B15: On your personal sheet, you will find the text in column B.
B16: Column C contains a drop-down for picking the appropriate label. The options are:
B18: TRUE | C18: This text is relevant to SDG 12
B19: FALSE | C19: This text is not relevant to SDG 12
B20: SKIP | C20: You can use this if you are not sure about the label
B22: If you want, you can put any comments in column D.
B24: Instructions for Labeling
B25: The text should be annotated as SDG 12 only if:
B27: 1. The text addresses SDG 12 or one of its targets
B28: See the official definitions of SDG 12 and its targets below ("SDG 12 Description & Targets").
B30: AND
B32: 2. The text addresses SDG 12 or its targets directly:
B33: - the text should be directly relevant to SDG 12 or to achieving SDG 12
B34: - if a text only has an indirect or implicit relevance, it should not be labeled SDG 12
B36: AND
B38: 3. The text addresses SDG 12 or its targets specifically:
B39: - the text should be specific to SDG 12 and its targets
... B48: SDG 12 Description & Targets
B49: SDG 12 | C49: Ensure sustainable consumption and production patterns
B50: Target 12.1 | C50: Implement the 10-year framework of programmes on sustainable consumption and production, all countries taking action, with developed countries taking the lead, taking into account the development and capabilities of developing countries
B51: Target 12.2 | C51: By 2030, achieve the sustainable management and efficient use of natural resources
B52: Target 12.3 | C52: By 2030, halve per capita global food waste at the retail and consumer levels and reduce food losses along production and supply chains, including post-harvest losses
B53: Target 12.4 | C53: By 2020, achieve the environmentally sound management of chemicals and all wastes throughout their life cycle, in accordance with agreed international frameworks, and significantly reduce their release to air, water and soil in order to minimize their adverse impacts on human health and the environment
B54: Target 12.5 | C54: By 2030, substantially reduce waste generation through prevention, reduction, recycling and reuse
B55: Target 12.6 | C55: Encourage companies, especially large and transnational companies, to adopt sustainable practices and to integrate sustainability information into their reporting cycle
B56: Target 12.7 | C56: Promote public procurement practices that are sustainable, in accordance with national policies and priorities
B57: Target 12.8 | C57: By 2030, ensure that people everywhere have the relevant information and awareness for sustainable development and lifestyles in harmony with nature
B58: Target 12.a | C58: Support developing countries to strengthen their scientific and technological capacity to move towards more sustainable patterns of consumption and production
B59: Target 12.b | C59: Develop and implement tools to monitor sustainable development impacts for sustainable tourism that creates jobs and promotes local culture and products
B60: Target 12.c | C60: Rationalize inefficient fossil-fuel subsidies that encourage wasteful consumption by removing market distortions, in accordance with national circumstances, including by restructuring taxation and phasing out those harmful subsidies, where they exist, to reflect their environmental impacts, taking fully into account the specific needs and conditions of developing countries and minimizing the possible adverse impacts on their development in a manner that protects the poor and the affected communities
B61: Click here to see all other SDGs and targets.
B63: Labeling Sheets
B64: Please click on your name to access your personal labeling sheet. Names are listed in alphabetical order.
B66: Name | C66: Progress (will update automatically)
B67: Finn | C67: =IFERROR(__xludf.DUMMYFUNCTION("SPARKLINE((100-COUNTIF(INDIRECT(B67&""!C:C""), ""TO DO""))/100+0.01,{""charttype"",""bar"";""max"",1.01;""min"",0; ""color1"", ""#4285f4""})"),"") | D67: =(100-COUNTIF(INDIRECT(B67&"!C:C"), "TO DO")) & " / 100" -> 100 / 100
B68: Gib | C68: =IFERROR(__xludf.DUMMYFUNCTION("SPARKLINE((100-COUNTIF(INDIRECT(B68&""!C:C""), ""TO DO""))/100+0.01,{""charttype"",""bar"";""max"",1.01;""min"",0; ""color1"", ""#4285f4""})"),"") | D68: =(100-COUNTIF(INDIRECT(B68&"!C:C"), "TO DO")) & " / 100" -> 37 / 100
B69: Jean-Baptiste | C69: =IFERROR(__xludf.DUMMYFUNCTION("SPARKLINE((100-COUNTIF(INDIRECT(B69&""!C:C""), ""TO DO""))/100+0.01,{""charttype"",""bar"";""max"",1.01;""min"",0; ""color1"", ""#4285f4""})"),"") | D69: =(100-COUNTIF(INDIRECT(B69&"!C:C"), "TO DO")) & " / 100" -> 0 / 100
B70: Meike | C70: =IFERROR(__xludf.DUMMYFUNCTION("SPARKLINE((100-COUNTIF(INDIRECT(B70&""!C:C""), ""TO DO""))/100+0.01,{""charttype"",""bar"";""max"",1.01;""min"",0; ""color1"", ""#4285f4""})"),"") | D70: =(100-COUNTIF(INDIRECT(B70&"!C:C"), "TO DO")) & " / 100" -> 71 / 100
B71: Steve | C71: =IFERROR(__xludf.DUMMYFUNCTION("SPARKLINE((100-COUNTIF(INDIRECT(B71&""!C:C""), ""TO DO""))/100+0.01,{""charttype"",""bar"";""max"",1.01;""min"",0; ""color1"", ""#4285f4""})"),"") | D71: =(100-COUNTIF(INDIRECT(B71&"!C:C"), "TO DO")) & " / 100" -> 97 / 100
B73: Thank you for being part of this exercise and thanks to OSDG for the dataset! ❤️
B75: Text Selection
B76: FYI: You do not need to read this section. We are just documenting how the texts for this exercise were selected.
B78: In total, 100 texts were selected from the OSDG dataset for SDG 12. The reason for selecting each text is documented in the "Source" sheet.
B80: Automatic Selection (50 texts)
B81: 50 texts were selected automatically
B82: - 25 texts that OSDG community labeled as "SDG 12"
B83: - 25 texts that OSDG community labeled as "not SDG 12"
B84: In the OSDG dataset, each text has an agreement score between 0 (equal positive and negative labels) to 1 (full consensus).
B85: Each set of the 25 texts above consist of:
B86: - 5 texts with agreement score > 0.8
B87: - 5 texts with agreement score > 0.6 and <= 0.8
... B99: - 22 texts (2 per target) that contain words relating to the SDG targets

Sheet Finn
A1: Text ID | B1: Text | C1: SDG 12 Label | D1: Comments (optional)
A2: a5de8ccef9a812d9b5c7cb312fee108f | B2: Part b) on measures taken before a product has become waste, that reduce the adverse impacts of the eventually generated waste on the environment and health also has some importance. Here though the focus should be on initiatives which reduce upstream environmental impacts caused by food waste rather than downstream impacts. This can be done for example through initiatives which reduce the share of products in food waste which cause a particularly high environmental impact during their production phase. Meat and dairy products are a prime example. The more edible food waste that is avoided in an economy, the less food production that is required to feed the population, with an accompanying reduction in environmental impacts caused during food production. | C2: TRUE
A3: fbb0aeba3247a1150aba110cad18dd81 | B3: There are several forms of capacity building where governments and the private sector can contribute: technical assistance, research for responsible business practices, development of training manuals and guidebooks, development of regional support hubs and the strengthening of the Global Compact local networks. They can also encourage and facilitate communications among key stakeholders for developing and implementing SRB initiatives. A strong dialogue about SRB must be encouraged amongst stakeholders, such as governments, corporations, financial institutions, NGOs and CSOs, for their capacity building. | C3: FALSE
A4: c2f4320ebfc7a98e97162886129820b2 | B4: As an industry, it often competes for prime real estate and juxtaposes visitors with different cultural practices and values to host communities, with consequent negative influences. Their economies and progress in development have been the subject of intense scrutiny, as a result of limitations in topographic character, vulnerability to natural disasters, climate changes and related impacts, threats to biological diversity, especially in coastal and marine areas, consumption of scarce natural resources, declining traditional productive sectors, poverty, and their reliance on the travel and tourism industry for economic performance. Large island nations comprising Papua New Guinea, Cuba, Hispaniola (Haiti and the Dominican Republic), Guinea Bissau and those located in Central/South America (Suriname, Guyana, Belize) make up the SIDS grouping with geographic areas in excess of 25,000 km2. There is significant variability in GDP per capita, as indicated in figure 8.3, with many of the more developed tourist economies such as Aruba, Singapore, US Virgin Islands (USVI) and the Bahamas, showing higher levels of prosperity. | C4: FALSE
A5: 989a430a480dfb2df0c37dd028d91db8 | B5: On another note, it is questionable whether there is even a need for a new scientific body for SAICM. As long as there are no legally binding obligations for states under SAICM, a scientific expert panel may not be needed. According to this view, the recommendations that SAICM provides could well be created without such a body. | C5: TRUE | D5: SAICM = Strategic Approach to International Chemicals Management
A6: 3174e5f65fdec525ecf8be88f1898329 | B6: These coverage percentages may be compared with the over 30 per cent of land covered by exploration licences in 2008 and the current aim of raising it again to 20 per cent. The Ministry estimates that about 30 per cent of the licensed area is being used, with the remainder idle because of low commodity prices, poor infrastructure or the risk of environmental impact. The number of licences for oil and gas and radioactive minerals is two orders of magnitude lower. Such permits are issued by soum and district governors based on the conclusions of NAMEM’s departments at local level. | C6: FALSE
A7: ad6accc9d24e23b3e302de529a942889 | B7: Policy instruments based on EPR can also be designed to drive eco-design at the beginning of the product lifecycle. However, if the instruments are focused only on improved recycling without driving initial eco-design, EPR may not generate the desired economic and environmental efficiencies (Tojo, N., 2004). Outcomes from economic incentives alone, however, may not be sufficient to generate environmentally or socially meaningful results, because actors generally stop making improvements once the economic incentive to do so ends, whether or not sufficient social or environmental progress has been made. Examples of economic mechanisms employed by OECD governments include also disincentives such as increased fees on waste disposal, and incentives such as government procurement policies and a potential reduction in the value added tax (VAT) and tax for environmentally friendly products (all promoted by the government of the Czech Republic, among others). | C7: TRUE | D7: EPR = Extended Producer Responsibility
A8: 84e48d25391c7a7cda69d5f9fb25ee36 | B8: Complementing the theoretical approach outlined in the previous chapter, this chapter focuses on the practical and strategic side of implementation, considering the multiple dimensions of successful implementation. Effective policies therefore often have to be developed in collaboration between line ministries. It is important to have effective mechanisms in place to support such collaboration. | C8: FALSE
A9: 703dd858d96d671944d27c5a06867a10 | B9: The indicator has an indirect relevance to food waste prevention since the more food waste that is avoided the lower should be the amount of food that is purchased for consumption to provide for the same intake of nutrients. It should be noted that the indicator is only relevant to reducing food waste at the end point of consum p-tion i.e. in households, restaurants canteens etc. However, the indicator can be affected by factors which are unrelated to waste prevention. These can include changes in food consumption behaviour-i.e. However, the indicator has been criticised in the past due to assumptions made in the calculations. Its acceptability as a food waste indicator might also be reduced as it has not been used in this context before. | C9: TRUE
A10: 3c57594c5de7b481d01d64593f4e51cb | B10: Design-for-disassembly was formulated to promote the easy recovery of parts and materials during the product disassembly process, while design-for-environment called for minimizing pollution and promoting resource conservation during product or system design. In product life-cycle considerations, extended producer responsibility (EPR) may be realized in collaboration with intelligent consumer behaviour. The European Union (EU) and WBCSD have shifted the leading concept of a resource-circulating society from sustainable production and consumption in the 1990s to sustainable consumption and production in a “consumer society”. | C10: TRUE
A11: 54b2538e906a8d503d9a71159d1d36ca | B11: It also prepares technical documentation related to chemical safety that can be downloaded from its website. The documentation includes government manuals, SDS and information on the GHS and other UN initiatives. There are ten ARLs - effectively insurance companies that cover workplace injuries and illnesses, each with a different focus. | C11: TRUE
A12: ee172df5f44bbedc59dd865962f75452 | B12: These inequalities were exacerbated by the structural adjustment programmes of the 1980s, the liberalisation of the economy in the 1990s, and the rapid growth of financial services after the liberalisation of financial markets in 1991. On the advice of the international financial institutions, governments have opted to offer targeted assistance to poor households rather than generalised subsidies on basic goods (e.g. staple foods) and services (e.g. water and electricity). Towards this end, the government has tracked the incidence and prevalence of poverty, and conducted poverty mapping to be able to identify the vulnerable households. | C12: FALSE
A13: 57946c8dba1a1a85b2078da67f09fea7 | B13: Refrain from seeking or accepting exemptions not contemplated in the statutory or regulatory framework related to human rights, environmental, health, safety, labour, taxation, financial incentives, or other issues. Support and uphold good corporate governance principles and develop and apply good corporate governance practices, including throughout enterprise groups. Develop and apply effective self-regulatory practices and management systems that foster a relationship of confidence and mutual trust between enterprises and the societies in which they operate. | C13: FALSE
A14: d679f7406fda45349991085239143a4e | B14: Good corporate governance makes for good business for all. Good corporate governance helps reduce the risks that smaller firms may face as well. At the other end of the spectrum, cases of corporate malfeasance in state-owned enterprises illustrate that regardless of size or ownership, good corporate governance is critical. | C14: FALSE
A15: 7a0048449e06bdb2c71ac177c5ced3c1 | B15: A delicate balance has to be maintained and this is where voluntary initiatives such as the Global Sustainable Tourism Council (GTSC) certification scheme play a critical role: there is no confrontation since the industry has voluntarily agreed to follow norms which will not only meet but frequently exceed the requirements of the law. The recommendations are based on a list of 12 principles for sustainable tourism development. Typically the Sustainable Tourism Criteria established by the j Global Sustainable Tourism Council extend to measurable indicators I and an appraisal and certification scheme which is rapaidly gaining j acceptance by the accommodation sector. Laws pertaining to land use, access, waster disposal, I pollution control, minimum wages and the like exist in almost all | countries: occasionally, these are relaxed for the tourism indistury in some developing countries in an effort to attract foreign tourists and i investments in the industry. | C15: TRUE | D15: sustainable consumption in the tourism sector
A16: 5a35e4bb86235463eff5866e9ee79739 | B16: More sustainable alternatives should be available and easily accessible, as well as suitable infrastructure to make it easier to practice sustainable behaviour. Even well-intended people cannot live sustainably if there are no sustainable products and alternatives available. These could include peer pressure, putting more taxes on unsustainable options and funding more sustainable practices. For example by providing input to policy design, in expressing what is meaningful to them and what they care about in real life and in society, in understanding the advantages and disadvantages of certain behavioural patterns. | C16: TRUE
A17: 13da70ac3a8ad54df495da6e6bf5bf08 | B17: Children and youth in cities”, in ISSC/UNESCO, World Social Science Report 2013: Changing Global Environments, OECD Publishing and Unesco Publishing. Each author is responsible for the facts contained in his/her article and the opinions expressed therein, which are not necessarily those of UNESCO, ISSC and do not commit either organisation. | C17: FALSE
A18: 43db05d16c51cafb451321dbca30d967 | B18: This huge increase alone speaks of amazing achievements in terms of ICT access and bridging the digital divide. This interpretation, however, would be very narrow as the factors leading to ICT access are bound to interact with the environments in which they operate. In this case, a critical analysis of mobile subscriptions by level of development should trigger alarm bells as the sharp increase in ICT access is inordinately skewed towards developing countries as illustrated in figure 9.2. | C18: FALSE
A19: c4fd5fb66459273c5dc10c4de4266f85 | B19: Its mandate is to foster cooperation between its 53 members and 9 associate members. It supports Governments of the region in consolidating regional positions and advocates regional approaches to meeting the region's unique socio-economic challenges in a globalizing world. The ESCAP head office is located in Bangkok, Thailand, with subregional offices in Almaty, Kazakhstan, Incheon, Republic of Korea, New Delhi, India, and Suva, Fiji. Please visit our website at <www.unescap.org> for further information. | C19: FALSE
A20: a941f19e7545ea877b4b9510f0be6a63 | B20: In 2014, the System was extended to include a dedicated web portal. This cadastre provides public access to the processes of issuing and reissuing of licences, licence revocation, transfer, pledge and surrender for the entire or a part of the licensed area, as well as to maintaining a register of licences. One of the main objectives of this tool is to prevent licences from overlapping other licences or protected areas. | C20: FALSE
A21: a218ee95081ac58f5a8c35f0fb15c302 | B21: The criteria for commitments are (1) advance one or more United Nations goal/issue, (2) include time-bound target(s) that can be measured for success, and (3) include an agreement to publicly disclose, on an annual basis, progress made to realize the commitment, throughout its duration. In all these areas issues related to innovation and collaboration were discussed. Available from http://www .unglobalcompact.org/docs/news_events/2012_CSF/Rio_CSF_Overview_Outcomes.pdf. | C21: TRUE | D21: link to global compact
A22: 37a02127ec1fb10fd005080ea6671271 | B22: Many countries have modernised their societies and economies enabling the greatest level of material wellbeing ever experienced. These changes were most prevalent in OECD countries and in urban centres in developing countries. The use of natural resources -biomass, fossil fuels, ores, minerals and water - has grown dramatically from less than 10 billion tonnes in 1950 to over 70 billion tonnes in 2010 (UNEP, 2011). This level of resource use was largely based on the assumption of limitless resources and overlooked the connections between resource use and environmental impacts. | C22: TRUE
A23: 9b3e0c684586646ce9eed8a9821e0b59 | B23: It takes stock of policy initiatives to reduce waste generation, encourage recycling and ensure safe disposal of municipal and hazardous waste. The chapter also highlights progress in integrating informal waste pickers into municipal waste management. It discusses the environmental and economic implications of specific measures, such as extended producer responsibility and waste collection charges. National, regional and local authorities have well-defined responsibilities in waste management. | C23: TRUE
A24: 039e770089eb0cbfb193a3ae3fadb893 | B24: International donors increased their involvement in waste management during the last few years and this resulted in improvements in management of obsolete pesticides and expired chemicals, but management of municipal and manufacturing waste is developing slowly and old practices remain. This development reduced generated amounts of waste and in some sectors also decreased the amount of waste previously accumulated. The development of modem waste management infrastructure is still in the initial phase. | C24: TRUE
A25: f83637f12da543fd9df8cb97ade0ef3c | B25: There are also examples at the national level. The Dutch Sustainable Growth Coalition, for example, unites the eighth largest big multinationals in shaping, sharing and stimulating sustainable business models. The changing role of business in society is also reflected in the increased participation by businesses in the discussions in various forums of the United Nations such as UN Global Compact, the development of the UN Sustainable Development Goals, as well as at international conferences such as the Rio+20 conference, which confirmed the importance of corporate sustainability reporting. When moving towards green growth requires a joint public private approach then there should also be more convergence between public and private measurement and reporting to follow the progress made to achieve the goals of green growth. | C25: TRUE | D25: corporate sustainability reporting
A26: d743d13d397544036f2266ae050c2dd8 | B26: According to the System of National Accounts, the principles underlying International Financial Reporting Standards are in most cases consistent with its principles, providing a comprehensive, consistent and flexible set of macroeconomic accounts.11 The System of National Accounts states that there could be areas of difference between the two systems, however, cooperation would be useful with a view to showing a reconciliation between the two positions. | C26: FALSE
A27: dfd51e36b47fe8a10fdd1d789001501e | B27: Commercial waste, street sweepings and ash were not included in this analysis. These show comparable results, differing only in metals fraction, because the EcoPark study also included waste separation and recycling data. Construction waste is normally found in MSW in a share lower than 1 or 2 per cent, therefore, it was excluded from data reported by Batbileg et al. | C27: FALSE
A28: 14ddb3509efb3be82081e905f697dba3 | B28: The strategy's objectives are to sensitize and raise awareness among school children of the negative impact that using plastic bags has on the environment, to encourage schoolchildren to replace plastic bags with other less-polluting alternatives and to teach them how to properly dispose of plastic bags after use. A key event was organized for Earth Day 2010 in all the schools, and a guide to waste management was widely distributed at the event. The children not only participated in collecting plastic bags at nature sites and clean-up projects, but were also asked to pass on what they learned to friends and neighbours. | C28: TRUE
A29: e63e24fa452209fc8000bc37d582ff2c | B29: Policy principles and objectives have been established, municipalities are required to prepare Integrated Solid Waste Management Plans and technical regulations and guidelines have been issued. However, the policies and action plans that were developed in parallel to address waste issues at national, regional and municipal levels do not provide comprehensive and consistent guidance. As a consequence, opportunities to increase the environmental effectiveness and economic efficiency of waste policies (by developing an efficient waste infrastructure network, for example) remain unexploited. Positive policy developments include the 2010 Policy on Sustainable Production and Consumption, efforts to promote cleaner production, an ambitious policy on extended producer responsibility (EPR) and attempts to establish green public purchasing. | C29: TRUE
A30: 1cd8c5958dad8616aabc4fa432b5ead7 | B30: For material flows and waste there are still unresolved conceptual issues and establishing indicators requires a lot of effort, if they are based on a national physical input-output table showing interdependencies among sectors in physical flows. We have employed sectoral footprints to show the natural resource use per expenditure in sectors. Footprint accounts deliver sectoral disaggregation by expenditure categories for products of major sectors. | C30: FALSE
A31: 4e9eb663a8c64d8e3cabfe7e4b87d7d0 | B31: In this sense, it was based on natural resources that were transformed into cement using energy-intensive processes. Again, the viability of this industry assumed cheap energy supplies. Demand for middle-class housing, hotels and physical infrastructure drove the rapid expansion of the construction sector in the 1950s and 1960s. The supply of housing and hotels was also dependent on imported building materials and construction equipment. | C31: FALSE
A32: 18900ef1e2742e858bbed6264b3a046c | B32: It is therefore evident that current patterns of consumption and production are environmentally unsustainable and socially inequitable. Economic growth, human development and wellbeing would need to be substantially decoupled from resource use and environmental impact (UNEP, 2011). Achieving gains in decoupling will not happen spontaneously, but will require well designed public policies that enable economic restructuring toward sustainable consumption and production and resource efficiency. | C32: TRUE
A33: 759b95e2698c40e89242d61169ef6b4d | B33: We have not been able to get a clear answer from the responsible person at Teijin, and in the basic scenario it was therefore chosen to use a conservative approach, assuming a low yield of the process. For climate change, the increased efficiency means that there is a net benefit instead of an impact. The same finding is seen for human toxicity, cancer effects. | C33: FALSE
A34: fa745ce3576ef1930376e33760b5d835 | B34: It can provide better recreational and cultural facilities but also create overcrowding, traffic congestion, litter, vandalism and crime (UNESCAP 2003). Started as the World Tourism Organisation in 1970 when its statutes were adopted, it became a working entity in 1975 with Headquarters in Madrid and joined the UN system in 2003, becoming known as UNWTO. Following the recommendations of the Johannesburg Plan of Implementation (JPOI) that “developed countries must take the lead" in accelerating the shift towards more sustainable consumption and production, each of the Marrakech Task Forces was chaired by a developed country. | C34: TRUE
A35: 08ee208db6cafa5ea057212223ece39c | B35: One legacy of that programme was the establishment of the Programme of Advancement through Health and Education (PATH), a conditional cash transfer programme that now constitutes the core of the social safety net. Advocacy has been initiated by scientists and their students in the Climate Studies Group of the Department of Physics at the University of the West Indies (UWI), individual scholars in the Faculty of Social Sciences, the Centre for Sustainable Development at UWI, as well as by various ENGOs. Some of the research and the outreach based on this work have been funded by the Caribbean Community Climate Change Centre (CCCCC) and the Environmental Foundation of Jamaica (EFJ). | C35: FALSE
A36: 78906f21b8873984506469c09306a3e3 | B36: The varied relief has resulted in several distinct climatic regimes, with the prevailing south-east trade winds depositing moisture in the form of rainfall over the central and highest part of the island. A significant feature of Mauritian climatology, however, is the occurrence of tropical cyclones during the summer months. Almost 300 endemic species have been identified, of which the most famous was the Dodo, a large flightless bird now extinct. Permanent human settlement started in the fifteenth century and, ever since, the environment has come under severe threat as its few precious resources (such as ebony) have been exploited indiscriminately. | C36: FALSE
A37: 2d147468df0200d5f90ff5d75bcadbe6 | B37: Against a backdrop of social issues, natural resource limits and waste problems, the question of how people live and consume - the lifestyles they pursue - becomes central to sustainability. The continuing increase in population in Asia, Africa and Latin America needs to sustain itself, in a fast growing economic environment, the level of material consumption per person also increases. For example, according to the African development Bank (AtDB 2011), there was a growth rate of 3.1% in the middle-class (defined as those consuming between 2-20 USD per day) in Africa, rising from 126 million people (27%) in 1980 to 350 million (34%) in 2010. | C37: TRUE
... A41: 6f4ffd29a57cb6598908ad274d7dfdaa | B41: Not to act is no longer an option. And I was encouraged by the sense of reality shown by the G8-leaders a few weeks ago, when they talked about a 50% cut in global emissions by 2050. It bodes well for the Conference of the Parties to be held in Copenhagen in 2009, where we will work hard to reach a global deal beyond Kyoto. | C41: FALSE
A42: 9fef02dedda6d91de6e74e1d7d3baab2 | B42: It identifies opportunities and challenges for implementing SPP and provides guidance for governments in developing and implementing successful SPP programs. It saw reiteration in the Johannesburg Plan of Implementation in 2002 and more recently, at the 19m Session of the Commission on Sustainable Development in 2011. It forms part of the 10 year Framework of Programmes suggested at the recently concluded Summit in Rio in June 2012. | C42: TRUE | D42: SPP = Sustainable Public Procurement
A43: ad30b568778b199cdbabb1a10d691944 | B43: It is often difficult to see from the statistics if this waste is included. Due to new EU - regulations this system no longer exists (withdrawn in 2003). The newest data is therefore from 2001 when it was collected 21,000 tons of food waste. The system of separate collection of food waste included commercial kitchens that generated more than 100 kg / week. Smaller kitchens and kitchens in cost sector were not covered by the collection scheme. | C43: TRUE
A44: 175fad9c8b9dcce44c7cc98b032d07e1 | B44: Importantly, the IUCN works through specialist commissions that provide the Union with information and know-how. All the members of the IUCN together agree on, for example, the work programme of the organization. This would mean conducting studies and developing new policy recommendations or instruments based on the latest scientific findings. In addition, the IUCN governance structure could be used as a partial model for the post-2020 chemicals and waste management regime: the ICCM acts as the general assembly of members, and a governing council could be established to work under the direction and monitoring of the ICCM. | C44: TRUE
A45: 0963ea06d1b60ca64affa94911f329d2 | B45: In response, international organizations such as the UN Development Programme (UNDP), the UN Environment Programme (UNEP) and the Organisation for Economic Co-operation and Development (OECD) have promoted the exchange of policy initiatives, action programmes and practices among member countries, industrial associations and academic institutions. For example, UNEP introduced cleaner production (CP), which promotes a shift from end-of-pipe treatment to pollution prevention, while the UNDP has appealed for environmentally sound technology in technology transfer programmes and assistance to developing countries. In the follow-up meeting after the Rio Declaration and Agenda 21, the International Human Dimensions Programme (IHDP) was established as a collaborative platform for social scientists and policy-oriented academics. | C45: TRUE
A46: e9c0953d695ff92ee3c092d3b13b280c | B46: This increase can be caused by both an actual increase in waste generation and by improved monitoring of collected waste amounts. The average MSW composition was derived from analyses in Minsk, Gomel, Mogilev, Bobruisk and Polotsk (table 6.2). Also, analysis of waste composition was performed in Minsk Oblast in 2013. | C46: TRUE
A47: 0bafd5e13fe32c31b5b4d9f7536c941d | B47: Some definition of technology is necessary- it should be 100% recyclable under readily available current technology. Cotton/polyester mixes, for example, can be more technically durable than pure cotton. This suggests that the 100% recyclable stamp would be more applicable to fast fashion and not recommended for textiles where lifetime is generally limited by technical strength rather than change in style or change in fit e.g. bed-linen. This would rule out linking to some of the information proposed in the provision - unless the regulation was to be changed. | C47: TRUE
A48: 86236555aba7f7bec5e1aed8f189e77a | B48: At local level, the main partners have been the collaboration of local food producers, R0rosmat as well as the R0ros Museum and World Heritage and local businesses. Destination Roros is currently (spring 2016) undergoing the recertification process. Additionally, the goal is to encourage even more companies to apply for an environmental certificate and to train more people. | C48: TRUE
A49: 17a9f0d1e3733dac32f98dd1b6ee7ae0 | B49: Owing to success of the first phase, UNU and Shimadzu agreed to continue the project, establishing the second phase in 1999. In continuation of the previous project, the same research group in each country was kept as partner and national implementation unit. The Philippines joined the project at the beginning of the second phase. The three components were closely linked together and implemented through collaboration of the UNU network on coastal issues. | C49: FALSE
A50: 861a903bf623d4873b2e27e84775ea64 | B50: In moving towards green growth such frameworks should where applicable be aligned. However, in recent years the term "accounting" has also been applied to non-financial aspects. Corporate accounting can be defined as the identification, collection, estimation, analysis, internal and external reporting, of economic, social and environmental effects and impacts to provide accountability to stakeholders on strategy, actions and performance and to support internal and external decision-making. | C50: TRUE
A51: 53a72b1c4248dc4bbce2a197b5573d72 | B51: The transformation process is necessarily long term. With governments elected for five years, there is an inherent tendency to postpone addressing long-term development issues that is all the more difficult in the context of a highly partisan political tradition that resists consensus over development strategies. Progress in mainstreaming the environmental dimension of sustainable development strategies has been slow. Such policies address cross-cutting issues, and in the Westminster system of sectoral portfolio ministerial responsibilities, such issues tend to fall between ministerial responsibilities. | C51: FALSE
A52: 0342980e48fbffd359a20628d9450485 | B52: Mauritius covers a total land area of 720 square miles, and is almost entirely of volcanic origin, except for stretches of beaches, coral reefs and small patches of alluvium at the mouths of rivers. Pear-shaped, mountainous with its highest peak standing at 2,711 feet above sea level, Mauritius emerged from the ocean floor some 5 million years ago. Volcanic activity over thousands of years has given rise to varied types of soil. | C52: FALSE
A53: f0d7085f21c4e88d7448e29c10b34cee | B53: This trend has been boosted by market liberalization and augmented by convergence, new technologies and resultant innovations such as mobile phones which continue to be the most rapidly adopted technology in history. While sector growth has been experienced worldwide, the impact has been exponential in developing countries. Today the mobile phone is the most popular and widespread personal communication technology on the planet, with an estimated average subscription world rate of 87 per 100 inhabitants in 20111. | C53: FALSE
A54: 3b1add4085af6afe2ca52a55fc3fb5a9 | B54: In addition, the Major Groups and other Stakeholders (MGOS)21 group seeks to represent all sectors of society in international environmental and developmental policy-making. It appears that MGOS do not have an established position within SAICM, the representation of stakeholders is sectoral and the involvement of all major groups is not automatic - for example, organizations focused on promoting the rights of women, children, and indigenous peoples do not routinely participate in SAICM meetings. In 2015, the ICCM4, in its Resolution i/IV (para 5), called for the deepening and broadening of UN system-wide engagement through the work of IOMC and EMG. Furthermore, the WHO has been working with the SAICM Secretariat to provide a service to facilitate access to the Trust Fund, to establish an informal network of health-sector focal points for sharing experience, and to collect and share information on the capacity-building needs of the health sector (WHO 2010). | C54: FALSE
... A59: 062372c7882af8f7bb84943024eb6a2c | B59: Its mandate is two-fold: to promote energy security amongst its member countries through collective response to physical disruptions in oil supply and to advise member countries on sound energy policy. This paper reflects the views of the IEA Secretariat and may not necessarily reflect the views of the individual IEA member countries. The study also draws on contributions of Franziska Mueller-Langer, Jens Giersdorf and Anastasios Perimenis of the German Biomass Research Centre (DBFZ), who provided parts of the sustainability chapter and four country profiles commissioned by the Deutsche Gesellschaft fiir Technische Zusammenarbeit (GTZ). | C59: FALSE
A60: 1365feccc61adc4814c64ff7d9303893 | B60: Further extending the green purchasing requirements to local governments would enhance the effectiveness of the policy, in particular since a large share of public expenditure is invested locally. In expanding its green purchasing policy, the government should make sure that it targets goods and services with the highest potential environmental returns. This outcome was achieved with minor increases in public expenditure. Since the introduction of the green public procurement policy, the market shares of eco-friendly products widely used in the public administration have substantially increased (Figure 9). According to MOE’s estimates, the national government’s green purchasing policy resulted in a reduction of C02 emissions by 89 500 tonnes in 2006, which is equivalent to the amount of C02 emitted by a town of 42 000 inhabitants. The financial implications of Japan’s green public procurement policy and the overall costs to the Japanese economy of achieving such emission reductions should be assessed and compared with the costs of alternative policy measures. | C60: TRUE | D60: public procurement
A61: 89ca4fa4c89388e266f44db315cd78d8 | B61: The statement was made in 1972, long before the world became conscious of acceleration in anthropogenic GHG emissions. Nevertheless, Mrs Gandhi’s statement was one of the earliest to create a direct link between environmental concerns and poverty alleviation. Neither can the poor be held responsible for the major part of the GHG emissions. | C61: FALSE
A62: e4ff2d35f08d2d1acc0d03aa9df6f4b9 | B62: These challenges include issues of ownership, economic leakage (from the local economy and through imports), local employment, benefit distribution, social and environmental impacts and dependency. These problems can only be effectively addressed at the destination level with the active participation of the local communities. It summarises by stating that "The effective development, execution and management of a successful pro-poor tourism strategy reaches far beyond local communities”. | C62: FALSE
A63: 4305276298bfe07e216b55b3e150ff68 | B63: For the last one a comply or explain principle is in use. To enable readers to find the particular sustainability information in the report, GRI is using a mandatory content index table that informs the reader on what page the disclosures or the indicator can be found. The Guidelines of the IIRC are currently in development and will be released as draft in April 2013 and finalized by the end of 2013. | C63: TRUE
A64: 8b7a84a06c90ba7a095b0307ada9a5f2 | B64: Additional documentation is required in an application for mineral water use. The issuance of the permit itself, and the signing of a contract with the water user, is done by the State-owned enterprise, Mongol Us ("Mongolian Water"). In the case of the utilization of water for strategically important minerals, the duration of the water use permit is the same as for the exploitation licence. | C64: FALSE
A65: a287d825bd346605da1b8e5017d13524 | B65: The initiative engaging the manufacturer, Grameen Bank, National Building Research Organization and vulnerable families encourages the use of local sustainable building materials, quality durable construction and livelihood considerations such as including shop fronts in the houses. The initiative required a high degree of informal collaborative learning and training. Learning occurs at both the level of the community, as well as within the company, where lessons of Mexican success are explored to be translated across other regions. | C65: TRUE
A66: 6f18255d6435f943053c754e2ff406e0 | B66: While this may or may not lead to a net increase in employment, it will change the skill profile of the workforce. Governments should therefore assess new job skill requirements and adjust education and training programmes accordingly. This could help to co-ordinate efforts by engaging key stakeholders, to monitor progress, and generally to provide the political impetus needed to achieve ambitious policy objectives. | C66: FALSE
A67: 1b8a501a7bbb0802fa4a05da3a8cd65a | B67: At the same time internal transparency through environmental management accounting started to increase with a business rationale to improve efficiency and reduce costs, in relation to using natural resources, reducing emissions to air, water and soil, as well as in reducing waste. More recently companies increasingly see the relevance of sustainability for their long term business continuity and identify sustainability challenges as a business growth driver. They even transform their business to address such business opportunities. The company, DSM, active in health, nutrition and materials, for example, is not only changing from a chemical company to bio-based solutions, but also focuses its business activities much more on nutrition, as this will be a major global challenge. | C67: TRUE
A68: eeccafbe1d2736fec1608bfebb02b882 | B68: Between 2000 and 2008, Japan’s economy grew by about 1.3% annually, a rate below the OECD average (about 2% per year). As a result of the global economic slowdown of 2008, the Japanese economy contracted sharply, and w'as dragged into the deepest recession since the Second World War (Section 2). Similarly, the OECD Europe aggregate does not include Estonia and Slovenia. In 2009, Japan’s GDP per capita in purchasing power parity was USD 29 800 and the OECD average was USD 30 500. | C68: FALSE
A69: 12128c9d99e298a5a86fec6053a25347 | B69: There is high uncertainty of data, because of the lack of data verification procedures. Additionally, as well as receiving user fees, collection companies receive a subsidy from the municipality, which is based on the amount of w aste collected and distance to the disposal site. Disposal site operators do not collect a gate fee but receive a subsidy based on the amount of waste received. | C69: FALSE
A70: 4d5ac9213ea93621546badea52220286 | B70: The project investigates the possibility for using policy actions to support and expand the market for waste plastics in the Nordic region. This has the objective of increasing the recycling of plastics and minimising the down-cycling and incineration of plastic waste. Separately collecting and recycling this plastic waste would have significant economic and environmental benefits. For example, recovering and recycling half of the plastic waste generated in the Nordic countries corresponds roughly to a reduction of greenhouse gas emissions equivalent to the total emissions from cars in the Nordic capitals. | C70: TRUE
A71: 201aa211051c6d69b54de666dbd44994 | B71: The industry added USD 44 billion to the US GDP in 2015 and paid USD 10 billion in taxes (RFA, 2016). One strategy to ultimately reach the Renewable Fuels Standard (RFS) targets is to make stepwise improvements in the existing biorefinery concepts. These stepwise improvements must include a regional strategy that builds in enough flexibility to use the “cheapest sources of renewable carbon” within a given region. Such flexibility implies, for example, using grain sorghum, switchgrass, or miscanthus in the US Midwest, sweet sorghum or cane sugar in the US South, guayule bagasse in the US Southwest, almond hull sugars in California and even citrus peel waste in Florida. | C71: FALSE
A72: e459110a0e5288867d180b786d5e620a | B72: Topics that have both an impact on the organization as well as on its stakeholders are the most material and therefore are discussed in more depth in the sustainability report. Once these topics are selected the company can identify the related indicators and use the GRI protocols to measure the data. Currently the GRI has three application levels, differing from reporting on 10 indicators with particular context information (Level C) to reporting on all material indicators (Level A). | C72: FALSE
... A101: 97c185a074f856c7e9768753e9b7046d | B101: Food losses are highest in North America and Oceania, reaching close to 300 kg per person. The focus would need to be on addressing the financial, managerial and technical limitations in harvesting techniques, as well as ensuring adequate storage and cooling facilities in often challenging climatic conditions. Quantifying postharvest losses in Sub-Saharan Africa with a focus on cereals and pulses Presentation at the Bellagio Workshop on Postharvest Management, 12-14 September 2017. International Food Policy Research Institute (IFPRI) has developed a methodology to improve the measurement of food losses across the value chain, as well as to factor in deterioration in quality that result in economic losses. | C101: TRUE

Sheet Gib
A1: Text ID | B1: Text | C1: SDG 12 Label | D1: Comments (optional)
A2: e4ff2d35f08d2d1acc0d03aa9df6f4b9 | B2: These challenges include issues of ownership, economic leakage (from the local economy and through imports), local employment, benefit distribution, social and environmental impacts and dependency. These problems can only be effectively addressed at the destination level with the active participation of the local communities. It summarises by stating that "The effective development, execution and management of a successful pro-poor tourism strategy reaches far beyond local communities”. | C2: TRUE | D2: Can be false. The passage states facts on challenges of sustainable tourism but does not directly addressing the goal.
A3: 0686b17a9aeedb103f46b38f9d94eeb8 | B3: Thus the government's role is dual. On the one hand, it must act as a facilitator by providing the necessary infrastructure for tourists, promoting attractions and encouraging tourist arrivals. On the other hand, government’s role is to enforce laws of the land and these may, in some cases, be in conflict with its role as a promoter of tourism. | C3: FALSE
A4: 88220c7fe94cff6b5a90c20459c70000 | B4: In recent years, significant improvements in the assessment methodologies have been made in an effort mostly co-ordinated by the UNEP/ SETAC initiative (de Haes, 2002, UNEP, 2003, Jolliet et al., The EU Joint Research Centre has also made an important input in the determination of effective practice in impact assessment, which has resulted in the adoption of 14 default impact categories for the EU footprinting initiative (Product Environmental Footprint (PEF)/ Organisational Environmental Footprint (OEF), European Commission, 2013a, European Commission, 2013b). | C4: TRUE
A5: 642f69433572aed4342a2026f0513b5b | B5: If an EIA is carried out, but improperly and leading to environmental damage, the licensed EIA entity must pay compensation. There is also a mismatch between the economic value for animals, their conservation status and their market value (chapter 3). The 2012 Law on Hunting, for example, foresees a reward of 15 per cent of fines imposed to be given to the citizen identifying the person responsible for the violation. | C5: FALSE
A6: a5de8ccef9a812d9b5c7cb312fee108f | B6: Part b) on measures taken before a product has become waste, that reduce the adverse impacts of the eventually generated waste on the environment and health also has some importance. Here though the focus should be on initiatives which reduce upstream environmental impacts caused by food waste rather than downstream impacts. This can be done for example through initiatives which reduce the share of products in food waste which cause a particularly high environmental impact during their production phase. Meat and dairy products are a prime example. The more edible food waste that is avoided in an economy, the less food production that is required to feed the population, with an accompanying reduction in environmental impacts caused during food production. | C6: TRUE
A7: b877f11b0df84d337b544b552a684afd | B7: In their comprehensive analysis of revenue management of Scottish tourism attractions, Leask et al. ( Including stakeholders is therefore often perceived from governmental perspectives as an obstacle to efficient planning. Conflict resolution, meditation and the building of a consensus about shared platforms should nevertheless be seen an integral component of sustainable tourism development and planning (Hall, 2008, McCool, 2009). In other words, tourism should be considered in the context of other systems that interact with tourism (Ritchie and Crouch, 2003). | C7: TRUE
A8: 0963ea06d1b60ca64affa94911f329d2 | B8: In response, international organizations such as the UN Development Programme (UNDP), the UN Environment Programme (UNEP) and the Organisation for Economic Co-operation and Development (OECD) have promoted the exchange of policy initiatives, action programmes and practices among member countries, industrial associations and academic institutions. For example, UNEP introduced cleaner production (CP), which promotes a shift from end-of-pipe treatment to pollution prevention, while the UNDP has appealed for environmentally sound technology in technology transfer programmes and assistance to developing countries. In the follow-up meeting after the Rio Declaration and Agenda 21, the International Human Dimensions Programme (IHDP) was established as a collaborative platform for social scientists and policy-oriented academics. | C8: TRUE
A9: fa745ce3576ef1930376e33760b5d835 | B9: It can provide better recreational and cultural facilities but also create overcrowding, traffic congestion, litter, vandalism and crime (UNESCAP 2003). Started as the World Tourism Organisation in 1970 when its statutes were adopted, it became a working entity in 1975 with Headquarters in Madrid and joined the UN system in 2003, becoming known as UNWTO. Following the recommendations of the Johannesburg Plan of Implementation (JPOI) that “developed countries must take the lead" in accelerating the shift towards more sustainable consumption and production, each of the Marrakech Task Forces was chaired by a developed country. | C9: TRUE
A10: 759b95e2698c40e89242d61169ef6b4d | B10: We have not been able to get a clear answer from the responsible person at Teijin, and in the basic scenario it was therefore chosen to use a conservative approach, assuming a low yield of the process. For climate change, the increased efficiency means that there is a net benefit instead of an impact. The same finding is seen for human toxicity, cancer effects. | C10: FALSE
A11: 34b4f1f3f5ea4fe7b006371c5ed60765 | B11: During the latter two decades, protected areas have gradually become more closely connected to their economic and social environments, with an emphasisto integrate national parksto wider regional and local development processes (see e.g. Puhakka and Saarinen (2013). In peripheries, closer connections between the tourism industry and national parks are used as tools. While the original biocentric conservation policy used to be characterized by top-down governance, stakeholders of the local communities and the tourism industry are today increasingly involved in adaptive management strategies. During the last three decades, international tourist arrivals to Iceland have generally increased, including by 25% over the past six years. The number of international visitors to Iceland was approximately 2.3 million in 2017, which is almost seven times more than the entire Icelandic population. Tourism is now one of the main pillars of the economy and represents the country's largest export sector. | C11: FALSE | D11: Fact stating about tourism
A12: 83a90deca523f0cfc53e97ed2921a6a6 | B12: The importance of considering products and services in terms of their complete lifecycle is introduced and explained. This remains the single most important of the Millennium Development Goals. Economic growth is thus of key importance to developing countries and many of their policymakers believe that developed countries, having already accomplished a high level of satisfaction of their needs, now wish to suggest frugality and restraint on consumption in the developing world. China, for instance, is now considered the "factory to the world”. | C12: FALSE
A13: 293bd72b65dfbb4252d5df5ee43dee5a | B13: Indicators can go beyond simple data and illustrate trends or cause-and-effect relationships between different phenomena. Indicators are useful for describing baseline and current conditions (e.g. the amount or magnitude of something) and the performance of a system. They can provide the common language for describing a particular system that is needed for effective and clear communication among interested parties (McCool and Stankey, 2004). | C13: FALSE
A14: 861a903bf623d4873b2e27e84775ea64 | B14: In moving towards green growth such frameworks should where applicable be aligned. However, in recent years the term "accounting" has also been applied to non-financial aspects. Corporate accounting can be defined as the identification, collection, estimation, analysis, internal and external reporting, of economic, social and environmental effects and impacts to provide accountability to stakeholders on strategy, actions and performance and to support internal and external decision-making. | C14: TRUE
A15: 2d147468df0200d5f90ff5d75bcadbe6 | B15: Against a backdrop of social issues, natural resource limits and waste problems, the question of how people live and consume - the lifestyles they pursue - becomes central to sustainability. The continuing increase in population in Asia, Africa and Latin America needs to sustain itself, in a fast growing economic environment, the level of material consumption per person also increases. For example, according to the African development Bank (AtDB 2011), there was a growth rate of 3.1% in the middle-class (defined as those consuming between 2-20 USD per day) in Africa, rising from 126 million people (27%) in 1980 to 350 million (34%) in 2010. | C15: TRUE
A16: cd39a832a230705ef131f4d8b858f65f | B16: Once among the least developed Western economies, with high levels of emigration, since 2003 Ireland has enjoyed the third highest per capita GDP in OECD Europe (Figure 6.1).1 The growing economy attracted an inflow of foreign workers, the unemployment rate was 4.7% in 2007, below the OECD average. In the first half of the 2000s, large public sector deficits were transformed into substantial surpluses and the ratio of national debt to GNP was greatly reduced, while the tax-to-GDP ratio remained low (31.9% of GDP in 2006, compared with an OECD Europe average of 38%). The combination of a low corporate tax (12.5%), state grants and access to the European single market boosted foreign direct investment. | C16: FALSE
A17: c8dbfdb5972aba5f9f4da67a683fee62 | B17: The framework also functions as a bridging mechanism between the narrowly construed MEAs pertaining to chemicals and waste, which include the Stockholm, Rotterdam, Basel, and Minamata Conventions. The Dubai Declaration, which expresses high-level political support forthe framework. The Overarching Policy Strategy (OPS), which contains the five key thematic objectives of SAICM: (1) risk reduction, (2) knowledge and information, (3) governance, (4) capacity-building and technical cooperation, and (5) illegal international traffic in chemicals. The OPS also lays down the scope, needs, underlying principles, and approaches of SAICM and elaborates on implementation and progress review mechanisms. The Global Plan of Action, which is an evolving and practical toolkit for implementation that currently lists more than 270 activities that can be undertaken by diverse stakeholders to operationalize SAICM. | C17: TRUE
A18: ce798611bb26ebcb1fd0887f02a72387 | B18: Some of the chemical applications to control weeds and pests on the plantations have run off from rain into the rivers and transferred to the inshore, especially the main harbour in Kingston. In other cases, chemicals have soaked through the soil into underground aquifers. This is particularly true of the acidic waste from the processing of bauxite ore, which is deposited in lakes of red mud. | C18: TRUE | D18: Information about the situation
A19: 1f90c5a8981fc4c095f70aea892ff94e | B19: Based on 2011 data, generation is above average in the Capital area at 460 kg/cap/y, and in the coastal region influenced by tourism at 480 kg/cap/y, although excluding the impact of tourists the average is 420 kg/cap/y. The remaining inland region shows under-average waste generation, at only 223 kg/cap/y. The reason for such a high variation in per capita waste generation at county level could be because the impact of the non-permanent tourist population is not considered in the calculation of this indicator. | C19: TRUE
A20: 5a35e4bb86235463eff5866e9ee79739 | B20: More sustainable alternatives should be available and easily accessible, as well as suitable infrastructure to make it easier to practice sustainable behaviour. Even well-intended people cannot live sustainably if there are no sustainable products and alternatives available. These could include peer pressure, putting more taxes on unsustainable options and funding more sustainable practices. For example by providing input to policy design, in expressing what is meaningful to them and what they care about in real life and in society, in understanding the advantages and disadvantages of certain behavioural patterns. | C20: TO DO
A21: 9fef02dedda6d91de6e74e1d7d3baab2 | B21: It identifies opportunities and challenges for implementing SPP and provides guidance for governments in developing and implementing successful SPP programs. It saw reiteration in the Johannesburg Plan of Implementation in 2002 and more recently, at the 19m Session of the Commission on Sustainable Development in 2011. It forms part of the 10 year Framework of Programmes suggested at the recently concluded Summit in Rio in June 2012. | C21: TO DO
A22: 37a02127ec1fb10fd005080ea6671271 | B22: Many countries have modernised their societies and economies enabling the greatest level of material wellbeing ever experienced. These changes were most prevalent in OECD countries and in urban centres in developing countries. The use of natural resources -biomass, fossil fuels, ores, minerals and water - has grown dramatically from less than 10 billion tonnes in 1950 to over 70 billion tonnes in 2010 (UNEP, 2011). This level of resource use was largely based on the assumption of limitless resources and overlooked the connections between resource use and environmental impacts. | C22: TO DO
A23: 1365feccc61adc4814c64ff7d9303893 | B23: Further extending the green purchasing requirements to local governments would enhance the effectiveness of the policy, in particular since a large share of public expenditure is invested locally. In expanding its green purchasing policy, the government should make sure that it targets goods and services with the highest potential environmental returns. This outcome was achieved with minor increases in public expenditure. Since the introduction of the green public procurement policy, the market shares of eco-friendly products widely used in the public administration have substantially increased (Figure 9). According to MOE’s estimates, the national government’s green purchasing policy resulted in a reduction of C02 emissions by 89 500 tonnes in 2006, which is equivalent to the amount of C02 emitted by a town of 42 000 inhabitants. The financial implications of Japan’s green public procurement policy and the overall costs to the Japanese economy of achieving such emission reductions should be assessed and compared with the costs of alternative policy measures. | C23: TO DO
A24: 1cd8c5958dad8616aabc4fa432b5ead7 | B24: For material flows and waste there are still unresolved conceptual issues and establishing indicators requires a lot of effort, if they are based on a national physical input-output table showing interdependencies among sectors in physical flows. We have employed sectoral footprints to show the natural resource use per expenditure in sectors. Footprint accounts deliver sectoral disaggregation by expenditure categories for products of major sectors. | C24: TO DO
A25: 549df2a4d76c942d8369308429752184 | B25: This term, however, is often used as a synonym for material productivity. Productivity measurement and analysis of natural resource and material flows complement the traditional indicators of capital, land and labour productivity. Used in parallel, these three types of productivity indicators afford a much deeper understanding of total factor productivity. | C25: TO DO
A26: e459110a0e5288867d180b786d5e620a | B26: Topics that have both an impact on the organization as well as on its stakeholders are the most material and therefore are discussed in more depth in the sustainability report. Once these topics are selected the company can identify the related indicators and use the GRI protocols to measure the data. Currently the GRI has three application levels, differing from reporting on 10 indicators with particular context information (Level C) to reporting on all material indicators (Level A). | C26: TO DO
A27: 989a430a480dfb2df0c37dd028d91db8 | B27: On another note, it is questionable whether there is even a need for a new scientific body for SAICM. As long as there are no legally binding obligations for states under SAICM, a scientific expert panel may not be needed. According to this view, the recommendations that SAICM provides could well be created without such a body. | C27: TO DO
A28: ad6accc9d24e23b3e302de529a942889 | B28: Policy instruments based on EPR can also be designed to drive eco-design at the beginning of the product lifecycle. However, if the instruments are focused only on improved recycling without driving initial eco-design, EPR may not generate the desired economic and environmental efficiencies (Tojo, N., 2004). Outcomes from economic incentives alone, however, may not be sufficient to generate environmentally or socially meaningful results, because actors generally stop making improvements once the economic incentive to do so ends, whether or not sufficient social or environmental progress has been made. Examples of economic mechanisms employed by OECD governments include also disincentives such as increased fees on waste disposal, and incentives such as government procurement policies and a potential reduction in the value added tax (VAT) and tax for environmentally friendly products (all promoted by the government of the Czech Republic, among others). | C28: TO DO
A29: ea3c7154e3fd84c3e502a9219b2e3cc8 | B29: However, it does not include information on when licences are applied for (while providing the date of issue), nor on the reasons for and conditions on the numerous licence transfers. There is also a problem at present with accessing the area covered by petroleum licences in the Ministry of Mining and Heavy Industry database. In addition, the Ministry of Environment and Tourism is not providing the most recent data on receipts to its special fund for mining rehabilitation, arguing that this is not permitted by banking legislation. Further, though licence holders provide information to the EITI, they are often unwilling to present the same information on their own websites, thus reducing transparency. | C29: TO DO
A30: 039e770089eb0cbfb193a3ae3fadb893 | B30: International donors increased their involvement in waste management during the last few years and this resulted in improvements in management of obsolete pesticides and expired chemicals, but management of municipal and manufacturing waste is developing slowly and old practices remain. This development reduced generated amounts of waste and in some sectors also decreased the amount of waste previously accumulated. The development of modem waste management infrastructure is still in the initial phase. | C30: TO DO
A31: 62694a749fb81e3268ea0ffba0de1e95 | B31: The ways in which the tourists value different aspects of the surroundings are also influenced by experiences made during the visit. To the extent that information, interpretation and education do not have a sufficient influence on peoples' actual behaviour, co-creation initiatives are proposed as a more efficient way of transferring responsibility to visitors (Campos, Mendes, Valle, and Scott, 2015, Prebensen, Vitterso, and Dahl, 2013). Co-creation implies that the tourists participate in the design, production and consumption of an experience, even collaborating in the creation of new products and services (Binkhorst and Dekker, 2009). | C31: TO DO
... A82: 17a9f0d1e3733dac32f98dd1b6ee7ae0 | B82: Owing to success of the first phase, UNU and Shimadzu agreed to continue the project, establishing the second phase in 1999. In continuation of the previous project, the same research group in each country was kept as partner and national implementation unit. The Philippines joined the project at the beginning of the second phase. The three components were closely linked together and implemented through collaboration of the UNU network on coastal issues. | C82: TO DO
A83: 4305276298bfe07e216b55b3e150ff68 | B83: For the last one a comply or explain principle is in use. To enable readers to find the particular sustainability information in the report, GRI is using a mandatory content index table that informs the reader on what page the disclosures or the indicator can be found. The Guidelines of the IIRC are currently in development and will be released as draft in April 2013 and finalized by the end of 2013. | C83: TRUE | D83: Could be false. I assumed that the sustainability information and indicators cover SDG 12 indicators.
A84: f25d81a6f6dd57b990eb23725cf894a1 | B84: Today, the dominant research on the effect of the educational systems and approaches related to sustainable development clearly favours impact on the individuals (as opposed to organisations and communities) and formal education (as opposed to non-formal and informal learning). In the modern world characterised by accelerated changes, lack of predictability and multiple economic, financial and environmental crises, different forms of knowledge and learning become a necessity. Even sectors that for a long time adhered to traditional ways of doing things, find themselves in need to adapt to the constant demand for (at least partial) transformation. | C84: FALSE
A85: c2f4320ebfc7a98e97162886129820b2 | B85: As an industry, it often competes for prime real estate and juxtaposes visitors with different cultural practices and values to host communities, with consequent negative influences. Their economies and progress in development have been the subject of intense scrutiny, as a result of limitations in topographic character, vulnerability to natural disasters, climate changes and related impacts, threats to biological diversity, especially in coastal and marine areas, consumption of scarce natural resources, declining traditional productive sectors, poverty, and their reliance on the travel and tourism industry for economic performance. Large island nations comprising Papua New Guinea, Cuba, Hispaniola (Haiti and the Dominican Republic), Guinea Bissau and those located in Central/South America (Suriname, Guyana, Belize) make up the SIDS grouping with geographic areas in excess of 25,000 km2. There is significant variability in GDP per capita, as indicated in figure 8.3, with many of the more developed tourist economies such as Aruba, Singapore, US Virgin Islands (USVI) and the Bahamas, showing higher levels of prosperity. | C85: TRUE
A86: ee172df5f44bbedc59dd865962f75452 | B86: These inequalities were exacerbated by the structural adjustment programmes of the 1980s, the liberalisation of the economy in the 1990s, and the rapid growth of financial services after the liberalisation of financial markets in 1991. On the advice of the international financial institutions, governments have opted to offer targeted assistance to poor households rather than generalised subsidies on basic goods (e.g. staple foods) and services (e.g. water and electricity). Towards this end, the government has tracked the incidence and prevalence of poverty, and conducted poverty mapping to be able to identify the vulnerable households. | C86: FALSE
A87: 1b8a501a7bbb0802fa4a05da3a8cd65a | B87: At the same time internal transparency through environmental management accounting started to increase with a business rationale to improve efficiency and reduce costs, in relation to using natural resources, reducing emissions to air, water and soil, as well as in reducing waste. More recently companies increasingly see the relevance of sustainability for their long term business continuity and identify sustainability challenges as a business growth driver. They even transform their business to address such business opportunities. The company, DSM, active in health, nutrition and materials, for example, is not only changing from a chemical company to bio-based solutions, but also focuses its business activities much more on nutrition, as this will be a major global challenge. | C87: TRUE
A88: 64aced7c4d814e32f8a3cfe50ddd81c9 | B88: These are primarily wind, solar, hydro, biofuels and co-generation. In addition, governments have partnered with private sector and civil society organisations to support small and microenterprises with training and concessionary financing. The annual budget is Jamaica’s short-term plan. There is also a rolling three-year Medium Term Social and Economic Policy Framework, and an annually revised three-year macroeconomic plan, which frames the annual budget. In theory, all of these should be aligned with one another within the long-term plan, Vision 2030. In addition, there are ongoing initiatives to prepare parish plans under the Local Sustainable Development Plans, which also ought to be aligned to the national plans. | C88: FALSE
A89: 78906f21b8873984506469c09306a3e3 | B89: The varied relief has resulted in several distinct climatic regimes, with the prevailing south-east trade winds depositing moisture in the form of rainfall over the central and highest part of the island. A significant feature of Mauritian climatology, however, is the occurrence of tropical cyclones during the summer months. Almost 300 endemic species have been identified, of which the most famous was the Dodo, a large flightless bird now extinct. Permanent human settlement started in the fifteenth century and, ever since, the environment has come under severe threat as its few precious resources (such as ebony) have been exploited indiscriminately. | C89: FALSE
A90: f0d7085f21c4e88d7448e29c10b34cee | B90: This trend has been boosted by market liberalization and augmented by convergence, new technologies and resultant innovations such as mobile phones which continue to be the most rapidly adopted technology in history. While sector growth has been experienced worldwide, the impact has been exponential in developing countries. Today the mobile phone is the most popular and widespread personal communication technology on the planet, with an estimated average subscription world rate of 87 per 100 inhabitants in 20111. | C90: FALSE | D90: Could be SDG 12 if we were to consider mobile phone owning as "consumption". But this passage just states facts and is most likely not about reclycling mobile phone.
A91: fe00789e13ec56b1624f016c682abea0 | B91: Such information is provided in the form of quantitative and qualitative data as part of a company’s reporting process. Key performance indicators comprise the quantitative data, an example of qualitative data can be found in the description of a company’s sustainability strategies and reporting policies. Examples include the portal of the Government of France (info-financiere. | C91: FALSE | D91: Could be SDG 12, but it is unclear what companies report about.
A92: 175fad9c8b9dcce44c7cc98b032d07e1 | B92: Importantly, the IUCN works through specialist commissions that provide the Union with information and know-how. All the members of the IUCN together agree on, for example, the work programme of the organization. This would mean conducting studies and developing new policy recommendations or instruments based on the latest scientific findings. In addition, the IUCN governance structure could be used as a partial model for the post-2020 chemicals and waste management regime: the ICCM acts as the general assembly of members, and a governing council could be established to work under the direction and monitoring of the ICCM. | C92: TRUE
A93: a287d825bd346605da1b8e5017d13524 | B93: The initiative engaging the manufacturer, Grameen Bank, National Building Research Organization and vulnerable families encourages the use of local sustainable building materials, quality durable construction and livelihood considerations such as including shop fronts in the houses. The initiative required a high degree of informal collaborative learning and training. Learning occurs at both the level of the community, as well as within the company, where lessons of Mexican success are explored to be translated across other regions. | C93: TRUE
A94: 062372c7882af8f7bb84943024eb6a2c | B94: Its mandate is two-fold: to promote energy security amongst its member countries through collective response to physical disruptions in oil supply and to advise member countries on sound energy policy. This paper reflects the views of the IEA Secretariat and may not necessarily reflect the views of the individual IEA member countries. The study also draws on contributions of Franziska Mueller-Langer, Jens Giersdorf and Anastasios Perimenis of the German Biomass Research Centre (DBFZ), who provided parts of the sustainability chapter and four country profiles commissioned by the Deutsche Gesellschaft fiir Technische Zusammenarbeit (GTZ). | C94: FALSE | D94: Could be SDG 12 because oil is natural resource. But it is very, very vague and should be considered as the SDG on energy instead if we were to avoid double counting.
A95: 0b4a31dd0bc5b9cb6a3da2b48eb54401 | B95: As a result, poverty is endemic, generously underestimated at 20 per cent of the population in 2011, with the majority of poor households located in rural communities. It is well known that poor communities generate negative pressure on the environment from ‘slash-and-burn’ agricultural activities, improper waste disposal for want of facilities, and settlement on fragile lands that are vulnerable to natural hazards. In the case of Jamaica, there are the additional challenges of servicing the mounting national debt, which in 2013 stood at over 140 per cent of GDP, and ensuring macroeconomic stability so as to provide a basis for economic growth. | C95: TRUE
A96: 2247ea809c4b3069265b106b3819af19 | B96: However, both face a number of challenges in implementation including the establishment 0/effective targets. The purpose of this chapter is to explore the opportunities, challenges and important considerations faced by policy makers when setting and implementing SMM-related targets. Finland attributes waste management improvements to changes in EU legislation, specifically stricter waste management standards and requirements. | C96: TRUE
A97: 53a72b1c4248dc4bbce2a197b5573d72 | B97: The transformation process is necessarily long term. With governments elected for five years, there is an inherent tendency to postpone addressing long-term development issues that is all the more difficult in the context of a highly partisan political tradition that resists consensus over development strategies. Progress in mainstreaming the environmental dimension of sustainable development strategies has been slow. Such policies address cross-cutting issues, and in the Westminster system of sectoral portfolio ministerial responsibilities, such issues tend to fall between ministerial responsibilities. | C97: FALSE | D97: not specific enough to be considered consumption and production
A98: 84e48d25391c7a7cda69d5f9fb25ee36 | B98: Complementing the theoretical approach outlined in the previous chapter, this chapter focuses on the practical and strategic side of implementation, considering the multiple dimensions of successful implementation. Effective policies therefore often have to be developed in collaboration between line ministries. It is important to have effective mechanisms in place to support such collaboration. | C98: FALSE | D98: Unclear about what the policies are about.
A99: 08ee208db6cafa5ea057212223ece39c | B99: One legacy of that programme was the establishment of the Programme of Advancement through Health and Education (PATH), a conditional cash transfer programme that now constitutes the core of the social safety net. Advocacy has been initiated by scientists and their students in the Climate Studies Group of the Department of Physics at the University of the West Indies (UWI), individual scholars in the Faculty of Social Sciences, the Centre for Sustainable Development at UWI, as well as by various ENGOs. Some of the research and the outreach based on this work have been funded by the Caribbean Community Climate Change Centre (CCCCC) and the Environmental Foundation of Jamaica (EFJ). | C99: FALSE | D99: Environment is another SDG
A100: 3c57594c5de7b481d01d64593f4e51cb | B100: Design-for-disassembly was formulated to promote the easy recovery of parts and materials during the product disassembly process, while design-for-environment called for minimizing pollution and promoting resource conservation during product or system design. In product life-cycle considerations, extended producer responsibility (EPR) may be realized in collaboration with intelligent consumer behaviour. The European Union (EU) and WBCSD have shifted the leading concept of a resource-circulating society from sustainable production and consumption in the 1990s to sustainable consumption and production in a “consumer society”. | C100: TRUE
A101: 78625638c482b151a88161b2f6e4894f | B101: Resource efficiency can be achieved by increasing resource productivity (value added / resource use) or reducing resource intensity (resource use / value added). It is related to strategies like dematerialisation, such as fuel efficient cars. It will be clear that no production can be said to be sustainable if it is profligate in the use of resources, thus there is a direct link between resource efficiency and SCP, particularly sustainable production. | C101: TRUE

Sheet Jean-Baptiste
A1: Text ID | B1: Text | C1: SDG 12 Label | D1: Comments (optional)
A2: f83637f12da543fd9df8cb97ade0ef3c | B2: There are also examples at the national level. The Dutch Sustainable Growth Coalition, for example, unites the eighth largest big multinationals in shaping, sharing and stimulating sustainable business models. The changing role of business in society is also reflected in the increased participation by businesses in the discussions in various forums of the United Nations such as UN Global Compact, the development of the UN Sustainable Development Goals, as well as at international conferences such as the Rio+20 conference, which confirmed the importance of corporate sustainability reporting. When moving towards green growth requires a joint public private approach then there should also be more convergence between public and private measurement and reporting to follow the progress made to achieve the goals of green growth. | C2: TO DO
A3: 3083f5dee9e6201a9043b765d1c7c644 | B3: Dr Edward W Manning and T David Dougherty, 2000. The study (Lot 1 Research Capacity) was conducted by PA Government Services under the Caribbean Regional Sustainable Tourism Development Programme (CRSTDP), funded by the 8th European Development Fund (EDF), August 2006. See Reil G Cruz, 2006, 47pp. Also World Bank, Caribbean Country Management Unit, 2005. | C3: TO DO
A4: 2b1b85e4586716ccac4cfbab9226cc65 | B4: Both sugar and bananas have lost preferential access to their traditional European Union (EU) markets in the age of liberalisation of the global economy. In addition, with the frequency of hurricane damage increasing in recent years, it was decided to abandon the exports of bananas completely. The bauxite/ alumina industry all but shut down in 2008, when international demand plummeted in the global crisis that was precipitated by the financial crisis of that year. The current owners of the mines and processing facilities have demanded access to cheaper energy as the price for restarting the industry. This is one of the major drivers for the urgent transformation of the energy supply that has become a high priority for the Jamaican government. Forests were cleared, and the habitats they supported were destroyed, to establish the sugar industry in the seventeenth to the nineteenth centuries. | C4: TO DO
A5: 89ca4fa4c89388e266f44db315cd78d8 | B5: The statement was made in 1972, long before the world became conscious of acceleration in anthropogenic GHG emissions. Nevertheless, Mrs Gandhi’s statement was one of the earliest to create a direct link between environmental concerns and poverty alleviation. Neither can the poor be held responsible for the major part of the GHG emissions. | C5: TO DO
A6: 8928aa79bf65a8ea8b41802634887e4c | B6: There are estimated to be 500 international treaties and agreements on the environment (155 biodiversity-related, 179 chemicals-related, 46 land-related, and 196 water-related) and a proliferation of subsidiary bodies for the different conventions and administrative arrangements. Additionally, important are leveraging synergies in responsibilities of conventions across various sectoral policies, with the promotion of joint implementation and coordination of funding sources and programmes, as well as multi-stakeholder outreach and engagement to ensure buy-in.5 Capacity building is required given the increasingly complex scientific and technical issues involved. Meanwhile, critical actions may not be taken with fallout for human and environmental health. | C6: TO DO
A7: 6f4ffd29a57cb6598908ad274d7dfdaa | B7: Not to act is no longer an option. And I was encouraged by the sense of reality shown by the G8-leaders a few weeks ago, when they talked about a 50% cut in global emissions by 2050. It bodes well for the Conference of the Parties to be held in Copenhagen in 2009, where we will work hard to reach a global deal beyond Kyoto. | C7: TO DO
A8: 86236555aba7f7bec5e1aed8f189e77a | B8: At local level, the main partners have been the collaboration of local food producers, R0rosmat as well as the R0ros Museum and World Heritage and local businesses. Destination Roros is currently (spring 2016) undergoing the recertification process. Additionally, the goal is to encourage even more companies to apply for an environmental certificate and to train more people. | C8: TO DO
A9: 0b4a31dd0bc5b9cb6a3da2b48eb54401 | B9: As a result, poverty is endemic, generously underestimated at 20 per cent of the population in 2011, with the majority of poor households located in rural communities. It is well known that poor communities generate negative pressure on the environment from ‘slash-and-burn’ agricultural activities, improper waste disposal for want of facilities, and settlement on fragile lands that are vulnerable to natural hazards. In the case of Jamaica, there are the additional challenges of servicing the mounting national debt, which in 2013 stood at over 140 per cent of GDP, and ensuring macroeconomic stability so as to provide a basis for economic growth. | C9: TO DO
A10: 43db05d16c51cafb451321dbca30d967 | B10: This huge increase alone speaks of amazing achievements in terms of ICT access and bridging the digital divide. This interpretation, however, would be very narrow as the factors leading to ICT access are bound to interact with the environments in which they operate. In this case, a critical analysis of mobile subscriptions by level of development should trigger alarm bells as the sharp increase in ICT access is inordinately skewed towards developing countries as illustrated in figure 9.2. | C10: TO DO
A11: ad6accc9d24e23b3e302de529a942889 | B11: Policy instruments based on EPR can also be designed to drive eco-design at the beginning of the product lifecycle. However, if the instruments are focused only on improved recycling without driving initial eco-design, EPR may not generate the desired economic and environmental efficiencies (Tojo, N., 2004). Outcomes from economic incentives alone, however, may not be sufficient to generate environmentally or socially meaningful results, because actors generally stop making improvements once the economic incentive to do so ends, whether or not sufficient social or environmental progress has been made. Examples of economic mechanisms employed by OECD governments include also disincentives such as increased fees on waste disposal, and incentives such as government procurement policies and a potential reduction in the value added tax (VAT) and tax for environmentally friendly products (all promoted by the government of the Czech Republic, among others). | C11: TO DO
A12: 55eb56bec1db9ca76b6d2aa3c09712e2 | B12: The World Bank estimates that out of the 500 largest cities in the developing countries, only 4% are deemed credit worthy in international capital markets and 20% on the local markets. Of the available funding over the last 10 years, two-thirds has gone to just 10 middle-income countries. Making the necessary investment finance available to those who need it most, in the low-income countries, is an urgent priority and a particular challenge. | C12: TO DO
A13: a287d825bd346605da1b8e5017d13524 | B13: The initiative engaging the manufacturer, Grameen Bank, National Building Research Organization and vulnerable families encourages the use of local sustainable building materials, quality durable construction and livelihood considerations such as including shop fronts in the houses. The initiative required a high degree of informal collaborative learning and training. Learning occurs at both the level of the community, as well as within the company, where lessons of Mexican success are explored to be translated across other regions. | C13: TO DO
... A101: 9b3e0c684586646ce9eed8a9821e0b59 | B101: It takes stock of policy initiatives to reduce waste generation, encourage recycling and ensure safe disposal of municipal and hazardous waste. The chapter also highlights progress in integrating informal waste pickers into municipal waste management. It discusses the environmental and economic implications of specific measures, such as extended producer responsibility and waste collection charges. National, regional and local authorities have well-defined responsibilities in waste management. | C101: TO DO

Sheet Meike
A1: Text ID | B1: Text | C1: SDG 12 Label | D1: Comments (optional) | E1: priority
A2: 78906f21b8873984506469c09306a3e3 | B2: The varied relief has resulted in several distinct climatic regimes, with the prevailing south-east trade winds depositing moisture in the form of rainfall over the central and highest part of the island. A significant feature of Mauritian climatology, however, is the occurrence of tropical cyclones during the summer months. Almost 300 endemic species have been identified, of which the most famous was the Dodo, a large flightless bird now extinct. Permanent human settlement started in the fifteenth century and, ever since, the environment has come under severe threat as its few precious resources (such as ebony) have been exploited indiscriminately. | C2: FALSE | E2: FALSE
A3: d46652f3f1c84a1b471f30c8d0087137 | B3: Many governments are recognizing this, and some have reformed their subsidies or are in the process of phasing them out. In 2015 and 2016, with low oil prices, around 50 countries increased or removed government controls on prices of fossil fuels, directly or partially removing subsidies. In 2013 Finland scrutinized 400 subsidy measures according to their environmental and social impacts and costs. | C3: TRUE | E3: FALSE
A4: d679f7406fda45349991085239143a4e | B4: Good corporate governance makes for good business for all. Good corporate governance helps reduce the risks that smaller firms may face as well. At the other end of the spectrum, cases of corporate malfeasance in state-owned enterprises illustrate that regardless of size or ownership, good corporate governance is critical. | C4: FALSE | E4: FALSE
A5: 549df2a4d76c942d8369308429752184 | B5: This term, however, is often used as a synonym for material productivity. Productivity measurement and analysis of natural resource and material flows complement the traditional indicators of capital, land and labour productivity. Used in parallel, these three types of productivity indicators afford a much deeper understanding of total factor productivity. | C5: TRUE | E5: FALSE
A6: 0963ea06d1b60ca64affa94911f329d2 | B6: In response, international organizations such as the UN Development Programme (UNDP), the UN Environment Programme (UNEP) and the Organisation for Economic Co-operation and Development (OECD) have promoted the exchange of policy initiatives, action programmes and practices among member countries, industrial associations and academic institutions. For example, UNEP introduced cleaner production (CP), which promotes a shift from end-of-pipe treatment to pollution prevention, while the UNDP has appealed for environmentally sound technology in technology transfer programmes and assistance to developing countries. In the follow-up meeting after the Rio Declaration and Agenda 21, the International Human Dimensions Programme (IHDP) was established as a collaborative platform for social scientists and policy-oriented academics. | C6: TRUE | E6: FALSE
A7: 2b1b85e4586716ccac4cfbab9226cc65 | B7: Both sugar and bananas have lost preferential access to their traditional European Union (EU) markets in the age of liberalisation of the global economy. In addition, with the frequency of hurricane damage increasing in recent years, it was decided to abandon the exports of bananas completely. The bauxite/ alumina industry all but shut down in 2008, when international demand plummeted in the global crisis that was precipitated by the financial crisis of that year. The current owners of the mines and processing facilities have demanded access to cheaper energy as the price for restarting the industry. This is one of the major drivers for the urgent transformation of the energy supply that has become a high priority for the Jamaican government. Forests were cleared, and the habitats they supported were destroyed, to establish the sugar industry in the seventeenth to the nineteenth centuries. | C7: TRUE | E7: FALSE
A8: 759b95e2698c40e89242d61169ef6b4d | B8: We have not been able to get a clear answer from the responsible person at Teijin, and in the basic scenario it was therefore chosen to use a conservative approach, assuming a low yield of the process. For climate change, the increased efficiency means that there is a net benefit instead of an impact. The same finding is seen for human toxicity, cancer effects. | C8: TRUE | E8: FALSE
A9: 8928aa79bf65a8ea8b41802634887e4c | B9: There are estimated to be 500 international treaties and agreements on the environment (155 biodiversity-related, 179 chemicals-related, 46 land-related, and 196 water-related) and a proliferation of subsidiary bodies for the different conventions and administrative arrangements. Additionally, important are leveraging synergies in responsibilities of conventions across various sectoral policies, with the promotion of joint implementation and coordination of funding sources and programmes, as well as multi-stakeholder outreach and engagement to ensure buy-in.5 Capacity building is required given the increasingly complex scientific and technical issues involved. Meanwhile, critical actions may not be taken with fallout for human and environmental health. | C9: TRUE | E9: FALSE
A10: 54b2538e906a8d503d9a71159d1d36ca | B10: It also prepares technical documentation related to chemical safety that can be downloaded from its website. The documentation includes government manuals, SDS and information on the GHS and other UN initiatives. There are ten ARLs - effectively insurance companies that cover workplace injuries and illnesses, each with a different focus. | C10: FALSE | E10: FALSE
A11: 13da70ac3a8ad54df495da6e6bf5bf08 | B11: Children and youth in cities”, in ISSC/UNESCO, World Social Science Report 2013: Changing Global Environments, OECD Publishing and Unesco Publishing. Each author is responsible for the facts contained in his/her article and the opinions expressed therein, which are not necessarily those of UNESCO, ISSC and do not commit either organisation. | C11: FALSE | E11: FALSE
A12: a941f19e7545ea877b4b9510f0be6a63 | B12: In 2014, the System was extended to include a dedicated web portal. This cadastre provides public access to the processes of issuing and reissuing of licences, licence revocation, transfer, pledge and surrender for the entire or a part of the licensed area, as well as to maintaining a register of licences. One of the main objectives of this tool is to prevent licences from overlapping other licences or protected areas. | C12: FALSE | E12: FALSE
A13: 89ca4fa4c89388e266f44db315cd78d8 | B13: The statement was made in 1972, long before the world became conscious of acceleration in anthropogenic GHG emissions. Nevertheless, Mrs Gandhi’s statement was one of the earliest to create a direct link between environmental concerns and poverty alleviation. Neither can the poor be held responsible for the major part of the GHG emissions. | C13: FALSE | E13: FALSE
... A60: 0bafd5e13fe32c31b5b4d9f7536c941d | B60: Some definition of technology is necessary- it should be 100% recyclable under readily available current technology. Cotton/polyester mixes, for example, can be more technically durable than pure cotton. This suggests that the 100% recyclable stamp would be more applicable to fast fashion and not recommended for textiles where lifetime is generally limited by technical strength rather than change in style or change in fit e.g. bed-linen. This would rule out linking to some of the information proposed in the provision - unless the regulation was to be changed. | C60: TRUE | E60: TRUE
A61: 12128c9d99e298a5a86fec6053a25347 | B61: There is high uncertainty of data, because of the lack of data verification procedures. Additionally, as well as receiving user fees, collection companies receive a subsidy from the municipality, which is based on the amount of w aste collected and distance to the disposal site. Disposal site operators do not collect a gate fee but receive a subsidy based on the amount of waste received. | C61: TO DO | E61: FALSE
A62: c4fd5fb66459273c5dc10c4de4266f85 | B62: Its mandate is to foster cooperation between its 53 members and 9 associate members. It supports Governments of the region in consolidating regional positions and advocates regional approaches to meeting the region's unique socio-economic challenges in a globalizing world. The ESCAP head office is located in Bangkok, Thailand, with subregional offices in Almaty, Kazakhstan, Incheon, Republic of Korea, New Delhi, India, and Suva, Fiji. Please visit our website at <www.unescap.org> for further information. | C62: FALSE | E62: TRUE
A63: e9c0953d695ff92ee3c092d3b13b280c | B63: This increase can be caused by both an actual increase in waste generation and by improved monitoring of collected waste amounts. The average MSW composition was derived from analyses in Minsk, Gomel, Mogilev, Bobruisk and Polotsk (table 6.2). Also, analysis of waste composition was performed in Minsk Oblast in 2013. | C63: TRUE | E63: TRUE
A64: e63e24fa452209fc8000bc37d582ff2c | B64: Policy principles and objectives have been established, municipalities are required to prepare Integrated Solid Waste Management Plans and technical regulations and guidelines have been issued. However, the policies and action plans that were developed in parallel to address waste issues at national, regional and municipal levels do not provide comprehensive and consistent guidance. As a consequence, opportunities to increase the environmental effectiveness and economic efficiency of waste policies (by developing an efficient waste infrastructure network, for example) remain unexploited. Positive policy developments include the 2010 Policy on Sustainable Production and Consumption, efforts to promote cleaner production, an ambitious policy on extended producer responsibility (EPR) and attempts to establish green public purchasing. | C64: TO DO | E64: FALSE
A65: ad6accc9d24e23b3e302de529a942889 | B65: Policy instruments based on EPR can also be designed to drive eco-design at the beginning of the product lifecycle. However, if the instruments are focused only on improved recycling without driving initial eco-design, EPR may not generate the desired economic and environmental efficiencies (Tojo, N., 2004). Outcomes from economic incentives alone, however, may not be sufficient to generate environmentally or socially meaningful results, because actors generally stop making improvements once the economic incentive to do so ends, whether or not sufficient social or environmental progress has been made. Examples of economic mechanisms employed by OECD governments include also disincentives such as increased fees on waste disposal, and incentives such as government procurement policies and a potential reduction in the value added tax (VAT) and tax for environmentally friendly products (all promoted by the government of the Czech Republic, among others). | C65: TRUE | E65: TRUE
A66: 1cd8c5958dad8616aabc4fa432b5ead7 | B66: For material flows and waste there are still unresolved conceptual issues and establishing indicators requires a lot of effort, if they are based on a national physical input-output table showing interdependencies among sectors in physical flows. We have employed sectoral footprints to show the natural resource use per expenditure in sectors. Footprint accounts deliver sectoral disaggregation by expenditure categories for products of major sectors. | C66: TO DO | E66: FALSE
A67: 5a35e4bb86235463eff5866e9ee79739 | B67: More sustainable alternatives should be available and easily accessible, as well as suitable infrastructure to make it easier to practice sustainable behaviour. Even well-intended people cannot live sustainably if there are no sustainable products and alternatives available. These could include peer pressure, putting more taxes on unsustainable options and funding more sustainable practices. For example by providing input to policy design, in expressing what is meaningful to them and what they care about in real life and in society, in understanding the advantages and disadvantages of certain behavioural patterns. | C67: TRUE | E67: TRUE
A68: 78625638c482b151a88161b2f6e4894f | B68: Resource efficiency can be achieved by increasing resource productivity (value added / resource use) or reducing resource intensity (resource use / value added). It is related to strategies like dematerialisation, such as fuel efficient cars. It will be clear that no production can be said to be sustainable if it is profligate in the use of resources, thus there is a direct link between resource efficiency and SCP, particularly sustainable production. | C68: TO DO | E68: FALSE
A69: 4305276298bfe07e216b55b3e150ff68 | B69: For the last one a comply or explain principle is in use. To enable readers to find the particular sustainability information in the report, GRI is using a mandatory content index table that informs the reader on what page the disclosures or the indicator can be found. The Guidelines of the IIRC are currently in development and will be released as draft in April 2013 and finalized by the end of 2013. | C69: TO DO | E69: FALSE
A70: ea3c7154e3fd84c3e502a9219b2e3cc8 | B70: However, it does not include information on when licences are applied for (while providing the date of issue), nor on the reasons for and conditions on the numerous licence transfers. There is also a problem at present with accessing the area covered by petroleum licences in the Ministry of Mining and Heavy Industry database. In addition, the Ministry of Environment and Tourism is not providing the most recent data on receipts to its special fund for mining rehabilitation, arguing that this is not permitted by banking legislation. Further, though licence holders provide information to the EITI, they are often unwilling to present the same information on their own websites, thus reducing transparency. | C70: FALSE | E70: TRUE
A71: 642f69433572aed4342a2026f0513b5b | B71: If an EIA is carried out, but improperly and leading to environmental damage, the licensed EIA entity must pay compensation. There is also a mismatch between the economic value for animals, their conservation status and their market value (chapter 3). The 2012 Law on Hunting, for example, foresees a reward of 15 per cent of fines imposed to be given to the citizen identifying the person responsible for the violation. | C71: TO DO | E71: FALSE
A72: 703dd858d96d671944d27c5a06867a10 | B72: The indicator has an indirect relevance to food waste prevention since the more food waste that is avoided the lower should be the amount of food that is purchased for consumption to provide for the same intake of nutrients. It should be noted that the indicator is only relevant to reducing food waste at the end point of consum p-tion i.e. in households, restaurants canteens etc. However, the indicator can be affected by factors which are unrelated to waste prevention. These can include changes in food consumption behaviour-i.e. However, the indicator has been criticised in the past due to assumptions made in the calculations. Its acceptability as a food waste indicator might also be reduced as it has not been used in this context before. | C72: TO DO | E72: FALSE
A73: 3c57594c5de7b481d01d64593f4e51cb | B73: Design-for-disassembly was formulated to promote the easy recovery of parts and materials during the product disassembly process, while design-for-environment called for minimizing pollution and promoting resource conservation during product or system design. In product life-cycle considerations, extended producer responsibility (EPR) may be realized in collaboration with intelligent consumer behaviour. The European Union (EU) and WBCSD have shifted the leading concept of a resource-circulating society from sustainable production and consumption in the 1990s to sustainable consumption and production in a “consumer society”. | C73: TO DO | E73: FALSE
A74: 0b4a31dd0bc5b9cb6a3da2b48eb54401 | B74: As a result, poverty is endemic, generously underestimated at 20 per cent of the population in 2011, with the majority of poor households located in rural communities. It is well known that poor communities generate negative pressure on the environment from ‘slash-and-burn’ agricultural activities, improper waste disposal for want of facilities, and settlement on fragile lands that are vulnerable to natural hazards. In the case of Jamaica, there are the additional challenges of servicing the mounting national debt, which in 2013 stood at over 140 per cent of GDP, and ensuring macroeconomic stability so as to provide a basis for economic growth. | C74: TO DO | E74: FALSE
A75: 84e48d25391c7a7cda69d5f9fb25ee36 | B75: Complementing the theoretical approach outlined in the previous chapter, this chapter focuses on the practical and strategic side of implementation, considering the multiple dimensions of successful implementation. Effective policies therefore often have to be developed in collaboration between line ministries. It is important to have effective mechanisms in place to support such collaboration. | C75: TO DO | E75: FALSE
A76: f25d81a6f6dd57b990eb23725cf894a1 | B76: Today, the dominant research on the effect of the educational systems and approaches related to sustainable development clearly favours impact on the individuals (as opposed to organisations and communities) and formal education (as opposed to non-formal and informal learning). In the modern world characterised by accelerated changes, lack of predictability and multiple economic, financial and environmental crises, different forms of knowledge and learning become a necessity. Even sectors that for a long time adhered to traditional ways of doing things, find themselves in need to adapt to the constant demand for (at least partial) transformation. | C76: TO DO | E76: FALSE
A77: a287d825bd346605da1b8e5017d13524 | B77: The initiative engaging the manufacturer, Grameen Bank, National Building Research Organization and vulnerable families encourages the use of local sustainable building materials, quality durable construction and livelihood considerations such as including shop fronts in the houses. The initiative required a high degree of informal collaborative learning and training. Learning occurs at both the level of the community, as well as within the company, where lessons of Mexican success are explored to be translated across other regions. | C77: TO DO | E77: FALSE
A78: 88220c7fe94cff6b5a90c20459c70000 | B78: In recent years, significant improvements in the assessment methodologies have been made in an effort mostly co-ordinated by the UNEP/ SETAC initiative (de Haes, 2002, UNEP, 2003, Jolliet et al., The EU Joint Research Centre has also made an important input in the determination of effective practice in impact assessment, which has resulted in the adoption of 14 default impact categories for the EU footprinting initiative (Product Environmental Footprint (PEF)/ Organisational Environmental Footprint (OEF), European Commission, 2013a, European Commission, 2013b). | C78: TO DO | E78: FALSE
A79: fe00789e13ec56b1624f016c682abea0 | B79: Such information is provided in the form of quantitative and qualitative data as part of a company’s reporting process. Key performance indicators comprise the quantitative data, an example of qualitative data can be found in the description of a company’s sustainability strategies and reporting policies. Examples include the portal of the Government of France (info-financiere. | C79: TO DO | E79: FALSE
A80: 53a72b1c4248dc4bbce2a197b5573d72 | B80: The transformation process is necessarily long term. With governments elected for five years, there is an inherent tendency to postpone addressing long-term development issues that is all the more difficult in the context of a highly partisan political tradition that resists consensus over development strategies. Progress in mainstreaming the environmental dimension of sustainable development strategies has been slow. Such policies address cross-cutting issues, and in the Westminster system of sectoral portfolio ministerial responsibilities, such issues tend to fall between ministerial responsibilities. | C80: TO DO | E80: FALSE
A81: 1f90c5a8981fc4c095f70aea892ff94e | B81: Based on 2011 data, generation is above average in the Capital area at 460 kg/cap/y, and in the coastal region influenced by tourism at 480 kg/cap/y, although excluding the impact of tourists the average is 420 kg/cap/y. The remaining inland region shows under-average waste generation, at only 223 kg/cap/y. The reason for such a high variation in per capita waste generation at county level could be because the impact of the non-permanent tourist population is not considered in the calculation of this indicator. | C81: TO DO | E81: FALSE
A82: ee172df5f44bbedc59dd865962f75452 | B82: These inequalities were exacerbated by the structural adjustment programmes of the 1980s, the liberalisation of the economy in the 1990s, and the rapid growth of financial services after the liberalisation of financial markets in 1991. On the advice of the international financial institutions, governments have opted to offer targeted assistance to poor households rather than generalised subsidies on basic goods (e.g. staple foods) and services (e.g. water and electricity). Towards this end, the government has tracked the incidence and prevalence of poverty, and conducted poverty mapping to be able to identify the vulnerable households. | C82: TO DO | E82: FALSE
A83: fa745ce3576ef1930376e33760b5d835 | B83: It can provide better recreational and cultural facilities but also create overcrowding, traffic congestion, litter, vandalism and crime (UNESCAP 2003). Started as the World Tourism Organisation in 1970 when its statutes were adopted, it became a working entity in 1975 with Headquarters in Madrid and joined the UN system in 2003, becoming known as UNWTO. Following the recommendations of the Johannesburg Plan of Implementation (JPOI) that “developed countries must take the lead" in accelerating the shift towards more sustainable consumption and production, each of the Marrakech Task Forces was chaired by a developed country. | C83: TO DO | E83: FALSE
A84: 1365feccc61adc4814c64ff7d9303893 | B84: Further extending the green purchasing requirements to local governments would enhance the effectiveness of the policy, in particular since a large share of public expenditure is invested locally. In expanding its green purchasing policy, the government should make sure that it targets goods and services with the highest potential environmental returns. This outcome was achieved with minor increases in public expenditure. Since the introduction of the green public procurement policy, the market shares of eco-friendly products widely used in the public administration have substantially increased (Figure 9). According to MOE’s estimates, the national government’s green purchasing policy resulted in a reduction of C02 emissions by 89 500 tonnes in 2006, which is equivalent to the amount of C02 emitted by a town of 42 000 inhabitants. The financial implications of Japan’s green public procurement policy and the overall costs to the Japanese economy of achieving such emission reductions should be assessed and compared with the costs of alternative policy measures. | C84: TRUE | E84: TRUE
A85: e072c8b659169b5939e49be5c5fc3ae3 | B85: To do this, Section 1.1 looks at the reasons why fossil-fuel subsidies are generally considered to be harmful for the economy and the environment. Section 1.2 then shows how this helps explain the recent emergence of a consensus for reforming fossil-fuel subsidies, and how this growing consensus has led to a number ofpolicy initiatives internationally and domestically. Section 1.3 then concludes by placing the OECD Inventory onto that broader stage, emphasising the important role it plays in ongoing discussions of energy policies and their reform. The use of such data by the OECD is without prejudice to the status of the Golan Heights, East Jerusalem and Israeli settlements in the West Bank under the terms of international law. | C85: TRUE | E85: TRUE
A86: 0342980e48fbffd359a20628d9450485 | B86: Mauritius covers a total land area of 720 square miles, and is almost entirely of volcanic origin, except for stretches of beaches, coral reefs and small patches of alluvium at the mouths of rivers. Pear-shaped, mountainous with its highest peak standing at 2,711 feet above sea level, Mauritius emerged from the ocean floor some 5 million years ago. Volcanic activity over thousands of years has given rise to varied types of soil. | C86: FALSE | E86: TRUE
A87: f0d7085f21c4e88d7448e29c10b34cee | B87: This trend has been boosted by market liberalization and augmented by convergence, new technologies and resultant innovations such as mobile phones which continue to be the most rapidly adopted technology in history. While sector growth has been experienced worldwide, the impact has been exponential in developing countries. Today the mobile phone is the most popular and widespread personal communication technology on the planet, with an estimated average subscription world rate of 87 per 100 inhabitants in 20111. | C87: TO DO | E87: FALSE
A88: ca472909daa94e1ce61c174548d7198d | B88: Jamaica has a small but active group of ENGOs that are advocates for the green economy. Some of their voices have acquired national recognition and respect, and can no longer be ignored by policy-makers. Since the Earth Summit in 1992, there have been several civil society organisations12 that have kept the pressure on the Government of Jamaica to honour its commitments to sustainable development in general, and to the various multilateral environmental agreements. | C88: TO DO | E88: FALSE
A89: 3174e5f65fdec525ecf8be88f1898329 | B89: These coverage percentages may be compared with the over 30 per cent of land covered by exploration licences in 2008 and the current aim of raising it again to 20 per cent. The Ministry estimates that about 30 per cent of the licensed area is being used, with the remainder idle because of low commodity prices, poor infrastructure or the risk of environmental impact. The number of licences for oil and gas and radioactive minerals is two orders of magnitude lower. Such permits are issued by soum and district governors based on the conclusions of NAMEM’s departments at local level. | C89: TO DO | E89: FALSE
A90: 4da053336ea3efd2695efd580c54584b | B90: It contributes 8.4 per cent to global employment (238 million jobs)1 and is projected to grow at an average of 4 per cent over the next decade. Rising per capita incomes and the operation of competitive low-cost airlines have also contributed to this increase. China is particularly significant as it alone is expected to contribute 100 million travellers.4 All indications are that in spite of a downturn in the global economy beginning in 2008 due to the global financial crisis, the travel and tourism industry is robust enough to withstand these pressures over the next decade. Depending upon the sophistication of the industry in terms of the solidity of its linkages and supply chains, some destinations are likely to recover more quickly than others. | C90: FALSE | E90: TRUE
A91: 175fad9c8b9dcce44c7cc98b032d07e1 | B91: Importantly, the IUCN works through specialist commissions that provide the Union with information and know-how. All the members of the IUCN together agree on, for example, the work programme of the organization. This would mean conducting studies and developing new policy recommendations or instruments based on the latest scientific findings. In addition, the IUCN governance structure could be used as a partial model for the post-2020 chemicals and waste management regime: the ICCM acts as the general assembly of members, and a governing council could be established to work under the direction and monitoring of the ICCM. | C91: TO DO | E91: FALSE
A92: 08ee208db6cafa5ea057212223ece39c | B92: One legacy of that programme was the establishment of the Programme of Advancement through Health and Education (PATH), a conditional cash transfer programme that now constitutes the core of the social safety net. Advocacy has been initiated by scientists and their students in the Climate Studies Group of the Department of Physics at the University of the West Indies (UWI), individual scholars in the Faculty of Social Sciences, the Centre for Sustainable Development at UWI, as well as by various ENGOs. Some of the research and the outreach based on this work have been funded by the Caribbean Community Climate Change Centre (CCCCC) and the Environmental Foundation of Jamaica (EFJ). | C92: TO DO | E92: FALSE
A93: 2247ea809c4b3069265b106b3819af19 | B93: However, both face a number of challenges in implementation including the establishment 0/effective targets. The purpose of this chapter is to explore the opportunities, challenges and important considerations faced by policy makers when setting and implementing SMM-related targets. Finland attributes waste management improvements to changes in EU legislation, specifically stricter waste management standards and requirements. | C93: TO DO | E93: FALSE
A94: a218ee95081ac58f5a8c35f0fb15c302 | B94: The criteria for commitments are (1) advance one or more United Nations goal/issue, (2) include time-bound target(s) that can be measured for success, and (3) include an agreement to publicly disclose, on an annual basis, progress made to realize the commitment, throughout its duration. In all these areas issues related to innovation and collaboration were discussed. Available from http://www .unglobalcompact.org/docs/news_events/2012_CSF/Rio_CSF_Overview_Outcomes.pdf. | C94: TO DO | E94: FALSE
A95: 8b7a84a06c90ba7a095b0307ada9a5f2 | B95: Additional documentation is required in an application for mineral water use. The issuance of the permit itself, and the signing of a contract with the water user, is done by the State-owned enterprise, Mongol Us ("Mongolian Water"). In the case of the utilization of water for strategically important minerals, the duration of the water use permit is the same as for the exploitation licence. | C95: TRUE | E95: TRUE
A96: ad30b568778b199cdbabb1a10d691944 | B96: It is often difficult to see from the statistics if this waste is included. Due to new EU - regulations this system no longer exists (withdrawn in 2003). The newest data is therefore from 2001 when it was collected 21,000 tons of food waste. The system of separate collection of food waste included commercial kitchens that generated more than 100 kg / week. Smaller kitchens and kitchens in cost sector were not covered by the collection scheme. | C96: TO DO | E96: FALSE
A97: 5e9b3bcf4aac69ed3ef73cbca12ee72b | B97: For each of these topics different indicators have been developed and the indicator protocols include definitions and the way the data need to be compiled, as well as further references. To measure for example the CO2 emissions the indicator protocol refers to Green House Gas measurement protocol of the WBCSD/World Resource Institute. The information that is reported in a sustainability report according to the GRI guidelines does not only include quantitative indicators but also provides information on the strategy, the organizational profile, the governance processes, the stakeholder engagement processes and the management approach. This information is relevant to obtain the context in which the data are provided. Each organization has a different ambition level and specific sustainability issues and therefore reporting is different for different organizations. The topics and indicators to report on are based on a materiality analysis that the company performs. | C97: TRUE | E97: TRUE
A98: e459110a0e5288867d180b786d5e620a | B98: Topics that have both an impact on the organization as well as on its stakeholders are the most material and therefore are discussed in more depth in the sustainability report. Once these topics are selected the company can identify the related indicators and use the GRI protocols to measure the data. Currently the GRI has three application levels, differing from reporting on 10 indicators with particular context information (Level C) to reporting on all material indicators (Level A). | C98: TO DO | E98: FALSE
A99: c8dbfdb5972aba5f9f4da67a683fee62 | B99: The framework also functions as a bridging mechanism between the narrowly construed MEAs pertaining to chemicals and waste, which include the Stockholm, Rotterdam, Basel, and Minamata Conventions. The Dubai Declaration, which expresses high-level political support forthe framework. The Overarching Policy Strategy (OPS), which contains the five key thematic objectives of SAICM: (1) risk reduction, (2) knowledge and information, (3) governance, (4) capacity-building and technical cooperation, and (5) illegal international traffic in chemicals. The OPS also lays down the scope, needs, underlying principles, and approaches of SAICM and elaborates on implementation and progress review mechanisms. The Global Plan of Action, which is an evolving and practical toolkit for implementation that currently lists more than 270 activities that can be undertaken by diverse stakeholders to operationalize SAICM. | C99: TO DO | E99: FALSE
A100: 989a430a480dfb2df0c37dd028d91db8 | B100: On another note, it is questionable whether there is even a need for a new scientific body for SAICM. As long as there are no legally binding obligations for states under SAICM, a scientific expert panel may not be needed. According to this view, the recommendations that SAICM provides could well be created without such a body. | C100: TRUE | E100: TRUE
A101: cd39a832a230705ef131f4d8b858f65f | B101: Once among the least developed Western economies, with high levels of emigration, since 2003 Ireland has enjoyed the third highest per capita GDP in OECD Europe (Figure 6.1).1 The growing economy attracted an inflow of foreign workers, the unemployment rate was 4.7% in 2007, below the OECD average. In the first half of the 2000s, large public sector deficits were transformed into substantial surpluses and the ratio of national debt to GNP was greatly reduced, while the tax-to-GDP ratio remained low (31.9% of GDP in 2006, compared with an OECD Europe average of 38%). The combination of a low corporate tax (12.5%), state grants and access to the European single market boosted foreign direct investment. | C101: TO DO | E101: FALSE

Sheet Steve
A1: Text ID | B1: Text | C1: SDG 12 Label | D1: Comments (optional) | E1: priority
A2: ee172df5f44bbedc59dd865962f75452 | B2: These inequalities were exacerbated by the structural adjustment programmes of the 1980s, the liberalisation of the economy in the 1990s, and the rapid growth of financial services after the liberalisation of financial markets in 1991. On the advice of the international financial institutions, governments have opted to offer targeted assistance to poor households rather than generalised subsidies on basic goods (e.g. staple foods) and services (e.g. water and electricity). Towards this end, the government has tracked the incidence and prevalence of poverty, and conducted poverty mapping to be able to identify the vulnerable households. | C2: FALSE | E2: FALSE
A3: eeccafbe1d2736fec1608bfebb02b882 | B3: Between 2000 and 2008, Japan’s economy grew by about 1.3% annually, a rate below the OECD average (about 2% per year). As a result of the global economic slowdown of 2008, the Japanese economy contracted sharply, and w'as dragged into the deepest recession since the Second World War (Section 2). Similarly, the OECD Europe aggregate does not include Estonia and Slovenia. In 2009, Japan’s GDP per capita in purchasing power parity was USD 29 800 and the OECD average was USD 30 500. | C3: FALSE | E3: FALSE
A4: d46652f3f1c84a1b471f30c8d0087137 | B4: Many governments are recognizing this, and some have reformed their subsidies or are in the process of phasing them out. In 2015 and 2016, with low oil prices, around 50 countries increased or removed government controls on prices of fossil fuels, directly or partially removing subsidies. In 2013 Finland scrutinized 400 subsidy measures according to their environmental and social impacts and costs. | C4: TRUE | E4: FALSE
A5: 12128c9d99e298a5a86fec6053a25347 | B5: There is high uncertainty of data, because of the lack of data verification procedures. Additionally, as well as receiving user fees, collection companies receive a subsidy from the municipality, which is based on the amount of w aste collected and distance to the disposal site. Disposal site operators do not collect a gate fee but receive a subsidy based on the amount of waste received. | C5: TRUE | D5: on waste reduction | E5: TRUE
A6: 0686b17a9aeedb103f46b38f9d94eeb8 | B6: Thus the government's role is dual. On the one hand, it must act as a facilitator by providing the necessary infrastructure for tourists, promoting attractions and encouraging tourist arrivals. On the other hand, government’s role is to enforce laws of the land and these may, in some cases, be in conflict with its role as a promoter of tourism. | C6: FALSE | D6: 12.b is specifically on developing and implementing monitoring tools | E6: FALSE
A7: 0963ea06d1b60ca64affa94911f329d2 | B7: In response, international organizations such as the UN Development Programme (UNDP), the UN Environment Programme (UNEP) and the Organisation for Economic Co-operation and Development (OECD) have promoted the exchange of policy initiatives, action programmes and practices among member countries, industrial associations and academic institutions. For example, UNEP introduced cleaner production (CP), which promotes a shift from end-of-pipe treatment to pollution prevention, while the UNDP has appealed for environmentally sound technology in technology transfer programmes and assistance to developing countries. In the follow-up meeting after the Rio Declaration and Agenda 21, the International Human Dimensions Programme (IHDP) was established as a collaborative platform for social scientists and policy-oriented academics. | C7: TRUE | E7: FALSE
A8: 14ddb3509efb3be82081e905f697dba3 | B8: The strategy's objectives are to sensitize and raise awareness among school children of the negative impact that using plastic bags has on the environment, to encourage schoolchildren to replace plastic bags with other less-polluting alternatives and to teach them how to properly dispose of plastic bags after use. A key event was organized for Earth Day 2010 in all the schools, and a guide to waste management was widely distributed at the event. The children not only participated in collecting plastic bags at nature sites and clean-up projects, but were also asked to pass on what they learned to friends and neighbours. | C8: TRUE | E8: FALSE
A9: 3083f5dee9e6201a9043b765d1c7c644 | B9: Dr Edward W Manning and T David Dougherty, 2000. The study (Lot 1 Research Capacity) was conducted by PA Government Services under the Caribbean Regional Sustainable Tourism Development Programme (CRSTDP), funded by the 8th European Development Fund (EDF), August 2006. See Reil G Cruz, 2006, 47pp. Also World Bank, Caribbean Country Management Unit, 2005. | C9: FALSE | D9: again not on monitoring | E9: TRUE
A10: 53a72b1c4248dc4bbce2a197b5573d72 | B10: The transformation process is necessarily long term. With governments elected for five years, there is an inherent tendency to postpone addressing long-term development issues that is all the more difficult in the context of a highly partisan political tradition that resists consensus over development strategies. Progress in mainstreaming the environmental dimension of sustainable development strategies has been slow. Such policies address cross-cutting issues, and in the Westminster system of sectoral portfolio ministerial responsibilities, such issues tend to fall between ministerial responsibilities. | C10: FALSE | D10: 12.1 maybe? though more on sustainability strategies in general and not on SCP specifically | E10: TRUE
A11: 7a0048449e06bdb2c71ac177c5ced3c1 | B11: A delicate balance has to be maintained and this is where voluntary initiatives such as the Global Sustainable Tourism Council (GTSC) certification scheme play a critical role: there is no confrontation since the industry has voluntarily agreed to follow norms which will not only meet but frequently exceed the requirements of the law. The recommendations are based on a list of 12 principles for sustainable tourism development. Typically the Sustainable Tourism Criteria established by the j Global Sustainable Tourism Council extend to measurable indicators I and an appraisal and certification scheme which is rapaidly gaining j acceptance by the accommodation sector. Laws pertaining to land use, access, waster disposal, I pollution control, minimum wages and the like exist in almost all | countries: occasionally, these are relaxed for the tourism indistury in some developing countries in an effort to attract foreign tourists and i investments in the industry. | C11: TRUE | E11: TRUE
A12: 483a4125e7fab32d4fcb2b5d1ffa00d2 | B12: The recommendations on waste and materials management are summarised in a box at the end of the chapter. More recently, building on its well-established track record in waste management, the government has been laying the groundwork to stimulate the transition towards a circular economy. This is defined as "an economic system that is predicated on the reusability of products and raw materials and the conservation of natural resources and that pursues the creation of value in each link in the system” (Ministry of Infrastructure and Environment, 2014a). | C12: TRUE | E12: TRUE
A13: 0bafd5e13fe32c31b5b4d9f7536c941d | B13: Some definition of technology is necessary- it should be 100% recyclable under readily available current technology. Cotton/polyester mixes, for example, can be more technically durable than pure cotton. This suggests that the 100% recyclable stamp would be more applicable to fast fashion and not recommended for textiles where lifetime is generally limited by technical strength rather than change in style or change in fit e.g. bed-linen. This would rule out linking to some of the information proposed in the provision - unless the regulation was to be changed. | C13: TRUE | E13: FALSE
A14: c8dbfdb5972aba5f9f4da67a683fee62 | B14: The framework also functions as a bridging mechanism between the narrowly construed MEAs pertaining to chemicals and waste, which include the Stockholm, Rotterdam, Basel, and Minamata Conventions. The Dubai Declaration, which expresses high-level political support forthe framework. The Overarching Policy Strategy (OPS), which contains the five key thematic objectives of SAICM: (1) risk reduction, (2) knowledge and information, (3) governance, (4) capacity-building and technical cooperation, and (5) illegal international traffic in chemicals. The OPS also lays down the scope, needs, underlying principles, and approaches of SAICM and elaborates on implementation and progress review mechanisms. The Global Plan of Action, which is an evolving and practical toolkit for implementation that currently lists more than 270 activities that can be undertaken by diverse stakeholders to operationalize SAICM. | C14: TRUE | E14: TRUE
A15: f83637f12da543fd9df8cb97ade0ef3c | B15: There are also examples at the national level. The Dutch Sustainable Growth Coalition, for example, unites the eighth largest big multinationals in shaping, sharing and stimulating sustainable business models. The changing role of business in society is also reflected in the increased participation by businesses in the discussions in various forums of the United Nations such as UN Global Compact, the development of the UN Sustainable Development Goals, as well as at international conferences such as the Rio+20 conference, which confirmed the importance of corporate sustainability reporting. When moving towards green growth requires a joint public private approach then there should also be more convergence between public and private measurement and reporting to follow the progress made to achieve the goals of green growth. | C15: TRUE | D15: csr reporting | E15: FALSE
A16: a218ee95081ac58f5a8c35f0fb15c302 | B16: The criteria for commitments are (1) advance one or more United Nations goal/issue, (2) include time-bound target(s) that can be measured for success, and (3) include an agreement to publicly disclose, on an annual basis, progress made to realize the commitment, throughout its duration. In all these areas issues related to innovation and collaboration were discussed. Available from http://www .unglobalcompact.org/docs/news_events/2012_CSF/Rio_CSF_Overview_Outcomes.pdf. | C16: FALSE | E16: FALSE
A17: 3c57594c5de7b481d01d64593f4e51cb | B17: Design-for-disassembly was formulated to promote the easy recovery of parts and materials during the product disassembly process, while design-for-environment called for minimizing pollution and promoting resource conservation during product or system design. In product life-cycle considerations, extended producer responsibility (EPR) may be realized in collaboration with intelligent consumer behaviour. The European Union (EU) and WBCSD have shifted the leading concept of a resource-circulating society from sustainable production and consumption in the 1990s to sustainable consumption and production in a “consumer society”. | C17: TRUE | E17: TRUE
A18: 2b1b85e4586716ccac4cfbab9226cc65 | B18: Both sugar and bananas have lost preferential access to their traditional European Union (EU) markets in the age of liberalisation of the global economy. In addition, with the frequency of hurricane damage increasing in recent years, it was decided to abandon the exports of bananas completely. The bauxite/ alumina industry all but shut down in 2008, when international demand plummeted in the global crisis that was precipitated by the financial crisis of that year. The current owners of the mines and processing facilities have demanded access to cheaper energy as the price for restarting the industry. This is one of the major drivers for the urgent transformation of the energy supply that has become a high priority for the Jamaican government. Forests were cleared, and the habitats they supported were destroyed, to establish the sugar industry in the seventeenth to the nineteenth centuries. | C18: TRUE | D18: links to sustainable resource management | E18: TRUE
A19: 9fef02dedda6d91de6e74e1d7d3baab2 | B19: It identifies opportunities and challenges for implementing SPP and provides guidance for governments in developing and implementing successful SPP programs. It saw reiteration in the Johannesburg Plan of Implementation in 2002 and more recently, at the 19m Session of the Commission on Sustainable Development in 2011. It forms part of the 10 year Framework of Programmes suggested at the recently concluded Summit in Rio in June 2012. | C19: TRUE | D19: sustainable public procurement | E19: TRUE
A20: 97c185a074f856c7e9768753e9b7046d | B20: Food losses are highest in North America and Oceania, reaching close to 300 kg per person. The focus would need to be on addressing the financial, managerial and technical limitations in harvesting techniques, as well as ensuring adequate storage and cooling facilities in often challenging climatic conditions. Quantifying postharvest losses in Sub-Saharan Africa with a focus on cereals and pulses Presentation at the Bellagio Workshop on Postharvest Management, 12-14 September 2017. International Food Policy Research Institute (IFPRI) has developed a methodology to improve the measurement of food losses across the value chain, as well as to factor in deterioration in quality that result in economic losses. | C20: TRUE | E20: TRUE
A21: 83a90deca523f0cfc53e97ed2921a6a6 | B21: The importance of considering products and services in terms of their complete lifecycle is introduced and explained. This remains the single most important of the Millennium Development Goals. Economic growth is thus of key importance to developing countries and many of their policymakers believe that developed countries, having already accomplished a high level of satisfaction of their needs, now wish to suggest frugality and restraint on consumption in the developing world. China, for instance, is now considered the "factory to the world”. | C21: TRUE | D21: resource use efficiency | E21: FALSE
A22: 549df2a4d76c942d8369308429752184 | B22: This term, however, is often used as a synonym for material productivity. Productivity measurement and analysis of natural resource and material flows complement the traditional indicators of capital, land and labour productivity. Used in parallel, these three types of productivity indicators afford a much deeper understanding of total factor productivity. | C22: FALSE | E22: TRUE
A23: 201aa211051c6d69b54de666dbd44994 | B23: The industry added USD 44 billion to the US GDP in 2015 and paid USD 10 billion in taxes (RFA, 2016). One strategy to ultimately reach the Renewable Fuels Standard (RFS) targets is to make stepwise improvements in the existing biorefinery concepts. These stepwise improvements must include a regional strategy that builds in enough flexibility to use the “cheapest sources of renewable carbon” within a given region. Such flexibility implies, for example, using grain sorghum, switchgrass, or miscanthus in the US Midwest, sweet sorghum or cane sugar in the US South, guayule bagasse in the US Southwest, almond hull sugars in California and even citrus peel waste in Florida. | C23: FALSE | E23: TRUE
A24: 55eb56bec1db9ca76b6d2aa3c09712e2 | B24: The World Bank estimates that out of the 500 largest cities in the developing countries, only 4% are deemed credit worthy in international capital markets and 20% on the local markets. Of the available funding over the last 10 years, two-thirds has gone to just 10 middle-income countries. Making the necessary investment finance available to those who need it most, in the low-income countries, is an urgent priority and a particular challenge. | C24: FALSE | E24: TRUE
A25: 2d147468df0200d5f90ff5d75bcadbe6 | B25: Against a backdrop of social issues, natural resource limits and waste problems, the question of how people live and consume - the lifestyles they pursue - becomes central to sustainability. The continuing increase in population in Asia, Africa and Latin America needs to sustain itself, in a fast growing economic environment, the level of material consumption per person also increases. For example, according to the African development Bank (AtDB 2011), there was a growth rate of 3.1% in the middle-class (defined as those consuming between 2-20 USD per day) in Africa, rising from 126 million people (27%) in 1980 to 350 million (34%) in 2010. | C25: TRUE | E25: FALSE
A26: 3b1add4085af6afe2ca52a55fc3fb5a9 | B26: In addition, the Major Groups and other Stakeholders (MGOS)21 group seeks to represent all sectors of society in international environmental and developmental policy-making. It appears that MGOS do not have an established position within SAICM, the representation of stakeholders is sectoral and the involvement of all major groups is not automatic - for example, organizations focused on promoting the rights of women, children, and indigenous peoples do not routinely participate in SAICM meetings. In 2015, the ICCM4, in its Resolution i/IV (para 5), called for the deepening and broadening of UN system-wide engagement through the work of IOMC and EMG. Furthermore, the WHO has been working with the SAICM Secretariat to provide a service to facilitate access to the Trust Fund, to establish an informal network of health-sector focal points for sharing experience, and to collect and share information on the capacity-building needs of the health sector (WHO 2010). | C26: FALSE | E26: TRUE
A27: 84e48d25391c7a7cda69d5f9fb25ee36 | B27: Complementing the theoretical approach outlined in the previous chapter, this chapter focuses on the practical and strategic side of implementation, considering the multiple dimensions of successful implementation. Effective policies therefore often have to be developed in collaboration between line ministries. It is important to have effective mechanisms in place to support such collaboration. | C27: FALSE | E27: TRUE
A28: 197c9502970d6583f6f3e33dceb5550f | B28: Having been conceived, tested and refined in Dhaka, the IRRC approach was found to be robustly suited to the realities of low and middle-income cities. Under this project, ESCAP and Waste Concern, in partnership with national and local governments, community groups and technical teams, promoted the IRRC model in 17 cities, ultimately establishing facilities and pursuing associated activities in seven of them (Figure 4). The centre is a small-scale facility that can receive different types of waste, including organic and inorganic waste, and then transform it all into resources, such as compost, biogas and other fuels and clean recyclable material. | C28: TRUE | D28: irrc = integrated resource recovery centre | E28: TRUE
A29: c2f4320ebfc7a98e97162886129820b2 | B29: As an industry, it often competes for prime real estate and juxtaposes visitors with different cultural practices and values to host communities, with consequent negative influences. Their economies and progress in development have been the subject of intense scrutiny, as a result of limitations in topographic character, vulnerability to natural disasters, climate changes and related impacts, threats to biological diversity, especially in coastal and marine areas, consumption of scarce natural resources, declining traditional productive sectors, poverty, and their reliance on the travel and tourism industry for economic performance. Large island nations comprising Papua New Guinea, Cuba, Hispaniola (Haiti and the Dominican Republic), Guinea Bissau and those located in Central/South America (Suriname, Guyana, Belize) make up the SIDS grouping with geographic areas in excess of 25,000 km2. There is significant variability in GDP per capita, as indicated in figure 8.3, with many of the more developed tourist economies such as Aruba, Singapore, US Virgin Islands (USVI) and the Bahamas, showing higher levels of prosperity. | C29: FALSE | E29: FALSE
A30: dfd51e36b47fe8a10fdd1d789001501e | B30: Commercial waste, street sweepings and ash were not included in this analysis. These show comparable results, differing only in metals fraction, because the EcoPark study also included waste separation and recycling data. Construction waste is normally found in MSW in a share lower than 1 or 2 per cent, therefore, it was excluded from data reported by Batbileg et al. | C30: FALSE | D30: just data reporting | E30: TRUE
A31: 62694a749fb81e3268ea0ffba0de1e95 | B31: The ways in which the tourists value different aspects of the surroundings are also influenced by experiences made during the visit. To the extent that information, interpretation and education do not have a sufficient influence on peoples' actual behaviour, co-creation initiatives are proposed as a more efficient way of transferring responsibility to visitors (Campos, Mendes, Valle, and Scott, 2015, Prebensen, Vitterso, and Dahl, 2013). Co-creation implies that the tourists participate in the design, production and consumption of an experience, even collaborating in the creation of new products and services (Binkhorst and Dekker, 2009). | C31: FALSE | D31: not on monitoring tools for tourism | E31: TRUE
A32: 1cd8c5958dad8616aabc4fa432b5ead7 | B32: For material flows and waste there are still unresolved conceptual issues and establishing indicators requires a lot of effort, if they are based on a national physical input-output table showing interdependencies among sectors in physical flows. We have employed sectoral footprints to show the natural resource use per expenditure in sectors. Footprint accounts deliver sectoral disaggregation by expenditure categories for products of major sectors. | C32: TO DO | E32: FALSE
A33: 18900ef1e2742e858bbed6264b3a046c | B33: It is therefore evident that current patterns of consumption and production are environmentally unsustainable and socially inequitable. Economic growth, human development and wellbeing would need to be substantially decoupled from resource use and environmental impact (UNEP, 2011). Achieving gains in decoupling will not happen spontaneously, but will require well designed public policies that enable economic restructuring toward sustainable consumption and production and resource efficiency. | C33: TRUE | E33: TRUE
A34: 759b95e2698c40e89242d61169ef6b4d | B34: We have not been able to get a clear answer from the responsible person at Teijin, and in the basic scenario it was therefore chosen to use a conservative approach, assuming a low yield of the process. For climate change, the increased efficiency means that there is a net benefit instead of an impact. The same finding is seen for human toxicity, cancer effects. | C34: FALSE | E34: FALSE
A35: 1f90c5a8981fc4c095f70aea892ff94e | B35: Based on 2011 data, generation is above average in the Capital area at 460 kg/cap/y, and in the coastal region influenced by tourism at 480 kg/cap/y, although excluding the impact of tourists the average is 420 kg/cap/y. The remaining inland region shows under-average waste generation, at only 223 kg/cap/y. The reason for such a high variation in per capita waste generation at county level could be because the impact of the non-permanent tourist population is not considered in the calculation of this indicator. | C35: TRUE | E35: TRUE
A36: 4da053336ea3efd2695efd580c54584b | B36: It contributes 8.4 per cent to global employment (238 million jobs)1 and is projected to grow at an average of 4 per cent over the next decade. Rising per capita incomes and the operation of competitive low-cost airlines have also contributed to this increase. China is particularly significant as it alone is expected to contribute 100 million travellers.4 All indications are that in spite of a downturn in the global economy beginning in 2008 due to the global financial crisis, the travel and tourism industry is robust enough to withstand these pressures over the next decade. Depending upon the sophistication of the industry in terms of the solidity of its linkages and supply chains, some destinations are likely to recover more quickly than others. | C36: FALSE | E36: FALSE
A37: ad30b568778b199cdbabb1a10d691944 | B37: It is often difficult to see from the statistics if this waste is included. Due to new EU - regulations this system no longer exists (withdrawn in 2003). The newest data is therefore from 2001 when it was collected 21,000 tons of food waste. The system of separate collection of food waste included commercial kitchens that generated more than 100 kg / week. Smaller kitchens and kitchens in cost sector were not covered by the collection scheme. | C37: FALSE | D37: data reporting only | E37: FALSE
A38: 703dd858d96d671944d27c5a06867a10 | B38: The indicator has an indirect relevance to food waste prevention since the more food waste that is avoided the lower should be the amount of food that is purchased for consumption to provide for the same intake of nutrients. It should be noted that the indicator is only relevant to reducing food waste at the end point of consum p-tion i.e. in households, restaurants canteens etc. However, the indicator can be affected by factors which are unrelated to waste prevention. These can include changes in food consumption behaviour-i.e. However, the indicator has been criticised in the past due to assumptions made in the calculations. Its acceptability as a food waste indicator might also be reduced as it has not been used in this context before. | C38: FALSE | D38: on data only | E38: FALSE
A39: 8b7a84a06c90ba7a095b0307ada9a5f2 | B39: Additional documentation is required in an application for mineral water use. The issuance of the permit itself, and the signing of a contract with the water user, is done by the State-owned enterprise, Mongol Us ("Mongolian Water"). In the case of the utilization of water for strategically important minerals, the duration of the water use permit is the same as for the exploitation licence. | C39: FALSE | D39: though vaguely linked to natural resource management (but without any notion of sustainable use) | E39: FALSE
A40: e4ff2d35f08d2d1acc0d03aa9df6f4b9 | B40: These challenges include issues of ownership, economic leakage (from the local economy and through imports), local employment, benefit distribution, social and environmental impacts and dependency. These problems can only be effectively addressed at the destination level with the active participation of the local communities. It summarises by stating that "The effective development, execution and management of a successful pro-poor tourism strategy reaches far beyond local communities”. | C40: FALSE | D40: again not on monitoring | E40: FALSE
A41: 062372c7882af8f7bb84943024eb6a2c | B41: Its mandate is two-fold: to promote energy security amongst its member countries through collective response to physical disruptions in oil supply and to advise member countries on sound energy policy. This paper reflects the views of the IEA Secretariat and may not necessarily reflect the views of the individual IEA member countries. The study also draws on contributions of Franziska Mueller-Langer, Jens Giersdorf and Anastasios Perimenis of the German Biomass Research Centre (DBFZ), who provided parts of the sustainability chapter and four country profiles commissioned by the Deutsche Gesellschaft fiir Technische Zusammenarbeit (GTZ). | C41: FALSE | E41: FALSE
A42: 88220c7fe94cff6b5a90c20459c70000 | B42: In recent years, significant improvements in the assessment methodologies have been made in an effort mostly co-ordinated by the UNEP/ SETAC initiative (de Haes, 2002, UNEP, 2003, Jolliet et al., The EU Joint Research Centre has also made an important input in the determination of effective practice in impact assessment, which has resulted in the adoption of 14 default impact categories for the EU footprinting initiative (Product Environmental Footprint (PEF)/ Organisational Environmental Footprint (OEF), European Commission, 2013a, European Commission, 2013b). | C42: TRUE | E42: TRUE
A43: 4305276298bfe07e216b55b3e150ff68 | B43: For the last one a comply or explain principle is in use. To enable readers to find the particular sustainability information in the report, GRI is using a mandatory content index table that informs the reader on what page the disclosures or the indicator can be found. The Guidelines of the IIRC are currently in development and will be released as draft in April 2013 and finalized by the end of 2013. | C43: TRUE | E43: TRUE
A44: 37a02127ec1fb10fd005080ea6671271 | B44: Many countries have modernised their societies and economies enabling the greatest level of material wellbeing ever experienced. These changes were most prevalent in OECD countries and in urban centres in developing countries. The use of natural resources -biomass, fossil fuels, ores, minerals and water - has grown dramatically from less than 10 billion tonnes in 1950 to over 70 billion tonnes in 2010 (UNEP, 2011). This level of resource use was largely based on the assumption of limitless resources and overlooked the connections between resource use and environmental impacts. | C44: TRUE | E44: TRUE
A45: 86236555aba7f7bec5e1aed8f189e77a | B45: At local level, the main partners have been the collaboration of local food producers, R0rosmat as well as the R0ros Museum and World Heritage and local businesses. Destination Roros is currently (spring 2016) undergoing the recertification process. Additionally, the goal is to encourage even more companies to apply for an environmental certificate and to train more people. | C45: TRUE | E45: TRUE
A46: ca472909daa94e1ce61c174548d7198d | B46: Jamaica has a small but active group of ENGOs that are advocates for the green economy. Some of their voices have acquired national recognition and respect, and can no longer be ignored by policy-makers. Since the Earth Summit in 1992, there have been several civil society organisations12 that have kept the pressure on the Government of Jamaica to honour its commitments to sustainable development in general, and to the various multilateral environmental agreements. | C46: TO DO | E46: FALSE
A47: f17f196c4431d28aeac6205c78ddb847 | B47: The statement was welcomed by the Advisory Group. During the intersessional period, discussion continued on whether sustainability reporting and core indicators should be used at a corporate consolidated level or at a legal entity level. Given that the impact of companies is realized at the local level, some experts argue that data should be provided by a legal entity of a home country. However, it is also important to consider that group-level consolidated sustainability reporting is critical as a means to align corporate behaviour and business models with the 2030 Agenda. Consolidated reporting is also a basis for financial decision-making by investors. | C47: TRUE | E47: TRUE
A48: e63e24fa452209fc8000bc37d582ff2c | B48: Policy principles and objectives have been established, municipalities are required to prepare Integrated Solid Waste Management Plans and technical regulations and guidelines have been issued. However, the policies and action plans that were developed in parallel to address waste issues at national, regional and municipal levels do not provide comprehensive and consistent guidance. As a consequence, opportunities to increase the environmental effectiveness and economic efficiency of waste policies (by developing an efficient waste infrastructure network, for example) remain unexploited. Positive policy developments include the 2010 Policy on Sustainable Production and Consumption, efforts to promote cleaner production, an ambitious policy on extended producer responsibility (EPR) and attempts to establish green public purchasing. | C48: TO DO | E48: FALSE
A49: cd39a832a230705ef131f4d8b858f65f | B49: Once among the least developed Western economies, with high levels of emigration, since 2003 Ireland has enjoyed the third highest per capita GDP in OECD Europe (Figure 6.1).1 The growing economy attracted an inflow of foreign workers, the unemployment rate was 4.7% in 2007, below the OECD average. In the first half of the 2000s, large public sector deficits were transformed into substantial surpluses and the ratio of national debt to GNP was greatly reduced, while the tax-to-GDP ratio remained low (31.9% of GDP in 2006, compared with an OECD Europe average of 38%). The combination of a low corporate tax (12.5%), state grants and access to the European single market boosted foreign direct investment. | C49: FALSE | E49: TRUE
A50: f25d81a6f6dd57b990eb23725cf894a1 | B50: Today, the dominant research on the effect of the educational systems and approaches related to sustainable development clearly favours impact on the individuals (as opposed to organisations and communities) and formal education (as opposed to non-formal and informal learning). In the modern world characterised by accelerated changes, lack of predictability and multiple economic, financial and environmental crises, different forms of knowledge and learning become a necessity. Even sectors that for a long time adhered to traditional ways of doing things, find themselves in need to adapt to the constant demand for (at least partial) transformation. | C50: FALSE | D50: somehow on awareness and sustainable lifestyles but not so clear | E50: TRUE
A51: c4fd5fb66459273c5dc10c4de4266f85 | B51: Its mandate is to foster cooperation between its 53 members and 9 associate members. It supports Governments of the region in consolidating regional positions and advocates regional approaches to meeting the region's unique socio-economic challenges in a globalizing world. The ESCAP head office is located in Bangkok, Thailand, with subregional offices in Almaty, Kazakhstan, Incheon, Republic of Korea, New Delhi, India, and Suva, Fiji. Please visit our website at <www.unescap.org> for further information. | C51: FALSE | E51: FALSE
A52: 642f69433572aed4342a2026f0513b5b | B52: If an EIA is carried out, but improperly and leading to environmental damage, the licensed EIA entity must pay compensation. There is also a mismatch between the economic value for animals, their conservation status and their market value (chapter 3). The 2012 Law on Hunting, for example, foresees a reward of 15 per cent of fines imposed to be given to the citizen identifying the person responsible for the violation. | C52: FALSE | E52: TRUE
A53: 1365feccc61adc4814c64ff7d9303893 | B53: Further extending the green purchasing requirements to local governments would enhance the effectiveness of the policy, in particular since a large share of public expenditure is invested locally. In expanding its green purchasing policy, the government should make sure that it targets goods and services with the highest potential environmental returns. This outcome was achieved with minor increases in public expenditure. Since the introduction of the green public procurement policy, the market shares of eco-friendly products widely used in the public administration have substantially increased (Figure 9). According to MOE’s estimates, the national government’s green purchasing policy resulted in a reduction of C02 emissions by 89 500 tonnes in 2006, which is equivalent to the amount of C02 emitted by a town of 42 000 inhabitants. The financial implications of Japan’s green public procurement policy and the overall costs to the Japanese economy of achieving such emission reductions should be assessed and compared with the costs of alternative policy measures. | C53: TRUE | D53: on green public procuremnt | E53: FALSE
A54: 64aced7c4d814e32f8a3cfe50ddd81c9 | B54: These are primarily wind, solar, hydro, biofuels and co-generation. In addition, governments have partnered with private sector and civil society organisations to support small and microenterprises with training and concessionary financing. The annual budget is Jamaica’s short-term plan. There is also a rolling three-year Medium Term Social and Economic Policy Framework, and an annually revised three-year macroeconomic plan, which frames the annual budget. In theory, all of these should be aligned with one another within the long-term plan, Vision 2030. In addition, there are ongoing initiatives to prepare parish plans under the Local Sustainable Development Plans, which also ought to be aligned to the national plans. | C54: FALSE | E54: FALSE
A55: a5de8ccef9a812d9b5c7cb312fee108f | B55: Part b) on measures taken before a product has become waste, that reduce the adverse impacts of the eventually generated waste on the environment and health also has some importance. Here though the focus should be on initiatives which reduce upstream environmental impacts caused by food waste rather than downstream impacts. This can be done for example through initiatives which reduce the share of products in food waste which cause a particularly high environmental impact during their production phase. Meat and dairy products are a prime example. The more edible food waste that is avoided in an economy, the less food production that is required to feed the population, with an accompanying reduction in environmental impacts caused during food production. | C55: TRUE | E55: FALSE
A56: 5e9b3bcf4aac69ed3ef73cbca12ee72b | B56: For each of these topics different indicators have been developed and the indicator protocols include definitions and the way the data need to be compiled, as well as further references. To measure for example the CO2 emissions the indicator protocol refers to Green House Gas measurement protocol of the WBCSD/World Resource Institute. The information that is reported in a sustainability report according to the GRI guidelines does not only include quantitative indicators but also provides information on the strategy, the organizational profile, the governance processes, the stakeholder engagement processes and the management approach. This information is relevant to obtain the context in which the data are provided. Each organization has a different ambition level and specific sustainability issues and therefore reporting is different for different organizations. The topics and indicators to report on are based on a materiality analysis that the company performs. | C56: TRUE | E56: FALSE
A57: 08ee208db6cafa5ea057212223ece39c | B57: One legacy of that programme was the establishment of the Programme of Advancement through Health and Education (PATH), a conditional cash transfer programme that now constitutes the core of the social safety net. Advocacy has been initiated by scientists and their students in the Climate Studies Group of the Department of Physics at the University of the West Indies (UWI), individual scholars in the Faculty of Social Sciences, the Centre for Sustainable Development at UWI, as well as by various ENGOs. Some of the research and the outreach based on this work have been funded by the Caribbean Community Climate Change Centre (CCCCC) and the Environmental Foundation of Jamaica (EFJ). | C57: FALSE | E57: TRUE
A58: 54b2538e906a8d503d9a71159d1d36ca | B58: It also prepares technical documentation related to chemical safety that can be downloaded from its website. The documentation includes government manuals, SDS and information on the GHS and other UN initiatives. There are ten ARLs - effectively insurance companies that cover workplace injuries and illnesses, each with a different focus. | C58: TRUE | E58: TRUE
A59: 9b3e0c684586646ce9eed8a9821e0b59 | B59: It takes stock of policy initiatives to reduce waste generation, encourage recycling and ensure safe disposal of municipal and hazardous waste. The chapter also highlights progress in integrating informal waste pickers into municipal waste management. It discusses the environmental and economic implications of specific measures, such as extended producer responsibility and waste collection charges. National, regional and local authorities have well-defined responsibilities in waste management. | C59: TRUE | E59: TRUE
A60: b877f11b0df84d337b544b552a684afd | B60: In their comprehensive analysis of revenue management of Scottish tourism attractions, Leask et al. ( Including stakeholders is therefore often perceived from governmental perspectives as an obstacle to efficient planning. Conflict resolution, meditation and the building of a consensus about shared platforms should nevertheless be seen an integral component of sustainable tourism development and planning (Hall, 2008, McCool, 2009). In other words, tourism should be considered in the context of other systems that interact with tourism (Ritchie and Crouch, 2003). | C60: FALSE | D60: no monitoring tools | E60: FALSE
A61: 13da70ac3a8ad54df495da6e6bf5bf08 | B61: Children and youth in cities”, in ISSC/UNESCO, World Social Science Report 2013: Changing Global Environments, OECD Publishing and Unesco Publishing. Each author is responsible for the facts contained in his/her article and the opinions expressed therein, which are not necessarily those of UNESCO, ISSC and do not commit either organisation. | C61: FALSE | E61: TRUE
A62: 989a430a480dfb2df0c37dd028d91db8 | B62: On another note, it is questionable whether there is even a need for a new scientific body for SAICM. As long as there are no legally binding obligations for states under SAICM, a scientific expert panel may not be needed. According to this view, the recommendations that SAICM provides could well be created without such a body. | C62: TRUE | D62: SAICM strategic approach on integrated chemical management | E62: FALSE
A63: 8bfce44dab94a2b5fedbbd3adae56749 | B63: This refers to the manufacture, use and disposal of lifestyle goods such as electronics and clothing. Key sectors of high impact include food, housing and transport. In these sectors, wafer, energy and waste can be considered as crosscutting sectors affecting and affected by almost every lifestyle domain. | C63: TRUE | E63: TRUE
A64: 8928aa79bf65a8ea8b41802634887e4c | B64: There are estimated to be 500 international treaties and agreements on the environment (155 biodiversity-related, 179 chemicals-related, 46 land-related, and 196 water-related) and a proliferation of subsidiary bodies for the different conventions and administrative arrangements. Additionally, important are leveraging synergies in responsibilities of conventions across various sectoral policies, with the promotion of joint implementation and coordination of funding sources and programmes, as well as multi-stakeholder outreach and engagement to ensure buy-in.5 Capacity building is required given the increasingly complex scientific and technical issues involved. Meanwhile, critical actions may not be taken with fallout for human and environmental health. | C64: TRUE | D64: not fully convinced though | E64: TRUE
A65: 17a9f0d1e3733dac32f98dd1b6ee7ae0 | B65: Owing to success of the first phase, UNU and Shimadzu agreed to continue the project, establishing the second phase in 1999. In continuation of the previous project, the same research group in each country was kept as partner and national implementation unit. The Philippines joined the project at the beginning of the second phase. The three components were closely linked together and implemented through collaboration of the UNU network on coastal issues. | C65: FALSE | D65: not clear what project is about | E65: TRUE
A66: ad6accc9d24e23b3e302de529a942889 | B66: Policy instruments based on EPR can also be designed to drive eco-design at the beginning of the product lifecycle. However, if the instruments are focused only on improved recycling without driving initial eco-design, EPR may not generate the desired economic and environmental efficiencies (Tojo, N., 2004). Outcomes from economic incentives alone, however, may not be sufficient to generate environmentally or socially meaningful results, because actors generally stop making improvements once the economic incentive to do so ends, whether or not sufficient social or environmental progress has been made. Examples of economic mechanisms employed by OECD governments include also disincentives such as increased fees on waste disposal, and incentives such as government procurement policies and a potential reduction in the value added tax (VAT) and tax for environmentally friendly products (all promoted by the government of the Czech Republic, among others). | C66: TRUE | E66: FALSE
A67: a941f19e7545ea877b4b9510f0be6a63 | B67: In 2014, the System was extended to include a dedicated web portal. This cadastre provides public access to the processes of issuing and reissuing of licences, licence revocation, transfer, pledge and surrender for the entire or a part of the licensed area, as well as to maintaining a register of licences. One of the main objectives of this tool is to prevent licences from overlapping other licences or protected areas. | C67: FALSE | D67: not clear what licenses | E67: TRUE
A68: e459110a0e5288867d180b786d5e620a | B68: Topics that have both an impact on the organization as well as on its stakeholders are the most material and therefore are discussed in more depth in the sustainability report. Once these topics are selected the company can identify the related indicators and use the GRI protocols to measure the data. Currently the GRI has three application levels, differing from reporting on 10 indicators with particular context information (Level C) to reporting on all material indicators (Level A). | C68: TRUE | E68: FALSE
A69: 1b8a501a7bbb0802fa4a05da3a8cd65a | B69: At the same time internal transparency through environmental management accounting started to increase with a business rationale to improve efficiency and reduce costs, in relation to using natural resources, reducing emissions to air, water and soil, as well as in reducing waste. More recently companies increasingly see the relevance of sustainability for their long term business continuity and identify sustainability challenges as a business growth driver. They even transform their business to address such business opportunities. The company, DSM, active in health, nutrition and materials, for example, is not only changing from a chemical company to bio-based solutions, but also focuses its business activities much more on nutrition, as this will be a major global challenge. | C69: TRUE | E69: FALSE
A70: 78906f21b8873984506469c09306a3e3 | B70: The varied relief has resulted in several distinct climatic regimes, with the prevailing south-east trade winds depositing moisture in the form of rainfall over the central and highest part of the island. A significant feature of Mauritian climatology, however, is the occurrence of tropical cyclones during the summer months. Almost 300 endemic species have been identified, of which the most famous was the Dodo, a large flightless bird now extinct. Permanent human settlement started in the fifteenth century and, ever since, the environment has come under severe threat as its few precious resources (such as ebony) have been exploited indiscriminately. | C70: FALSE | E70: FALSE
A71: d679f7406fda45349991085239143a4e | B71: Good corporate governance makes for good business for all. Good corporate governance helps reduce the risks that smaller firms may face as well. At the other end of the spectrum, cases of corporate malfeasance in state-owned enterprises illustrate that regardless of size or ownership, good corporate governance is critical. | C71: FALSE | D71: good corporate governance does not necessarily mean ESG or CSR | E71: TRUE
A72: ce798611bb26ebcb1fd0887f02a72387 | B72: Some of the chemical applications to control weeds and pests on the plantations have run off from rain into the rivers and transferred to the inshore, especially the main harbour in Kingston. In other cases, chemicals have soaked through the soil into underground aquifers. This is particularly true of the acidic waste from the processing of bauxite ore, which is deposited in lakes of red mud. | C72: TRUE | E72: FALSE
A73: 4d5ac9213ea93621546badea52220286 | B73: The project investigates the possibility for using policy actions to support and expand the market for waste plastics in the Nordic region. This has the objective of increasing the recycling of plastics and minimising the down-cycling and incineration of plastic waste. Separately collecting and recycling this plastic waste would have significant economic and environmental benefits. For example, recovering and recycling half of the plastic waste generated in the Nordic countries corresponds roughly to a reduction of greenhouse gas emissions equivalent to the total emissions from cars in the Nordic capitals. | C73: TRUE | E73: TRUE
A74: 34b4f1f3f5ea4fe7b006371c5ed60765 | B74: During the latter two decades, protected areas have gradually become more closely connected to their economic and social environments, with an emphasisto integrate national parksto wider regional and local development processes (see e.g. Puhakka and Saarinen (2013). In peripheries, closer connections between the tourism industry and national parks are used as tools. While the original biocentric conservation policy used to be characterized by top-down governance, stakeholders of the local communities and the tourism industry are today increasingly involved in adaptive management strategies. During the last three decades, international tourist arrivals to Iceland have generally increased, including by 25% over the past six years. The number of international visitors to Iceland was approximately 2.3 million in 2017, which is almost seven times more than the entire Icelandic population. Tourism is now one of the main pillars of the economy and represents the country's largest export sector. | C74: FALSE | E74: FALSE
A75: 0b4a31dd0bc5b9cb6a3da2b48eb54401 | B75: As a result, poverty is endemic, generously underestimated at 20 per cent of the population in 2011, with the majority of poor households located in rural communities. It is well known that poor communities generate negative pressure on the environment from ‘slash-and-burn’ agricultural activities, improper waste disposal for want of facilities, and settlement on fragile lands that are vulnerable to natural hazards. In the case of Jamaica, there are the additional challenges of servicing the mounting national debt, which in 2013 stood at over 140 per cent of GDP, and ensuring macroeconomic stability so as to provide a basis for economic growth. | C75: TRUE | E75: TRUE
A76: 6f18255d6435f943053c754e2ff406e0 | B76: While this may or may not lead to a net increase in employment, it will change the skill profile of the workforce. Governments should therefore assess new job skill requirements and adjust education and training programmes accordingly. This could help to co-ordinate efforts by engaging key stakeholders, to monitor progress, and generally to provide the political impetus needed to achieve ambitious policy objectives. | C76: FALSE | E76: FALSE
A77: 0342980e48fbffd359a20628d9450485 | B77: Mauritius covers a total land area of 720 square miles, and is almost entirely of volcanic origin, except for stretches of beaches, coral reefs and small patches of alluvium at the mouths of rivers. Pear-shaped, mountainous with its highest peak standing at 2,711 feet above sea level, Mauritius emerged from the ocean floor some 5 million years ago. Volcanic activity over thousands of years has given rise to varied types of soil. | C77: FALSE | E77: FALSE
A78: 039e770089eb0cbfb193a3ae3fadb893 | B78: International donors increased their involvement in waste management during the last few years and this resulted in improvements in management of obsolete pesticides and expired chemicals, but management of municipal and manufacturing waste is developing slowly and old practices remain. This development reduced generated amounts of waste and in some sectors also decreased the amount of waste previously accumulated. The development of modem waste management infrastructure is still in the initial phase. | C78: TRUE | E78: TRUE
A79: fe00789e13ec56b1624f016c682abea0 | B79: Such information is provided in the form of quantitative and qualitative data as part of a company’s reporting process. Key performance indicators comprise the quantitative data, an example of qualitative data can be found in the description of a company’s sustainability strategies and reporting policies. Examples include the portal of the Government of France (info-financiere. | C79: TRUE | E79: TRUE
A80: 2247ea809c4b3069265b106b3819af19 | B80: However, both face a number of challenges in implementation including the establishment 0/effective targets. The purpose of this chapter is to explore the opportunities, challenges and important considerations faced by policy makers when setting and implementing SMM-related targets. Finland attributes waste management improvements to changes in EU legislation, specifically stricter waste management standards and requirements. | C80: TRUE | E80: TRUE
A81: 78625638c482b151a88161b2f6e4894f | B81: Resource efficiency can be achieved by increasing resource productivity (value added / resource use) or reducing resource intensity (resource use / value added). It is related to strategies like dematerialisation, such as fuel efficient cars. It will be clear that no production can be said to be sustainable if it is profligate in the use of resources, thus there is a direct link between resource efficiency and SCP, particularly sustainable production. | C81: TRUE | E81: TRUE
A82: e9c0953d695ff92ee3c092d3b13b280c | B82: This increase can be caused by both an actual increase in waste generation and by improved monitoring of collected waste amounts. The average MSW composition was derived from analyses in Minsk, Gomel, Mogilev, Bobruisk and Polotsk (table 6.2). Also, analysis of waste composition was performed in Minsk Oblast in 2013. | C82: TRUE | E82: FALSE
A83: a287d825bd346605da1b8e5017d13524 | B83: The initiative engaging the manufacturer, Grameen Bank, National Building Research Organization and vulnerable families encourages the use of local sustainable building materials, quality durable construction and livelihood considerations such as including shop fronts in the houses. The initiative required a high degree of informal collaborative learning and training. Learning occurs at both the level of the community, as well as within the company, where lessons of Mexican success are explored to be translated across other regions. | C83: TRUE | E83: TRUE
... A86: 3174e5f65fdec525ecf8be88f1898329 | B86: These coverage percentages may be compared with the over 30 per cent of land covered by exploration licences in 2008 and the current aim of raising it again to 20 per cent. The Ministry estimates that about 30 per cent of the licensed area is being used, with the remainder idle because of low commodity prices, poor infrastructure or the risk of environmental impact. The number of licences for oil and gas and radioactive minerals is two orders of magnitude lower. Such permits are issued by soum and district governors based on the conclusions of NAMEM’s departments at local level. | C86: TRUE | E86: FALSE
A87: 4e9eb663a8c64d8e3cabfe7e4b87d7d0 | B87: In this sense, it was based on natural resources that were transformed into cement using energy-intensive processes. Again, the viability of this industry assumed cheap energy supplies. Demand for middle-class housing, hotels and physical infrastructure drove the rapid expansion of the construction sector in the 1950s and 1960s. The supply of housing and hotels was also dependent on imported building materials and construction equipment. | C87: FALSE | D87: on resource use, though unsustainable and no notion of trying to improve it | E87: TRUE
A88: 175fad9c8b9dcce44c7cc98b032d07e1 | B88: Importantly, the IUCN works through specialist commissions that provide the Union with information and know-how. All the members of the IUCN together agree on, for example, the work programme of the organization. This would mean conducting studies and developing new policy recommendations or instruments based on the latest scientific findings. In addition, the IUCN governance structure could be used as a partial model for the post-2020 chemicals and waste management regime: the ICCM acts as the general assembly of members, and a governing council could be established to work under the direction and monitoring of the ICCM. | C88: TRUE | D88: though no direct notion to improve chemicals or waste management | E88: TRUE
A89: f0d7085f21c4e88d7448e29c10b34cee | B89: This trend has been boosted by market liberalization and augmented by convergence, new technologies and resultant innovations such as mobile phones which continue to be the most rapidly adopted technology in history. While sector growth has been experienced worldwide, the impact has been exponential in developing countries. Today the mobile phone is the most popular and widespread personal communication technology on the planet, with an estimated average subscription world rate of 87 per 100 inhabitants in 20111. | C89: FALSE | E89: TRUE
A90: fbb0aeba3247a1150aba110cad18dd81 | B90: There are several forms of capacity building where governments and the private sector can contribute: technical assistance, research for responsible business practices, development of training manuals and guidebooks, development of regional support hubs and the strengthening of the Global Compact local networks. They can also encourage and facilitate communications among key stakeholders for developing and implementing SRB initiatives. A strong dialogue about SRB must be encouraged amongst stakeholders, such as governments, corporations, financial institutions, NGOs and CSOs, for their capacity building. | C90: TRUE | E90: TRUE
A91: 89ca4fa4c89388e266f44db315cd78d8 | B91: The statement was made in 1972, long before the world became conscious of acceleration in anthropogenic GHG emissions. Nevertheless, Mrs Gandhi’s statement was one of the earliest to create a direct link between environmental concerns and poverty alleviation. Neither can the poor be held responsible for the major part of the GHG emissions. | C91: FALSE | E91: TRUE
A92: f3e26c31fc440748f4dacd18dbecbc65 | B92: They were first identified and defined by the ESCAP Sustainable Business Network (ESBN) Task Force on Banking and Finance.55 These principles are constituent components of the SRB model (Figure 6). They establish strong ethical guidelines so that business practices meet globally accepted standards for the valuing and pricing of products, sen/ices and assets, engaging with stakeholders, and assessing and managing risks. Each principle is defined, and its role in the SRB Model for a Sustainable Future explained. | C92: TRUE | E92: TRUE
A93: fa745ce3576ef1930376e33760b5d835 | B93: It can provide better recreational and cultural facilities but also create overcrowding, traffic congestion, litter, vandalism and crime (UNESCAP 2003). Started as the World Tourism Organisation in 1970 when its statutes were adopted, it became a working entity in 1975 with Headquarters in Madrid and joined the UN system in 2003, becoming known as UNWTO. Following the recommendations of the Johannesburg Plan of Implementation (JPOI) that “developed countries must take the lead" in accelerating the shift towards more sustainable consumption and production, each of the Marrakech Task Forces was chaired by a developed country. | C93: TRUE | E93: TRUE
A94: 6f4ffd29a57cb6598908ad274d7dfdaa | B94: Not to act is no longer an option. And I was encouraged by the sense of reality shown by the G8-leaders a few weeks ago, when they talked about a 50% cut in global emissions by 2050. It bodes well for the Conference of the Parties to be held in Copenhagen in 2009, where we will work hard to reach a global deal beyond Kyoto. | C94: FALSE | E94: TRUE
A95: 43db05d16c51cafb451321dbca30d967 | B95: This huge increase alone speaks of amazing achievements in terms of ICT access and bridging the digital divide. This interpretation, however, would be very narrow as the factors leading to ICT access are bound to interact with the environments in which they operate. In this case, a critical analysis of mobile subscriptions by level of development should trigger alarm bells as the sharp increase in ICT access is inordinately skewed towards developing countries as illustrated in figure 9.2. | C95: FALSE | E95: TRUE
A96: 5a35e4bb86235463eff5866e9ee79739 | B96: More sustainable alternatives should be available and easily accessible, as well as suitable infrastructure to make it easier to practice sustainable behaviour. Even well-intended people cannot live sustainably if there are no sustainable products and alternatives available. These could include peer pressure, putting more taxes on unsustainable options and funding more sustainable practices. For example by providing input to policy design, in expressing what is meaningful to them and what they care about in real life and in society, in understanding the advantages and disadvantages of certain behavioural patterns. | C96: TRUE | E96: FALSE
A97: ce542ae33bf4f70a34b8641eaac2e4d0 | B97: Previous studies, of wildlife crime, have revealed some variation of sentencing across the country, in different aimags, but, generally speaking, limits on data availability prevent a thorough comparison. For example, a mining licence can be revoked for failure to adopt an EMP, comply with such a plan or submit compliance reports. The former data set provides information on the location, date of detection, type of crime or infringement, classification of the offence and status of the procedure (e.g. whether transferred to the prosecutor’s office with a recommendation to prosecute). The latter data set provides information on damage and on items seized. Information is not available on the outcome of prosecution, including sentencing. Figure 2.5 shows the evolution of criminal law violations over the period 2011-2016 with the data appearing to be incomplete in the period 2009-2010. | C97: FALSE | D97: wildlife crimes | E97: TRUE
A98: 57946c8dba1a1a85b2078da67f09fea7 | B98: Refrain from seeking or accepting exemptions not contemplated in the statutory or regulatory framework related to human rights, environmental, health, safety, labour, taxation, financial incentives, or other issues. Support and uphold good corporate governance principles and develop and apply good corporate governance practices, including throughout enterprise groups. Develop and apply effective self-regulatory practices and management systems that foster a relationship of confidence and mutual trust between enterprises and the societies in which they operate. | C98: FALSE | D98: mentions environmental health only marginally and not really a clear link to SCP | E98: TRUE
A99: 293bd72b65dfbb4252d5df5ee43dee5a | B99: Indicators can go beyond simple data and illustrate trends or cause-and-effect relationships between different phenomena. Indicators are useful for describing baseline and current conditions (e.g. the amount or magnitude of something) and the performance of a system. They can provide the common language for describing a particular system that is needed for effective and clear communication among interested parties (McCool and Stankey, 2004). | C99: FALSE | E99: FALSE
A100: 861a903bf623d4873b2e27e84775ea64 | B100: In moving towards green growth such frameworks should where applicable be aligned. However, in recent years the term "accounting" has also been applied to non-financial aspects. Corporate accounting can be defined as the identification, collection, estimation, analysis, internal and external reporting, of economic, social and environmental effects and impacts to provide accountability to stakeholders on strategy, actions and performance and to support internal and external decision-making. | C100: FALSE | E100: FALSE
A101: d743d13d397544036f2266ae050c2dd8 | B101: According to the System of National Accounts, the principles underlying International Financial Reporting Standards are in most cases consistent with its principles, providing a comprehensive, consistent and flexible set of macroeconomic accounts.11 The System of National Accounts states that there could be areas of difference between the two systems, however, cooperation would be useful with a view to showing a reconciliation between the two positions. | C101: FALSE | E101: FALSE

Sheet Source
A1: doi | B1: text_id | C1: text | D1: sdg | E1: labels_negative | F1: labels_positive | G1: labels_total | H1: agreement | I1: label | J1: difficulty | K1: selection reason
A2: 10.18356/ad0bffd4-en | B2: 039e770089eb0cbfb193a3ae3fadb893 | C2: International donors increased their involvement in waste management during the last few years and this resulted in improvements in management of obsolete pesticides and expired chemicals, but management of municipal and manufacturing waste is developing slowly and old practices remain. This development reduced generated amounts of waste and in some sectors also decreased the amount of waste previously accumulated. The development of modem waste management infrastructure is still in the initial phase. | D2: 12 | E2: 0 | F2: 9 | G2: 9 | H2: 1 | I2: TRUE | J2: very easy | K2: target 12.4
A3: 10.18356/974c3e9b-en | B3: 0963ea06d1b60ca64affa94911f329d2 | C3: In response, international organizations such as the UN Development Programme (UNDP), the UN Environment Programme (UNEP) and the Organisation for Economic Co-operation and Development (OECD) have promoted the exchange of policy initiatives, action programmes and practices among member countries, industrial associations and academic institutions. For example, UNEP introduced cleaner production (CP), which promotes a shift from end-of-pipe treatment to pollution prevention, while the UNDP has appealed for environmentally sound technology in technology transfer programmes and assistance to developing countries. In the follow-up meeting after the Rio Declaration and Agenda 21, the International Human Dimensions Programme (IHDP) was established as a collaborative platform for social scientists and policy-oriented academics. | D3: 12 | E3: 0 | F3: 12 | G3: 12 | H3: 1 | I3: TRUE | J3: very easy | K3: target 12.a
A4: 10.14217/9781848599178-8-en | B4: 0342980e48fbffd359a20628d9450485 | C4: Mauritius covers a total land area of 720 square miles, and is almost entirely of volcanic origin, except for stretches of beaches, coral reefs and small patches of alluvium at the mouths of rivers. Pear-shaped, mountainous with its highest peak standing at 2,711 feet above sea level, Mauritius emerged from the ocean floor some 5 million years ago. Volcanic activity over thousands of years has given rise to varied types of soil. | D4: 12 | E4: 7 | F4: 2 | G4: 9 | H4: 0.55555556 | I4: FALSE | J4: medium | K4: automated selection
A5: 10.18356/f29e3817-en | B5: 14ddb3509efb3be82081e905f697dba3 | C5: The strategy's objectives are to sensitize and raise awareness among school children of the negative impact that using plastic bags has on the environment, to encourage schoolchildren to replace plastic bags with other less-polluting alternatives and to teach them how to properly dispose of plastic bags after use. A key event was organized for Earth Day 2010 in all the schools, and a guide to waste management was widely distributed at the event. The children not only participated in collecting plastic bags at nature sites and clean-up projects, but were also asked to pass on what they learned to friends and neighbours. | D5: 12 | E5: 0 | F5: 9 | G5: 9 | H5: 1 | I5: TRUE | J5: very easy | K5: target 12.8
A6: 10.18356/6236c858-en | B6: 18900ef1e2742e858bbed6264b3a046c | C6: It is therefore evident that current patterns of consumption and production are environmentally unsustainable and socially inequitable. Economic growth, human development and wellbeing would need to be substantially decoupled from resource use and environmental impact (UNEP, 2011). Achieving gains in decoupling will not happen spontaneously, but will require well designed public policies that enable economic restructuring toward sustainable consumption and production and resource efficiency. | D6: 12 | E6: 0 | F6: 9 | G6: 9 | H6: 1 | I6: TRUE | J6: very easy | K6: SDG 12
A7: 10.1787/5kmh3njpt6r0-en | B7: 062372c7882af8f7bb84943024eb6a2c | C7: Its mandate is two-fold: to promote energy security amongst its member countries through collective response to physical disruptions in oil supply and to advise member countries on sound energy policy. This paper reflects the views of the IEA Secretariat and may not necessarily reflect the views of the individual IEA member countries. The study also draws on contributions of Franziska Mueller-Langer, Jens Giersdorf and Anastasios Perimenis of the German Biomass Research Centre (DBFZ), who provided parts of the sustainability chapter and four country profiles commissioned by the Deutsche Gesellschaft fiir Technische Zusammenarbeit (GTZ). | D7: 12 | E7: 7 | F7: 2 | G7: 9 | H7: 0.55555556 | I7: FALSE | J7: medium | K7: automated selection
A8: 10.18356/524212d8-en | B8: 0686b17a9aeedb103f46b38f9d94eeb8 | C8: Thus the government's role is dual. On the one hand, it must act as a facilitator by providing the necessary infrastructure for tourists, promoting attractions and encouraging tourist arrivals. On the other hand, government’s role is to enforce laws of the land and these may, in some cases, be in conflict with its role as a promoter of tourism. | D8: 12 | E8: 7 | F8: 2 | G8: 9 | H8: 0.55555556 | I8: FALSE | J8: medium | K8: automated selection
A9: 10.14217/9781848599178-7-en | B9: 08ee208db6cafa5ea057212223ece39c | C9: One legacy of that programme was the establishment of the Programme of Advancement through Health and Education (PATH), a conditional cash transfer programme that now constitutes the core of the social safety net. Advocacy has been initiated by scientists and their students in the Climate Studies Group of the Department of Physics at the University of the West Indies (UWI), individual scholars in the Faculty of Social Sciences, the Centre for Sustainable Development at UWI, as well as by various ENGOs. Some of the research and the outreach based on this work have been funded by the Caribbean Community Climate Change Centre (CCCCC) and the Environmental Foundation of Jamaica (EFJ). | D9: 12 | E9: 8 | F9: 1 | G9: 9 | H9: 0.77777778 | I9: FALSE | J9: easy | K9: automated selection
A10: 10.14217/9781848599178-7-en | B10: 0b4a31dd0bc5b9cb6a3da2b48eb54401 | C10: As a result, poverty is endemic, generously underestimated at 20 per cent of the population in 2011, with the majority of poor households located in rural communities. It is well known that poor communities generate negative pressure on the environment from ‘slash-and-burn’ agricultural activities, improper waste disposal for want of facilities, and settlement on fragile lands that are vulnerable to natural hazards. In the case of Jamaica, there are the additional challenges of servicing the mounting national debt, which in 2013 stood at over 140 per cent of GDP, and ensuring macroeconomic stability so as to provide a basis for economic growth. | D10: 12 | E10: 9 | F10: 20 | G10: 29 | H10: 0.37931034 | I10: TRUE | J10: hard | K10: automated selection
A11: 10.6027/bbc022bf-en | B11: 0bafd5e13fe32c31b5b4d9f7536c941d | C11: Some definition of technology is necessary- it should be 100% recyclable under readily available current technology. Cotton/polyester mixes, for example, can be more technically durable than pure cotton. This suggests that the 100% recyclable stamp would be more applicable to fast fashion and not recommended for textiles where lifetime is generally limited by technical strength rather than change in style or change in fit e.g. bed-linen. This would rule out linking to some of the information proposed in the provision - unless the regulation was to be changed. | D11: 12 | E11: 0 | F11: 31 | G11: 31 | H11: 1 | I11: TRUE | J11: very easy | K11: automated selection
A12: 10.18356/974c3e9b-en | B12: 3c57594c5de7b481d01d64593f4e51cb | C12: Design-for-disassembly was formulated to promote the easy recovery of parts and materials during the product disassembly process, while design-for-environment called for minimizing pollution and promoting resource conservation during product or system design. In product life-cycle considerations, extended producer responsibility (EPR) may be realized in collaboration with intelligent consumer behaviour. The European Union (EU) and WBCSD have shifted the leading concept of a resource-circulating society from sustainable production and consumption in the 1990s to sustainable consumption and production in a “consumer society”. | D12: 12 | E12: 0 | F12: 9 | G12: 9 | H12: 1 | I12: TRUE | J12: very easy | K12: target 12.1
A13: 10.18356/6236c858-en | B13: 78625638c482b151a88161b2f6e4894f | C13: Resource efficiency can be achieved by increasing resource productivity (value added / resource use) or reducing resource intensity (resource use / value added). It is related to strategies like dematerialisation, such as fuel efficient cars. It will be clear that no production can be said to be sustainable if it is profligate in the use of resources, thus there is a direct link between resource efficiency and SCP, particularly sustainable production. | D13: 12 | E13: 0 | F13: 9 | G13: 9 | H13: 1 | I13: TRUE | J13: very easy | K13: SDG 12
... A101: 10.18356/312bd0fb-en | B101: f3e26c31fc440748f4dacd18dbecbc65 | C101: They were first identified and defined by the ESCAP Sustainable Business Network (ESBN) Task Force on Banking and Finance.55 These principles are constituent components of the SRB model (Figure 6). They establish strong ethical guidelines so that business practices meet globally accepted standards for the valuing and pricing of products, sen/ices and assets, engaging with stakeholders, and assessing and managing risks. Each principle is defined, and its role in the SRB Model for a Sustainable Future explained. | D101: 12 | E101: 13 | F101: 11 | G101: 24 | H101: 0.083333333 | I101: FALSE | J101: very hard | K101: target 12.8

Sheet Final Review
A1: Text ID | B1: Text | C1: Group | D1: Finn | E1: Gib | F1: Jean-Baptiste | G1: Meike | H1: Steve | I1: Alignment | J1: Finn | K1: Gib | L1: Jean-Baptiste | M1: Meike | N1: Steve | O1: Comments | P1: {=O:O} -> Comments | Q1: Consensus | R1: Labelers | S1: Rationale | T1: Notes
